Workbook

Sheet Cover
B2: Copart, Inc. (NASDAQ: CPRT)
B3: Revenue architecture, three-statement model, DCF and reverse DCF — Harvard pitch team, October 2026
B5: Ticker | D5: NASDAQ: $CPRT | F5: Colour and label legend
B6: Current share price (26 Sep 2026) | D6: 29.95 | F6: Blue: typed input, with label and source | H6: Owner-entered close — the one typed price in the workbook. DCF H118, the WACC build (Reverse DCF S5) and the Summary read this cell; a rebuild keeps whatever is typed here
B7: Price target (DCF implied share price, selected case) | D7: =DCF!H98 | F7: Black: formula | H7: DCF equity bridge on the Cover statistics and fully diluted shares
B8: Implied upside / (downside) | D8: =D7/D6-1 | F8: Green: link from another tab
B9: Key statistics — the hub: the DCF bridge, the WACC build and the Summary read these cells | F9: Red: toggle, probability or scenario selector
B10: Market capitalisation ($m) | D10: =D6*D15 | F10: Grey italic: notes and sources | H10: Price × fully diluted shares; feeds the WACC build (Reverse DCF S7)
B11: Enterprise value ($m) | D11: =D10-D12+D13+D14 | F11: Labels: VERIFIED · MEASURED · FITTED · CALIBRATED · ASSUMED · UNVERIFIED · ENGINE | H11: Market cap − cash & HTM + lease debt + non-controlling interest
B12: Cash & held-to-maturity securities, 31 Jul 2026 ($m) | D12: ='D 10-K FY26'!C12+'D 10-K FY26'!C13 | F12: Tab map | H12: 10-K balance sheet (D 10-K FY26: 1,907.9 + 2,581.9); feeds DCF H107
B13: Debt: lease liabilities, 31 Jul 2026 ($m) | D13: ='3SM'!H77 | F13: Key Drivers | G13: the numbers the theses turn on | H13: 3SM balance sheet (PitchBook / 10-K): 15.2 current + 73.2 non-current; no funded debt. Feeds DCF H108 and the WACC build (S8)
B14: Non-controlling interest, 31 Jul 2026 ($m) | D14: ='3SM'!H72 | F14: Summary | G14: headline financials, Street Δ, component delta to Street | H14: 3SM balance sheet; feeds DCF H109
B15: Fully diluted shares (mn) = basic + treasury-method options + RSUs | D15: =D16+D17+D18 | F15: RPM | G15: one-page revenue build; scenario dropdown in D3 | H15: Feeds DCF H112 and the WACC build (Reverse DCF S6)
B16: Basic shares outstanding, 31 Jul 2026 (mn) | D16: ='D 10-K FY26'!C5 | F16: 3SM | G16: three statements FY22A–FY31E with schedules; feeds the DCF | H16: 10-K Note 12: 926,298,293 shares at 31 Jul 2026
B17: Net shares from options, treasury method (mn): N × max(0, 1 − K/P) | D17: ='D 10-K FY26'!C6/1000*MAX(0,1-'D 10-K FY26'!D6/D6) | F17: DCF / Reverse DCF | G17: valuation; WACC and tax build in Reverse DCF columns R–X | H17: 10-K Note 12: 12.759m options at a $24.19 weighted-average exercise price; P = the price in D6
B18: Unvested RSUs (mn) | D18: =IF(ISNUMBER('D 10-K FY26'!C8),'D 10-K FY26'!C8/1000,0) | F18: E1–E6 | G18: engines: fleet, claims, carriers, aftermarket, fees, branches | H18: RSU count not parsed from the filing text; enter it from Note 12 on D 10-K FY26
B19: EV / FY2026A adjusted EBITDA (x) | D19: =D11/D22 | F19: Scenarios / Street | G19: seven cases on one base; broker assumptions
B20: Price / FY2026A diluted EPS (x) | D20: =D6/'3SM'!H28 | F20: Sources / Checks | G20: every input with its source; live checks | H20: 3SM FY2026A diluted EPS
B21: FY2026A revenue ($m) | D21: =RPM!H6 | F21: D … | G21: data tabs with sources and dates
B22: FY2026A adjusted EBITDA ($m) | D22: ='3SM'!H18 | H22: 3SM: EBIT + D&A (Barclays definition)
B23: FY2027E legacy service revenue, selected case ($m) | D23: =RPM!I10
B24: Δ to JPMorgan FY27E service revenue ($m) | D24: =RPM!D50
B25: Selected scenario (dropdown on RPM D3) | D25: =RPM!D3
B26: WACC (bottom-up build, Reverse DCF R–X) | D26: ='WACC, Tax, and Reverse DCF'!N31
B27: Structural effective tax rate | D27: ='WACC, Tax, and Reverse DCF'!N39

Sheet Key Drivers
B1: Key Drivers (all cells link to the engines; labels and sources travel with them)
B2: Green = link. Change an input on its engine tab, not here. FQ4 FY26 is the last reported quarter; FQ1 FY27 is the first forecast quarter.
D4: Value | E4: Unit | F4: Label | H4: Source / where it lives
B5: Thesis 1 — coverage persistence (E2 block F, D Coverage)
B6: Motor-vehicle-insurance CPI, latest month y/y (Aug 2026) | D6: ='D Coverage'!Q17 | E6: % | F6: VERIFIED | H6: BLS CUUR0000SETE, raw/bls; the premium index is falling
B7: Premium growth used for FY27 (selected path; E2 row 127 selects BLS trend or S&P-consistent) | D7: ='E2 Claims & Totals'!D123 | E7: % | F7: selected | H7: E2 D123
B8: Average hourly earnings growth, latest year | D8: ='E2 Claims & Totals'!D124 | E8: % | F8: VERIFIED | H8: BLS CES0500000003
B9: Premium burden 2023 (level at which households left) / 2026 to date (2025 = 1) | D9: ='E2 Claims & Totals'!J108 | E9: x | F9: MEASURED | H9: E2 row 108; 2026 value in M108 (0.956): still 10% above 2023 after the 2026 premium decline
B10: First quarter the burden falls below its 2023 level, selected path | D10: ='E2 Claims & Totals'!D131 | F10: MEASURED | H10: E2 D131; "beyond FQ4 FY28" on the S&P-consistent path
B11: S&P auto combined ratio path 2025P / 2026P / 2027P | D11: ='D Coverage'!D20 | E11: ratio | F11: VERIFIED (republication) | H11: D Coverage rows 20–22: 94.5 / 97.1 / 98.9, breaching 100 in 2028 (Carrier Management, 6 Jan 2026)
B12: Uninsured-motorist rate 2017 / 2023 | D12: ='D Coverage'!D8 | E12: % | F12: VERIFIED endpoints | H12: IRC release 20 Feb 2025; 2023 = 15.4% (D Coverage J8)
B13: Physical-damage coverage index 2017 (2025 = 1.000; the 2017–23 change is the measured coverage decline) | D13: ='E2 Claims & Totals'!D107 | E13: x | F13: MEASURED | H13: E2 row 107; collision share 76–77% flat 2021–23, so the decline is the uninsured leg
B14: Share of insured drivers with collision coverage, 2021 / 2022 / 2023 | D14: ='D Coverage'!H9 | E14: % | F14: VERIFIED (republication) | H14: III via Wayback snapshots 2024 and 2025 plus the live page: 76% / 77% / 77%
B15: Two-point coverage response to premium burden (ε) | D15: ='E2 Claims & Totals'!D110 | E15: x | F15: UNVERIFIED | H15: E2 D110; n = 2
B16: Street-implied FY27 coverage recovery r (reverse-solved to JPM) | D16: ='E2 Claims & Totals'!D126 | E16: % | F16: MEASURED | H16: E2 D124: what the Street number needs
B17: Coverage ratio FQ1 FY27: sticky / premium-response / recovery | D17: ='E2 Claims & Totals'!H116 | E17: x | F17: paths | H17: E2 rows 116–118 (H117, H118 for the other paths)
B18: CCC total claim volume y/y, 2024 / 2025 | D18: ='D Coverage'!K10 | E18: % | F18: VERIFIED | H18: D Coverage K10 / L10 (2025 = −3.3%)
B20: Thesis 2 — aftermarket substitution (E4)
B21: Aftermarket share of replacement-part dollars, 2025 | D21: ='E4 Aftermarket'!D47 | E21: % | F21: VERIFIED | H21: CCC Crash Course 2026 (21.0% in 2024)
B22: Recycled share of replacement-part dollars, 2025 | D22: ='E4 Aftermarket'!D48 | E22: % | F22: VERIFIED | H22: CCC (10.7% in 2024)
B23: Aftermarket price relative to OEM at the anchor | D23: ='E4 Aftermarket'!D50 | E23: x | F23: VERIFIED (historical) | H23: Mitchell 2016 discounts, mean 27%; recycled set equal at the anchor
B24: Aftermarket relative-price drift per year (PartsTrader: OEM +4.3%, aftermarket <1%) | D24: ='E4 Aftermarket'!D68 | E24: % | F24: VERIFIED (trend, one year) | H24: E4 D68
B25: Aftermarket price relative to OEM by FQ4 FY28 (recycled stays at 0.73) | D25: ='E4 Aftermarket'!O9 | E25: x | F25: derived | H25: E4 row 9
B26: Sourcing path selector (1 observed trend, 2 memo stress) | D26: ='E4 Aftermarket'!D64 | F26: TOGGLE | H26: E4 D64
B27: Cumulative aftermarket share shift at FQ4 FY27 (selected path) | D27: ='E4 Aftermarket'!K7 | E27: pts | F27: path | H27: E4 row 7
B28: Complete repair-bill change at FQ4 FY27 | D28: ='E4 Aftermarket'!K14 | E28: % | F28: derived | H28: E4 row 14
B29: Change in total-loss units at FQ4 FY27 | D29: ='E4 Aftermarket'!K40 | E29: % | F29: ENGINE-derived η × bill change | H29: E4 row 40
B30: Change in auction price at FQ4 FY27 | D30: ='E4 Aftermarket'!K41 | E30: % | F30: ASSUMED scaling | H30: E4 row 41
B31: Memo stress case (5.5 pts) at sourced prices: bill change / units | D31: ='E4 Aftermarket'!D31 | E31: % | F31: derived | H31: E4 D31 / E31; engine basket reproduces 1.03% in D30
B33: Thesis 3 — carrier allocation (E3)
B34: Copart share of the insured total-loss pool, FQ4 FY26 | D34: ='E3 Carriers'!G43 | E34: % | F34: reconstructed | H34: E3 row 43 (frozen weights × inherited allocation)
B35: Share FQ4 FY27, base (known runoff only) | D35: ='E3 Carriers'!K43 | E35: % | F35: scenario | H35: E3 row 43
B36: Share FQ4 FY27, thesis 3 (probability-weighted moves) | D36: ='E3 Carriers'!K44 | E36: % | F36: scenario | H36: E3 row 44; memo: 56.6% → 55.3%
B37: Progressive allocation to Copart, FQ4 FY26 / FQ4 FY27 | D37: ='E3 Carriers'!G20 | E37: share | F37: UNVERIFIED path | H37: E3 row 20 (K20 for FY27)
B38: Expected move: State Farm / Other (pts) | D38: ='E3 Carriers'!F77 | E38: pts | F38: UNVERIFIED | H38: E3 rows 77–78: −5 pts × 45% each
B39: Progressive move: effect on FQ4 FY26 service revenue | D39: ='E3 Carriers'!D83 | E39: % | F39: MEASURED chain | H39: E3 row 83 (E83 = % of total revenue)
B40: Listed-inventory split, Copart share of duopoly (4 nights) | D40: ='E3 Carriers'!G45 | E40: % | F40: MEASURED | H40: data/csv/duopoly_daily.csv
B41: IAA acreage (owned + leased) | D41: ='E3 Carriers'!E86 | E41: acres | F41: VERIFIED | H41: RB Global FY2025 10-K
B42: RB Global automotive lots, Q2 2026 y/y | D42: ='E3 Carriers'!E94 | E42: % | F42: VERIFIED | H42: RB Global 10-Q
B43: Effective seller commission, thesis 3, FQ4 FY27 | D43: ='E3 Carriers'!K56 | E43: % | F43: UNVERIFIED (Barclays 4% base) | H43: E3 row 56
B45: Prices, fees and the ledger (E5)
B46: US insurance ASP growth, FY27+ (input) | D46: ='E5 Prices & Fees'!D44 | E46: % | F46: ASSUMED continuation | H46: E5 D44; FQ4 FY26 disclosed +3.7%
B47: All-in insurance RPU y/y, FQ1 FY27 (base) | D47: ='E5 Prices & Fees'!H26 | E47: % | F47: derived | H47: E5 row 26
B48: Buyer-fee elasticity to ASP | D48: ='E5 Prices & Fees'!D51 | E48: x | F48: ENGINE-derived | H48: E5 D51
B49: Insurance share of US service dollars | D49: ='E5 Prices & Fees'!D39 | E49: % | F49: ASSUMED | H49: E5 D39 (0.80 alternative)
B50: Implied US insurance units, FY26 | D50: ='E5 Prices & Fees'!P11 | E50: 000s | F50: MODELED | H50: E5 row 11
B52: Outputs (Scenarios, RPM)
B53: JPMorgan FY27 legacy service revenue (ex-ACV), 11 Sep 2026 | D53: =Scenarios!D108 | E53: $M | F53: VERIFIED (licensed) | H53: Scenarios D108
B54: Case 0 Street-implied FY27 | D54: =Scenarios!D112 | E54: $M | F54: by construction | H54: Scenarios summary
B55: Case 1 Known facts FY27 / Δ vs JPM | D55: =Scenarios!D113 | E55: $M | F55: model | H55: Scenarios D113; Δ vs JPM in G113
B56: Thesis 2 FY27 / Δ vs case 1 | D56: =Scenarios!D115 | E56: $M | F56: model | H56: Scenarios E115
B57: Thesis 3 FY27 / Δ vs case 1 | D57: =Scenarios!D116 | E57: $M | F57: model | H57: Scenarios E116
B58: All three FY27 / Δ vs JPM | D58: =Scenarios!D117 | E58: $M | F58: model | H58: Scenarios G117
B59: Selected case (dropdown on RPM D3) | D59: =RPM!D3 | E59: case | F59: selector | H59: RPM D3 (index in I3); I10 holds the revenue
B60: Selected case Δ to JPM | D60: =RPM!D50 | E60: $M | F60: model | H60: RPM D50 (E50 in %)
B62: Three-statement model (3SM) vs Barclays, FY2027E
B63: 3SM revenue FY27E | D63: ='3SM'!I8 | E63: $M | F63: model | H63: 3SM row 8; Δ to Barclays in row 32
B64: 3SM adjusted EBITDA FY27E | D64: ='3SM'!I18 | E64: $M | F64: model | H64: 3SM row 18; Barclays 1,916; Δ in row 34
B65: 3SM diluted EPS FY27E | D65: ='3SM'!I28 | E65: $ | F65: model | H65: 3SM row 28; Barclays $1.56 in row 41
B66: 3SM free cash flow FY27E (CFO + capex) | D66: ='3SM'!I112 | E66: $M | F66: model | H66: 3SM row 112
B67: 3SM cash & HTM FY27E | D67: ='3SM'!I47 | E67: $M | F67: model | H67: 3SM row 47; Barclays 5,656; Δ in row 79
B68: ΔNWC method on the 3SM (dropdown) | D68: ='3SM'!D163 | E68: case | F68: selector | H68: 3SM D163

Sheet Summary
B1: Copart, Inc. — Summary: headline financials, Street comparison and the component delta to Street
B2: Every cell links to the 3SM, DCF, Scenarios, Street, Cover or D Barclays tab (green). Fiscal years end 31 July. $M except per share. Barclays = 11 Sep 2026 model (Underweight, $25). – = no line for that year.
C4: Units | D4: Historicals | G4: Projected | L4: Notes / sources
B5: Headline financials — 3SM, selected case (RPM D3) | D5: FY2024A | E5: FY2025A | F5: FY2026A | G5: FY2027E | H5: FY2028E | I5: FY2029E
B6: Revenue | C6: $M | D6: ='3SM'!F8 | E6: ='3SM'!G8 | F6: ='3SM'!H8 | G6: ='3SM'!I8 | H6: ='3SM'!J8 | I6: ='3SM'!K8 | L6: 3SM row 8 (RPM)
B7: y/y growth | C7: % | D7: – | E7: =IF(D6=0,0,E6/D6-1) | F7: =IF(E6=0,0,F6/E6-1) | G7: =IF(F6=0,0,G6/F6-1) | H7: =IF(G6=0,0,H6/G6-1) | I7: =IF(H6=0,0,I6/H6-1)
B8: Adjusted EBITDA | C8: $M | D8: ='3SM'!F18 | E8: ='3SM'!G18 | F8: ='3SM'!H18 | G8: ='3SM'!I18 | H8: ='3SM'!J18 | I8: ='3SM'!K18 | L8: 3SM row 18 (EBIT + D&A, Barclays definition)
B9: margin | C9: % | D9: =IF(D6=0,0,D8/D6) | E9: =IF(E6=0,0,E8/E6) | F9: =IF(F6=0,0,F8/F6) | G9: =IF(G6=0,0,G8/G6) | H9: =IF(H6=0,0,H8/H6) | I9: =IF(I6=0,0,I8/I6)
B10: GAAP diluted EPS | C10: $ | D10: ='3SM'!F28 | E10: ='3SM'!G28 | F10: ='3SM'!H28 | G10: ='3SM'!I28 | H10: ='3SM'!J28 | I10: ='3SM'!K28 | L10: 3SM row 28
B11: y/y growth | C11: % | D11: – | E11: =IF(D10=0,0,E10/D10-1) | F11: =IF(E10=0,0,F10/E10-1) | G11: =IF(F10=0,0,G10/F10-1) | H11: =IF(G10=0,0,H10/G10-1) | I11: =IF(H10=0,0,I10/H10-1)
B12: Free cash flow (CFO + capex) | C12: $M | D12: ='3SM'!F112 | E12: ='3SM'!G112 | F12: ='3SM'!H112 | G12: ='3SM'!I112 | H12: ='3SM'!J112 | I12: ='3SM'!K112 | L12: 3SM row 112
B13: margin | C13: % | D13: =IF(D6=0,0,D12/D6) | E13: =IF(E6=0,0,E12/E6) | F13: =IF(F6=0,0,F12/F6) | G13: =IF(G6=0,0,G12/G6) | H13: =IF(H6=0,0,H12/H6) | I13: =IF(I6=0,0,I12/I6)
B14: Unlevered free cash flow (DCF) | C14: $M | D14: =DCF!F59 | E14: =DCF!G59 | F14: =DCF!H59 | G14: =DCF!I59 | H14: =DCF!J59 | I14: =DCF!K59 | L14: DCF row 63: NOPAT + D&A + SBC − capex − ΔNWC; D&A, SBC, capex and ΔNWC read the 3SM
B15: margin | C15: % | D15: =IF(D6=0,0,D14/D6) | E15: =IF(E6=0,0,E14/E6) | F15: =IF(F6=0,0,F14/F6) | G15: =IF(G6=0,0,G14/G6) | H15: =IF(H6=0,0,H14/H6) | I15: =IF(I6=0,0,I14/I6)
B16: Street — Barclays model (11 Sep 2026) and consensus EPS; % Δ = 3SM ÷ Street − 1 | D16: FY2024A | E16: FY2025A | F16: FY2026A | G16: FY2027E | H16: FY2028E | I16: FY2029E
B17: Barclays revenue | C17: $M | D17: – | E17: – | F17: ='D Barclays'!D5 | G17: ='D Barclays'!E5 | H17: ='D Barclays'!F5 | I17: ='D Barclays'!G5 | L17: D Barclays (numeric extraction from the licensed report held locally; FY2026A = reported)
B18: y/y growth | C18: % | D18: – | E18: – | F18: – | G18: =IF(F17=0,0,G17/F17-1) | H18: =IF(G17=0,0,H17/G17-1) | I18: =IF(H17=0,0,I17/H17-1)
B19: % Δ 3SM vs Barclays | C19: % | D19: – | E19: – | F19: =IF(F17=0,0,F6/F17-1) | G19: =IF(G17=0,0,G6/G17-1) | H19: =IF(H17=0,0,H6/H17-1) | I19: =IF(I17=0,0,I6/I17-1)
B20: Barclays adjusted EBITDA | C20: $M | D20: – | E20: – | F20: ='D Barclays'!D6 | G20: ='D Barclays'!E6 | H20: ='D Barclays'!F6 | I20: ='D Barclays'!G6
B21: margin | C21: % | D21: – | E21: – | F21: =IF(F17=0,0,F20/F17) | G21: =IF(G17=0,0,G20/G17) | H21: =IF(H17=0,0,H20/H17) | I21: =IF(I17=0,0,I20/I17)
B22: % Δ 3SM vs Barclays | C22: % | D22: – | E22: – | F22: =IF(F20=0,0,F8/F20-1) | G22: =IF(G20=0,0,G8/G20-1) | H22: =IF(H20=0,0,H8/H20-1) | I22: =IF(I20=0,0,I8/I20-1)
B23: Barclays diluted EPS | C23: $ | D23: – | E23: – | F23: ='D Barclays'!D10 | G23: ='D Barclays'!E10 | H23: ='D Barclays'!F10 | I23: ='D Barclays'!G10
B24: % Δ 3SM vs Barclays | C24: % | D24: – | E24: – | F24: =IF(F23=0,0,F10/F23-1) | G24: =IF(G23=0,0,G10/G23-1) | H24: =IF(H23=0,0,H10/H23-1) | I24: =IF(I23=0,0,I10/I23-1)
B25: DCF diluted EPS (owner's DCF row 41; the DCF keeps its own cost build) | C25: $ | D25: – | E25: – | F25: =DCF!H41 | G25: =DCF!I41 | H25: =DCF!J41 | I25: =DCF!K41 | L25: DCF row 41 (DCF EBIT build differs from the 3SM; see 3SM schedule 9)
B26: % Δ DCF EPS vs Barclays | C26: % | D26: – | E26: – | F26: =IF(F23=0,0,F25/F23-1) | G26: =IF(G23=0,0,G25/G23-1) | H26: =IF(H23=0,0,H25/H23-1) | I26: =IF(I23=0,0,I25/I23-1) | L26: Summary row 23 holds Barclays EPS
B27: Broker total revenue — BNP Paribas (Outperform, $40) | C27: $M | D27: – | E27: – | F27: – | G27: =Street!E9 | H27: =Street!E10 | I27: – | L27: Street tab rows 9–10 (named-broker extractions; report dates in Street row 5)
B28: Broker total revenue — J.P. Morgan | C28: $M | D28: – | E28: – | F28: – | G28: =Street!F9 | H28: =Street!F10 | I28: – | L28: Street tab rows 9–10 (named-broker extractions; report dates in Street row 5)
B29: Broker total revenue — BofA Global Research | C29: $M | D29: – | E29: – | F29: – | G29: =Street!G9 | H29: =Street!G10 | I29: – | L29: Street tab rows 9–10 (named-broker extractions; report dates in Street row 5)
B30: Broker total revenue — Barclays, 25 Aug 2026 note | C30: $M | D30: – | E30: – | F30: – | G30: =Street!I9 | H30: =Street!I10 | I30: – | L30: Street tab rows 9–10 (named-broker extractions; report dates in Street row 5)
B31: Component delta to Street — legacy service revenue by case ($M; engines run FY27–28) and the EBITDA bridge to Barclays | D31: FY2024A | E31: FY2025A | F31: FY2026A | G31: FY2027E | H31: FY2028E | I31: FY2029E
B32: Street-implied (case 0): known runoff, coverage recovering to the Street path | C32: $M | D32: – | E32: – | F32: – | G32: =Scenarios!Q16 | H32: =Scenarios!R16 | I32: – | L32: Scenarios Q/R16; the recovery rate is reverse-solved so FY27 equals JPMorgan
B33: JPMorgan FY27E legacy service revenue, 11 Sep 2026 (ex-ACV) | C33: $M | D33: – | E33: – | F33: – | G33: =Scenarios!$D$108 | H33: – | I33: – | L33: Scenarios D108 ← D Facts (licensed report held locally); JPMorgan publishes no FY28 service line
B34: Thesis 1 — coverage persistence: case 1 (known facts, sticky coverage) − case 0 | C34: $M | D34: – | E34: – | F34: – | G34: =Scenarios!Q29-Scenarios!Q16 | H34: =Scenarios!R29-Scenarios!R16 | I34: – | L34: Scenarios rows 29 − 16
B35: Thesis 2 — aftermarket substitution: thesis 2 case − case 1 | C35: $M | D35: – | E35: – | F35: – | G35: =Scenarios!Q55-Scenarios!Q29 | H35: =Scenarios!R55-Scenarios!R29 | I35: – | L35: Scenarios rows 55 − 29
B36: Thesis 3 — carrier reallocation (probability-weighted): thesis 3 case − case 1 | C36: $M | D36: – | E36: – | F36: – | G36: =Scenarios!Q68-Scenarios!Q29 | H36: =Scenarios!R68-Scenarios!R29 | I36: – | L36: Scenarios rows 68 − 29
B37: Interaction (all three − case 0 − sum of the three parts; exact on the common base) | C37: $M | D37: – | E37: – | F37: – | G37: =Scenarios!Q81-Scenarios!Q16-G34-G35-G36 | H37: =Scenarios!R81-Scenarios!R16-H34-H35-H36 | I37: –
B38: All three vs Street-implied | C38: $M | D38: – | E38: – | F38: – | G38: =Scenarios!Q81-Scenarios!Q16 | H38: =Scenarios!R81-Scenarios!R16 | I38: – | L38: Scenarios rows 81 − 16
B39: All three vs JPMorgan, % | C39: % | D39: – | E39: – | F39: – | G39: =Scenarios!H117 | H39: – | I39: – | L39: Scenarios H117
B40: Selected case on the RPM (D3): service revenue | C40: $M | D40: – | E40: – | F40: – | G40: =RPM!I10 | H40: =RPM!J10 | I40: – | L40: RPM I10 / J10 → 3SM
B41: Δ selected case vs Street-implied | C41: $M | D41: – | E41: – | F41: – | G41: =G40-G32 | H41: =H40-H32 | I41: –
B42: Vehicle sales (RPM) | C42: $M | D42: – | E42: – | F42: – | G42: =RPM!I12 | H42: =RPM!J12 | I42: – | L42: RPM I12 / J12; JPMorgan FY27E purchased-vehicle revenue 710 on Street F8
B43: Δ vs JPMorgan FY27E purchased-vehicle revenue | C43: $M | D43: – | E43: – | F43: – | G43: =RPM!I12-Street!F8 | H43: – | I43: –
B44: EBITDA bridge to Barclays (3SM − Barclays; Barclays publishes FY27–29)
B45: Δ revenue | C45: $M | D45: – | E45: – | F45: – | G45: ='3SM'!I32 | H45: ='3SM'!J32 | I45: ='3SM'!K32 | L45: 3SM row 32
B46: of which revenue effect at Barclays' EBITDA margin | C46: $M | D46: – | E46: – | F46: – | G46: =G45*'3SM'!I33/'3SM'!I31 | H46: =H45*'3SM'!J33/'3SM'!J31 | I46: =I45*'3SM'!K33/'3SM'!K31
B47: Δ adjusted EBITDA | C47: $M | D47: – | E47: – | F47: – | G47: ='3SM'!I34 | H47: ='3SM'!J34 | I47: ='3SM'!K34 | L47: 3SM row 34
B48: of which margin effect (facility cost per unit on fewer units; Barclays-implied G&A ratio) | C48: $M | D48: – | E48: – | F48: – | G48: =G47-G46 | H48: =H47-H46 | I48: =I47-I46
B49: Δ diluted EPS ($) | C49: $ | D49: – | E49: – | F49: – | G49: ='3SM'!I28-'3SM'!I41 | H49: ='3SM'!J28-'3SM'!J41 | I49: ='3SM'!K28-'3SM'!K41
B50: Δ diluted EPS (%) | C50: % | D50: – | E50: – | F50: – | G50: ='3SM'!I42 | H50: ='3SM'!J42 | I50: ='3SM'!K42
B51: Valuation (links) | D51: Price (Cover) | E51: DCF implied | F51: Upside | G51: WACC | H51: Exit multiple | I51: Tax rate
B52: Current price (Cover D6) · DCF implied share price (H113) · upside (H114) · WACC (Reverse DCF S25) · exit EV/EBITDA (DCF H92; Barclays 10×) · structural tax rate (S33) | D52: =Cover!D6 | E52: =DCF!H98 | F52: =DCF!H99 | G52: ='WACC, Tax, and Reverse DCF'!N31 | H52: =DCF!H77 | I52: ='WACC, Tax, and Reverse DCF'!N39

Sheet MODEL -------->

Sheet RPM
B1: Copart, Inc. (NASDAQ: CPRT)
B2: Revenue = fee units * service revenue per unit + principal vehicle sales. In $M
B3: Scenario selector — click D3 and choose a case (drives rows 10, 12, 21 for FY27–28; case index in I3) | D3: 6 · All three — sticky coverage + aftermarket + carriers | I3: =MATCH(D3,$U$5:$U$11,0)
C4: Units | D4: Historicals | I4: Projected | U4: Scenario options (list source for the D3 dropdown; do not edit)
B5: Reported revenue | D5: FY2022A | E5: FY2023A | F5: FY2024A | G5: FY2025A | H5: FY2026A | I5: FY2027E | J5: FY2028E | K5: FY2029E | L5: FY2030E | M5: FY2031E | N5: FY26–31 CAGR | U5: 1 · Case 0 — Street-implied (coverage recovers to JPM)
B6: Total Revenue | C6: $M | D6: ='PB IS (Annual)'!Q14/1000 | E6: ='PB IS (Annual)'!P14/1000 | F6: ='PB IS (Annual)'!O14/1000 | G6: ='PB IS (Annual)'!N14/1000 | H6: ='PB IS (Annual)'!M14/1000 | I6: =I10+I12 | J6: =J10+J12 | K6: =K10+K12 | L6: =L10+L12 | M6: =M10+M12 | N6: =IFERROR((M6/H6)^(1/5)-1,"") | U6: 2 · Case 1 — Known facts, sticky coverage (thesis 1)
B7: y/y growth | C7: % | D7: -- | E7: =E6/D6-1 | F7: =F6/E6-1 | G7: =G6/F6-1 | H7: =H6/G6-1 | I7: =I6/H6-1 | J7: =J6/I6-1 | K7: =K6/J6-1 | L7: =L6/K6-1 | M7: =M6/L6-1 | U7: 3 · Case 1b — Premium-response coverage
U8: 4 · Thesis 2 — aftermarket substitution on case 1
B9: Revenue by type | U9: 5 · Thesis 3 — carrier moves on case 1
B10: Service revenue (fee-based) | C10: $M | D10: 2881.7 | E10: 3199.6 | F10: 3561 | G10: 3968.7 | H10: 3969.5 | I10: =Scenarios!Q126 | J10: =Scenarios!R126 | K10: =J10*(1+$D$43) | L10: =K10*(1+$D$43) | M10: =L10*(1+$D$43) | N10: =IFERROR((M10/H10)^(1/5)-1,"") | P10: FY27–28 from Scenarios (selected case); FY29–31 fade at row 43 | U10: 6 · All three — sticky coverage + aftermarket + carriers
B11: y/y growth | C11: % | D11: -- | E11: =E10/D10-1 | F11: =F10/E10-1 | G11: =G10/F10-1 | H11: =H10/G10-1 | I11: =I10/H10-1 | J11: =J10/I10-1 | K11: =K10/J10-1 | L11: =L10/K10-1 | M11: =M10/L10-1 | U11: 7 · Bull — premium-response coverage, ASP +6%
B12: Vehicle sales (bought & resold) | C12: $M | D12: 619.2 | E12: 669.9 | F12: 675.8 | G12: 678.3 | H12: 696.7 | I12: =Scenarios!Q127 | J12: =Scenarios!R127 | K12: =J12*(1+$D$44) | L12: =K12*(1+$D$44) | M12: =L12*(1+$D$44) | N12: =IFERROR((M12/H12)^(1/5)-1,"") | P12: FY27–28 from Scenarios (E6 purchased overlay); FY29–31 fade at row 44
B13: y/y growth | C13: % | D13: -- | E13: =E12/D12-1 | F13: =F12/E12-1 | G13: =G12/F12-1 | H13: =H12/G12-1 | I13: =I12/H12-1 | J13: =J12/I12-1 | K13: =K12/J12-1 | L13: =L12/K12-1 | M13: =M12/L12-1
B14: check (service + vehicle sales = total reported revenue) | C14: $M | D14: =D10+D12-D6 | E14: =E10+E12-E6 | F14: =F10+F12-F6 | G14: =G10+G12-G6 | H14: =H10+H12-H6
B16: Unit build
B17: FY2026 global units | C17: 000s | H17: 4000 | P17: <- As an anchor for forecasts. Copart only discloses % change in its units sold. FY2026, Copart said "over 4million"-> assuming 4m units for FY2026
B18: FY2026 unit mix: US insurance / US non-insurance / International | C18: % | F18: 0.65 | G18: 0.17 | H18: =1-F18-G18 | P18: Estimates
B20: Unit growth by channel
B21: US insurance units, y/y | C21: % | G21: 0.042 | H21: -0.08 | I21: =Scenarios!Q128/Scenarios!P128-1 | J21: =Scenarios!R128/Scenarios!Q128-1 | K21: =$D$45 | L21: =$D$45 | M21: =$D$45 | P21: FY27–28 from Scenarios (E2 pool × E3 share × E4); FY29–31 fade at row 45
B22: US non-insurance units, y/y | C22: % | G22: 0.028 | H22: -0.039 | I22: ='Volume Build'!I33 | J22: ='Volume Build'!J33 | K22: ='Volume Build'!K33 | L22: ='Volume Build'!L33 | M22: ='Volume Build'!M33 | P22: Forecasts link to volume build
B23: International units, y/y | C23: % | G23: 0.081 | H23: 0.037 | I23: ='Volume Build'!I34 | J23: ='Volume Build'!J34 | K23: ='Volume Build'!K34 | L23: ='Volume Build'!L34 | M23: ='Volume Build'!M34 | P23: Owner-entered from Copart calls (international units y/y)
B25: Units by channel
B26: US insurance units | C26: 000s | F26: =G26/(1+G21) | G26: =H26/(1+H21) | H26: =$H$17*$F$18 | I26: =H26*(1+I21) | J26: =I26*(1+J21) | K26: =J26*(1+K21) | L26: =K26*(1+L21) | M26: =L26*(1+M21) | P26: Starting from FY2026 anchor (4m), work backwards using disclosed growth rates to reconstruct FY25 and FY24, and forecast forward
B27: US non-insurance units (dealer, BluCar, Direct, charity) | C27: 000s | F27: =G27/(1+G22) | G27: =H27/(1+H22) | H27: =$H$17*$G$18 | I27: =H27*(1+I22) | J27: =I27*(1+J22) | K27: =J27*(1+K22) | L27: =K27*(1+L22) | M27: =L27*(1+M22)
B28: International units | C28: 000s | F28: =G28/(1+G23) | G28: =H28/(1+H23) | H28: =$H$17*$H$18 | I28: =H28*(1+I23) | J28: =I28*(1+J23) | K28: =J28*(1+K23) | L28: =K28*(1+L23) | M28: =L28*(1+M23)
B29: Global fee units | C29: 000s | D29: =IF(COUNT(D26:D28)=3,SUM(D26:D28),"") | E29: =IF(COUNT(E26:E28)=3,SUM(E26:E28),"") | F29: =SUM(F26:F28) | G29: =SUM(G26:G28) | H29: =SUM(H26:H28) | I29: =SUM(I26:I28) | J29: =SUM(J26:J28) | K29: =SUM(K26:K28) | L29: =SUM(L26:L28) | M29: =SUM(M26:M28) | N29: =IFERROR((M29/H29)^(1/5)-1,"")
B30: y/y growth | C30: % | D30: -- | E30: =IFERROR(E29/D29-1,"") | F30: =IFERROR(F29/E29-1,"") | G30: =G29/F29-1 | H30: =H29/G29-1 | I30: =I29/H29-1 | J30: =J29/I29-1 | K30: =K29/J29-1 | L30: =L29/K29-1 | M30: =M29/L29-1
B32: Revenue per unit (RPU)
B33: Service revenue per fee unit | C33: $ | D33: =IFERROR(D10*1000/D29,"") | E33: =IFERROR(E10*1000/E29,"") | F33: =F10*1000/F29 | G33: =G10*1000/G29 | H33: =H10*1000/H29 | I33: =I10*1000/I29 | J33: =J10*1000/J29 | K33: =K10*1000/K29 | L33: =L10*1000/L29 | M33: =M10*1000/M29 | N33: =(M33/H33)^(1/5)-1 | P33: Implied: service revenue ÷ global fee units (no longer a driver)
B34: RPU growth, y/y | C34: % | E34: =IFERROR(E33/D33-1,"") | F34: =IFERROR(F33/E33-1,"") | G34: =G33/F33-1 | H34: =H33/G33-1 | I34: =I33/H33-1 | J34: =J33/I33-1 | K34: =K33/J33-1 | L34: =L33/K33-1 | M34: =M33/L33-1 | P34: Implied from row 33
B36: Disclosed revenue-per-unit and ASP growth (for checking purposes) | P36: Disclosed by Copart (calls, 8-Ks); owner-entered in v1
B37: Global revenue per unit, y/y (disclosed) | C37: % | H37: 0.057 | P37: Disclosed by Copart (calls); owner-entered in v1
B38: Global ASP, y/y (disclosed) | C38: % | H38: 0.055 | P38: Disclosed by Copart (calls); owner-entered in v1
B39: International revenue, $M (disclosed) | C39: $M | G39: 791.9 | H39: 858.8 | P39: 8-K segment revenue; owner-entered in v1 (see D Reported geography table)
B40: US revenue, $M (disclosed) | C40: $M | G40: 3855.1 | H40: 3807.4 | P40: 8-K segment revenue; owner-entered in v1 (see D Reported geography table)
B42: Beyond the engine horizon (FY29–31): fade inputs
B43: Service revenue growth, FY29–31 | C43: % | D43: 0.03 | P43: ASSUMED: roughly the FY28 engine growth; the engines stop at FY28
B44: Vehicle-sales revenue growth, FY29–31 | C44: % | D44: 0 | P44: ASSUMED flat
B45: US insurance unit growth, FY29–31 | C45: % | D45: 0.01 | P45: ASSUMED
B47: Delta Δ to Street and to the engine (FY27E service revenue, legacy, ex-ACV)
B48: JPMorgan 11 Sep 2026 | C48: $M | D48: =Scenarios!$D$108 | P48: VERIFIED, licensed report held locally
B49: Model, selected case | C49: $M | D49: =I10
B50: Δ model − JPM | C50: $M | D50: =D49-D48 | E50: =D50/D48
B51: Engine saved reference (mask 10) / reference + allocation (mask 11, comparable with case 1) | C51: $M | D51: =Scenarios!D120 | E51: =Scenarios!D121 | P51: ENGINE; see Scenarios summary

Sheet 3SM
B1: Copart, Inc. — Three-statement model (3SM), FY2022A–FY2031E ($M; fiscal year ends 31 July)
B2: Revenue = RPM (selected case). Facility operations = fee units × cost per unit. Other lines: Barclays 11 Sep 2026 where published, else FY2026 actual ratio held. Blue = input, black = formula, green = link, red = selector. History = PitchBook / 10-K.
C4: Units | D4: Historicals | I4: Projected | O4: Notes / sources
B5: Income statement | D5: FY2022A | E5: FY2023A | F5: FY2024A | G5: FY2025A | H5: FY2026A | I5: FY2027E | J5: FY2028E | K5: FY2029E | L5: FY2030E | M5: FY2031E
B6: Service revenue | C6: $M | D6: =RPM!D10 | E6: =RPM!E10 | F6: =RPM!F10 | G6: =RPM!G10 | H6: =RPM!H10 | I6: =RPM!I10 | J6: =RPM!J10 | K6: =RPM!K10 | ... M6: =RPM!M10 | O6: RPM row 10: FY24–26 per 10-K; FY27–28 from the engines (selected case, RPM D3); FY29–31 fade (RPM row 43)
B7: Vehicle sales | C7: $M | D7: =RPM!D12 | E7: =RPM!E12 | F7: =RPM!F12 | G7: =RPM!G12 | H7: =RPM!H12 | I7: =RPM!I12 | J7: =RPM!J12 | K7: =RPM!K12 | ... M7: =RPM!M12 | O7: RPM row 12
B8: Total revenue | C8: $M | D8: =RPM!D6 | E8: =RPM!E6 | F8: =RPM!F6 | G8: =RPM!G6 | H8: =RPM!H6 | I8: =RPM!I6 | J8: =RPM!J6 | K8: =RPM!K6 | ... M8: =RPM!M6 | O8: RPM row 6 (history = PitchBook total revenue)
B9: y/y growth | C9: % | D9: – | E9: =IF(D8=0,0,E8/D8-1) | F9: =IF(E8=0,0,F8/E8-1) | G9: =IF(F8=0,0,G8/F8-1) | H9: =IF(G8=0,0,H8/G8-1) | I9: =IF(H8=0,0,I8/H8-1) | J9: =IF(I8=0,0,J8/I8-1) | K9: =IF(J8=0,0,K8/J8-1) | L9: =IF(K8=0,0,L8/K8-1) | M9: =IF(L8=0,0,M8/L8-1)
B10: Facility operations (incl. yard D&A) | C10: $M | D10: ='PB IS (Annual)'!Q19/1000-D11 | E10: ='PB IS (Annual)'!P19/1000-E11 | F10: ='PB IS (Annual)'!O19/1000-F11 | G10: ='PB IS (Annual)'!N19/1000-G11 | H10: ='PB IS (Annual)'!M19/1000-H11 | I10: =I124*I125/1000 | J10: =J124*J125/1000 | K10: =K124*K125/1000 | L10: =L124*L125/1000 | M10: =M124*M125/1000 | O10: History: PitchBook total cost of revenue − cost of vehicle sales (10-K). Projection: global fee units (RPM row 29) × facility cost per unit (schedule 1) — the volume-driven margin lever
B11: Cost of vehicle sales | C11: $M | D11: ='D 10-K FY26'!E56 | E11: ='D 10-K FY26'!D56 | F11: ='D 10-K FY26'!E39 | G11: ='D 10-K FY26'!D39 | H11: ='D 10-K FY26'!C39 | I11: =I7*I127 | J11: =J7*J127 | K11: =K7*K127 | L11: =L7*L127 | M11: =M7*M127 | O11: History: 10-K income statements (FY2026 and FY2024 filings, D 10-K FY26). Projection: vehicle sales × FY2026 ratio (schedule 1)
B12: Gross profit | C12: $M | D12: =D8-D10-D11 | E12: =E8-E10-E11 | F12: =F8-F10-F11 | G12: =G8-G10-G11 | H12: =H8-H10-H11 | I12: =I8-I10-I11 | J12: =J8-J10-J11 | K12: =K8-K10-K11 | ... M12: =M8-M10-M11
B13: Gross margin | C13: % | D13: =IF(D8=0,0,D12/D8) | E13: =IF(E8=0,0,E12/E8) | F13: =IF(F8=0,0,F12/F8) | G13: =IF(G8=0,0,G12/G8) | H13: =IF(H8=0,0,H12/H8) | I13: =IF(I8=0,0,I12/I8) | J13: =IF(J8=0,0,J12/J8) | K13: =IF(K8=0,0,K12/K8) | ... M13: =IF(M8=0,0,M12/M8)
B14: General and administrative (incl. D&A, SBC) | C14: $M | D14: ='PB IS (Annual)'!Q31/1000 | E14: ='PB IS (Annual)'!P31/1000 | F14: ='PB IS (Annual)'!O31/1000 | G14: ='PB IS (Annual)'!N31/1000 | H14: ='PB IS (Annual)'!M31/1000 | I14: =I8*I128 | J14: =J8*J128 | K14: =K8*K128 | L14: =L8*L128 | M14: =M8*M128 | O14: History: PitchBook total operating expenses = 10-K G&A. Projection: revenue × Barclays-implied G&A ratio (schedule 1)
B15: Operating income (EBIT) | C15: $M | D15: =D12-D14 | E15: =E12-E14 | F15: =F12-F14 | G15: =G12-G14 | H15: =H12-H14 | I15: =I12-I14 | J15: =J12-J14 | K15: =K12-K14 | ... M15: =M12-M14
B16: Operating margin | C16: % | D16: =IF(D8=0,0,D15/D8) | E16: =IF(E8=0,0,E15/E8) | F16: =IF(F8=0,0,F15/F8) | G16: =IF(G8=0,0,G15/G8) | H16: =IF(H8=0,0,H15/H8) | I16: =IF(I8=0,0,I15/I8) | J16: =IF(J8=0,0,J15/J8) | K16: =IF(K8=0,0,K15/K8) | ... M16: =IF(M8=0,0,M15/M8)
B17: Depreciation and amortization | C17: $M | D17: ='PB IS (Annual)'!Q93/1000 | E17: ='PB IS (Annual)'!P93/1000 | F17: ='PB IS (Annual)'!O93/1000 | G17: ='PB IS (Annual)'!N93/1000 | H17: ='PB IS (Annual)'!M93/1000 | I17: =I133 | J17: =J133 | K17: =K133 | L17: =L133 | M17: =M133 | O17: History: PitchBook supplemental D&A (10-K). Projection: schedule 2 (Barclays EBITDA − EBIT for FY27–29)
B18: Adjusted EBITDA (EBIT + D&A; Barclays definition) | C18: $M | D18: =D15+D17 | E18: =E15+E17 | F18: =F15+F17 | G18: =G15+G17 | H18: =H15+H17 | I18: =I15+I17 | J18: =J15+J17 | K18: =K15+K17 | ... M18: =M15+M17 | O18: Barclays' "EBITDA (adj)" = EBIT + D&A (FY26: 1,882); no SBC add-back
B19: Adjusted EBITDA margin | C19: % | D19: =IF(D8=0,0,D18/D8) | E19: =IF(E8=0,0,E18/E8) | F19: =IF(F8=0,0,F18/F8) | G19: =IF(G8=0,0,G18/G8) | H19: =IF(H8=0,0,H18/H8) | I19: =IF(I8=0,0,I18/I8) | J19: =IF(J8=0,0,J18/J8) | K19: =IF(K8=0,0,K18/K8) | ... M19: =IF(M8=0,0,M18/M8)
B20: Interest and other income, net | C20: $M | D20: ='PB IS (Annual)'!Q48/1000 | E20: ='PB IS (Annual)'!P48/1000 | F20: ='PB IS (Annual)'!O48/1000 | G20: ='PB IS (Annual)'!N48/1000 | H20: ='PB IS (Annual)'!M48/1000 | I20: =I139 | J20: =J139 | K20: =K139 | L20: =L139 | M20: =M139 | O20: History: PitchBook total non-operating income (interest income, net + other). Projection: yield × opening cash & HTM (schedule 3)
B21: Pre-tax income | C21: $M | D21: =D15+D20 | E21: =E15+E20 | F21: =F15+F20 | G21: =G15+G20 | H21: =H15+H20 | I21: =I15+I20 | J21: =J15+J20 | K21: =K15+K20 | ... M21: =M15+M20
B22: Income tax expense | C22: $M | D22: ='PB IS (Annual)'!Q50/1000 | E22: ='PB IS (Annual)'!P50/1000 | F22: ='PB IS (Annual)'!O50/1000 | G22: ='PB IS (Annual)'!N50/1000 | H22: ='PB IS (Annual)'!M50/1000 | I22: =I21*I23 | J22: =J21*J23 | K22: =K21*K23 | L22: =L21*L23 | M22: =M21*M23 | O22: Projection: pre-tax × structural rate
B23: Effective tax rate | C23: % | D23: =IF(D21=0,0,D22/D21) | E23: =IF(E21=0,0,E22/E21) | F23: =IF(F21=0,0,F22/F21) | G23: =IF(G21=0,0,G22/G21) | H23: =IF(H21=0,0,H22/H21) | I23: ='WACC, Tax, and Reverse DCF'!$N$39 | J23: ='WACC, Tax, and Reverse DCF'!$N$39 | K23: ='WACC, Tax, and Reverse DCF'!$N$39 | L23: ='WACC, Tax, and Reverse DCF'!$N$39 | M23: ='WACC, Tax, and Reverse DCF'!$N$39 | O23: FY27+: structural rate from the tax build (Reverse DCF S29–S33: 21% statutory + state − FDII − option benefit); Barclays-implied 20.3% in schedule 7
B24: Net income (consolidated) | C24: $M | D24: =D21-D22 | E24: =E21-E22 | F24: =F21-F22 | G24: =G21-G22 | H24: =H21-H22 | I24: =I21-I22 | J24: =J21-J22 | K24: =K21-K22 | ... M24: =M21-M22
B25: Net (income) loss attributable to noncontrolling interest | C25: $M | D25: ='PB IS (Annual)'!Q56/1000-'PB IS (Annual)'!Q54/1000 | E25: ='PB IS (Annual)'!P56/1000-'PB IS (Annual)'!P54/1000 | F25: ='PB IS (Annual)'!O56/1000-'PB IS (Annual)'!O54/1000 | G25: ='PB IS (Annual)'!N56/1000-'PB IS (Annual)'!N54/1000 | H25: ='PB IS (Annual)'!M56/1000-'PB IS (Annual)'!M54/1000 | I25: 0 | J25: 0 | K25: 0 | L25: 0 | M25: 0 | O25: History: NI to Copart − consolidated NI (positive = NCI loss added back). Projection: ASSUMED 0 (Barclays ignores NCI; FY26 was +3.9)
B26: Net income attributable to Copart | C26: $M | D26: =D24+D25 | E26: =E24+E25 | F26: =F24+F25 | G26: =G24+G25 | H26: =H24+H25 | I26: =I24+I25 | J26: =J24+J25 | K26: =K24+K25 | ... M26: =M24+M25
B27: Diluted weighted-average shares | C27: M | D27: ='PB IS (Annual)'!Q68/1000000 | E27: ='PB IS (Annual)'!P68/1000000 | F27: ='PB IS (Annual)'!O68/1000000 | G27: ='PB IS (Annual)'!N68/1000000 | H27: ='PB IS (Annual)'!M68/1000000 | I27: =I151 | J27: =J151 | K27: =K151 | L27: =L151 | M27: =M151 | O27: Projection: schedule 5
B28: Diluted EPS | C28: $ | D28: =IF(D27=0,0,D26/D27) | E28: =IF(E27=0,0,E26/E27) | F28: =IF(F27=0,0,F26/F27) | G28: =IF(G27=0,0,G26/G27) | H28: =IF(H27=0,0,H26/H27) | I28: =IF(I27=0,0,I26/I27) | J28: =IF(J27=0,0,J26/J27) | K28: =IF(K27=0,0,K26/K27) | ... M28: =IF(M27=0,0,M26/M27)
B29: y/y growth | C29: % | D29: – | E29: =IF(D28=0,0,E28/D28-1) | F29: =IF(E28=0,0,F28/E28-1) | G29: =IF(F28=0,0,G28/F28-1) | H29: =IF(G28=0,0,H28/G28-1) | I29: =IF(H28=0,0,I28/H28-1) | J29: =IF(I28=0,0,J28/I28-1) | K29: =IF(J28=0,0,K28/J28-1) | L29: =IF(K28=0,0,L28/K28-1) | M29: =IF(L28=0,0,M28/L28-1)
B30: Barclays parity — income statement (Barclays publishes FY2026A–FY2029E only; Δ = 3SM − Barclays)
B31: Barclays revenue | C31: $M | D31: – | E31: – | F31: – | G31: – | H31: ='D Barclays'!D5 | I31: ='D Barclays'!E5 | J31: ='D Barclays'!F5 | K31: ='D Barclays'!G5 | L31: – | M31: – | O31: D Barclays row 5
B32: Δ revenue | C32: $M | D32: – | E32: – | F32: – | G32: – | H32: =H8-H31 | I32: =I8-I31 | J32: =J8-J31 | K32: =K8-K31 | L32: – | M32: –
B33: Barclays adjusted EBITDA | C33: $M | D33: – | E33: – | F33: – | G33: – | H33: ='D Barclays'!D6 | I33: ='D Barclays'!E6 | J33: ='D Barclays'!F6 | K33: ='D Barclays'!G6 | L33: – | M33: –
B34: Δ adjusted EBITDA | C34: $M | D34: – | E34: – | F34: – | G34: – | H34: =H18-H33 | I34: =I18-I33 | J34: =J18-J33 | K34: =K18-K33 | L34: – | M34: –
B35: Barclays EBIT | C35: $M | D35: – | E35: – | F35: – | G35: – | H35: ='D Barclays'!D7 | I35: ='D Barclays'!E7 | J35: ='D Barclays'!F7 | K35: ='D Barclays'!G7 | L35: – | M35: –
B36: Δ EBIT | C36: $M | D36: – | E36: – | F36: – | G36: – | H36: =H15-H35 | I36: =I15-I35 | J36: =J15-J35 | K36: =K15-K35 | L36: – | M36: –
B37: Barclays pre-tax income | C37: $M | D37: – | E37: – | F37: – | G37: – | H37: ='D Barclays'!D8 | I37: ='D Barclays'!E8 | J37: ='D Barclays'!F8 | K37: ='D Barclays'!G8 | L37: – | M37: –
B38: Δ pre-tax income | C38: $M | D38: – | E38: – | F38: – | G38: – | H38: =H21-H37 | I38: =I21-I37 | J38: =J21-J37 | K38: =K21-K37 | L38: – | M38: –
B39: Barclays net income | C39: $M | D39: – | E39: – | F39: – | G39: – | H39: ='D Barclays'!D9 | I39: ='D Barclays'!E9 | J39: ='D Barclays'!F9 | K39: ='D Barclays'!G9 | L39: – | M39: –
B40: Δ net income | C40: $M | D40: – | E40: – | F40: – | G40: – | H40: =H26-H39 | I40: =I26-I39 | J40: =J26-J39 | K40: =K26-K39 | L40: – | M40: –
B41: Barclays diluted EPS | C41: $ | D41: – | E41: – | F41: – | G41: – | H41: ='D Barclays'!D10 | I41: ='D Barclays'!E10 | J41: ='D Barclays'!F10 | K41: ='D Barclays'!G10 | L41: – | M41: –
B42: Δ EPS, % | C42: % | D42: – | E42: – | F42: – | G42: – | H42: =IF(H41=0,0,H28/H41-1) | I42: =IF(I41=0,0,I28/I41-1) | J42: =IF(J41=0,0,J28/J41-1) | K42: =IF(K41=0,0,K28/K41-1) | L42: – | M42: –
B43: Balance sheet | D43: FY2022A | E43: FY2023A | F43: FY2024A | G43: FY2025A | H43: FY2026A | I43: FY2027E | J43: FY2028E | K43: FY2029E | L43: FY2030E | M43: FY2031E
B44: Assets
B45: Cash and cash equivalents | C45: $M | D45: ='PB BS (Annual)'!Q14/1000 | E45: ='PB BS (Annual)'!P14/1000 | F45: ='PB BS (Annual)'!O14/1000 | G45: ='PB BS (Annual)'!N14/1000 | H45: ='PB BS (Annual)'!M14/1000 | I45: =I110 | J45: =J110 | K45: =K110 | L45: =L110 | M45: =M110 | O45: Projection: cash-flow statement ending cash (the plug)
B46: Held-to-maturity securities (Treasury bills) | C46: $M | D46: ='PB BS (Annual)'!Q16/1000 | E46: ='PB BS (Annual)'!P16/1000 | F46: ='PB BS (Annual)'!O16/1000 | G46: ='PB BS (Annual)'!N16/1000 | H46: ='PB BS (Annual)'!M16/1000 | I46: =H46 | J46: =I46 | K46: =J46 | L46: =K46 | M46: =L46 | O46: ASSUMED held flat: no net HTM purchases modelled; all liquidity accrues in cash (same pool for interest income)
B47: Cash & HTM securities | C47: $M | D47: =D45+D46 | E47: =E45+E46 | F47: =F45+F46 | G47: =G45+G46 | H47: =H45+H46 | I47: =I45+I46 | J47: =J45+J46 | K47: =K45+K46 | ... M47: =M45+M46 | O47: Barclays' "cash and equivalents" line combines both (FY26: 4,490)
B48: Accounts receivable, net | C48: $M | D48: ='PB BS (Annual)'!Q28/1000-'PB BS (Annual)'!Q25/1000 | E48: ='PB BS (Annual)'!P28/1000-'PB BS (Annual)'!P25/1000 | F48: ='PB BS (Annual)'!O28/1000-'PB BS (Annual)'!O25/1000 | G48: ='PB BS (Annual)'!N28/1000-'PB BS (Annual)'!N25/1000 | H48: ='PB BS (Annual)'!M28/1000-'PB BS (Annual)'!M25/1000 | I48: =I8*I155/365 | J48: =J8*J155/365 | K48: =K8*K155/365 | L48: =L8*L155/365 | M48: =M8*M155/365 | O48: History: PitchBook trade and other receivables − taxes receivable (= 10-K AR, net). Projection: days of revenue (schedule 6)
B49: Income taxes receivable | C49: $M | D49: ='PB BS (Annual)'!Q25/1000 | E49: ='PB BS (Annual)'!P25/1000 | F49: ='PB BS (Annual)'!O25/1000 | G49: ='PB BS (Annual)'!N25/1000 | H49: ='PB BS (Annual)'!M25/1000 | I49: =H49 | J49: =I49 | K49: =J49 | L49: =K49 | M49: =L49 | O49: ASSUMED held flat
B50: Vehicle pooling costs | C50: $M | D50: ='PB BS (Annual)'!Q31/1000 | E50: ='PB BS (Annual)'!P31/1000 | F50: ='PB BS (Annual)'!O31/1000 | G50: ='PB BS (Annual)'!N31/1000 | H50: ='PB BS (Annual)'!M31/1000 | I50: =I10*I156/365 | J50: =J10*J156/365 | K50: =K10*K156/365 | L50: =L10*L156/365 | M50: =M10*M156/365 | O50: Projection: days of facility operations (schedule 6)
B51: Inventories | C51: $M | D51: ='PB BS (Annual)'!Q19/1000 | E51: ='PB BS (Annual)'!P19/1000 | F51: ='PB BS (Annual)'!O19/1000 | G51: ='PB BS (Annual)'!N19/1000 | H51: ='PB BS (Annual)'!M19/1000 | I51: =I11*I157/365 | J51: =J11*J157/365 | K51: =K11*K157/365 | L51: =L11*L157/365 | M51: =M11*M157/365 | O51: Projection: days of cost of vehicle sales (schedule 6)
B52: Prepaid expenses and other current assets | C52: $M | D52: ='PB BS (Annual)'!Q33/1000 | E52: ='PB BS (Annual)'!P33/1000 | F52: ='PB BS (Annual)'!O33/1000 | G52: ='PB BS (Annual)'!N33/1000 | H52: ='PB BS (Annual)'!M33/1000 | I52: =I8*I158/365 | J52: =J8*J158/365 | K52: =K8*K158/365 | L52: =L8*L158/365 | M52: =M8*M158/365 | O52: Projection: days of revenue (schedule 6)
B53: Other operating assets (Barclays ΔNWC reconciliation) | C53: $M | D53: 0 | E53: 0 | F53: 0 | G53: 0 | H53: 0 | I53: =H53+(I161-I164) | J53: =I53+(J161-J164) | K53: =J53+(K161-K164) | L53: =K53+(L161-L164) | M53: =L53+(M161-M164) | O53: Zero under the days schedule; under the Barclays ΔNWC method it carries the working capital Barclays assumes beyond what the days lines generate, so the balance sheet still balances
B54: Total current assets | C54: $M | D54: =SUM(D45:D53)-D47 | E54: =SUM(E45:E53)-E47 | F54: =SUM(F45:F53)-F47 | G54: =SUM(G45:G53)-G47 | H54: =SUM(H45:H53)-H47 | I54: =SUM(I45:I53)-I47 | J54: =SUM(J45:J53)-J47 | K54: =SUM(K45:K53)-K47 | ... M54: =SUM(M45:M53)-M47
B55: Property and equipment, net (excl. lease ROU) | C55: $M | D55: ='PB BS (Annual)'!Q52/1000-'PB BS (Annual)'!Q46/1000 | E55: ='PB BS (Annual)'!P52/1000-'PB BS (Annual)'!P46/1000 | F55: ='PB BS (Annual)'!O52/1000-'PB BS (Annual)'!O46/1000 | G55: ='PB BS (Annual)'!N52/1000-'PB BS (Annual)'!N46/1000 | H55: ='PB BS (Annual)'!M52/1000-'PB BS (Annual)'!M46/1000 | I55: =I135 | J55: =J135 | K55: =K135 | L55: =L135 | M55: =M135 | O55: History: PitchBook net PP&E − leased assets (= 10-K PP&E, net). Projection: schedule 2
B56: Operating lease right-of-use assets | C56: $M | D56: ='PB BS (Annual)'!Q46/1000 | E56: ='PB BS (Annual)'!P46/1000 | F56: ='PB BS (Annual)'!O46/1000 | G56: ='PB BS (Annual)'!N46/1000 | H56: ='PB BS (Annual)'!M46/1000 | I56: =H56 | J56: =I56 | K56: =J56 | L56: =K56 | M56: =L56 | O56: ASSUMED held flat (Barclays holds lease debt flat at 88)
B57: Goodwill | C57: $M | D57: ='PB BS (Annual)'!Q55/1000 | E57: ='PB BS (Annual)'!P55/1000 | F57: ='PB BS (Annual)'!O55/1000 | G57: ='PB BS (Annual)'!N55/1000 | H57: ='PB BS (Annual)'!M55/1000 | I57: =H57+I173 | J57: =I57+J173 | K57: =J57+K173 | L57: =K57+L173 | M57: =L57+M173 | O57: Flat; rises by the ACV consideration in the close year if the DCF toggle is on (schedule 8)
B58: Intangible assets, net | C58: $M | D58: ='PB BS (Annual)'!Q73/1000-'PB BS (Annual)'!Q55/1000 | E58: ='PB BS (Annual)'!P73/1000-'PB BS (Annual)'!P55/1000 | F58: ='PB BS (Annual)'!O73/1000-'PB BS (Annual)'!O55/1000 | G58: ='PB BS (Annual)'!N73/1000-'PB BS (Annual)'!N55/1000 | H58: ='PB BS (Annual)'!M73/1000-'PB BS (Annual)'!M55/1000 | I58: =H58 | J58: =I58 | K58: =J58 | L58: =K58 | M58: =L58 | O58: ASSUMED held flat (amortisation is carried inside D&A against PP&E)
B59: Other non-current assets | C59: $M | D59: ='PB BS (Annual)'!Q76/1000 | E59: ='PB BS (Annual)'!P76/1000 | F59: ='PB BS (Annual)'!O76/1000 | G59: ='PB BS (Annual)'!N76/1000 | H59: ='PB BS (Annual)'!M76/1000 | I59: =H59 | J59: =I59 | K59: =J59 | L59: =K59 | M59: =L59 | O59: ASSUMED held flat
B60: Total assets | C60: $M | D60: =D54+SUM(D55:D59) | E60: =E54+SUM(E55:E59) | F60: =F54+SUM(F55:F59) | G60: =G54+SUM(G55:G59) | H60: =H54+SUM(H55:H59) | I60: =I54+SUM(I55:I59) | J60: =J54+SUM(J55:J59) | K60: =K54+SUM(K55:K59) | ... M60: =M54+SUM(M55:M59)
B61: Liabilities
B62: Accounts payable, accrued liabilities and deferred revenue | C62: $M | D62: ='PB BS (Annual)'!Q112/1000-'PB BS (Annual)'!Q85/1000-'PB BS (Annual)'!Q98/1000 | E62: ='PB BS (Annual)'!P112/1000-'PB BS (Annual)'!P85/1000-'PB BS (Annual)'!P98/1000 | F62: ='PB BS (Annual)'!O112/1000-'PB BS (Annual)'!O85/1000-'PB BS (Annual)'!O98/1000 | G62: ='PB BS (Annual)'!N112/1000-'PB BS (Annual)'!N85/1000-'PB BS (Annual)'!N98/1000 | H62: ='PB BS (Annual)'!M112/1000-'PB BS (Annual)'!M85/1000-'PB BS (Annual)'!M98/1000 | I62: =(I10+I11+I14-I17)*I159/365 | J62: =(J10+J11+J14-J17)*J159/365 | K62: =(K10+K11+K14-K17)*K159/365 | L62: =(L10+L11+L14-L17)*L159/365 | M62: =(M10+M11+M14-M17)*M159/365 | O62: History: PitchBook total current liabilities − income taxes payable − current lease liabilities (FY26: 634.7 AP & accrued + 32.5 deferred revenue). Projection: days of cash operating costs (schedule 6)
B63: Income taxes payable | C63: $M | D63: ='PB BS (Annual)'!Q85/1000 | E63: ='PB BS (Annual)'!P85/1000 | F63: ='PB BS (Annual)'!O85/1000 | G63: ='PB BS (Annual)'!N85/1000 | H63: ='PB BS (Annual)'!M85/1000 | I63: =H63 | J63: =I63 | K63: =J63 | L63: =K63 | M63: =L63 | O63: ASSUMED held flat
B64: Lease liabilities, current | C64: $M | D64: ='PB BS (Annual)'!Q98/1000 | E64: ='PB BS (Annual)'!P98/1000 | F64: ='PB BS (Annual)'!O98/1000 | G64: ='PB BS (Annual)'!N98/1000 | H64: ='PB BS (Annual)'!M98/1000 | I64: =H64 | J64: =I64 | K64: =J64 | L64: =K64 | M64: =L64 | O64: ASSUMED held flat
B65: Total current liabilities | C65: $M | D65: =SUM(D62:D64) | E65: =SUM(E62:E64) | F65: =SUM(F62:F64) | G65: =SUM(G62:G64) | H65: =SUM(H62:H64) | I65: =SUM(I62:I64) | J65: =SUM(J62:J64) | K65: =SUM(K62:K64) | ... M65: =SUM(M62:M64)
B66: Lease liabilities and debt, non-current | C66: $M | D66: ='PB BS (Annual)'!Q119/1000 | E66: ='PB BS (Annual)'!P119/1000 | F66: ='PB BS (Annual)'!O119/1000 | G66: ='PB BS (Annual)'!N119/1000 | H66: ='PB BS (Annual)'!M119/1000 | I66: =H66 | J66: =I66 | K66: =J66 | L66: =K66 | M66: =L66 | O66: ASSUMED held flat; with the current portion this is Barclays' "debt" of 88
B67: Deferred tax liabilities | C67: $M | D67: ='PB BS (Annual)'!Q121/1000 | E67: ='PB BS (Annual)'!P121/1000 | F67: ='PB BS (Annual)'!O121/1000 | G67: ='PB BS (Annual)'!N121/1000 | H67: ='PB BS (Annual)'!M121/1000 | I67: =H67 | J67: =I67 | K67: =J67 | L67: =K67 | M67: =L67 | O67: ASSUMED held flat
B68: Other non-current liabilities (taxes payable) | C68: $M | D68: ='PB BS (Annual)'!Q125/1000 | E68: ='PB BS (Annual)'!P125/1000 | F68: ='PB BS (Annual)'!O125/1000 | G68: ='PB BS (Annual)'!N125/1000 | H68: ='PB BS (Annual)'!M125/1000 | I68: =H68 | J68: =I68 | K68: =J68 | L68: =K68 | M68: =L68 | O68: ASSUMED held flat
B69: Total liabilities | C69: $M | D69: =D65+SUM(D66:D68) | E69: =E65+SUM(E66:E68) | F69: =F65+SUM(F66:F68) | G69: =G65+SUM(G66:G68) | H69: =H65+SUM(H66:H68) | I69: =I65+SUM(I66:I68) | J69: =J65+SUM(J66:J68) | K69: =K65+SUM(K66:K68) | ... M69: =M65+SUM(M66:M68)
B70: Equity
B71: Copart stockholders' equity | C71: $M | D71: ='PB BS (Annual)'!Q147/1000 | E71: ='PB BS (Annual)'!P147/1000 | F71: ='PB BS (Annual)'!O147/1000 | G71: ='PB BS (Annual)'!N147/1000 | H71: ='PB BS (Annual)'!M147/1000 | I71: =H71+I26+I90+I103+I102 | J71: =I71+J26+J90+J103+J102 | K71: =J71+K26+K90+K103+K102 | L71: =K71+L26+L90+L103+L102 | M71: =L71+M26+M90+M103+M102 | O71: Projection: prior + net income to Copart + SBC + option proceeds − repurchases (no OCI movement assumed)
B72: Noncontrolling interest | C72: $M | D72: ='PB BS (Annual)'!Q148/1000 | E72: ='PB BS (Annual)'!P148/1000 | F72: ='PB BS (Annual)'!O148/1000 | G72: ='PB BS (Annual)'!N148/1000 | H72: ='PB BS (Annual)'!M148/1000 | I72: =H72-I25 | J72: =I72-J25 | K72: =J72-K25 | L72: =K72-L25 | M72: =L72-M25 | O72: Projection: prior less the NCI loss carried on the income statement (0 by assumption)
B73: Total equity | C73: $M | D73: =D71+D72 | E73: =E71+E72 | F73: =F71+F72 | G73: =G71+G72 | H73: =H71+H72 | I73: =I71+I72 | J73: =J71+J72 | K73: =K71+K72 | ... M73: =M71+M72
B74: Total liabilities and equity | C74: $M | D74: =D69+D73 | E74: =E69+E73 | F74: =F69+F73 | G74: =G69+G73 | H74: =H69+H73 | I74: =I69+I73 | J74: =J69+J73 | K74: =K69+K73 | ... M74: =M69+M73
B75: Balance check (assets − liabilities and equity; should be 0) | C75: $M | D75: =ROUND(D60-D74,3) | E75: =ROUND(E60-E74,3) | F75: =ROUND(F60-F74,3) | G75: =ROUND(G60-G74,3) | H75: =ROUND(H60-H74,3) | I75: =ROUND(I60-I74,3) | J75: =ROUND(J60-J74,3) | K75: =ROUND(K60-K74,3) | ... M75: =ROUND(M60-M74,3)
B76: Barclays parity — balance sheet
B77: Debt, Barclays definition (lease liabilities, current + non-current) | C77: $M | D77: =D64+D66 | E77: =E64+E66 | F77: =F64+F66 | G77: =G64+G66 | H77: =H64+H66 | I77: =I64+I66 | J77: =J64+J66 | K77: =K64+K66 | ... M77: =M64+M66
B78: Barclays cash and equivalents | C78: $M | D78: – | E78: – | F78: – | G78: – | H78: ='D Barclays'!D12 | I78: ='D Barclays'!E12 | J78: ='D Barclays'!F12 | K78: ='D Barclays'!G12 | L78: – | M78: –
B79: Δ cash & HTM | C79: $M | D79: – | E79: – | F79: – | G79: – | H79: =H47-H78 | I79: =I47-I78 | J79: =J47-J78 | K79: =K47-K78 | L79: – | M79: –
B80: Barclays total assets | C80: $M | D80: – | E80: – | F80: – | G80: – | H80: ='D Barclays'!D13 | I80: ='D Barclays'!E13 | J80: ='D Barclays'!F13 | K80: ='D Barclays'!G13 | L80: – | M80: –
B81: Δ total assets | C81: $M | D81: – | E81: – | F81: – | G81: – | H81: =H60-H80 | I81: =I60-I80 | J81: =J60-J80 | K81: =K60-K80 | L81: – | M81: –
B82: Barclays debt | C82: $M | D82: – | E82: – | F82: – | G82: – | H82: ='D Barclays'!D14 | I82: ='D Barclays'!E14 | J82: ='D Barclays'!F14 | K82: ='D Barclays'!G14 | L82: – | M82: –
B83: Δ debt | C83: $M | D83: – | E83: – | F83: – | G83: – | H83: =H77-H82 | I83: =I77-I82 | J83: =J77-J82 | K83: =K77-K82 | L83: – | M83: –
B84: Barclays shareholders' equity | C84: $M | D84: – | E84: – | F84: – | G84: – | H84: ='D Barclays'!D16 | I84: ='D Barclays'!E16 | J84: ='D Barclays'!F16 | K84: ='D Barclays'!G16 | L84: – | M84: –
B85: Δ Copart stockholders' equity | C85: $M | D85: – | E85: – | F85: – | G85: – | H85: =H71-H84 | I85: =I71-I84 | J85: =J71-J84 | K85: =K71-K84 | L85: – | M85: –
B86: Cash flow statement | D86: FY2022A | E86: FY2023A | F86: FY2024A | G86: FY2025A | H86: FY2026A | I86: FY2027E | J86: FY2028E | K86: FY2029E | L86: FY2030E | M86: FY2031E
B87: Operating activities
B88: Net income (consolidated) | C88: $M | D88: ='PB CF (Annual)'!Q14/1000 | E88: ='PB CF (Annual)'!P14/1000 | F88: ='PB CF (Annual)'!O14/1000 | G88: ='PB CF (Annual)'!N14/1000 | H88: ='PB CF (Annual)'!M14/1000 | I88: =I24 | J88: =J24 | K88: =K24 | L88: =L24 | M88: =M24
B89: (+) Depreciation and amortization | C89: $M | D89: ='PB CF (Annual)'!Q17/1000 | E89: ='PB CF (Annual)'!P17/1000 | F89: ='PB CF (Annual)'!O17/1000 | G89: ='PB CF (Annual)'!N17/1000 | H89: ='PB CF (Annual)'!M17/1000 | I89: =I17 | J89: =J17 | K89: =K17 | L89: =L17 | M89: =M17 | O89: History: cash-flow D&A incl. debt-cost amortisation (FY26 238.5 vs 229.4 on the income statement)
B90: (+) Stock-based compensation | C90: $M | D90: ='PB CF (Annual)'!Q20/1000 | E90: ='PB CF (Annual)'!P20/1000 | F90: ='PB CF (Annual)'!O20/1000 | G90: ='PB CF (Annual)'!N20/1000 | H90: ='PB CF (Annual)'!M20/1000 | I90: =I142 | J90: =J142 | K90: =K142 | L90: =L142 | M90: =M142 | O90: Projection: schedule 4
B91: (+) Other non-cash items (deferred taxes, disposals, other) | C91: $M | D91: ='PB CF (Annual)'!Q35/1000-'PB CF (Annual)'!Q17/1000-'PB CF (Annual)'!Q20/1000 | E91: ='PB CF (Annual)'!P35/1000-'PB CF (Annual)'!P17/1000-'PB CF (Annual)'!P20/1000 | F91: ='PB CF (Annual)'!O35/1000-'PB CF (Annual)'!O17/1000-'PB CF (Annual)'!O20/1000 | G91: ='PB CF (Annual)'!N35/1000-'PB CF (Annual)'!N17/1000-'PB CF (Annual)'!N20/1000 | H91: ='PB CF (Annual)'!M35/1000-'PB CF (Annual)'!M17/1000-'PB CF (Annual)'!M20/1000 | I91: 0 | J91: 0 | K91: 0 | L91: 0 | M91: 0 | O91: ASSUMED 0 in projection (FY26: 54.4, mostly deferred taxes)
B92: (−) Change in operating working capital | C92: $M | D92: ='PB CF (Annual)'!Q55/1000 | E92: ='PB CF (Annual)'!P55/1000 | F92: ='PB CF (Annual)'!O55/1000 | G92: ='PB CF (Annual)'!N55/1000 | H92: ='PB CF (Annual)'!M55/1000 | I92: =I164 | J92: =J164 | K92: =K164 | L92: =L164 | M92: =M164 | O92: Projection: selected method (schedule 6; default = Barclays −83 a year)
B93: Cash flow from operations | C93: $M | D93: =SUM(D88:D92) | E93: =SUM(E88:E92) | F93: =SUM(F88:F92) | G93: =SUM(G88:G92) | H93: =SUM(H88:H92) | I93: =SUM(I88:I92) | J93: =SUM(J88:J92) | K93: =SUM(K88:K92) | ... M93: =SUM(M88:M92)
B94: Investing activities
B95: (−) Purchases of property and equipment | C95: $M | D95: ='PB CF (Annual)'!Q64/1000 | E95: ='PB CF (Annual)'!P64/1000 | F95: ='PB CF (Annual)'!O64/1000 | G95: ='PB CF (Annual)'!N64/1000 | H95: ='PB CF (Annual)'!M64/1000 | I95: =I131 | J95: =J131 | K95: =K131 | L95: =L131 | M95: =M131 | O95: Projection: schedule 2 (Barclays −500 a year FY27–29)
B96: (+) Proceeds from disposals of property and equipment | C96: $M | D96: ='PB CF (Annual)'!Q65/1000 | E96: ='PB CF (Annual)'!P65/1000 | F96: ='PB CF (Annual)'!O65/1000 | G96: ='PB CF (Annual)'!N65/1000 | H96: ='PB CF (Annual)'!M65/1000 | I96: 0 | J96: 0 | K96: 0 | L96: 0 | M96: 0 | O96: ASSUMED 0
B97: (−) Acquisitions and investments in businesses (ACV if toggled) | C97: $M | D97: ='PB CF (Annual)'!Q70/1000+'PB CF (Annual)'!Q73/1000 | E97: ='PB CF (Annual)'!P70/1000+'PB CF (Annual)'!P73/1000 | F97: ='PB CF (Annual)'!O70/1000+'PB CF (Annual)'!O73/1000 | G97: ='PB CF (Annual)'!N70/1000+'PB CF (Annual)'!N73/1000 | H97: ='PB CF (Annual)'!M70/1000+'PB CF (Annual)'!M73/1000 | I97: =-I173 | J97: =-J173 | K97: =-K173 | L97: =-L173 | M97: =-M173 | O97: Projection: ACV cash consideration in the close year when the DCF toggle is on (schedule 8)
B98: (−) Net purchases of held-to-maturity securities | C98: $M | D98: ='PB CF (Annual)'!Q77/1000 | E98: ='PB CF (Annual)'!P77/1000 | F98: ='PB CF (Annual)'!O77/1000 | G98: ='PB CF (Annual)'!N77/1000 | H98: ='PB CF (Annual)'!M77/1000 | I98: 0 | J98: 0 | K98: 0 | L98: 0 | M98: 0 | O98: ASSUMED 0: HTM held flat (balance sheet)
B99: Other investing | C99: $M | D99: ='PB CF (Annual)'!Q84/1000-(D95+D96+D97+D98) | E99: ='PB CF (Annual)'!P84/1000-(E95+E96+E97+E98) | F99: ='PB CF (Annual)'!O84/1000-(F95+F96+F97+F98) | G99: ='PB CF (Annual)'!N84/1000-(G95+G96+G97+G98) | H99: ='PB CF (Annual)'!M84/1000-(H95+H96+H97+H98) | I99: 0 | J99: 0 | K99: 0 | L99: 0 | M99: 0 | O99: History: residual to PitchBook total investing cash flow
B100: Cash flow from investing | C100: $M | D100: =SUM(D95:D99) | E100: =SUM(E95:E99) | F100: =SUM(F95:F99) | G100: =SUM(G95:G99) | H100: =SUM(H95:H99) | I100: =SUM(I95:I99) | J100: =SUM(J95:J99) | K100: =SUM(K95:K99) | ... M100: =SUM(M95:M99)
B101: Financing activities
...

Sheet DCF
B1: Copart, Inc. — Discounted Cash Flow
B2: Fiscal year ends 31 July. $M unless noted. Historicals link to PitchBook tabs; revenue links to RPM.
C4: Units | D4: Historicals | I4: Projected
B5: Income statement | D5: FY2022A | E5: FY2023A | F5: FY2024A | G5: FY2025A | H5: FY2026A | I5: FY2027E | J5: FY2028E | K5: FY2029E | L5: FY2030E | M5: FY2031E | N5: FY26–31 CAGR
B6: Revenue | C6: $M | D6: =RPM!D6 | E6: =RPM!E6 | F6: =RPM!F6 | G6: =RPM!G6 | H6: =RPM!H6 | I6: =RPM!I6 | J6: =RPM!J6 | K6: =RPM!K6 | ... M6: =RPM!M6 | N6: =(M6/H6)^(1/5)-1
B7: y/y growth | C7: % | D7: -- | E7: =E6/D6-1 | F7: =F6/E6-1 | G7: =G6/F6-1 | H7: =H6/G6-1 | I7: =I6/H6-1 | J7: =J6/I6-1 | K7: =K6/J6-1 | L7: =L6/K6-1 | M7: =M6/L6-1
B8: of which service revenue | C8: $M | D8: =RPM!D10 | E8: =RPM!E10 | F8: =RPM!F10 | G8: =RPM!G10 | H8: =RPM!H10 | I8: =RPM!I10 | J8: =RPM!J10 | K8: =RPM!K10 | ... M8: =RPM!M10 | P8: Copart doesn't own car
B9: of which vehicle sales | C9: $M | D9: =RPM!D12 | E9: =RPM!E12 | F9: =RPM!F12 | G9: =RPM!G12 | H9: =RPM!H12 | I9: =RPM!I12 | J9: =RPM!J12 | K9: =RPM!K12 | ... M9: =RPM!M12 | P9: Copart buys & resells car
B11: Global fee units | C11: 000s | F11: =RPM!F29 | G11: =RPM!G29 | H11: =RPM!H29 | I11: =RPM!I29 | J11: =RPM!J29 | K11: =RPM!K29 | L11: =RPM!L29 | M11: =RPM!M29 | P11: # of times Copart sold through auctions
B13: Facility operations (cost of service revenue, incl. yard D&A) | C13: $M | D13: 1275.5 | E13: 1462.6 | F13: 1653.8 | G13: 1944.3 | H13: 1965.9 | I13: =I11*I14/1000 | J13: =J11*J14/1000 | K13: =K11*K14/1000 | L13: =L11*L14/1000 | M13: =M11*M14/1000
B14: Facility cost per fee unit | C14: $ | F14: =F13*1000/F11 | G14: =G13*1000/G11 | H14: =H13*1000/H11 | I14: =H14*(1+I15) | J14: =I14*(1+J15) | K14: =J14*(1+K15) | L14: =K14*(1+L15) | M14: =L14*(1+M15) | P14: facility ops / # of cars. If Copart handles fewer cars but yard costs stay the same, cost/car rises
B15: Facility cost per unit, y/y | C15: % | G15: =G14/F14-1 | H15: =H14/G14-1 | I15: 0.045 | J15: 0.025 | K15: 0.02 | L15: 0.02 | M15: 0.02
B16: Cost of vehicle sales | C16: $M | D16: 619.2 | E16: 669.9 | F16: 675.8 | G16: 603 | H16: 616.5 | I16: =I9*I17 | J16: =J9*J17 | K16: =K9*K17 | L16: =L9*L17 | M16: =M9*M17
B17: as % of vehicle sales | C17: % | D17: =D16/D9 | E17: =E16/E9 | F17: =F16/F9 | G17: =G16/G9 | H17: =H16/H9 | I17: 0.885 | J17: 0.885 | K17: 0.885 | L17: 0.885 | M17: 0.885
B18: Gross profit | C18: $M | D18: =D6-D13-D16 | E18: =E6-E13-E16 | F18: =F6-F13-F16 | G18: =G6-G13-G16 | H18: =H6-H13-H16 | I18: =I6-I13-I16 | J18: =J6-J13-J16 | K18: =K6-K13-K16 | ... M18: =M6-M13-M16 | N18: =(M18/H18)^(1/5)-1
B19: Gross margin | C19: % | D19: =D18/D6 | E19: =E18/E6 | F19: =F18/F6 | G19: =G18/G6 | H19: =H18/H6 | I19: =I18/I6 | J19: =J18/J6 | K19: =K18/K6 | ... M19: =M18/M6
B21: General & administrative (incl. D&A, SBC) | C21: $M | D21: ='PB IS (Annual)'!Q31/1000 | E21: ='PB IS (Annual)'!P31/1000 | F21: ='PB IS (Annual)'!O31/1000 | G21: ='PB IS (Annual)'!N31/1000 | H21: ='PB IS (Annual)'!M31/1000 | I21: =H21*(1+I22) | J21: =I21*(1+J22) | K21: =J21*(1+K22) | L21: =K21*(1+L22) | M21: =L21*(1+M22)
B22: G&A growth, y/y | C22: % | E22: =E21/D21-1 | F22: =F21/E21-1 | G22: =G21/F21-1 | H22: =H21/G21-1 | I22: 0.07 | J22: 0.05 | K22: 0.04 | L22: 0.04 | M22: 0.04
B23: as % of revenue | C23: % | D23: =D21/D6 | E23: =E21/E6 | F23: =F21/F6 | G23: =G21/G6 | H23: =H21/H6 | I23: =I21/I6 | J23: =J21/J6 | K23: =K21/K6 | ... M23: =M21/M6
B24: Operating income (EBIT) | C24: $M | D24: =D18-D21 | E24: =E18-E21 | F24: =F18-F21 | G24: =G18-G21 | H24: =H18-H21 | I24: =I18-I21 | J24: =J18-J21 | K24: =K18-K21 | ... M24: =M18-M21 | N24: =(M24/H24)^(1/5)-1
B25: Operating margin | C25: % | D25: =D24/D6 | E25: =E24/E6 | F25: =F24/F6 | G25: =G24/G6 | H25: =H24/H6 | I25: =I24/I6 | J25: =J24/J6 | K25: =K24/K6 | ... M25: =M24/M6
B26: y/y growth | C26: % | D26: -- | E26: =E24/D24-1 | F26: =F24/E24-1 | G26: =G24/F24-1 | H26: =H24/G24-1 | I26: =I24/H24-1 | J26: =J24/I24-1 | K26: =K24/J24-1 | L26: =L24/K24-1 | M26: =M24/L24-1
B27: check vs pitchBook operating profit | C27: $M | D27: =D24-'PB IS (Annual)'!Q32/1000 | E27: =E24-'PB IS (Annual)'!P32/1000 | F27: =F24-'PB IS (Annual)'!O32/1000 | G27: =G24-'PB IS (Annual)'!N32/1000 | H27: =H24-'PB IS (Annual)'!M32/1000
B29: Depreciation & amortization | C29: $M | D29: ='PB CF (Annual)'!Q18/1000 | E29: ='PB CF (Annual)'!P18/1000 | F29: ='PB CF (Annual)'!O18/1000 | G29: ='PB CF (Annual)'!N18/1000 | H29: ='PB CF (Annual)'!M18/1000 | I29: ='3SM'!I17 | J29: ='3SM'!J17 | K29: ='3SM'!K17 | L29: ='3SM'!L17 | M29: ='3SM'!M17 | P29: From the 3SM row 17 (Barclays D&A FY27–29; FY30–31 at the FY29 rate); row 30 is now the implied %
B30: as % of revenue | C30: % | D30: =D29/D6 | E30: =E29/E6 | F30: =F29/F6 | G30: =G29/G6 | H30: =H29/H6 | I30: =I29/I6 | J30: =J29/J6 | K30: =K29/K6 | ... M30: =M29/M6
B31: EBITDA | C31: $M | D31: =D24+D29 | E31: =E24+E29 | F31: =F24+F29 | G31: =G24+G29 | H31: =H24+H29 | I31: =I24+I29 | J31: =J24+J29 | K31: =K24+K29 | ... M31: =M24+M29 | N31: =(M31/H31)^(1/5)-1
B32: EBITDA margin | C32: % | D32: =D31/D6 | E32: =E31/E6 | F32: =F31/F6 | G32: =G31/G6 | H32: =H31/H6 | I32: =I31/I6 | J32: =J31/J6 | K32: =K31/K6 | ... M32: =M31/M6
B34: Interest & other income | C34: $M | D34: ='PB IS (Annual)'!Q48/1000 | E34: ='PB IS (Annual)'!P48/1000 | F34: ='PB IS (Annual)'!O48/1000 | G34: ='PB IS (Annual)'!N48/1000 | H34: ='PB IS (Annual)'!M48/1000 | I34: =H72*I35 | J34: =I72*J35 | K34: =J72*K35 | L34: =K72*L35 | M34: =L72*M35 | P34: Yield on Copart's $4.5b in Treasury bills
B35: Yield on cash & HTM securities | C35: % | I35: 0.036 | J35: 0.034 | K35: 0.033 | L35: 0.033 | M35: 0.033
B36: Pre-tax income | C36: $M | D36: =D24+D34 | E36: =E24+E34 | F36: =F24+F34 | G36: =G24+G34 | H36: =H24+H34 | I36: =I24+I34 | J36: =J24+J34 | K36: =K24+K34 | ... M36: =M24+M34
B37: Income tax | C37: $M | D37: ='PB IS (Annual)'!Q50/1000 | E37: ='PB IS (Annual)'!P50/1000 | F37: ='PB IS (Annual)'!O50/1000 | G37: ='PB IS (Annual)'!N50/1000 | H37: ='PB IS (Annual)'!M50/1000 | I37: =I36*I38 | J37: =J36*J38 | K37: =K36*K38 | L37: =L36*L38 | M37: =M36*M38
B38: Effective tax rate | C38: % | D38: =D37/D36 | E38: =E37/E36 | F38: =F37/F36 | G38: =G37/G36 | H38: =H37/H36 | I38: ='WACC, Tax, and Reverse DCF'!$N$39 | J38: ='WACC, Tax, and Reverse DCF'!$N$39 | K38: ='WACC, Tax, and Reverse DCF'!$N$39 | L38: ='WACC, Tax, and Reverse DCF'!$N$39 | M38: ='WACC, Tax, and Reverse DCF'!$N$39 | P38: FY27+ = structural effective rate from the tax build (Reverse DCF R28–R36)
B39: Net income | C39: $M | D39: ='PB IS (Annual)'!Q56/1000 | E39: ='PB IS (Annual)'!P56/1000 | F39: ='PB IS (Annual)'!O56/1000 | G39: ='PB IS (Annual)'!N56/1000 | H39: ='PB IS (Annual)'!M56/1000 | I39: =I36-I37 | J39: =J36-J37 | K39: =K36-K37 | L39: =L36-L37 | M39: =M36-M37 | N39: =(M39/H39)^(1/5)-1
B40: Diluted shares | C40: M | D40: ='PB IS (Annual)'!Q68/1000000 | E40: ='PB IS (Annual)'!P68/1000000 | F40: ='PB IS (Annual)'!O68/1000000 | G40: ='PB IS (Annual)'!N68/1000000 | H40: ='PB IS (Annual)'!M68/1000000 | I40: =H40-I69/I70 | J40: =I40-J69/J70 | K40: =J40-K69/K70 | L40: =K40-L69/L70 | M40: =L40-M69/M70
B41: Diluted EPS | C41: $ | D41: =D39/D40 | E41: =E39/E40 | F41: =F39/F40 | G41: =G39/G40 | H41: =H39/H40 | I41: =I39/I40 | J41: =J39/J40 | K41: =K39/K40 | ... M41: =M39/M40 | N41: =(M41/H41)^(1/5)-1
B42: y/y growth | C42: % | D42: -- | E42: =E41/D41-1 | F42: =F41/E41-1 | G42: =G41/F41-1 | H42: =H41/G41-1 | I42: =I41/H41-1 | J42: =J41/I41-1 | K42: =K41/J41-1 | L42: =L41/K41-1 | M42: =M41/L41-1
B44: Street EPS
B45: Barclays (UW, $25) -- 11 Sep 2026 | C45: $ | H45: 1.55 | I45: 1.56 | J45: 1.64 | K45: 1.72
B46: Model vs. Barclays | C46: % | I46: =I41/I45-1 | J46: =J41/J45-1
B48: Unlevered free cash flow
B49: EBIT | C49: $M | D49: =D24 | E49: =E24 | F49: =F24 | G49: =G24 | H49: =H24 | I49: =I24 | J49: =J24 | K49: =K24 | ... M49: =M24
B50: (−) Taxes on EBIT | C50: $M | D50: =-D24*D38 | E50: =-E24*E38 | F50: =-F24*F38 | G50: =-G24*G38 | H50: =-H24*H38 | I50: =-I24*I38 | J50: =-J24*J38 | K50: =-K24*K38 | ... M50: =-M24*M38
B51: NOPAT | C51: $M | D51: =D49+D50 | E51: =E49+E50 | F51: =F49+F50 | G51: =G49+G50 | H51: =H49+H50 | I51: =I49+I50 | J51: =J49+J50 | K51: =K49+K50 | ... M51: =M49+M50
B52: (+) D&A | C52: $M | D52: =D29 | E52: =E29 | F52: =F29 | G52: =G29 | H52: =H29 | I52: =I29 | J52: =J29 | K52: =K29 | ... M52: =M29
B53: (+) Stock-based compensation | C53: $M | D53: ='PB CF (Annual)'!Q20/1000 | E53: ='PB CF (Annual)'!P20/1000 | F53: ='PB CF (Annual)'!O20/1000 | G53: ='PB CF (Annual)'!N20/1000 | H53: ='PB CF (Annual)'!M20/1000 | I53: ='3SM'!I90 | J53: ='3SM'!J90 | K53: ='3SM'!K90 | L53: ='3SM'!L90 | M53: ='3SM'!M90 | P53: From the 3SM row 90 (FY26 % of revenue held); row 58 implied
B54: as % of revenue | C54: % | D54: =D53/D6 | E54: =E53/E6 | F54: =F53/F6 | G54: =G53/G6 | H54: =H53/H6 | I54: =I53/I6 | J54: =J53/J6 | K54: =K53/K6 | ... M54: =M53/M6
B55: (−) Capital expenditures | C55: $M | D55: ='PB CF (Annual)'!Q64/1000 | E55: ='PB CF (Annual)'!P64/1000 | F55: ='PB CF (Annual)'!O64/1000 | G55: ='PB CF (Annual)'!N64/1000 | H55: ='PB CF (Annual)'!M64/1000 | I55: ='3SM'!I95 | J55: ='3SM'!J95 | K55: ='3SM'!K95 | L55: ='3SM'!L95 | M55: ='3SM'!M95 | P55: From the 3SM row 95 (Barclays −500 FY27–29; FY29 ratio after); row 60 implied
B56: as % of revenue | C56: % | D56: =-D55/D6 | E56: =-E55/E6 | F56: =-F55/F6 | G56: =-G55/G6 | H56: =-H55/H6 | I56: =-I55/I6 | J56: =-J55/J6 | K56: =-K55/K6 | ... M56: =-M55/M6
B57: (−) Increase in net working capital | C57: $M | D57: ='PB CF (Annual)'!Q55/1000 | E57: ='PB CF (Annual)'!P55/1000 | F57: ='PB CF (Annual)'!O55/1000 | G57: ='PB CF (Annual)'!N55/1000 | H57: ='PB CF (Annual)'!M55/1000 | I57: ='3SM'!I92 | J57: ='3SM'!J92 | K57: ='3SM'!K92 | L57: ='3SM'!L92 | M57: ='3SM'!M92 | P57: From the 3SM row 92 (selected ΔNWC method, 3SM D163); row 62 implied
B58: Increase in NWC as % of revenue (reads the 3SM) | C58: % | I58: =-I57/I6 | J58: =-J57/J6 | K58: =-K57/K6 | L58: =-L57/L6 | M58: =-M57/M6
B59: Unlevered free cash flow | C59: $M | D59: =D51+D52+D53+D55+D57 | E59: =E51+E52+E53+E55+E57 | F59: =F51+F52+F53+F55+F57 | G59: =G51+G52+G53+G55+G57 | H59: =H51+H52+H53+H55+H57 | I59: =I51+I52+I53+I55+I57 | J59: =J51+J52+J53+J55+J57 | K59: =K51+K52+K53+K55+K57 | ... M59: =M51+M52+M53+M55+M57 | N59: =(M59/H59)^(1/5)-1
B60: FCF conversion (UFCF / EBITDA) | C60: % | D60: =D59/D31 | E60: =E59/E31 | F60: =F59/F31 | G60: =G59/G31 | H60: =H59/H31 | I60: =I59/I31 | J60: =J59/J31 | K60: =K59/K31 | ... M60: =M59/M31
B62: Discount period (30 Sep 2026) | C62: yrs | I62: 0.42 | J62: 1.42 | K62: 2.42 | L62: 3.42 | M62: 4.42
B63: Discount factor | C63: x | I63: =1/(1+'WACC, Tax, and Reverse DCF'!N31)^I62 | J63: =1/(1+'WACC, Tax, and Reverse DCF'!N31)^J62 | K63: =1/(1+'WACC, Tax, and Reverse DCF'!N31)^K62 | L63: =1/(1+'WACC, Tax, and Reverse DCF'!N31)^L62 | M63: =1/(1+'WACC, Tax, and Reverse DCF'!N31)^M62
B64: PV of UFCF | C64: $M | I64: =I59*I63 | J64: =J59*J63 | K64: =K59*K63 | L64: =L59*L63 | M64: =M59*M63
B66: Cash roll-forward (for interest income; simplified) | P66: to calculate interest income
B67: Beginning cash & investments | C67: $M | I67: =H72 | J67: =I72 | K67: =J72 | L67: =K72 | M67: =L72 | P67: beginnning cash + cash inflow - share buybacks - ACV acquisition
B68: (+) UFCF + after-tax interest | C68: $M | I68: =I59+I34*(1-I38) | J68: =J59+J34*(1-J38) | K68: =K59+K34*(1-K38) | L68: =L59+L34*(1-L38) | M68: =M59+M34*(1-M38)
B69: (−) Share repurchases | C69: $M | H69: 1632.5 | I69: 600 | J69: 600 | K69: 600 | L69: 600 | M69: 600
B70: Average repurchase price | C70: $ | H70: 37.6 | I70: 32 | J70: 34 | K70: 36 | L70: 38 | M70: 40
B71: (−) ACV Auctions acquisition (toggle) | C71: $M | I71: =IF(AND($H$100=1,I$5=$I$102),$H$101,0) | J71: =IF(AND($H$100=1,J$5=$I$102),$H$101,0) | K71: =IF(AND($H$100=1,K$5=$I$102),$H$101,0) | L71: =IF(AND($H$100=1,L$5=$I$102),$H$101,0) | M71: =IF(AND($H$100=1,M$5=$I$102),$H$101,0) | P71: can be toggled to consider/ignore -- H115
B72: Ending cash & investments | C72: $M | H72: =Cover!D12 | I72: =I67+I68-I69-I71 | J72: =J67+J68-J69-J71 | K72: =K67+K68-K69-K71 | L72: =L67+L68-L69-L71 | M72: =M67+M68-M69-M71 | P72: Opening cash & HTM from the Cover key statistics
B75: Terminal value & valuation
B76: Method (1 = exit multiple, 2 = perpetuity growth) | H76: 1
B77: Exit EV / EBITDA multiple | H77: 10
B78: Perpetuity growth rate | H78: 0.03
B79: Terminal year EBITDA (FY2031E) | H79: =M31
B80: Terminal year UFCF (FY2031E) | H80: =M59
B81: Terminal value -- exit multiple | H81: =H77*H79
B82: Terminal value -- perpetuity | H82: =H80*(1+H78)/('WACC, Tax, and Reverse DCF'!N31-H78)
B83: Terminal value (selected) | H83: =IF(H76=1,H81,H82)
B84: implied exit multiple / implied perpetuity growth | G84: =H83/H79 | H84: =(H83*'WACC, Tax, and Reverse DCF'!N31-H80)/(H83+H80)
B85: PV of terminal value | H85: =H83*M63
B86: PV of explicit UFCF (FY27-FY31) | H86: =SUM(I64:M64)
B87: Enterprise value | H87: =H85+H86
B88: terminal value as % of EV | H88: =H85/H87
B90: Equity bridge
B91: Enterprise value | H91: =H87
B92: (+) Cash & HTM securities, 31 Jul 2026 | H92: =Cover!D12 | P92: Rows 107–109, 112 and 118 read the Cover key statistics (cash & HTM, lease debt, NCI, fully diluted shares, price)
B93: (−) Total debt (finance leases) | H93: =-Cover!D13
B94: (−) Non-controlling interest | H94: =-Cover!D14
B95: (−) ACV Auctions cash consideration (if toggle on and not yet closed) | H95: =-IF(H100=1,H101,0)
B96: Equity value | H96: =SUM(H91:H95)
B97: Fully diluted shares (M) — Cover key statistics | H97: =Cover!D15
B98: Implied share price | H98: =H96/H97
B99: Upside / (downside) vs. current | H99: =H98/H103-1
B100: ACV toggle (1 = include cash outflow) | H100: 1
B101: ACV consideration ($M) | H101: 1900
B102: ACV closes in fiscal year | I102: FY2027E
B103: Current share price (26 Sep 2026) | H103: =Cover!D6 | P103: Type the price on the Cover (D6), not here
B104: Current market cap / EV | G104: =H103*H97 | H104: =G104-H92-H93-H94
B105: Current P/E (FY26A) / EV/EBITDA (FY26A) | G105: =H103/H41 | H105: =H104/H31
B107: Sensitivity -- implied share price: exit multiple (down) x WACC (across)
B108: Exit multiple \ WACC | D108: ='WACC, Tax, and Reverse DCF'!$N$31+(-0.01) | E108: ='WACC, Tax, and Reverse DCF'!$N$31+(-0.005) | F108: ='WACC, Tax, and Reverse DCF'!$N$31+(0) | G108: ='WACC, Tax, and Reverse DCF'!$N$31+(0.005) | H108: ='WACC, Tax, and Reverse DCF'!$N$31+(0.01)
C109: 8 | D109: =(($C109*$H$79)/(1+D$108)^$M$62+SUMPRODUCT($I$59:$M$59,1/(1+D$108)^$I$62:$M$62)+$H$92+$H$93+$H$94+$H$95)/$H$97 | E109: =(($C109*$H$79)/(1+E$108)^$M$62+SUMPRODUCT($I$59:$M$59,1/(1+E$108)^$I$62:$M$62)+$H$92+$H$93+$H$94+$H$95)/$H$97 | F109: =(($C109*$H$79)/(1+F$108)^$M$62+SUMPRODUCT($I$59:$M$59,1/(1+F$108)^$I$62:$M$62)+$H$92+$H$93+$H$94+$H$95)/$H$97 | G109: =(($C109*$H$79)/(1+G$108)^$M$62+SUMPRODUCT($I$59:$M$59,1/(1+G$108)^$I$62:$M$62)+$H$92+$H$93+$H$94+$H$95)/$H$97 | H109: =(($C109*$H$79)/(1+H$108)^$M$62+SUMPRODUCT($I$59:$M$59,1/(1+H$108)^$I$62:$M$62)+$H$92+$H$93+$H$94+$H$95)/$H$97
C110: 10 | D110: =(($C110*$H$79)/(1+D$108)^$M$62+SUMPRODUCT($I$59:$M$59,1/(1+D$108)^$I$62:$M$62)+$H$92+$H$93+$H$94+$H$95)/$H$97 | E110: =(($C110*$H$79)/(1+E$108)^$M$62+SUMPRODUCT($I$59:$M$59,1/(1+E$108)^$I$62:$M$62)+$H$92+$H$93+$H$94+$H$95)/$H$97 | F110: =(($C110*$H$79)/(1+F$108)^$M$62+SUMPRODUCT($I$59:$M$59,1/(1+F$108)^$I$62:$M$62)+$H$92+$H$93+$H$94+$H$95)/$H$97 | G110: =(($C110*$H$79)/(1+G$108)^$M$62+SUMPRODUCT($I$59:$M$59,1/(1+G$108)^$I$62:$M$62)+$H$92+$H$93+$H$94+$H$95)/$H$97 | H110: =(($C110*$H$79)/(1+H$108)^$M$62+SUMPRODUCT($I$59:$M$59,1/(1+H$108)^$I$62:$M$62)+$H$92+$H$93+$H$94+$H$95)/$H$97
C111: 12.5 | D111: =(($C111*$H$79)/(1+D$108)^$M$62+SUMPRODUCT($I$59:$M$59,1/(1+D$108)^$I$62:$M$62)+$H$92+$H$93+$H$94+$H$95)/$H$97 | E111: =(($C111*$H$79)/(1+E$108)^$M$62+SUMPRODUCT($I$59:$M$59,1/(1+E$108)^$I$62:$M$62)+$H$92+$H$93+$H$94+$H$95)/$H$97 | F111: =(($C111*$H$79)/(1+F$108)^$M$62+SUMPRODUCT($I$59:$M$59,1/(1+F$108)^$I$62:$M$62)+$H$92+$H$93+$H$94+$H$95)/$H$97 | G111: =(($C111*$H$79)/(1+G$108)^$M$62+SUMPRODUCT($I$59:$M$59,1/(1+G$108)^$I$62:$M$62)+$H$92+$H$93+$H$94+$H$95)/$H$97 | H111: =(($C111*$H$79)/(1+H$108)^$M$62+SUMPRODUCT($I$59:$M$59,1/(1+H$108)^$I$62:$M$62)+$H$92+$H$93+$H$94+$H$95)/$H$97
C112: 15 | D112: =(($C112*$H$79)/(1+D$108)^$M$62+SUMPRODUCT($I$59:$M$59,1/(1+D$108)^$I$62:$M$62)+$H$92+$H$93+$H$94+$H$95)/$H$97 | E112: =(($C112*$H$79)/(1+E$108)^$M$62+SUMPRODUCT($I$59:$M$59,1/(1+E$108)^$I$62:$M$62)+$H$92+$H$93+$H$94+$H$95)/$H$97 | F112: =(($C112*$H$79)/(1+F$108)^$M$62+SUMPRODUCT($I$59:$M$59,1/(1+F$108)^$I$62:$M$62)+$H$92+$H$93+$H$94+$H$95)/$H$97 | G112: =(($C112*$H$79)/(1+G$108)^$M$62+SUMPRODUCT($I$59:$M$59,1/(1+G$108)^$I$62:$M$62)+$H$92+$H$93+$H$94+$H$95)/$H$97 | H112: =(($C112*$H$79)/(1+H$108)^$M$62+SUMPRODUCT($I$59:$M$59,1/(1+H$108)^$I$62:$M$62)+$H$92+$H$93+$H$94+$H$95)/$H$97
C113: 18 | D113: =(($C113*$H$79)/(1+D$108)^$M$62+SUMPRODUCT($I$59:$M$59,1/(1+D$108)^$I$62:$M$62)+$H$92+$H$93+$H$94+$H$95)/$H$97 | E113: =(($C113*$H$79)/(1+E$108)^$M$62+SUMPRODUCT($I$59:$M$59,1/(1+E$108)^$I$62:$M$62)+$H$92+$H$93+$H$94+$H$95)/$H$97 | F113: =(($C113*$H$79)/(1+F$108)^$M$62+SUMPRODUCT($I$59:$M$59,1/(1+F$108)^$I$62:$M$62)+$H$92+$H$93+$H$94+$H$95)/$H$97 | G113: =(($C113*$H$79)/(1+G$108)^$M$62+SUMPRODUCT($I$59:$M$59,1/(1+G$108)^$I$62:$M$62)+$H$92+$H$93+$H$94+$H$95)/$H$97 | H113: =(($C113*$H$79)/(1+H$108)^$M$62+SUMPRODUCT($I$59:$M$59,1/(1+H$108)^$I$62:$M$62)+$H$92+$H$93+$H$94+$H$95)/$H$97
B116: Sensitivity is exit-multiple method only

Sheet WACC, Tax, and Reverse DCF
B1: Copart, Inc. — Reverse DCF
B4: Market-implied case
B5: Implied flat revenue growth, FY27–FY28 (solved so the implied price in H51 equals the current price in H52 at the exit multiple in H36) | H5: 0.158089
C8: Units | D8: Historicals | I8: Projected
B9: Income statement | D9: FY2022A | E9: FY2023A | F9: FY2024A | G9: FY2025A | H9: FY2026A | I9: FY2027E | J9: FY2028E | K9: CAGR
B10: Revenue | C10: $M | D10: ='PB IS (Annual)'!Q14/1000 | E10: ='PB IS (Annual)'!P14/1000 | F10: ='PB IS (Annual)'!O14/1000 | G10: ='PB IS (Annual)'!N14/1000 | H10: ='PB IS (Annual)'!M14/1000 | I10: =H10*(1+$H$5) | J10: =I10*(1+$H$5) | K10: =_xlfn.RRI(3, H10, J10) | M10: WACC build | N10: Value | O10: Label
B11: y/y growth | C11: % | D11: -- | E11: =E10/D10-1 | F11: =F10/E10-1 | G11: =G10/F10-1 | H11: =H10/G10-1 | I11: =I10/H10-1 | J11: =J10/I10-1 | K11: – | M11: Current share price | N11: =Cover!$D$6 | O11: – | P11: – | Q11: – | R11: Cover D6 — the one typed price in the workbook
M12: Fully diluted shares, mn | N12: =Cover!$D$15 | O12: – | P12: – | Q12: – | R12: Cover D15: basic + treasury-method options + RSUs (10-K Note 12)
B13: EBITDA | C13: $M | D13: =DCF!D31 | E13: =DCF!E31 | F13: =DCF!F31 | G13: =DCF!G31 | H13: =DCF!H31 | I13: =I10*I14 | J13: =J10*J14 | K13: =_xlfn.RRI(3, H13, J13) | M13: Market value of equity ($m) | N13: =Cover!$D$10 | O13: – | P13: – | Q13: –
B14: EBITDA margin | C14: % | D14: =D13/D10 | E14: =E13/E10 | F14: =F13/F10 | G14: =G13/G10 | H14: =H13/H10 | I14: 0.408 | J14: 0.412 | K14: – | M14: Debt: lease liabilities ($m), no funded debt | N14: =Cover!$D$13 | O14: – | P14: – | Q14: – | R14: Cover D13 ← 3SM balance sheet; revolver undrawn
B15: y/y growth | C15: % | D15: -- | E15: =E13/D13-1 | F15: =F13/E13-1 | G15: =G13/F13-1 | H15: =H13/G13-1 | I15: =I13/H13-1 | J15: =J13/I13-1 | K15: – | M15: Weight of equity / weight of debt | N15: =N13/(N13+N14) | O15: =N14/(N13+N14) | P15: – | Q15: –
B17: D&A | C17: $M | D17: =DCF!D29 | E17: =DCF!E29 | F17: =DCF!F29 | G17: =DCF!G29 | H17: =DCF!H29 | I17: 226 | J17: 234 | K17: – | M17: Risk-free rate (10-yr US Treasury, 1 Oct 2026) | N17: 0.0524 | O17: VERIFIED | P17: – | Q17: – | R17: Risk-free rate: 10-year US Treasury par yield, 1 Oct 2026. VERIFIED — US Treasury daily par yield curve, raw/discovery_2026-10-02/ust_yield_curve_2026.csv (row 10/01/2026, 10 Yr)
B18: EBIT | C18: $M | D18: =D13-D17 | E18: =E13-E17 | F18: =F13-F17 | G18: =G13-G17 | H18: =H13-H17 | I18: =I13-I17 | J18: =J13-J17 | K18: =_xlfn.RRI(3, H18, J18) | M18: Equity risk premium (Damodaran, Jan 2026) | N18: 0.0446 | O18: VERIFIED | P18: – | Q18: – | R18: Equity risk premium: United States, Damodaran, January 2026. VERIFIED — Damodaran country risk premiums table (Aa1; mature-market 4.23% + 0.23% CRP), raw/discovery_2026-10-02/damodaran_ctryprem.html
B19: y/y growth | C19: % | D19: -- | E19: =E18/D18-1 | F19: =F18/E18-1 | G19: =G18/F18-1 | H19: =H18/G18-1 | I19: =I18/H18-1 | J19: =J18/I18-1 | K19: – | M19: Industry beta (Damodaran, Jan 2026) | N19: Levered | O19: Unlevered | P19: Cash-corrected | Q19: – | R19: Beta (Damodaran, January 2026): levered / unlevered / cash-corrected unlevered. VERIFIED — raw/discovery_2026-10-02/damodaran_betas.html
M20: Business & Consumer Services (155 firms) | N20: 0.89 | O20: 0.77 | P20: 0.81 | Q20: –
B21: Unlevered free cash flow | M21: Retail (Automotive) (34 firms) | N21: 0.94 | O21: 0.7 | P21: 0.71 | Q21: –
B22: EBIT | C22: $M | D22: =D18 | E22: =E18 | F22: =F18 | G22: =G18 | H22: =H18 | I22: =I18 | J22: =J18 | K22: =_xlfn.RRI(3, H22, J22) | M22: Auto Parts (35 firms) | N22: 1.34 | O22: 1.02 | P22: 1.13 | Q22: –
B23: (−) Taxes on EBIT | C23: $M | D23: =-D18*DCF!D38 | E23: =-E18*DCF!E38 | F23: =-F18*DCF!F38 | G23: =-G18*DCF!G38 | H23: =-H18*DCF!H38 | I23: =-I18*DCF!I38 | J23: =-J18*DCF!J38 | K23: – | M23: Transportation (19 firms) | N23: 0.86 | O23: 0.68 | P23: 0.71 | Q23: –
B24: NOPAT | C24: $M | D24: =D22+D23 | E24: =E22+E23 | F24: =F22+F23 | G24: =G22+G23 | H24: =H22+H23 | I24: =I22+I23 | J24: =J22+J23 | K24: =_xlfn.RRI(3, H24, J24) | M24: Total market (5,994 firms) | N24: 0.91 | O24: 0.72 | P24: 0.76 | Q24: –
B25: (+) D&A | C25: $M | D25: =D17 | E25: =E17 | F25: =F17 | G25: =G17 | H25: =H17 | I25: =I17 | J25: =J17 | K25: – | M25: Peer betas, 5-yr monthly: RBA / KAR / ACVA / CVNA | N25: RBA | O25: KAR | P25: ACVA | Q25: CVNA | R25: Peer company betas (5-year monthly): RB Global, OPENLANE, ACV Auctions, Carvana, Copart. NOT OBTAINED — price downloads refused by the only permitted free source's robots file; paste CapIQ or Bloomberg values here (dated) to override the industry beta
B26: (+) Stock-based compensation (DCF % of revenue) | C26: $M | D26: =DCF!D53 | E26: =DCF!E53 | F26: =DCF!F53 | G26: =DCF!G53 | H26: =DCF!H53 | I26: =I10*DCF!I54 | J26: =J10*DCF!J54 | K26: – | M26: Selected unlevered beta (avg of two closest) | N26: =AVERAGE(P20,P21) | O26: ASSUMED | P26: – | Q26: – | R26: Selected unlevered beta (default: average of the two closest industries, cash-corrected). ASSUMED choice of industries; Copart is an auction-services business with retail-automotive exposure
B27: (−) Capital expenditures (DCF % of revenue) | C27: $M | D27: =DCF!D55 | E27: =DCF!E55 | F27: =DCF!F55 | G27: =DCF!G55 | H27: =DCF!H55 | I27: =-I10*DCF!I56 | J27: =-J10*DCF!J56 | K27: – | M27: Relevered beta = βu × (1 + (1 − t) × D/E) | N27: =N26*(1+(1-N39)*N14/N13) | O27: – | P27: – | Q27: –
B28: (−) Increase in NWC (DCF % of Δrevenue) | C28: $M | D28: =DCF!D57 | E28: =DCF!E57 | F28: =DCF!F57 | G28: =DCF!G57 | H28: =DCF!H57 | I28: -83 | J28: -83 | K28: – | M28: Cost of equity (CAPM) | N28: =N17+N27*N18 | O28: – | P28: – | Q28: –
B29: Unlevered free cash flow | C29: $M | D29: =D24+D25+D26+D27+D28 | E29: =E24+E25+E26+E27+E28 | F29: =F24+F25+F26+F27+F28 | G29: =G24+G25+G26+G27+G28 | H29: =H24+H25+H26+H27+H28 | I29: =I24+I25+I26+I27+I28 | J29: =J24+J25+J26+J27+J28 | K29: =_xlfn.RRI(3, H29, J29) | M29: Pre-tax cost of debt (revolver proxy; weight ≈ 0) | N29: 0.0575 | O29: ASSUMED | P29: – | Q29: – | R29: Pre-tax cost of debt (revolver pricing proxy; weight ≈ 0). ASSUMED: 10-K describes the $1,250m unsecured revolver maturing 23 Jan 2031 without the margin; SOFR + 1.0–1.5% proxy
B30: Discount period (DCF) | C30: yrs | D30: – | E30: – | F30: – | G30: – | H30: – | I30: =DCF!I62 | J30: =DCF!J62 | K30: – | M30: After-tax cost of debt | N30: =N29*(1-N39) | O30: – | P30: – | Q30: –
B31: Discount factor (DCF WACC) | C31: x | D31: – | E31: – | F31: – | G31: – | H31: – | I31: =DCF!I63 | J31: =DCF!J63 | K31: – | M31: WACC | N31: =N15*N28+O15*N30 | O31: – | P31: – | Q31: –
B32: PV of UFCF | C32: $M | D32: – | E32: – | F32: – | G32: – | H32: – | I32: =I29*I31 | J32: =J29*J31 | K32: – | M32: Memo: DCF's previous WACC inputs → 8.725% | R32: Memo: DCF's previous inputs — risk-free 4.21%, beta 1.05, ERP 4.30% → 8.725%
B34: Valuation | M34: Effective tax rate build | N34: Value | O34: Label
B35: WACC | D35: – | E35: – | F35: – | G35: – | H35: =N31 | I35: – | J35: – | K35: – | M35: US federal statutory rate | N35: 0.21 | O35: VERIFIED | P35: – | Q35: – | R35: 10-K MD&A
B36: Exit EV / EBITDA multiple (Barclays: 10× on 2026) | D36: – | E36: – | F36: – | G36: – | H36: 10 | I36: – | J36: – | K36: – | M36: (+) State income taxes ÷ pre-tax income | N36: ='D 10-K FY26'!E34/1834.977 | O36: VERIFIED | P36: – | Q36: – | R36: (+) State income taxes: $21.5m ÷ pre-tax income $1,835m. 10-K MD&A Income Taxes; pre-tax income from the income statement
B37: Terminal year EBITDA (FY2028E, market-implied) | D37: – | E37: – | F37: – | G37: – | H37: =J13 | I37: – | J37: – | K37: – | M37: (−) FDII deduction: $46.7m ÷ pre-tax income | N37: ='D 10-K FY26'!C34/1834.977 | O37: VERIFIED | P37: – | Q37: – | R37: 10-K MD&A; set by federal tax law, check the FY27 deduction rate
B38: Terminal value | D38: – | E38: – | F38: – | G38: – | H38: =H36*H37 | I38: – | J38: – | K38: – | M38: (−) Excess option tax benefit ÷ pre-tax income | N38: ='D 10-K FY26'!D34/1834.977 | O38: VERIFIED | P38: – | Q38: – | R38: (−) Excess tax benefit on option exercises: $6.6m (FY25: $36.7m); excluded from the forward rate because it depends on the share price. 10-K MD&A
B39: PV of terminal value | D39: – | E39: – | F39: – | G39: – | H39: =H38*J31 | I39: – | J39: – | K39: – | M39: Structural effective tax rate → DCF, 3SM | N39: =N35+N36+N37 | O39: – | P39: – | Q39: – | R39: Structural effective tax rate (statutory + state − FDII) → DCF tax rows
B40: PV of explicit UFCF (FY27-FY31) | D40: – | E40: – | F40: – | G40: – | H40: =SUM(I32:L32) | I40: – | J40: – | K40: – | M40: Reported effective rate FY2026 / FY2025 | N40: ='D 10-K FY26'!C33 | O40: ='D 10-K FY26'!D33 | P40: – | Q40: –
B41: Enterprise value | D41: – | E41: – | F41: – | G41: – | H41: =H39+H40 | I41: – | J41: – | K41: – | M41: Cash taxes paid ÷ pre-tax income, FY26 / FY25 | N41: ='D 10-K FY26'!C32/1834.977 | O41: ='D 10-K FY26'!D32/1895.581 | P41: – | Q41: – | R41: Cash taxes paid ÷ pre-tax income, FY2026 / FY2025. Supplemental cash flow
M42: Barclays-implied tax rate, FY2027E | N42: =1-'D Barclays'!E9/'D Barclays'!E8 | O42: – | P42: – | Q42: – | R42: Barclays-implied rate FY2027E (1 − adj. net income ÷ adj. pre-tax)
B43: Equity bridge
B44: Enterprise value | D44: – | E44: – | F44: – | G44: – | H44: =H41 | I44: – | J44: – | K44: –
B45: (+) Cash & HTM securities | D45: – | E45: – | F45: – | G45: – | H45: =Cover!D12 | I45: – | J45: – | K45: –
B46: (−) Total debt | D46: – | E46: – | F46: – | G46: – | H46: =-Cover!D13 | I46: – | J46: – | K46: –
B47: (−) Non-controlling interest | D47: – | E47: – | F47: – | G47: – | H47: =-Cover!D14 | I47: – | J47: – | K47: –
B48: (−) ACV consideration (DCF toggle) | D48: – | E48: – | F48: – | G48: – | H48: =DCF!H95 | I48: – | J48: – | K48: –
B49: Equity value | D49: – | E49: – | F49: – | G49: – | H49: =SUM(H44:H48) | I49: – | J49: – | K49: –
B50: FDSO (M) | D50: – | E50: – | F50: – | G50: – | H50: =Cover!D15 | I50: – | J50: – | K50: –
B51: Implied share price | H51: =H49/H50
B52: Current share price | D52: – | E52: – | F52: – | G52: – | H52: =Cover!D6 | I52: – | J52: – | K52: –
B53: Implied - current | H53: =H51-H52
B55: Reverse DCF summary
B56: Implied revenue CAGR, FY26–FY28 | D56: – | E56: – | F56: – | G56: – | H56: =H5 | I56: – | J56: – | K56: –
B57: Implied FY2028E revenue | D57: – | E57: – | F57: – | G57: – | H57: =J10 | I57: – | J57: – | K57: –
B58: Implied FY2028E EBITDA | D58: – | E58: – | F58: – | G58: – | H58: =J13 | I58: – | J58: – | K58: –
B59: DCF base-case revenue CAGR, FY26-FY31 (for comparison) | D59: – | E59: – | F59: – | G59: – | H59: =(DCF!M6/DCF!H6)^(1/5)-1 | I59: – | J59: – | K59: –
B60: DCF base-case FY2031E EBITDA | D60: – | E60: – | F60: – | G60: – | H60: =DCF!M31 | I60: – | J60: – | K60: –
B61: Implied exit multiple if you keep the DCF base cash flows | D61: – | E61: – | F61: – | G61: – | H61: =((Cover!D6*Cover!D15-Cover!D12+Cover!D13+Cover!D14-DCF!H95)-DCF!H86)/DCF!M63/DCF!M31 | I61: – | J61: – | K61: –
B62: Implied perpetuity growth on the DCF base cash flows | D62: – | E62: – | F62: – | G62: – | H62: =(H61*DCF!M31*N31-DCF!M59)/(H61*DCF!M31+DCF!M59) | I62: – | J62: – | K62: –
B65: Sensitivity
B66: Flat revenue growth → | D66: -0.04 | E66: -0.02 | F66: 0 | G66: 0.02 | H66: 0.03 | I66: 0.04 | J66: 0.06 | K66: 0.08
B67: Implied share price | D67: =(($H$10*(1+D$66)*($I$14*(1-DCF!$I$38)+DCF!$I$54-DCF!$I$56)+($I$17*DCF!$I$38+$I$28))*$I$31+($H$10*(1+D$66)^2*($J$14*(1-DCF!$J$38)+DCF!$J$54-DCF!$J$56)+($J$17*DCF!$J$38+$J$28))*$J$31+$H$36*$J$14*$H$10*(1+D$66)^2*$J$31+$H$45+$H$46+$H$47+$H$48)/$H$50 | E67: =(($H$10*(1+E$66)*($I$14*(1-DCF!$I$38)+DCF!$I$54-DCF!$I$56)+($I$17*DCF!$I$38+$I$28))*$I$31+($H$10*(1+E$66)^2*($J$14*(1-DCF!$J$38)+DCF!$J$54-DCF!$J$56)+($J$17*DCF!$J$38+$J$28))*$J$31+$H$36*$J$14*$H$10*(1+E$66)^2*$J$31+$H$45+$H$46+$H$47+$H$48)/$H$50 | F67: =(($H$10*(1+F$66)*($I$14*(1-DCF!$I$38)+DCF!$I$54-DCF!$I$56)+($I$17*DCF!$I$38+$I$28))*$I$31+($H$10*(1+F$66)^2*($J$14*(1-DCF!$J$38)+DCF!$J$54-DCF!$J$56)+($J$17*DCF!$J$38+$J$28))*$J$31+$H$36*$J$14*$H$10*(1+F$66)^2*$J$31+$H$45+$H$46+$H$47+$H$48)/$H$50 | G67: =(($H$10*(1+G$66)*($I$14*(1-DCF!$I$38)+DCF!$I$54-DCF!$I$56)+($I$17*DCF!$I$38+$I$28))*$I$31+($H$10*(1+G$66)^2*($J$14*(1-DCF!$J$38)+DCF!$J$54-DCF!$J$56)+($J$17*DCF!$J$38+$J$28))*$J$31+$H$36*$J$14*$H$10*(1+G$66)^2*$J$31+$H$45+$H$46+$H$47+$H$48)/$H$50 | H67: =(($H$10*(1+H$66)*($I$14*(1-DCF!$I$38)+DCF!$I$54-DCF!$I$56)+($I$17*DCF!$I$38+$I$28))*$I$31+($H$10*(1+H$66)^2*($J$14*(1-DCF!$J$38)+DCF!$J$54-DCF!$J$56)+($J$17*DCF!$J$38+$J$28))*$J$31+$H$36*$J$14*$H$10*(1+H$66)^2*$J$31+$H$45+$H$46+$H$47+$H$48)/$H$50 | I67: =(($H$10*(1+I$66)*($I$14*(1-DCF!$I$38)+DCF!$I$54-DCF!$I$56)+($I$17*DCF!$I$38+$I$28))*$I$31+($H$10*(1+I$66)^2*($J$14*(1-DCF!$J$38)+DCF!$J$54-DCF!$J$56)+($J$17*DCF!$J$38+$J$28))*$J$31+$H$36*$J$14*$H$10*(1+I$66)^2*$J$31+$H$45+$H$46+$H$47+$H$48)/$H$50 | J67: =(($H$10*(1+J$66)*($I$14*(1-DCF!$I$38)+DCF!$I$54-DCF!$I$56)+($I$17*DCF!$I$38+$I$28))*$I$31+($H$10*(1+J$66)^2*($J$14*(1-DCF!$J$38)+DCF!$J$54-DCF!$J$56)+($J$17*DCF!$J$38+$J$28))*$J$31+$H$36*$J$14*$H$10*(1+J$66)^2*$J$31+$H$45+$H$46+$H$47+$H$48)/$H$50 | K67: =(($H$10*(1+K$66)*($I$14*(1-DCF!$I$38)+DCF!$I$54-DCF!$I$56)+($I$17*DCF!$I$38+$I$28))*$I$31+($H$10*(1+K$66)^2*($J$14*(1-DCF!$J$38)+DCF!$J$54-DCF!$J$56)+($J$17*DCF!$J$38+$J$28))*$J$31+$H$36*$J$14*$H$10*(1+K$66)^2*$J$31+$H$45+$H$46+$H$47+$H$48)/$H$50
B71: Street price targets and multiples (for reference)
B72: Broker | F72: Rating | H72: PT
B73: Barclays | F73: Underweight | H73: 25
B74: Stephens | F74: Equal-Weight | H74: 35
B75: BNP Paribas | F75: Outperform | H75: 40
B76: HSBC | F76: Buy | H76: 46
B77: Jefferies | F77: Buy | H77: 45
B78: Equisights | F78: Outperform | H78: 43.1

Sheet RPM ENGINES ----->
B3: RPM ENGINES ----->

Sheet E1 Fleet
B1: E1 Fleet — vehicles on the road by age and body (thousands)
B2: Fleet(a, b, Y) = Births(Y−a, b) × S_b(a ÷ k_b(Y)); k_b(Y) = k_b(2013) × m(Y). Calendar years; feeds E2 by fiscal-quarter weights. Appendix A, Eq. 1–3.
C3: CY | D3: 2019 | E3: 2020 | F3: 2021 | G3: 2022 | H3: 2023 | I3: 2024 | J3: 2025 | K3: 2026 | L3: 2027 | M3: 2028
C4: Units | D4: Historicals | K4: Projected | P4: Notes / sources
B5: A. Births by body (new light vehicles sold in the calendar year) | D5: CY2019 | E5: CY2020 | F5: CY2021 | G5: CY2022 | H5: CY2023 | I5: CY2024 | J5: CY2025 | K5: CY2026 | L5: CY2027 | M5: CY2028
B6: Car | C6: 000s | D6: =INDEX('D Fleet'!$C$5:$C$63,MATCH(D$3,'D Fleet'!$B$5:$B$63,0)) | E6: =INDEX('D Fleet'!$C$5:$C$63,MATCH(E$3,'D Fleet'!$B$5:$B$63,0)) | F6: =INDEX('D Fleet'!$C$5:$C$63,MATCH(F$3,'D Fleet'!$B$5:$B$63,0)) | G6: =INDEX('D Fleet'!$C$5:$C$63,MATCH(G$3,'D Fleet'!$B$5:$B$63,0)) | H6: =INDEX('D Fleet'!$C$5:$C$63,MATCH(H$3,'D Fleet'!$B$5:$B$63,0)) | I6: =INDEX('D Fleet'!$C$5:$C$63,MATCH(I$3,'D Fleet'!$B$5:$B$63,0)) | J6: =INDEX('D Fleet'!$C$5:$C$63,MATCH(J$3,'D Fleet'!$B$5:$B$63,0)) | K6: =INDEX('D Fleet'!$C$5:$C$63,MATCH(K$3,'D Fleet'!$B$5:$B$63,0)) | ... M6: =INDEX('D Fleet'!$C$5:$C$63,MATCH(M$3,'D Fleet'!$B$5:$B$63,0)) | N6: – | O6: – | P6: D Fleet; Ward's/ORNL to 2021, FRED 2022–25 (VERIFIED); SUV/pickup/van split is an EPA composition proxy (ASSUMED) | Q6: – | R6: –
B7: Utility vehicle (SUV) | C7: 000s | D7: =INDEX('D Fleet'!$D$5:$D$63,MATCH(D$3,'D Fleet'!$B$5:$B$63,0)) | E7: =INDEX('D Fleet'!$D$5:$D$63,MATCH(E$3,'D Fleet'!$B$5:$B$63,0)) | F7: =INDEX('D Fleet'!$D$5:$D$63,MATCH(F$3,'D Fleet'!$B$5:$B$63,0)) | G7: =INDEX('D Fleet'!$D$5:$D$63,MATCH(G$3,'D Fleet'!$B$5:$B$63,0)) | H7: =INDEX('D Fleet'!$D$5:$D$63,MATCH(H$3,'D Fleet'!$B$5:$B$63,0)) | I7: =INDEX('D Fleet'!$D$5:$D$63,MATCH(I$3,'D Fleet'!$B$5:$B$63,0)) | J7: =INDEX('D Fleet'!$D$5:$D$63,MATCH(J$3,'D Fleet'!$B$5:$B$63,0)) | K7: =INDEX('D Fleet'!$D$5:$D$63,MATCH(K$3,'D Fleet'!$B$5:$B$63,0)) | ... M7: =INDEX('D Fleet'!$D$5:$D$63,MATCH(M$3,'D Fleet'!$B$5:$B$63,0)) | N7: – | O7: – | P7: – | Q7: – | R7: –
B8: Pickup | C8: 000s | D8: =INDEX('D Fleet'!$E$5:$E$63,MATCH(D$3,'D Fleet'!$B$5:$B$63,0)) | E8: =INDEX('D Fleet'!$E$5:$E$63,MATCH(E$3,'D Fleet'!$B$5:$B$63,0)) | F8: =INDEX('D Fleet'!$E$5:$E$63,MATCH(F$3,'D Fleet'!$B$5:$B$63,0)) | G8: =INDEX('D Fleet'!$E$5:$E$63,MATCH(G$3,'D Fleet'!$B$5:$B$63,0)) | H8: =INDEX('D Fleet'!$E$5:$E$63,MATCH(H$3,'D Fleet'!$B$5:$B$63,0)) | I8: =INDEX('D Fleet'!$E$5:$E$63,MATCH(I$3,'D Fleet'!$B$5:$B$63,0)) | J8: =INDEX('D Fleet'!$E$5:$E$63,MATCH(J$3,'D Fleet'!$B$5:$B$63,0)) | K8: =INDEX('D Fleet'!$E$5:$E$63,MATCH(K$3,'D Fleet'!$B$5:$B$63,0)) | ... M8: =INDEX('D Fleet'!$E$5:$E$63,MATCH(M$3,'D Fleet'!$B$5:$B$63,0)) | N8: – | O8: – | P8: – | Q8: – | R8: –
B9: Van / minivan | C9: 000s | D9: =INDEX('D Fleet'!$F$5:$F$63,MATCH(D$3,'D Fleet'!$B$5:$B$63,0)) | E9: =INDEX('D Fleet'!$F$5:$F$63,MATCH(E$3,'D Fleet'!$B$5:$B$63,0)) | F9: =INDEX('D Fleet'!$F$5:$F$63,MATCH(F$3,'D Fleet'!$B$5:$B$63,0)) | G9: =INDEX('D Fleet'!$F$5:$F$63,MATCH(G$3,'D Fleet'!$B$5:$B$63,0)) | H9: =INDEX('D Fleet'!$F$5:$F$63,MATCH(H$3,'D Fleet'!$B$5:$B$63,0)) | I9: =INDEX('D Fleet'!$F$5:$F$63,MATCH(I$3,'D Fleet'!$B$5:$B$63,0)) | J9: =INDEX('D Fleet'!$F$5:$F$63,MATCH(J$3,'D Fleet'!$B$5:$B$63,0)) | K9: =INDEX('D Fleet'!$F$5:$F$63,MATCH(K$3,'D Fleet'!$B$5:$B$63,0)) | ... M9: =INDEX('D Fleet'!$F$5:$F$63,MATCH(M$3,'D Fleet'!$B$5:$B$63,0)) | N9: – | O9: – | P9: – | Q9: – | R9: –
B10: Total light vehicles | C10: 000s | D10: =SUM(D6:D9) | E10: =SUM(E6:E9) | F10: =SUM(F6:F9) | G10: =SUM(G6:G9) | H10: =SUM(H6:H9) | I10: =SUM(I6:I9) | J10: =SUM(J6:J9) | K10: =SUM(K6:K9) | ... M10: =SUM(M6:M9) | N10: – | O10: – | P10: – | Q10: – | R10: –
B11: y/y growth | C11: % | D11: – | E11: =E10/D10-1 | F11: =F10/E10-1 | G11: =G10/F10-1 | H11: =H10/G10-1 | I11: =I10/H10-1 | J11: =J10/I10-1 | K11: =K10/J10-1 | L11: =L10/K10-1 | M11: =M10/L10-1 | N11: – | O11: – | P11: – | Q11: – | R11: –
B13: B. Survival stretch (k = 1 is the raw EPA schedule; k > 1 means vehicles last longer)
B14: m(Y): drift multiplier, linear 2013 → 2024, flat after | C14: x | D14: =1+($D$92-1)*MIN(MAX(D$3-2013,0),11)/11 | E14: =1+($D$92-1)*MIN(MAX(E$3-2013,0),11)/11 | F14: =1+($D$92-1)*MIN(MAX(F$3-2013,0),11)/11 | G14: =1+($D$92-1)*MIN(MAX(G$3-2013,0),11)/11 | H14: =1+($D$92-1)*MIN(MAX(H$3-2013,0),11)/11 | I14: =1+($D$92-1)*MIN(MAX(I$3-2013,0),11)/11 | J14: =1+($D$92-1)*MIN(MAX(J$3-2013,0),11)/11 | K14: =1+($D$92-1)*MIN(MAX(K$3-2013,0),11)/11 | ... M14: =1+($D$92-1)*MIN(MAX(M$3-2013,0),11)/11 | N14: – | O14: – | P14: FITTED to two 2024 count anchors (Inputs rows); AGE_CURVES.md §2.4 | Q14: – | R14: –
B15: k_cars(Y) | C15: x | D15: =$D$90*D14 | E15: =$D$90*E14 | F15: =$D$90*F14 | G15: =$D$90*G14 | H15: =$D$90*H14 | I15: =$D$90*I14 | J15: =$D$90*J14 | K15: =$D$90*K14 | ... M15: =$D$90*M14 | N15: – | O15: – | P15: – | Q15: – | R15: –
B16: k_light trucks(Y) | C16: x | D16: =$D$91*D14 | E16: =$D$91*E14 | F16: =$D$91*F14 | G16: =$D$91*G14 | H16: =$D$91*H14 | I16: =$D$91*I14 | J16: =$D$91*J14 | K16: =$D$91*K14 | ... M16: =$D$91*M14 | N16: – | O16: – | P16: – | Q16: – | R16: –
B18: C. Vehicles on the road by age band × body (thousands; from E1a roll)
B19: Car — 0 (current or newer) | C19: 000s | D19: =SUMIFS('E1a Fleet (roll)'!E$7:E$190,'E1a Fleet (roll)'!$A$7:$A$190,"Car",'E1a Fleet (roll)'!$C$7:$C$190,0) | E19: =SUMIFS('E1a Fleet (roll)'!F$7:F$190,'E1a Fleet (roll)'!$A$7:$A$190,"Car",'E1a Fleet (roll)'!$C$7:$C$190,0) | F19: =SUMIFS('E1a Fleet (roll)'!G$7:G$190,'E1a Fleet (roll)'!$A$7:$A$190,"Car",'E1a Fleet (roll)'!$C$7:$C$190,0) | G19: =SUMIFS('E1a Fleet (roll)'!H$7:H$190,'E1a Fleet (roll)'!$A$7:$A$190,"Car",'E1a Fleet (roll)'!$C$7:$C$190,0) | H19: =SUMIFS('E1a Fleet (roll)'!I$7:I$190,'E1a Fleet (roll)'!$A$7:$A$190,"Car",'E1a Fleet (roll)'!$C$7:$C$190,0) | I19: =SUMIFS('E1a Fleet (roll)'!J$7:J$190,'E1a Fleet (roll)'!$A$7:$A$190,"Car",'E1a Fleet (roll)'!$C$7:$C$190,0) | J19: =SUMIFS('E1a Fleet (roll)'!K$7:K$190,'E1a Fleet (roll)'!$A$7:$A$190,"Car",'E1a Fleet (roll)'!$C$7:$C$190,0) | K19: =SUMIFS('E1a Fleet (roll)'!L$7:L$190,'E1a Fleet (roll)'!$A$7:$A$190,"Car",'E1a Fleet (roll)'!$C$7:$C$190,0) | ... M19: =SUMIFS('E1a Fleet (roll)'!N$7:N$190,'E1a Fleet (roll)'!$A$7:$A$190,"Car",'E1a Fleet (roll)'!$C$7:$C$190,0) | N19: – | O19: – | P19: – | Q19: – | R19: –
B20: Car — 1–3 years | C20: 000s | D20: =SUMIFS('E1a Fleet (roll)'!E$7:E$190,'E1a Fleet (roll)'!$A$7:$A$190,"Car",'E1a Fleet (roll)'!$C$7:$C$190,1) | E20: =SUMIFS('E1a Fleet (roll)'!F$7:F$190,'E1a Fleet (roll)'!$A$7:$A$190,"Car",'E1a Fleet (roll)'!$C$7:$C$190,1) | F20: =SUMIFS('E1a Fleet (roll)'!G$7:G$190,'E1a Fleet (roll)'!$A$7:$A$190,"Car",'E1a Fleet (roll)'!$C$7:$C$190,1) | G20: =SUMIFS('E1a Fleet (roll)'!H$7:H$190,'E1a Fleet (roll)'!$A$7:$A$190,"Car",'E1a Fleet (roll)'!$C$7:$C$190,1) | H20: =SUMIFS('E1a Fleet (roll)'!I$7:I$190,'E1a Fleet (roll)'!$A$7:$A$190,"Car",'E1a Fleet (roll)'!$C$7:$C$190,1) | I20: =SUMIFS('E1a Fleet (roll)'!J$7:J$190,'E1a Fleet (roll)'!$A$7:$A$190,"Car",'E1a Fleet (roll)'!$C$7:$C$190,1) | J20: =SUMIFS('E1a Fleet (roll)'!K$7:K$190,'E1a Fleet (roll)'!$A$7:$A$190,"Car",'E1a Fleet (roll)'!$C$7:$C$190,1) | K20: =SUMIFS('E1a Fleet (roll)'!L$7:L$190,'E1a Fleet (roll)'!$A$7:$A$190,"Car",'E1a Fleet (roll)'!$C$7:$C$190,1) | ... M20: =SUMIFS('E1a Fleet (roll)'!N$7:N$190,'E1a Fleet (roll)'!$A$7:$A$190,"Car",'E1a Fleet (roll)'!$C$7:$C$190,1) | N20: – | O20: – | P20: – | Q20: – | R20: –
B21: Car — 4–6 years | C21: 000s | D21: =SUMIFS('E1a Fleet (roll)'!E$7:E$190,'E1a Fleet (roll)'!$A$7:$A$190,"Car",'E1a Fleet (roll)'!$C$7:$C$190,2) | E21: =SUMIFS('E1a Fleet (roll)'!F$7:F$190,'E1a Fleet (roll)'!$A$7:$A$190,"Car",'E1a Fleet (roll)'!$C$7:$C$190,2) | F21: =SUMIFS('E1a Fleet (roll)'!G$7:G$190,'E1a Fleet (roll)'!$A$7:$A$190,"Car",'E1a Fleet (roll)'!$C$7:$C$190,2) | G21: =SUMIFS('E1a Fleet (roll)'!H$7:H$190,'E1a Fleet (roll)'!$A$7:$A$190,"Car",'E1a Fleet (roll)'!$C$7:$C$190,2) | H21: =SUMIFS('E1a Fleet (roll)'!I$7:I$190,'E1a Fleet (roll)'!$A$7:$A$190,"Car",'E1a Fleet (roll)'!$C$7:$C$190,2) | I21: =SUMIFS('E1a Fleet (roll)'!J$7:J$190,'E1a Fleet (roll)'!$A$7:$A$190,"Car",'E1a Fleet (roll)'!$C$7:$C$190,2) | J21: =SUMIFS('E1a Fleet (roll)'!K$7:K$190,'E1a Fleet (roll)'!$A$7:$A$190,"Car",'E1a Fleet (roll)'!$C$7:$C$190,2) | K21: =SUMIFS('E1a Fleet (roll)'!L$7:L$190,'E1a Fleet (roll)'!$A$7:$A$190,"Car",'E1a Fleet (roll)'!$C$7:$C$190,2) | ... M21: =SUMIFS('E1a Fleet (roll)'!N$7:N$190,'E1a Fleet (roll)'!$A$7:$A$190,"Car",'E1a Fleet (roll)'!$C$7:$C$190,2) | N21: – | O21: – | P21: – | Q21: – | R21: –
B22: Car — 7+ years | C22: 000s | D22: =SUMIFS('E1a Fleet (roll)'!E$7:E$190,'E1a Fleet (roll)'!$A$7:$A$190,"Car",'E1a Fleet (roll)'!$C$7:$C$190,3) | E22: =SUMIFS('E1a Fleet (roll)'!F$7:F$190,'E1a Fleet (roll)'!$A$7:$A$190,"Car",'E1a Fleet (roll)'!$C$7:$C$190,3) | F22: =SUMIFS('E1a Fleet (roll)'!G$7:G$190,'E1a Fleet (roll)'!$A$7:$A$190,"Car",'E1a Fleet (roll)'!$C$7:$C$190,3) | G22: =SUMIFS('E1a Fleet (roll)'!H$7:H$190,'E1a Fleet (roll)'!$A$7:$A$190,"Car",'E1a Fleet (roll)'!$C$7:$C$190,3) | H22: =SUMIFS('E1a Fleet (roll)'!I$7:I$190,'E1a Fleet (roll)'!$A$7:$A$190,"Car",'E1a Fleet (roll)'!$C$7:$C$190,3) | I22: =SUMIFS('E1a Fleet (roll)'!J$7:J$190,'E1a Fleet (roll)'!$A$7:$A$190,"Car",'E1a Fleet (roll)'!$C$7:$C$190,3) | J22: =SUMIFS('E1a Fleet (roll)'!K$7:K$190,'E1a Fleet (roll)'!$A$7:$A$190,"Car",'E1a Fleet (roll)'!$C$7:$C$190,3) | K22: =SUMIFS('E1a Fleet (roll)'!L$7:L$190,'E1a Fleet (roll)'!$A$7:$A$190,"Car",'E1a Fleet (roll)'!$C$7:$C$190,3) | ... M22: =SUMIFS('E1a Fleet (roll)'!N$7:N$190,'E1a Fleet (roll)'!$A$7:$A$190,"Car",'E1a Fleet (roll)'!$C$7:$C$190,3) | N22: – | O22: – | P22: – | Q22: – | R22: –
B23: Utility vehicle (SUV) — 0 (current or newer) | C23: 000s | D23: =SUMIFS('E1a Fleet (roll)'!E$7:E$190,'E1a Fleet (roll)'!$A$7:$A$190,"SUV",'E1a Fleet (roll)'!$C$7:$C$190,0) | E23: =SUMIFS('E1a Fleet (roll)'!F$7:F$190,'E1a Fleet (roll)'!$A$7:$A$190,"SUV",'E1a Fleet (roll)'!$C$7:$C$190,0) | F23: =SUMIFS('E1a Fleet (roll)'!G$7:G$190,'E1a Fleet (roll)'!$A$7:$A$190,"SUV",'E1a Fleet (roll)'!$C$7:$C$190,0) | G23: =SUMIFS('E1a Fleet (roll)'!H$7:H$190,'E1a Fleet (roll)'!$A$7:$A$190,"SUV",'E1a Fleet (roll)'!$C$7:$C$190,0) | H23: =SUMIFS('E1a Fleet (roll)'!I$7:I$190,'E1a Fleet (roll)'!$A$7:$A$190,"SUV",'E1a Fleet (roll)'!$C$7:$C$190,0) | I23: =SUMIFS('E1a Fleet (roll)'!J$7:J$190,'E1a Fleet (roll)'!$A$7:$A$190,"SUV",'E1a Fleet (roll)'!$C$7:$C$190,0) | J23: =SUMIFS('E1a Fleet (roll)'!K$7:K$190,'E1a Fleet (roll)'!$A$7:$A$190,"SUV",'E1a Fleet (roll)'!$C$7:$C$190,0) | K23: =SUMIFS('E1a Fleet (roll)'!L$7:L$190,'E1a Fleet (roll)'!$A$7:$A$190,"SUV",'E1a Fleet (roll)'!$C$7:$C$190,0) | ... M23: =SUMIFS('E1a Fleet (roll)'!N$7:N$190,'E1a Fleet (roll)'!$A$7:$A$190,"SUV",'E1a Fleet (roll)'!$C$7:$C$190,0) | N23: – | O23: – | P23: – | Q23: – | R23: –
B24: Utility vehicle (SUV) — 1–3 years | C24: 000s | D24: =SUMIFS('E1a Fleet (roll)'!E$7:E$190,'E1a Fleet (roll)'!$A$7:$A$190,"SUV",'E1a Fleet (roll)'!$C$7:$C$190,1) | E24: =SUMIFS('E1a Fleet (roll)'!F$7:F$190,'E1a Fleet (roll)'!$A$7:$A$190,"SUV",'E1a Fleet (roll)'!$C$7:$C$190,1) | F24: =SUMIFS('E1a Fleet (roll)'!G$7:G$190,'E1a Fleet (roll)'!$A$7:$A$190,"SUV",'E1a Fleet (roll)'!$C$7:$C$190,1) | G24: =SUMIFS('E1a Fleet (roll)'!H$7:H$190,'E1a Fleet (roll)'!$A$7:$A$190,"SUV",'E1a Fleet (roll)'!$C$7:$C$190,1) | H24: =SUMIFS('E1a Fleet (roll)'!I$7:I$190,'E1a Fleet (roll)'!$A$7:$A$190,"SUV",'E1a Fleet (roll)'!$C$7:$C$190,1) | I24: =SUMIFS('E1a Fleet (roll)'!J$7:J$190,'E1a Fleet (roll)'!$A$7:$A$190,"SUV",'E1a Fleet (roll)'!$C$7:$C$190,1) | J24: =SUMIFS('E1a Fleet (roll)'!K$7:K$190,'E1a Fleet (roll)'!$A$7:$A$190,"SUV",'E1a Fleet (roll)'!$C$7:$C$190,1) | K24: =SUMIFS('E1a Fleet (roll)'!L$7:L$190,'E1a Fleet (roll)'!$A$7:$A$190,"SUV",'E1a Fleet (roll)'!$C$7:$C$190,1) | ... M24: =SUMIFS('E1a Fleet (roll)'!N$7:N$190,'E1a Fleet (roll)'!$A$7:$A$190,"SUV",'E1a Fleet (roll)'!$C$7:$C$190,1) | N24: – | O24: – | P24: – | Q24: – | R24: –
B25: Utility vehicle (SUV) — 4–6 years | C25: 000s | D25: =SUMIFS('E1a Fleet (roll)'!E$7:E$190,'E1a Fleet (roll)'!$A$7:$A$190,"SUV",'E1a Fleet (roll)'!$C$7:$C$190,2) | E25: =SUMIFS('E1a Fleet (roll)'!F$7:F$190,'E1a Fleet (roll)'!$A$7:$A$190,"SUV",'E1a Fleet (roll)'!$C$7:$C$190,2) | F25: =SUMIFS('E1a Fleet (roll)'!G$7:G$190,'E1a Fleet (roll)'!$A$7:$A$190,"SUV",'E1a Fleet (roll)'!$C$7:$C$190,2) | G25: =SUMIFS('E1a Fleet (roll)'!H$7:H$190,'E1a Fleet (roll)'!$A$7:$A$190,"SUV",'E1a Fleet (roll)'!$C$7:$C$190,2) | H25: =SUMIFS('E1a Fleet (roll)'!I$7:I$190,'E1a Fleet (roll)'!$A$7:$A$190,"SUV",'E1a Fleet (roll)'!$C$7:$C$190,2) | I25: =SUMIFS('E1a Fleet (roll)'!J$7:J$190,'E1a Fleet (roll)'!$A$7:$A$190,"SUV",'E1a Fleet (roll)'!$C$7:$C$190,2) | J25: =SUMIFS('E1a Fleet (roll)'!K$7:K$190,'E1a Fleet (roll)'!$A$7:$A$190,"SUV",'E1a Fleet (roll)'!$C$7:$C$190,2) | K25: =SUMIFS('E1a Fleet (roll)'!L$7:L$190,'E1a Fleet (roll)'!$A$7:$A$190,"SUV",'E1a Fleet (roll)'!$C$7:$C$190,2) | ... M25: =SUMIFS('E1a Fleet (roll)'!N$7:N$190,'E1a Fleet (roll)'!$A$7:$A$190,"SUV",'E1a Fleet (roll)'!$C$7:$C$190,2) | N25: – | O25: – | P25: – | Q25: – | R25: –
B26: Utility vehicle (SUV) — 7+ years | C26: 000s | D26: =SUMIFS('E1a Fleet (roll)'!E$7:E$190,'E1a Fleet (roll)'!$A$7:$A$190,"SUV",'E1a Fleet (roll)'!$C$7:$C$190,3) | E26: =SUMIFS('E1a Fleet (roll)'!F$7:F$190,'E1a Fleet (roll)'!$A$7:$A$190,"SUV",'E1a Fleet (roll)'!$C$7:$C$190,3) | F26: =SUMIFS('E1a Fleet (roll)'!G$7:G$190,'E1a Fleet (roll)'!$A$7:$A$190,"SUV",'E1a Fleet (roll)'!$C$7:$C$190,3) | G26: =SUMIFS('E1a Fleet (roll)'!H$7:H$190,'E1a Fleet (roll)'!$A$7:$A$190,"SUV",'E1a Fleet (roll)'!$C$7:$C$190,3) | H26: =SUMIFS('E1a Fleet (roll)'!I$7:I$190,'E1a Fleet (roll)'!$A$7:$A$190,"SUV",'E1a Fleet (roll)'!$C$7:$C$190,3) | I26: =SUMIFS('E1a Fleet (roll)'!J$7:J$190,'E1a Fleet (roll)'!$A$7:$A$190,"SUV",'E1a Fleet (roll)'!$C$7:$C$190,3) | J26: =SUMIFS('E1a Fleet (roll)'!K$7:K$190,'E1a Fleet (roll)'!$A$7:$A$190,"SUV",'E1a Fleet (roll)'!$C$7:$C$190,3) | K26: =SUMIFS('E1a Fleet (roll)'!L$7:L$190,'E1a Fleet (roll)'!$A$7:$A$190,"SUV",'E1a Fleet (roll)'!$C$7:$C$190,3) | ... M26: =SUMIFS('E1a Fleet (roll)'!N$7:N$190,'E1a Fleet (roll)'!$A$7:$A$190,"SUV",'E1a Fleet (roll)'!$C$7:$C$190,3) | N26: – | O26: – | P26: – | Q26: – | R26: –
B27: Pickup — 0 (current or newer) | C27: 000s | D27: =SUMIFS('E1a Fleet (roll)'!E$7:E$190,'E1a Fleet (roll)'!$A$7:$A$190,"Pickup",'E1a Fleet (roll)'!$C$7:$C$190,0) | E27: =SUMIFS('E1a Fleet (roll)'!F$7:F$190,'E1a Fleet (roll)'!$A$7:$A$190,"Pickup",'E1a Fleet (roll)'!$C$7:$C$190,0) | F27: =SUMIFS('E1a Fleet (roll)'!G$7:G$190,'E1a Fleet (roll)'!$A$7:$A$190,"Pickup",'E1a Fleet (roll)'!$C$7:$C$190,0) | G27: =SUMIFS('E1a Fleet (roll)'!H$7:H$190,'E1a Fleet (roll)'!$A$7:$A$190,"Pickup",'E1a Fleet (roll)'!$C$7:$C$190,0) | H27: =SUMIFS('E1a Fleet (roll)'!I$7:I$190,'E1a Fleet (roll)'!$A$7:$A$190,"Pickup",'E1a Fleet (roll)'!$C$7:$C$190,0) | I27: =SUMIFS('E1a Fleet (roll)'!J$7:J$190,'E1a Fleet (roll)'!$A$7:$A$190,"Pickup",'E1a Fleet (roll)'!$C$7:$C$190,0) | J27: =SUMIFS('E1a Fleet (roll)'!K$7:K$190,'E1a Fleet (roll)'!$A$7:$A$190,"Pickup",'E1a Fleet (roll)'!$C$7:$C$190,0) | K27: =SUMIFS('E1a Fleet (roll)'!L$7:L$190,'E1a Fleet (roll)'!$A$7:$A$190,"Pickup",'E1a Fleet (roll)'!$C$7:$C$190,0) | ... M27: =SUMIFS('E1a Fleet (roll)'!N$7:N$190,'E1a Fleet (roll)'!$A$7:$A$190,"Pickup",'E1a Fleet (roll)'!$C$7:$C$190,0) | N27: – | O27: – | P27: – | Q27: – | R27: –
B28: Pickup — 1–3 years | C28: 000s | D28: =SUMIFS('E1a Fleet (roll)'!E$7:E$190,'E1a Fleet (roll)'!$A$7:$A$190,"Pickup",'E1a Fleet (roll)'!$C$7:$C$190,1) | E28: =SUMIFS('E1a Fleet (roll)'!F$7:F$190,'E1a Fleet (roll)'!$A$7:$A$190,"Pickup",'E1a Fleet (roll)'!$C$7:$C$190,1) | F28: =SUMIFS('E1a Fleet (roll)'!G$7:G$190,'E1a Fleet (roll)'!$A$7:$A$190,"Pickup",'E1a Fleet (roll)'!$C$7:$C$190,1) | G28: =SUMIFS('E1a Fleet (roll)'!H$7:H$190,'E1a Fleet (roll)'!$A$7:$A$190,"Pickup",'E1a Fleet (roll)'!$C$7:$C$190,1) | H28: =SUMIFS('E1a Fleet (roll)'!I$7:I$190,'E1a Fleet (roll)'!$A$7:$A$190,"Pickup",'E1a Fleet (roll)'!$C$7:$C$190,1) | I28: =SUMIFS('E1a Fleet (roll)'!J$7:J$190,'E1a Fleet (roll)'!$A$7:$A$190,"Pickup",'E1a Fleet (roll)'!$C$7:$C$190,1) | J28: =SUMIFS('E1a Fleet (roll)'!K$7:K$190,'E1a Fleet (roll)'!$A$7:$A$190,"Pickup",'E1a Fleet (roll)'!$C$7:$C$190,1) | K28: =SUMIFS('E1a Fleet (roll)'!L$7:L$190,'E1a Fleet (roll)'!$A$7:$A$190,"Pickup",'E1a Fleet (roll)'!$C$7:$C$190,1) | ... M28: =SUMIFS('E1a Fleet (roll)'!N$7:N$190,'E1a Fleet (roll)'!$A$7:$A$190,"Pickup",'E1a Fleet (roll)'!$C$7:$C$190,1) | N28: – | O28: – | P28: – | Q28: – | R28: –
B29: Pickup — 4–6 years | C29: 000s | D29: =SUMIFS('E1a Fleet (roll)'!E$7:E$190,'E1a Fleet (roll)'!$A$7:$A$190,"Pickup",'E1a Fleet (roll)'!$C$7:$C$190,2) | E29: =SUMIFS('E1a Fleet (roll)'!F$7:F$190,'E1a Fleet (roll)'!$A$7:$A$190,"Pickup",'E1a Fleet (roll)'!$C$7:$C$190,2) | F29: =SUMIFS('E1a Fleet (roll)'!G$7:G$190,'E1a Fleet (roll)'!$A$7:$A$190,"Pickup",'E1a Fleet (roll)'!$C$7:$C$190,2) | G29: =SUMIFS('E1a Fleet (roll)'!H$7:H$190,'E1a Fleet (roll)'!$A$7:$A$190,"Pickup",'E1a Fleet (roll)'!$C$7:$C$190,2) | H29: =SUMIFS('E1a Fleet (roll)'!I$7:I$190,'E1a Fleet (roll)'!$A$7:$A$190,"Pickup",'E1a Fleet (roll)'!$C$7:$C$190,2) | I29: =SUMIFS('E1a Fleet (roll)'!J$7:J$190,'E1a Fleet (roll)'!$A$7:$A$190,"Pickup",'E1a Fleet (roll)'!$C$7:$C$190,2) | J29: =SUMIFS('E1a Fleet (roll)'!K$7:K$190,'E1a Fleet (roll)'!$A$7:$A$190,"Pickup",'E1a Fleet (roll)'!$C$7:$C$190,2) | K29: =SUMIFS('E1a Fleet (roll)'!L$7:L$190,'E1a Fleet (roll)'!$A$7:$A$190,"Pickup",'E1a Fleet (roll)'!$C$7:$C$190,2) | ... M29: =SUMIFS('E1a Fleet (roll)'!N$7:N$190,'E1a Fleet (roll)'!$A$7:$A$190,"Pickup",'E1a Fleet (roll)'!$C$7:$C$190,2) | N29: – | O29: – | P29: – | Q29: – | R29: –
B30: Pickup — 7+ years | C30: 000s | D30: =SUMIFS('E1a Fleet (roll)'!E$7:E$190,'E1a Fleet (roll)'!$A$7:$A$190,"Pickup",'E1a Fleet (roll)'!$C$7:$C$190,3) | E30: =SUMIFS('E1a Fleet (roll)'!F$7:F$190,'E1a Fleet (roll)'!$A$7:$A$190,"Pickup",'E1a Fleet (roll)'!$C$7:$C$190,3) | F30: =SUMIFS('E1a Fleet (roll)'!G$7:G$190,'E1a Fleet (roll)'!$A$7:$A$190,"Pickup",'E1a Fleet (roll)'!$C$7:$C$190,3) | G30: =SUMIFS('E1a Fleet (roll)'!H$7:H$190,'E1a Fleet (roll)'!$A$7:$A$190,"Pickup",'E1a Fleet (roll)'!$C$7:$C$190,3) | H30: =SUMIFS('E1a Fleet (roll)'!I$7:I$190,'E1a Fleet (roll)'!$A$7:$A$190,"Pickup",'E1a Fleet (roll)'!$C$7:$C$190,3) | I30: =SUMIFS('E1a Fleet (roll)'!J$7:J$190,'E1a Fleet (roll)'!$A$7:$A$190,"Pickup",'E1a Fleet (roll)'!$C$7:$C$190,3) | J30: =SUMIFS('E1a Fleet (roll)'!K$7:K$190,'E1a Fleet (roll)'!$A$7:$A$190,"Pickup",'E1a Fleet (roll)'!$C$7:$C$190,3) | K30: =SUMIFS('E1a Fleet (roll)'!L$7:L$190,'E1a Fleet (roll)'!$A$7:$A$190,"Pickup",'E1a Fleet (roll)'!$C$7:$C$190,3) | ... M30: =SUMIFS('E1a Fleet (roll)'!N$7:N$190,'E1a Fleet (roll)'!$A$7:$A$190,"Pickup",'E1a Fleet (roll)'!$C$7:$C$190,3) | N30: – | O30: – | P30: – | Q30: – | R30: –
B31: Van / minivan — 0 (current or newer) | C31: 000s | D31: =SUMIFS('E1a Fleet (roll)'!E$7:E$190,'E1a Fleet (roll)'!$A$7:$A$190,"Van",'E1a Fleet (roll)'!$C$7:$C$190,0) | E31: =SUMIFS('E1a Fleet (roll)'!F$7:F$190,'E1a Fleet (roll)'!$A$7:$A$190,"Van",'E1a Fleet (roll)'!$C$7:$C$190,0) | F31: =SUMIFS('E1a Fleet (roll)'!G$7:G$190,'E1a Fleet (roll)'!$A$7:$A$190,"Van",'E1a Fleet (roll)'!$C$7:$C$190,0) | G31: =SUMIFS('E1a Fleet (roll)'!H$7:H$190,'E1a Fleet (roll)'!$A$7:$A$190,"Van",'E1a Fleet (roll)'!$C$7:$C$190,0) | H31: =SUMIFS('E1a Fleet (roll)'!I$7:I$190,'E1a Fleet (roll)'!$A$7:$A$190,"Van",'E1a Fleet (roll)'!$C$7:$C$190,0) | I31: =SUMIFS('E1a Fleet (roll)'!J$7:J$190,'E1a Fleet (roll)'!$A$7:$A$190,"Van",'E1a Fleet (roll)'!$C$7:$C$190,0) | J31: =SUMIFS('E1a Fleet (roll)'!K$7:K$190,'E1a Fleet (roll)'!$A$7:$A$190,"Van",'E1a Fleet (roll)'!$C$7:$C$190,0) | K31: =SUMIFS('E1a Fleet (roll)'!L$7:L$190,'E1a Fleet (roll)'!$A$7:$A$190,"Van",'E1a Fleet (roll)'!$C$7:$C$190,0) | ... M31: =SUMIFS('E1a Fleet (roll)'!N$7:N$190,'E1a Fleet (roll)'!$A$7:$A$190,"Van",'E1a Fleet (roll)'!$C$7:$C$190,0) | N31: – | O31: – | P31: – | Q31: – | R31: –
B32: Van / minivan — 1–3 years | C32: 000s | D32: =SUMIFS('E1a Fleet (roll)'!E$7:E$190,'E1a Fleet (roll)'!$A$7:$A$190,"Van",'E1a Fleet (roll)'!$C$7:$C$190,1) | E32: =SUMIFS('E1a Fleet (roll)'!F$7:F$190,'E1a Fleet (roll)'!$A$7:$A$190,"Van",'E1a Fleet (roll)'!$C$7:$C$190,1) | F32: =SUMIFS('E1a Fleet (roll)'!G$7:G$190,'E1a Fleet (roll)'!$A$7:$A$190,"Van",'E1a Fleet (roll)'!$C$7:$C$190,1) | G32: =SUMIFS('E1a Fleet (roll)'!H$7:H$190,'E1a Fleet (roll)'!$A$7:$A$190,"Van",'E1a Fleet (roll)'!$C$7:$C$190,1) | H32: =SUMIFS('E1a Fleet (roll)'!I$7:I$190,'E1a Fleet (roll)'!$A$7:$A$190,"Van",'E1a Fleet (roll)'!$C$7:$C$190,1) | I32: =SUMIFS('E1a Fleet (roll)'!J$7:J$190,'E1a Fleet (roll)'!$A$7:$A$190,"Van",'E1a Fleet (roll)'!$C$7:$C$190,1) | J32: =SUMIFS('E1a Fleet (roll)'!K$7:K$190,'E1a Fleet (roll)'!$A$7:$A$190,"Van",'E1a Fleet (roll)'!$C$7:$C$190,1) | K32: =SUMIFS('E1a Fleet (roll)'!L$7:L$190,'E1a Fleet (roll)'!$A$7:$A$190,"Van",'E1a Fleet (roll)'!$C$7:$C$190,1) | ... M32: =SUMIFS('E1a Fleet (roll)'!N$7:N$190,'E1a Fleet (roll)'!$A$7:$A$190,"Van",'E1a Fleet (roll)'!$C$7:$C$190,1) | N32: – | O32: – | P32: – | Q32: – | R32: –
B33: Van / minivan — 4–6 years | C33: 000s | D33: =SUMIFS('E1a Fleet (roll)'!E$7:E$190,'E1a Fleet (roll)'!$A$7:$A$190,"Van",'E1a Fleet (roll)'!$C$7:$C$190,2) | E33: =SUMIFS('E1a Fleet (roll)'!F$7:F$190,'E1a Fleet (roll)'!$A$7:$A$190,"Van",'E1a Fleet (roll)'!$C$7:$C$190,2) | F33: =SUMIFS('E1a Fleet (roll)'!G$7:G$190,'E1a Fleet (roll)'!$A$7:$A$190,"Van",'E1a Fleet (roll)'!$C$7:$C$190,2) | G33: =SUMIFS('E1a Fleet (roll)'!H$7:H$190,'E1a Fleet (roll)'!$A$7:$A$190,"Van",'E1a Fleet (roll)'!$C$7:$C$190,2) | H33: =SUMIFS('E1a Fleet (roll)'!I$7:I$190,'E1a Fleet (roll)'!$A$7:$A$190,"Van",'E1a Fleet (roll)'!$C$7:$C$190,2) | I33: =SUMIFS('E1a Fleet (roll)'!J$7:J$190,'E1a Fleet (roll)'!$A$7:$A$190,"Van",'E1a Fleet (roll)'!$C$7:$C$190,2) | J33: =SUMIFS('E1a Fleet (roll)'!K$7:K$190,'E1a Fleet (roll)'!$A$7:$A$190,"Van",'E1a Fleet (roll)'!$C$7:$C$190,2) | K33: =SUMIFS('E1a Fleet (roll)'!L$7:L$190,'E1a Fleet (roll)'!$A$7:$A$190,"Van",'E1a Fleet (roll)'!$C$7:$C$190,2) | ... M33: =SUMIFS('E1a Fleet (roll)'!N$7:N$190,'E1a Fleet (roll)'!$A$7:$A$190,"Van",'E1a Fleet (roll)'!$C$7:$C$190,2) | N33: – | O33: – | P33: – | Q33: – | R33: –
B34: Van / minivan — 7+ years | C34: 000s | D34: =SUMIFS('E1a Fleet (roll)'!E$7:E$190,'E1a Fleet (roll)'!$A$7:$A$190,"Van",'E1a Fleet (roll)'!$C$7:$C$190,3) | E34: =SUMIFS('E1a Fleet (roll)'!F$7:F$190,'E1a Fleet (roll)'!$A$7:$A$190,"Van",'E1a Fleet (roll)'!$C$7:$C$190,3) | F34: =SUMIFS('E1a Fleet (roll)'!G$7:G$190,'E1a Fleet (roll)'!$A$7:$A$190,"Van",'E1a Fleet (roll)'!$C$7:$C$190,3) | G34: =SUMIFS('E1a Fleet (roll)'!H$7:H$190,'E1a Fleet (roll)'!$A$7:$A$190,"Van",'E1a Fleet (roll)'!$C$7:$C$190,3) | H34: =SUMIFS('E1a Fleet (roll)'!I$7:I$190,'E1a Fleet (roll)'!$A$7:$A$190,"Van",'E1a Fleet (roll)'!$C$7:$C$190,3) | I34: =SUMIFS('E1a Fleet (roll)'!J$7:J$190,'E1a Fleet (roll)'!$A$7:$A$190,"Van",'E1a Fleet (roll)'!$C$7:$C$190,3) | J34: =SUMIFS('E1a Fleet (roll)'!K$7:K$190,'E1a Fleet (roll)'!$A$7:$A$190,"Van",'E1a Fleet (roll)'!$C$7:$C$190,3) | K34: =SUMIFS('E1a Fleet (roll)'!L$7:L$190,'E1a Fleet (roll)'!$A$7:$A$190,"Van",'E1a Fleet (roll)'!$C$7:$C$190,3) | ... M34: =SUMIFS('E1a Fleet (roll)'!N$7:N$190,'E1a Fleet (roll)'!$A$7:$A$190,"Van",'E1a Fleet (roll)'!$C$7:$C$190,3) | N34: – | O34: – | P34: – | Q34: – | R34: –
B35: Total vehicles on the road | C35: 000s | D35: =SUM(D19:D34) | E35: =SUM(E19:E34) | F35: =SUM(F19:F34) | G35: =SUM(G19:G34) | H35: =SUM(H19:H34) | I35: =SUM(I19:I34) | J35: =SUM(J19:J34) | K35: =SUM(K19:K34) | ... M35: =SUM(M19:M34) | N35: – | O35: – | P35: – | Q35: – | R35: –
B36: share aged 7+ | C36: % | D36: =SUMIFS('E1a Fleet (roll)'!D$7:D$190,'E1a Fleet (roll)'!$C$7:$C$190,3)/D35 | E36: =SUMIFS('E1a Fleet (roll)'!E$7:E$190,'E1a Fleet (roll)'!$C$7:$C$190,3)/E35 | F36: =SUMIFS('E1a Fleet (roll)'!F$7:F$190,'E1a Fleet (roll)'!$C$7:$C$190,3)/F35 | G36: =SUMIFS('E1a Fleet (roll)'!G$7:G$190,'E1a Fleet (roll)'!$C$7:$C$190,3)/G35 | H36: =SUMIFS('E1a Fleet (roll)'!H$7:H$190,'E1a Fleet (roll)'!$C$7:$C$190,3)/H35 | I36: =SUMIFS('E1a Fleet (roll)'!I$7:I$190,'E1a Fleet (roll)'!$C$7:$C$190,3)/I35 | J36: =SUMIFS('E1a Fleet (roll)'!J$7:J$190,'E1a Fleet (roll)'!$C$7:$C$190,3)/J35 | K36: =SUMIFS('E1a Fleet (roll)'!K$7:K$190,'E1a Fleet (roll)'!$C$7:$C$190,3)/K35 | ... M36: =SUMIFS('E1a Fleet (roll)'!M$7:M$190,'E1a Fleet (roll)'!$C$7:$C$190,3)/M35 | N36: – | O36: – | P36: – | Q36: – | R36: –
B39: D. Claims-weighted composition: share of claims by body × age band (model = fleet × R(age) × body factor; CCC-implied = TL mix ÷ TLF, normalised)
B40: Model: Car — 0 (current or newer) | C40: % | D40: =SUMIFS('E1a Fleet (roll)'!P$7:P$190,'E1a Fleet (roll)'!$A$7:$A$190,"Car",'E1a Fleet (roll)'!$C$7:$C$190,0)/SUM('E1a Fleet (roll)'!P$7:P$190) | E40: =SUMIFS('E1a Fleet (roll)'!Q$7:Q$190,'E1a Fleet (roll)'!$A$7:$A$190,"Car",'E1a Fleet (roll)'!$C$7:$C$190,0)/SUM('E1a Fleet (roll)'!Q$7:Q$190) | F40: =SUMIFS('E1a Fleet (roll)'!R$7:R$190,'E1a Fleet (roll)'!$A$7:$A$190,"Car",'E1a Fleet (roll)'!$C$7:$C$190,0)/SUM('E1a Fleet (roll)'!R$7:R$190) | G40: =SUMIFS('E1a Fleet (roll)'!S$7:S$190,'E1a Fleet (roll)'!$A$7:$A$190,"Car",'E1a Fleet (roll)'!$C$7:$C$190,0)/SUM('E1a Fleet (roll)'!S$7:S$190) | H40: =SUMIFS('E1a Fleet (roll)'!T$7:T$190,'E1a Fleet (roll)'!$A$7:$A$190,"Car",'E1a Fleet (roll)'!$C$7:$C$190,0)/SUM('E1a Fleet (roll)'!T$7:T$190) | I40: =SUMIFS('E1a Fleet (roll)'!U$7:U$190,'E1a Fleet (roll)'!$A$7:$A$190,"Car",'E1a Fleet (roll)'!$C$7:$C$190,0)/SUM('E1a Fleet (roll)'!U$7:U$190) | J40: =SUMIFS('E1a Fleet (roll)'!V$7:V$190,'E1a Fleet (roll)'!$A$7:$A$190,"Car",'E1a Fleet (roll)'!$C$7:$C$190,0)/SUM('E1a Fleet (roll)'!V$7:V$190) | K40: =SUMIFS('E1a Fleet (roll)'!W$7:W$190,'E1a Fleet (roll)'!$A$7:$A$190,"Car",'E1a Fleet (roll)'!$C$7:$C$190,0)/SUM('E1a Fleet (roll)'!W$7:W$190) | ... M40: =SUMIFS('E1a Fleet (roll)'!Y$7:Y$190,'E1a Fleet (roll)'!$A$7:$A$190,"Car",'E1a Fleet (roll)'!$C$7:$C$190,0)/SUM('E1a Fleet (roll)'!Y$7:Y$190) | N40: – | O40: – | P40: – | Q40: – | R40: –
B41: Model: Car — 1–3 years | C41: % | D41: =SUMIFS('E1a Fleet (roll)'!P$7:P$190,'E1a Fleet (roll)'!$A$7:$A$190,"Car",'E1a Fleet (roll)'!$C$7:$C$190,1)/SUM('E1a Fleet (roll)'!P$7:P$190) | E41: =SUMIFS('E1a Fleet (roll)'!Q$7:Q$190,'E1a Fleet (roll)'!$A$7:$A$190,"Car",'E1a Fleet (roll)'!$C$7:$C$190,1)/SUM('E1a Fleet (roll)'!Q$7:Q$190) | F41: =SUMIFS('E1a Fleet (roll)'!R$7:R$190,'E1a Fleet (roll)'!$A$7:$A$190,"Car",'E1a Fleet (roll)'!$C$7:$C$190,1)/SUM('E1a Fleet (roll)'!R$7:R$190) | G41: =SUMIFS('E1a Fleet (roll)'!S$7:S$190,'E1a Fleet (roll)'!$A$7:$A$190,"Car",'E1a Fleet (roll)'!$C$7:$C$190,1)/SUM('E1a Fleet (roll)'!S$7:S$190) | H41: =SUMIFS('E1a Fleet (roll)'!T$7:T$190,'E1a Fleet (roll)'!$A$7:$A$190,"Car",'E1a Fleet (roll)'!$C$7:$C$190,1)/SUM('E1a Fleet (roll)'!T$7:T$190) | I41: =SUMIFS('E1a Fleet (roll)'!U$7:U$190,'E1a Fleet (roll)'!$A$7:$A$190,"Car",'E1a Fleet (roll)'!$C$7:$C$190,1)/SUM('E1a Fleet (roll)'!U$7:U$190) | J41: =SUMIFS('E1a Fleet (roll)'!V$7:V$190,'E1a Fleet (roll)'!$A$7:$A$190,"Car",'E1a Fleet (roll)'!$C$7:$C$190,1)/SUM('E1a Fleet (roll)'!V$7:V$190) | K41: =SUMIFS('E1a Fleet (roll)'!W$7:W$190,'E1a Fleet (roll)'!$A$7:$A$190,"Car",'E1a Fleet (roll)'!$C$7:$C$190,1)/SUM('E1a Fleet (roll)'!W$7:W$190) | ... M41: =SUMIFS('E1a Fleet (roll)'!Y$7:Y$190,'E1a Fleet (roll)'!$A$7:$A$190,"Car",'E1a Fleet (roll)'!$C$7:$C$190,1)/SUM('E1a Fleet (roll)'!Y$7:Y$190) | N41: – | O41: – | P41: – | Q41: – | R41: –
B42: Model: Car — 4–6 years | C42: % | D42: =SUMIFS('E1a Fleet (roll)'!P$7:P$190,'E1a Fleet (roll)'!$A$7:$A$190,"Car",'E1a Fleet (roll)'!$C$7:$C$190,2)/SUM('E1a Fleet (roll)'!P$7:P$190) | E42: =SUMIFS('E1a Fleet (roll)'!Q$7:Q$190,'E1a Fleet (roll)'!$A$7:$A$190,"Car",'E1a Fleet (roll)'!$C$7:$C$190,2)/SUM('E1a Fleet (roll)'!Q$7:Q$190) | F42: =SUMIFS('E1a Fleet (roll)'!R$7:R$190,'E1a Fleet (roll)'!$A$7:$A$190,"Car",'E1a Fleet (roll)'!$C$7:$C$190,2)/SUM('E1a Fleet (roll)'!R$7:R$190) | G42: =SUMIFS('E1a Fleet (roll)'!S$7:S$190,'E1a Fleet (roll)'!$A$7:$A$190,"Car",'E1a Fleet (roll)'!$C$7:$C$190,2)/SUM('E1a Fleet (roll)'!S$7:S$190) | H42: =SUMIFS('E1a Fleet (roll)'!T$7:T$190,'E1a Fleet (roll)'!$A$7:$A$190,"Car",'E1a Fleet (roll)'!$C$7:$C$190,2)/SUM('E1a Fleet (roll)'!T$7:T$190) | I42: =SUMIFS('E1a Fleet (roll)'!U$7:U$190,'E1a Fleet (roll)'!$A$7:$A$190,"Car",'E1a Fleet (roll)'!$C$7:$C$190,2)/SUM('E1a Fleet (roll)'!U$7:U$190) | J42: =SUMIFS('E1a Fleet (roll)'!V$7:V$190,'E1a Fleet (roll)'!$A$7:$A$190,"Car",'E1a Fleet (roll)'!$C$7:$C$190,2)/SUM('E1a Fleet (roll)'!V$7:V$190) | K42: =SUMIFS('E1a Fleet (roll)'!W$7:W$190,'E1a Fleet (roll)'!$A$7:$A$190,"Car",'E1a Fleet (roll)'!$C$7:$C$190,2)/SUM('E1a Fleet (roll)'!W$7:W$190) | ... M42: =SUMIFS('E1a Fleet (roll)'!Y$7:Y$190,'E1a Fleet (roll)'!$A$7:$A$190,"Car",'E1a Fleet (roll)'!$C$7:$C$190,2)/SUM('E1a Fleet (roll)'!Y$7:Y$190) | N42: – | O42: – | P42: – | Q42: – | R42: –
B43: Model: Car — 7+ years | C43: % | D43: =SUMIFS('E1a Fleet (roll)'!P$7:P$190,'E1a Fleet (roll)'!$A$7:$A$190,"Car",'E1a Fleet (roll)'!$C$7:$C$190,3)/SUM('E1a Fleet (roll)'!P$7:P$190) | E43: =SUMIFS('E1a Fleet (roll)'!Q$7:Q$190,'E1a Fleet (roll)'!$A$7:$A$190,"Car",'E1a Fleet (roll)'!$C$7:$C$190,3)/SUM('E1a Fleet (roll)'!Q$7:Q$190) | F43: =SUMIFS('E1a Fleet (roll)'!R$7:R$190,'E1a Fleet (roll)'!$A$7:$A$190,"Car",'E1a Fleet (roll)'!$C$7:$C$190,3)/SUM('E1a Fleet (roll)'!R$7:R$190) | G43: =SUMIFS('E1a Fleet (roll)'!S$7:S$190,'E1a Fleet (roll)'!$A$7:$A$190,"Car",'E1a Fleet (roll)'!$C$7:$C$190,3)/SUM('E1a Fleet (roll)'!S$7:S$190) | H43: =SUMIFS('E1a Fleet (roll)'!T$7:T$190,'E1a Fleet (roll)'!$A$7:$A$190,"Car",'E1a Fleet (roll)'!$C$7:$C$190,3)/SUM('E1a Fleet (roll)'!T$7:T$190) | I43: =SUMIFS('E1a Fleet (roll)'!U$7:U$190,'E1a Fleet (roll)'!$A$7:$A$190,"Car",'E1a Fleet (roll)'!$C$7:$C$190,3)/SUM('E1a Fleet (roll)'!U$7:U$190) | J43: =SUMIFS('E1a Fleet (roll)'!V$7:V$190,'E1a Fleet (roll)'!$A$7:$A$190,"Car",'E1a Fleet (roll)'!$C$7:$C$190,3)/SUM('E1a Fleet (roll)'!V$7:V$190) | K43: =SUMIFS('E1a Fleet (roll)'!W$7:W$190,'E1a Fleet (roll)'!$A$7:$A$190,"Car",'E1a Fleet (roll)'!$C$7:$C$190,3)/SUM('E1a Fleet (roll)'!W$7:W$190) | ... M43: =SUMIFS('E1a Fleet (roll)'!Y$7:Y$190,'E1a Fleet (roll)'!$A$7:$A$190,"Car",'E1a Fleet (roll)'!$C$7:$C$190,3)/SUM('E1a Fleet (roll)'!Y$7:Y$190) | N43: – | O43: – | P43: – | Q43: – | R43: –
B44: Model: Utility vehicle (SUV) — 0 (current or newer) | C44: % | D44: =SUMIFS('E1a Fleet (roll)'!P$7:P$190,'E1a Fleet (roll)'!$A$7:$A$190,"SUV",'E1a Fleet (roll)'!$C$7:$C$190,0)/SUM('E1a Fleet (roll)'!P$7:P$190) | E44: =SUMIFS('E1a Fleet (roll)'!Q$7:Q$190,'E1a Fleet (roll)'!$A$7:$A$190,"SUV",'E1a Fleet (roll)'!$C$7:$C$190,0)/SUM('E1a Fleet (roll)'!Q$7:Q$190) | F44: =SUMIFS('E1a Fleet (roll)'!R$7:R$190,'E1a Fleet (roll)'!$A$7:$A$190,"SUV",'E1a Fleet (roll)'!$C$7:$C$190,0)/SUM('E1a Fleet (roll)'!R$7:R$190) | G44: =SUMIFS('E1a Fleet (roll)'!S$7:S$190,'E1a Fleet (roll)'!$A$7:$A$190,"SUV",'E1a Fleet (roll)'!$C$7:$C$190,0)/SUM('E1a Fleet (roll)'!S$7:S$190) | H44: =SUMIFS('E1a Fleet (roll)'!T$7:T$190,'E1a Fleet (roll)'!$A$7:$A$190,"SUV",'E1a Fleet (roll)'!$C$7:$C$190,0)/SUM('E1a Fleet (roll)'!T$7:T$190) | I44: =SUMIFS('E1a Fleet (roll)'!U$7:U$190,'E1a Fleet (roll)'!$A$7:$A$190,"SUV",'E1a Fleet (roll)'!$C$7:$C$190,0)/SUM('E1a Fleet (roll)'!U$7:U$190) | J44: =SUMIFS('E1a Fleet (roll)'!V$7:V$190,'E1a Fleet (roll)'!$A$7:$A$190,"SUV",'E1a Fleet (roll)'!$C$7:$C$190,0)/SUM('E1a Fleet (roll)'!V$7:V$190) | K44: =SUMIFS('E1a Fleet (roll)'!W$7:W$190,'E1a Fleet (roll)'!$A$7:$A$190,"SUV",'E1a Fleet (roll)'!$C$7:$C$190,0)/SUM('E1a Fleet (roll)'!W$7:W$190) | ... M44: =SUMIFS('E1a Fleet (roll)'!Y$7:Y$190,'E1a Fleet (roll)'!$A$7:$A$190,"SUV",'E1a Fleet (roll)'!$C$7:$C$190,0)/SUM('E1a Fleet (roll)'!Y$7:Y$190) | N44: – | O44: – | P44: – | Q44: – | R44: –
B45: Model: Utility vehicle (SUV) — 1–3 years | C45: % | D45: =SUMIFS('E1a Fleet (roll)'!P$7:P$190,'E1a Fleet (roll)'!$A$7:$A$190,"SUV",'E1a Fleet (roll)'!$C$7:$C$190,1)/SUM('E1a Fleet (roll)'!P$7:P$190) | E45: =SUMIFS('E1a Fleet (roll)'!Q$7:Q$190,'E1a Fleet (roll)'!$A$7:$A$190,"SUV",'E1a Fleet (roll)'!$C$7:$C$190,1)/SUM('E1a Fleet (roll)'!Q$7:Q$190) | F45: =SUMIFS('E1a Fleet (roll)'!R$7:R$190,'E1a Fleet (roll)'!$A$7:$A$190,"SUV",'E1a Fleet (roll)'!$C$7:$C$190,1)/SUM('E1a Fleet (roll)'!R$7:R$190) | G45: =SUMIFS('E1a Fleet (roll)'!S$7:S$190,'E1a Fleet (roll)'!$A$7:$A$190,"SUV",'E1a Fleet (roll)'!$C$7:$C$190,1)/SUM('E1a Fleet (roll)'!S$7:S$190) | H45: =SUMIFS('E1a Fleet (roll)'!T$7:T$190,'E1a Fleet (roll)'!$A$7:$A$190,"SUV",'E1a Fleet (roll)'!$C$7:$C$190,1)/SUM('E1a Fleet (roll)'!T$7:T$190) | I45: =SUMIFS('E1a Fleet (roll)'!U$7:U$190,'E1a Fleet (roll)'!$A$7:$A$190,"SUV",'E1a Fleet (roll)'!$C$7:$C$190,1)/SUM('E1a Fleet (roll)'!U$7:U$190) | J45: =SUMIFS('E1a Fleet (roll)'!V$7:V$190,'E1a Fleet (roll)'!$A$7:$A$190,"SUV",'E1a Fleet (roll)'!$C$7:$C$190,1)/SUM('E1a Fleet (roll)'!V$7:V$190) | K45: =SUMIFS('E1a Fleet (roll)'!W$7:W$190,'E1a Fleet (roll)'!$A$7:$A$190,"SUV",'E1a Fleet (roll)'!$C$7:$C$190,1)/SUM('E1a Fleet (roll)'!W$7:W$190) | ... M45: =SUMIFS('E1a Fleet (roll)'!Y$7:Y$190,'E1a Fleet (roll)'!$A$7:$A$190,"SUV",'E1a Fleet (roll)'!$C$7:$C$190,1)/SUM('E1a Fleet (roll)'!Y$7:Y$190) | N45: – | O45: – | P45: – | Q45: – | R45: –
B46: Model: Utility vehicle (SUV) — 4–6 years | C46: % | D46: =SUMIFS('E1a Fleet (roll)'!P$7:P$190,'E1a Fleet (roll)'!$A$7:$A$190,"SUV",'E1a Fleet (roll)'!$C$7:$C$190,2)/SUM('E1a Fleet (roll)'!P$7:P$190) | E46: =SUMIFS('E1a Fleet (roll)'!Q$7:Q$190,'E1a Fleet (roll)'!$A$7:$A$190,"SUV",'E1a Fleet (roll)'!$C$7:$C$190,2)/SUM('E1a Fleet (roll)'!Q$7:Q$190) | F46: =SUMIFS('E1a Fleet (roll)'!R$7:R$190,'E1a Fleet (roll)'!$A$7:$A$190,"SUV",'E1a Fleet (roll)'!$C$7:$C$190,2)/SUM('E1a Fleet (roll)'!R$7:R$190) | G46: =SUMIFS('E1a Fleet (roll)'!S$7:S$190,'E1a Fleet (roll)'!$A$7:$A$190,"SUV",'E1a Fleet (roll)'!$C$7:$C$190,2)/SUM('E1a Fleet (roll)'!S$7:S$190) | H46: =SUMIFS('E1a Fleet (roll)'!T$7:T$190,'E1a Fleet (roll)'!$A$7:$A$190,"SUV",'E1a Fleet (roll)'!$C$7:$C$190,2)/SUM('E1a Fleet (roll)'!T$7:T$190) | I46: =SUMIFS('E1a Fleet (roll)'!U$7:U$190,'E1a Fleet (roll)'!$A$7:$A$190,"SUV",'E1a Fleet (roll)'!$C$7:$C$190,2)/SUM('E1a Fleet (roll)'!U$7:U$190) | J46: =SUMIFS('E1a Fleet (roll)'!V$7:V$190,'E1a Fleet (roll)'!$A$7:$A$190,"SUV",'E1a Fleet (roll)'!$C$7:$C$190,2)/SUM('E1a Fleet (roll)'!V$7:V$190) | K46: =SUMIFS('E1a Fleet (roll)'!W$7:W$190,'E1a Fleet (roll)'!$A$7:$A$190,"SUV",'E1a Fleet (roll)'!$C$7:$C$190,2)/SUM('E1a Fleet (roll)'!W$7:W$190) | ... M46: =SUMIFS('E1a Fleet (roll)'!Y$7:Y$190,'E1a Fleet (roll)'!$A$7:$A$190,"SUV",'E1a Fleet (roll)'!$C$7:$C$190,2)/SUM('E1a Fleet (roll)'!Y$7:Y$190) | N46: – | O46: – | P46: – | Q46: – | R46: –
B47: Model: Utility vehicle (SUV) — 7+ years | C47: % | D47: =SUMIFS('E1a Fleet (roll)'!P$7:P$190,'E1a Fleet (roll)'!$A$7:$A$190,"SUV",'E1a Fleet (roll)'!$C$7:$C$190,3)/SUM('E1a Fleet (roll)'!P$7:P$190) | E47: =SUMIFS('E1a Fleet (roll)'!Q$7:Q$190,'E1a Fleet (roll)'!$A$7:$A$190,"SUV",'E1a Fleet (roll)'!$C$7:$C$190,3)/SUM('E1a Fleet (roll)'!Q$7:Q$190) | F47: =SUMIFS('E1a Fleet (roll)'!R$7:R$190,'E1a Fleet (roll)'!$A$7:$A$190,"SUV",'E1a Fleet (roll)'!$C$7:$C$190,3)/SUM('E1a Fleet (roll)'!R$7:R$190) | G47: =SUMIFS('E1a Fleet (roll)'!S$7:S$190,'E1a Fleet (roll)'!$A$7:$A$190,"SUV",'E1a Fleet (roll)'!$C$7:$C$190,3)/SUM('E1a Fleet (roll)'!S$7:S$190) | H47: =SUMIFS('E1a Fleet (roll)'!T$7:T$190,'E1a Fleet (roll)'!$A$7:$A$190,"SUV",'E1a Fleet (roll)'!$C$7:$C$190,3)/SUM('E1a Fleet (roll)'!T$7:T$190) | I47: =SUMIFS('E1a Fleet (roll)'!U$7:U$190,'E1a Fleet (roll)'!$A$7:$A$190,"SUV",'E1a Fleet (roll)'!$C$7:$C$190,3)/SUM('E1a Fleet (roll)'!U$7:U$190) | J47: =SUMIFS('E1a Fleet (roll)'!V$7:V$190,'E1a Fleet (roll)'!$A$7:$A$190,"SUV",'E1a Fleet (roll)'!$C$7:$C$190,3)/SUM('E1a Fleet (roll)'!V$7:V$190) | K47: =SUMIFS('E1a Fleet (roll)'!W$7:W$190,'E1a Fleet (roll)'!$A$7:$A$190,"SUV",'E1a Fleet (roll)'!$C$7:$C$190,3)/SUM('E1a Fleet (roll)'!W$7:W$190) | ... M47: =SUMIFS('E1a Fleet (roll)'!Y$7:Y$190,'E1a Fleet (roll)'!$A$7:$A$190,"SUV",'E1a Fleet (roll)'!$C$7:$C$190,3)/SUM('E1a Fleet (roll)'!Y$7:Y$190) | N47: – | O47: – | P47: – | Q47: – | R47: –
B48: Model: Pickup — 0 (current or newer) | C48: % | D48: =SUMIFS('E1a Fleet (roll)'!P$7:P$190,'E1a Fleet (roll)'!$A$7:$A$190,"Pickup",'E1a Fleet (roll)'!$C$7:$C$190,0)/SUM('E1a Fleet (roll)'!P$7:P$190) | E48: =SUMIFS('E1a Fleet (roll)'!Q$7:Q$190,'E1a Fleet (roll)'!$A$7:$A$190,"Pickup",'E1a Fleet (roll)'!$C$7:$C$190,0)/SUM('E1a Fleet (roll)'!Q$7:Q$190) | F48: =SUMIFS('E1a Fleet (roll)'!R$7:R$190,'E1a Fleet (roll)'!$A$7:$A$190,"Pickup",'E1a Fleet (roll)'!$C$7:$C$190,0)/SUM('E1a Fleet (roll)'!R$7:R$190) | G48: =SUMIFS('E1a Fleet (roll)'!S$7:S$190,'E1a Fleet (roll)'!$A$7:$A$190,"Pickup",'E1a Fleet (roll)'!$C$7:$C$190,0)/SUM('E1a Fleet (roll)'!S$7:S$190) | H48: =SUMIFS('E1a Fleet (roll)'!T$7:T$190,'E1a Fleet (roll)'!$A$7:$A$190,"Pickup",'E1a Fleet (roll)'!$C$7:$C$190,0)/SUM('E1a Fleet (roll)'!T$7:T$190) | I48: =SUMIFS('E1a Fleet (roll)'!U$7:U$190,'E1a Fleet (roll)'!$A$7:$A$190,"Pickup",'E1a Fleet (roll)'!$C$7:$C$190,0)/SUM('E1a Fleet (roll)'!U$7:U$190) | J48: =SUMIFS('E1a Fleet (roll)'!V$7:V$190,'E1a Fleet (roll)'!$A$7:$A$190,"Pickup",'E1a Fleet (roll)'!$C$7:$C$190,0)/SUM('E1a Fleet (roll)'!V$7:V$190) | K48: =SUMIFS('E1a Fleet (roll)'!W$7:W$190,'E1a Fleet (roll)'!$A$7:$A$190,"Pickup",'E1a Fleet (roll)'!$C$7:$C$190,0)/SUM('E1a Fleet (roll)'!W$7:W$190) | ... M48: =SUMIFS('E1a Fleet (roll)'!Y$7:Y$190,'E1a Fleet (roll)'!$A$7:$A$190,"Pickup",'E1a Fleet (roll)'!$C$7:$C$190,0)/SUM('E1a Fleet (roll)'!Y$7:Y$190) | N48: – | O48: – | P48: – | Q48: – | R48: –
B49: Model: Pickup — 1–3 years | C49: % | D49: =SUMIFS('E1a Fleet (roll)'!P$7:P$190,'E1a Fleet (roll)'!$A$7:$A$190,"Pickup",'E1a Fleet (roll)'!$C$7:$C$190,1)/SUM('E1a Fleet (roll)'!P$7:P$190) | E49: =SUMIFS('E1a Fleet (roll)'!Q$7:Q$190,'E1a Fleet (roll)'!$A$7:$A$190,"Pickup",'E1a Fleet (roll)'!$C$7:$C$190,1)/SUM('E1a Fleet (roll)'!Q$7:Q$190) | F49: =SUMIFS('E1a Fleet (roll)'!R$7:R$190,'E1a Fleet (roll)'!$A$7:$A$190,"Pickup",'E1a Fleet (roll)'!$C$7:$C$190,1)/SUM('E1a Fleet (roll)'!R$7:R$190) | G49: =SUMIFS('E1a Fleet (roll)'!S$7:S$190,'E1a Fleet (roll)'!$A$7:$A$190,"Pickup",'E1a Fleet (roll)'!$C$7:$C$190,1)/SUM('E1a Fleet (roll)'!S$7:S$190) | H49: =SUMIFS('E1a Fleet (roll)'!T$7:T$190,'E1a Fleet (roll)'!$A$7:$A$190,"Pickup",'E1a Fleet (roll)'!$C$7:$C$190,1)/SUM('E1a Fleet (roll)'!T$7:T$190) | I49: =SUMIFS('E1a Fleet (roll)'!U$7:U$190,'E1a Fleet (roll)'!$A$7:$A$190,"Pickup",'E1a Fleet (roll)'!$C$7:$C$190,1)/SUM('E1a Fleet (roll)'!U$7:U$190) | J49: =SUMIFS('E1a Fleet (roll)'!V$7:V$190,'E1a Fleet (roll)'!$A$7:$A$190,"Pickup",'E1a Fleet (roll)'!$C$7:$C$190,1)/SUM('E1a Fleet (roll)'!V$7:V$190) | K49: =SUMIFS('E1a Fleet (roll)'!W$7:W$190,'E1a Fleet (roll)'!$A$7:$A$190,"Pickup",'E1a Fleet (roll)'!$C$7:$C$190,1)/SUM('E1a Fleet (roll)'!W$7:W$190) | ... M49: =SUMIFS('E1a Fleet (roll)'!Y$7:Y$190,'E1a Fleet (roll)'!$A$7:$A$190,"Pickup",'E1a Fleet (roll)'!$C$7:$C$190,1)/SUM('E1a Fleet (roll)'!Y$7:Y$190) | N49: – | O49: – | P49: – | Q49: – | R49: –
B50: Model: Pickup — 4–6 years | C50: % | D50: =SUMIFS('E1a Fleet (roll)'!P$7:P$190,'E1a Fleet (roll)'!$A$7:$A$190,"Pickup",'E1a Fleet (roll)'!$C$7:$C$190,2)/SUM('E1a Fleet (roll)'!P$7:P$190) | E50: =SUMIFS('E1a Fleet (roll)'!Q$7:Q$190,'E1a Fleet (roll)'!$A$7:$A$190,"Pickup",'E1a Fleet (roll)'!$C$7:$C$190,2)/SUM('E1a Fleet (roll)'!Q$7:Q$190) | F50: =SUMIFS('E1a Fleet (roll)'!R$7:R$190,'E1a Fleet (roll)'!$A$7:$A$190,"Pickup",'E1a Fleet (roll)'!$C$7:$C$190,2)/SUM('E1a Fleet (roll)'!R$7:R$190) | G50: =SUMIFS('E1a Fleet (roll)'!S$7:S$190,'E1a Fleet (roll)'!$A$7:$A$190,"Pickup",'E1a Fleet (roll)'!$C$7:$C$190,2)/SUM('E1a Fleet (roll)'!S$7:S$190) | H50: =SUMIFS('E1a Fleet (roll)'!T$7:T$190,'E1a Fleet (roll)'!$A$7:$A$190,"Pickup",'E1a Fleet (roll)'!$C$7:$C$190,2)/SUM('E1a Fleet (roll)'!T$7:T$190) | I50: =SUMIFS('E1a Fleet (roll)'!U$7:U$190,'E1a Fleet (roll)'!$A$7:$A$190,"Pickup",'E1a Fleet (roll)'!$C$7:$C$190,2)/SUM('E1a Fleet (roll)'!U$7:U$190) | J50: =SUMIFS('E1a Fleet (roll)'!V$7:V$190,'E1a Fleet (roll)'!$A$7:$A$190,"Pickup",'E1a Fleet (roll)'!$C$7:$C$190,2)/SUM('E1a Fleet (roll)'!V$7:V$190) | K50: =SUMIFS('E1a Fleet (roll)'!W$7:W$190,'E1a Fleet (roll)'!$A$7:$A$190,"Pickup",'E1a Fleet (roll)'!$C$7:$C$190,2)/SUM('E1a Fleet (roll)'!W$7:W$190) | ... M50: =SUMIFS('E1a Fleet (roll)'!Y$7:Y$190,'E1a Fleet (roll)'!$A$7:$A$190,"Pickup",'E1a Fleet (roll)'!$C$7:$C$190,2)/SUM('E1a Fleet (roll)'!Y$7:Y$190) | N50: – | O50: – | P50: – | Q50: – | R50: –
B51: Model: Pickup — 7+ years | C51: % | D51: =SUMIFS('E1a Fleet (roll)'!P$7:P$190,'E1a Fleet (roll)'!$A$7:$A$190,"Pickup",'E1a Fleet (roll)'!$C$7:$C$190,3)/SUM('E1a Fleet (roll)'!P$7:P$190) | E51: =SUMIFS('E1a Fleet (roll)'!Q$7:Q$190,'E1a Fleet (roll)'!$A$7:$A$190,"Pickup",'E1a Fleet (roll)'!$C$7:$C$190,3)/SUM('E1a Fleet (roll)'!Q$7:Q$190) | F51: =SUMIFS('E1a Fleet (roll)'!R$7:R$190,'E1a Fleet (roll)'!$A$7:$A$190,"Pickup",'E1a Fleet (roll)'!$C$7:$C$190,3)/SUM('E1a Fleet (roll)'!R$7:R$190) | G51: =SUMIFS('E1a Fleet (roll)'!S$7:S$190,'E1a Fleet (roll)'!$A$7:$A$190,"Pickup",'E1a Fleet (roll)'!$C$7:$C$190,3)/SUM('E1a Fleet (roll)'!S$7:S$190) | H51: =SUMIFS('E1a Fleet (roll)'!T$7:T$190,'E1a Fleet (roll)'!$A$7:$A$190,"Pickup",'E1a Fleet (roll)'!$C$7:$C$190,3)/SUM('E1a Fleet (roll)'!T$7:T$190) | I51: =SUMIFS('E1a Fleet (roll)'!U$7:U$190,'E1a Fleet (roll)'!$A$7:$A$190,"Pickup",'E1a Fleet (roll)'!$C$7:$C$190,3)/SUM('E1a Fleet (roll)'!U$7:U$190) | J51: =SUMIFS('E1a Fleet (roll)'!V$7:V$190,'E1a Fleet (roll)'!$A$7:$A$190,"Pickup",'E1a Fleet (roll)'!$C$7:$C$190,3)/SUM('E1a Fleet (roll)'!V$7:V$190) | K51: =SUMIFS('E1a Fleet (roll)'!W$7:W$190,'E1a Fleet (roll)'!$A$7:$A$190,"Pickup",'E1a Fleet (roll)'!$C$7:$C$190,3)/SUM('E1a Fleet (roll)'!W$7:W$190) | ... M51: =SUMIFS('E1a Fleet (roll)'!Y$7:Y$190,'E1a Fleet (roll)'!$A$7:$A$190,"Pickup",'E1a Fleet (roll)'!$C$7:$C$190,3)/SUM('E1a Fleet (roll)'!Y$7:Y$190) | N51: – | O51: – | P51: – | Q51: – | R51: –
B52: Model: Van / minivan — 0 (current or newer) | C52: % | D52: =SUMIFS('E1a Fleet (roll)'!P$7:P$190,'E1a Fleet (roll)'!$A$7:$A$190,"Van",'E1a Fleet (roll)'!$C$7:$C$190,0)/SUM('E1a Fleet (roll)'!P$7:P$190) | E52: =SUMIFS('E1a Fleet (roll)'!Q$7:Q$190,'E1a Fleet (roll)'!$A$7:$A$190,"Van",'E1a Fleet (roll)'!$C$7:$C$190,0)/SUM('E1a Fleet (roll)'!Q$7:Q$190) | F52: =SUMIFS('E1a Fleet (roll)'!R$7:R$190,'E1a Fleet (roll)'!$A$7:$A$190,"Van",'E1a Fleet (roll)'!$C$7:$C$190,0)/SUM('E1a Fleet (roll)'!R$7:R$190) | G52: =SUMIFS('E1a Fleet (roll)'!S$7:S$190,'E1a Fleet (roll)'!$A$7:$A$190,"Van",'E1a Fleet (roll)'!$C$7:$C$190,0)/SUM('E1a Fleet (roll)'!S$7:S$190) | H52: =SUMIFS('E1a Fleet (roll)'!T$7:T$190,'E1a Fleet (roll)'!$A$7:$A$190,"Van",'E1a Fleet (roll)'!$C$7:$C$190,0)/SUM('E1a Fleet (roll)'!T$7:T$190) | I52: =SUMIFS('E1a Fleet (roll)'!U$7:U$190,'E1a Fleet (roll)'!$A$7:$A$190,"Van",'E1a Fleet (roll)'!$C$7:$C$190,0)/SUM('E1a Fleet (roll)'!U$7:U$190) | J52: =SUMIFS('E1a Fleet (roll)'!V$7:V$190,'E1a Fleet (roll)'!$A$7:$A$190,"Van",'E1a Fleet (roll)'!$C$7:$C$190,0)/SUM('E1a Fleet (roll)'!V$7:V$190) | K52: =SUMIFS('E1a Fleet (roll)'!W$7:W$190,'E1a Fleet (roll)'!$A$7:$A$190,"Van",'E1a Fleet (roll)'!$C$7:$C$190,0)/SUM('E1a Fleet (roll)'!W$7:W$190) | ... M52: =SUMIFS('E1a Fleet (roll)'!Y$7:Y$190,'E1a Fleet (roll)'!$A$7:$A$190,"Van",'E1a Fleet (roll)'!$C$7:$C$190,0)/SUM('E1a Fleet (roll)'!Y$7:Y$190) | N52: – | O52: – | P52: – | Q52: – | R52: –
B53: Model: Van / minivan — 1–3 years | C53: % | D53: =SUMIFS('E1a Fleet (roll)'!P$7:P$190,'E1a Fleet (roll)'!$A$7:$A$190,"Van",'E1a Fleet (roll)'!$C$7:$C$190,1)/SUM('E1a Fleet (roll)'!P$7:P$190) | E53: =SUMIFS('E1a Fleet (roll)'!Q$7:Q$190,'E1a Fleet (roll)'!$A$7:$A$190,"Van",'E1a Fleet (roll)'!$C$7:$C$190,1)/SUM('E1a Fleet (roll)'!Q$7:Q$190) | F53: =SUMIFS('E1a Fleet (roll)'!R$7:R$190,'E1a Fleet (roll)'!$A$7:$A$190,"Van",'E1a Fleet (roll)'!$C$7:$C$190,1)/SUM('E1a Fleet (roll)'!R$7:R$190) | G53: =SUMIFS('E1a Fleet (roll)'!S$7:S$190,'E1a Fleet (roll)'!$A$7:$A$190,"Van",'E1a Fleet (roll)'!$C$7:$C$190,1)/SUM('E1a Fleet (roll)'!S$7:S$190) | H53: =SUMIFS('E1a Fleet (roll)'!T$7:T$190,'E1a Fleet (roll)'!$A$7:$A$190,"Van",'E1a Fleet (roll)'!$C$7:$C$190,1)/SUM('E1a Fleet (roll)'!T$7:T$190) | I53: =SUMIFS('E1a Fleet (roll)'!U$7:U$190,'E1a Fleet (roll)'!$A$7:$A$190,"Van",'E1a Fleet (roll)'!$C$7:$C$190,1)/SUM('E1a Fleet (roll)'!U$7:U$190) | J53: =SUMIFS('E1a Fleet (roll)'!V$7:V$190,'E1a Fleet (roll)'!$A$7:$A$190,"Van",'E1a Fleet (roll)'!$C$7:$C$190,1)/SUM('E1a Fleet (roll)'!V$7:V$190) | K53: =SUMIFS('E1a Fleet (roll)'!W$7:W$190,'E1a Fleet (roll)'!$A$7:$A$190,"Van",'E1a Fleet (roll)'!$C$7:$C$190,1)/SUM('E1a Fleet (roll)'!W$7:W$190) | ... M53: =SUMIFS('E1a Fleet (roll)'!Y$7:Y$190,'E1a Fleet (roll)'!$A$7:$A$190,"Van",'E1a Fleet (roll)'!$C$7:$C$190,1)/SUM('E1a Fleet (roll)'!Y$7:Y$190) | N53: – | O53: – | P53: – | Q53: – | R53: –
B54: Model: Van / minivan — 4–6 years | C54: % | D54: =SUMIFS('E1a Fleet (roll)'!P$7:P$190,'E1a Fleet (roll)'!$A$7:$A$190,"Van",'E1a Fleet (roll)'!$C$7:$C$190,2)/SUM('E1a Fleet (roll)'!P$7:P$190) | E54: =SUMIFS('E1a Fleet (roll)'!Q$7:Q$190,'E1a Fleet (roll)'!$A$7:$A$190,"Van",'E1a Fleet (roll)'!$C$7:$C$190,2)/SUM('E1a Fleet (roll)'!Q$7:Q$190) | F54: =SUMIFS('E1a Fleet (roll)'!R$7:R$190,'E1a Fleet (roll)'!$A$7:$A$190,"Van",'E1a Fleet (roll)'!$C$7:$C$190,2)/SUM('E1a Fleet (roll)'!R$7:R$190) | G54: =SUMIFS('E1a Fleet (roll)'!S$7:S$190,'E1a Fleet (roll)'!$A$7:$A$190,"Van",'E1a Fleet (roll)'!$C$7:$C$190,2)/SUM('E1a Fleet (roll)'!S$7:S$190) | H54: =SUMIFS('E1a Fleet (roll)'!T$7:T$190,'E1a Fleet (roll)'!$A$7:$A$190,"Van",'E1a Fleet (roll)'!$C$7:$C$190,2)/SUM('E1a Fleet (roll)'!T$7:T$190) | I54: =SUMIFS('E1a Fleet (roll)'!U$7:U$190,'E1a Fleet (roll)'!$A$7:$A$190,"Van",'E1a Fleet (roll)'!$C$7:$C$190,2)/SUM('E1a Fleet (roll)'!U$7:U$190) | J54: =SUMIFS('E1a Fleet (roll)'!V$7:V$190,'E1a Fleet (roll)'!$A$7:$A$190,"Van",'E1a Fleet (roll)'!$C$7:$C$190,2)/SUM('E1a Fleet (roll)'!V$7:V$190) | K54: =SUMIFS('E1a Fleet (roll)'!W$7:W$190,'E1a Fleet (roll)'!$A$7:$A$190,"Van",'E1a Fleet (roll)'!$C$7:$C$190,2)/SUM('E1a Fleet (roll)'!W$7:W$190) | ... M54: =SUMIFS('E1a Fleet (roll)'!Y$7:Y$190,'E1a Fleet (roll)'!$A$7:$A$190,"Van",'E1a Fleet (roll)'!$C$7:$C$190,2)/SUM('E1a Fleet (roll)'!Y$7:Y$190) | N54: – | O54: – | P54: – | Q54: – | R54: –
B55: Model: Van / minivan — 7+ years | C55: % | D55: =SUMIFS('E1a Fleet (roll)'!P$7:P$190,'E1a Fleet (roll)'!$A$7:$A$190,"Van",'E1a Fleet (roll)'!$C$7:$C$190,3)/SUM('E1a Fleet (roll)'!P$7:P$190) | E55: =SUMIFS('E1a Fleet (roll)'!Q$7:Q$190,'E1a Fleet (roll)'!$A$7:$A$190,"Van",'E1a Fleet (roll)'!$C$7:$C$190,3)/SUM('E1a Fleet (roll)'!Q$7:Q$190) | F55: =SUMIFS('E1a Fleet (roll)'!R$7:R$190,'E1a Fleet (roll)'!$A$7:$A$190,"Van",'E1a Fleet (roll)'!$C$7:$C$190,3)/SUM('E1a Fleet (roll)'!R$7:R$190) | G55: =SUMIFS('E1a Fleet (roll)'!S$7:S$190,'E1a Fleet (roll)'!$A$7:$A$190,"Van",'E1a Fleet (roll)'!$C$7:$C$190,3)/SUM('E1a Fleet (roll)'!S$7:S$190) | H55: =SUMIFS('E1a Fleet (roll)'!T$7:T$190,'E1a Fleet (roll)'!$A$7:$A$190,"Van",'E1a Fleet (roll)'!$C$7:$C$190,3)/SUM('E1a Fleet (roll)'!T$7:T$190) | I55: =SUMIFS('E1a Fleet (roll)'!U$7:U$190,'E1a Fleet (roll)'!$A$7:$A$190,"Van",'E1a Fleet (roll)'!$C$7:$C$190,3)/SUM('E1a Fleet (roll)'!U$7:U$190) | J55: =SUMIFS('E1a Fleet (roll)'!V$7:V$190,'E1a Fleet (roll)'!$A$7:$A$190,"Van",'E1a Fleet (roll)'!$C$7:$C$190,3)/SUM('E1a Fleet (roll)'!V$7:V$190) | K55: =SUMIFS('E1a Fleet (roll)'!W$7:W$190,'E1a Fleet (roll)'!$A$7:$A$190,"Van",'E1a Fleet (roll)'!$C$7:$C$190,3)/SUM('E1a Fleet (roll)'!W$7:W$190) | ... M55: =SUMIFS('E1a Fleet (roll)'!Y$7:Y$190,'E1a Fleet (roll)'!$A$7:$A$190,"Van",'E1a Fleet (roll)'!$C$7:$C$190,3)/SUM('E1a Fleet (roll)'!Y$7:Y$190) | N55: – | O55: – | P55: – | Q55: – | R55: –
B56: CCC-implied: Car — 0 (current or newer) | C56: % | D56: – | E56: =SUMIFS('D CCC'!$K$5:$K$100,'D CCC'!$B$5:$B$100,E$3,'D CCC'!$C$5:$C$100,"Car",'D CCC'!$D$5:$D$100,0) | F56: =SUMIFS('D CCC'!$K$5:$K$100,'D CCC'!$B$5:$B$100,F$3,'D CCC'!$C$5:$C$100,"Car",'D CCC'!$D$5:$D$100,0) | G56: =SUMIFS('D CCC'!$K$5:$K$100,'D CCC'!$B$5:$B$100,G$3,'D CCC'!$C$5:$C$100,"Car",'D CCC'!$D$5:$D$100,0) | H56: =SUMIFS('D CCC'!$K$5:$K$100,'D CCC'!$B$5:$B$100,H$3,'D CCC'!$C$5:$C$100,"Car",'D CCC'!$D$5:$D$100,0) | I56: =SUMIFS('D CCC'!$K$5:$K$100,'D CCC'!$B$5:$B$100,I$3,'D CCC'!$C$5:$C$100,"Car",'D CCC'!$D$5:$D$100,0) | J56: =SUMIFS('D CCC'!$K$5:$K$100,'D CCC'!$B$5:$B$100,J$3,'D CCC'!$C$5:$C$100,"Car",'D CCC'!$D$5:$D$100,0) | K56: – | L56: – | M56: – | N56: – | O56: – | P56: D CCC column K (VERIFIED cells, derived ratio); 2020–2025 only | Q56: – | R56: –
B57: CCC-implied: Car — 1–3 years | C57: % | D57: – | E57: =SUMIFS('D CCC'!$K$5:$K$100,'D CCC'!$B$5:$B$100,E$3,'D CCC'!$C$5:$C$100,"Car",'D CCC'!$D$5:$D$100,1) | F57: =SUMIFS('D CCC'!$K$5:$K$100,'D CCC'!$B$5:$B$100,F$3,'D CCC'!$C$5:$C$100,"Car",'D CCC'!$D$5:$D$100,1) | G57: =SUMIFS('D CCC'!$K$5:$K$100,'D CCC'!$B$5:$B$100,G$3,'D CCC'!$C$5:$C$100,"Car",'D CCC'!$D$5:$D$100,1) | H57: =SUMIFS('D CCC'!$K$5:$K$100,'D CCC'!$B$5:$B$100,H$3,'D CCC'!$C$5:$C$100,"Car",'D CCC'!$D$5:$D$100,1) | I57: =SUMIFS('D CCC'!$K$5:$K$100,'D CCC'!$B$5:$B$100,I$3,'D CCC'!$C$5:$C$100,"Car",'D CCC'!$D$5:$D$100,1) | J57: =SUMIFS('D CCC'!$K$5:$K$100,'D CCC'!$B$5:$B$100,J$3,'D CCC'!$C$5:$C$100,"Car",'D CCC'!$D$5:$D$100,1) | K57: – | L57: – | M57: – | N57: – | O57: – | P57: – | Q57: – | R57: –
B58: CCC-implied: Car — 4–6 years | C58: % | D58: – | E58: =SUMIFS('D CCC'!$K$5:$K$100,'D CCC'!$B$5:$B$100,E$3,'D CCC'!$C$5:$C$100,"Car",'D CCC'!$D$5:$D$100,2) | F58: =SUMIFS('D CCC'!$K$5:$K$100,'D CCC'!$B$5:$B$100,F$3,'D CCC'!$C$5:$C$100,"Car",'D CCC'!$D$5:$D$100,2) | G58: =SUMIFS('D CCC'!$K$5:$K$100,'D CCC'!$B$5:$B$100,G$3,'D CCC'!$C$5:$C$100,"Car",'D CCC'!$D$5:$D$100,2) | H58: =SUMIFS('D CCC'!$K$5:$K$100,'D CCC'!$B$5:$B$100,H$3,'D CCC'!$C$5:$C$100,"Car",'D CCC'!$D$5:$D$100,2) | I58: =SUMIFS('D CCC'!$K$5:$K$100,'D CCC'!$B$5:$B$100,I$3,'D CCC'!$C$5:$C$100,"Car",'D CCC'!$D$5:$D$100,2) | J58: =SUMIFS('D CCC'!$K$5:$K$100,'D CCC'!$B$5:$B$100,J$3,'D CCC'!$C$5:$C$100,"Car",'D CCC'!$D$5:$D$100,2) | K58: – | L58: – | M58: – | N58: – | O58: – | P58: – | Q58: – | R58: –
B59: CCC-implied: Car — 7+ years | C59: % | D59: – | E59: =SUMIFS('D CCC'!$K$5:$K$100,'D CCC'!$B$5:$B$100,E$3,'D CCC'!$C$5:$C$100,"Car",'D CCC'!$D$5:$D$100,3) | F59: =SUMIFS('D CCC'!$K$5:$K$100,'D CCC'!$B$5:$B$100,F$3,'D CCC'!$C$5:$C$100,"Car",'D CCC'!$D$5:$D$100,3) | G59: =SUMIFS('D CCC'!$K$5:$K$100,'D CCC'!$B$5:$B$100,G$3,'D CCC'!$C$5:$C$100,"Car",'D CCC'!$D$5:$D$100,3) | H59: =SUMIFS('D CCC'!$K$5:$K$100,'D CCC'!$B$5:$B$100,H$3,'D CCC'!$C$5:$C$100,"Car",'D CCC'!$D$5:$D$100,3) | I59: =SUMIFS('D CCC'!$K$5:$K$100,'D CCC'!$B$5:$B$100,I$3,'D CCC'!$C$5:$C$100,"Car",'D CCC'!$D$5:$D$100,3) | J59: =SUMIFS('D CCC'!$K$5:$K$100,'D CCC'!$B$5:$B$100,J$3,'D CCC'!$C$5:$C$100,"Car",'D CCC'!$D$5:$D$100,3) | K59: – | L59: – | M59: – | N59: – | O59: – | P59: – | Q59: – | R59: –
B60: CCC-implied: Utility vehicle (SUV) — 0 (current or newer) | C60: % | D60: – | E60: =SUMIFS('D CCC'!$K$5:$K$100,'D CCC'!$B$5:$B$100,E$3,'D CCC'!$C$5:$C$100,"Utility Vehicle",'D CCC'!$D$5:$D$100,0) | F60: =SUMIFS('D CCC'!$K$5:$K$100,'D CCC'!$B$5:$B$100,F$3,'D CCC'!$C$5:$C$100,"Utility Vehicle",'D CCC'!$D$5:$D$100,0) | G60: =SUMIFS('D CCC'!$K$5:$K$100,'D CCC'!$B$5:$B$100,G$3,'D CCC'!$C$5:$C$100,"Utility Vehicle",'D CCC'!$D$5:$D$100,0) | H60: =SUMIFS('D CCC'!$K$5:$K$100,'D CCC'!$B$5:$B$100,H$3,'D CCC'!$C$5:$C$100,"Utility Vehicle",'D CCC'!$D$5:$D$100,0) | I60: =SUMIFS('D CCC'!$K$5:$K$100,'D CCC'!$B$5:$B$100,I$3,'D CCC'!$C$5:$C$100,"Utility Vehicle",'D CCC'!$D$5:$D$100,0) | J60: =SUMIFS('D CCC'!$K$5:$K$100,'D CCC'!$B$5:$B$100,J$3,'D CCC'!$C$5:$C$100,"Utility Vehicle",'D CCC'!$D$5:$D$100,0) | K60: – | L60: – | M60: – | N60: – | O60: – | P60: – | Q60: – | R60: –
B61: CCC-implied: Utility vehicle (SUV) — 1–3 years | C61: % | D61: – | E61: =SUMIFS('D CCC'!$K$5:$K$100,'D CCC'!$B$5:$B$100,E$3,'D CCC'!$C$5:$C$100,"Utility Vehicle",'D CCC'!$D$5:$D$100,1) | F61: =SUMIFS('D CCC'!$K$5:$K$100,'D CCC'!$B$5:$B$100,F$3,'D CCC'!$C$5:$C$100,"Utility Vehicle",'D CCC'!$D$5:$D$100,1) | G61: =SUMIFS('D CCC'!$K$5:$K$100,'D CCC'!$B$5:$B$100,G$3,'D CCC'!$C$5:$C$100,"Utility Vehicle",'D CCC'!$D$5:$D$100,1) | H61: =SUMIFS('D CCC'!$K$5:$K$100,'D CCC'!$B$5:$B$100,H$3,'D CCC'!$C$5:$C$100,"Utility Vehicle",'D CCC'!$D$5:$D$100,1) | I61: =SUMIFS('D CCC'!$K$5:$K$100,'D CCC'!$B$5:$B$100,I$3,'D CCC'!$C$5:$C$100,"Utility Vehicle",'D CCC'!$D$5:$D$100,1) | J61: =SUMIFS('D CCC'!$K$5:$K$100,'D CCC'!$B$5:$B$100,J$3,'D CCC'!$C$5:$C$100,"Utility Vehicle",'D CCC'!$D$5:$D$100,1) | K61: – | L61: – | M61: – | N61: – | O61: – | P61: – | Q61: – | R61: –
B62: CCC-implied: Utility vehicle (SUV) — 4–6 years | C62: % | D62: – | E62: =SUMIFS('D CCC'!$K$5:$K$100,'D CCC'!$B$5:$B$100,E$3,'D CCC'!$C$5:$C$100,"Utility Vehicle",'D CCC'!$D$5:$D$100,2) | F62: =SUMIFS('D CCC'!$K$5:$K$100,'D CCC'!$B$5:$B$100,F$3,'D CCC'!$C$5:$C$100,"Utility Vehicle",'D CCC'!$D$5:$D$100,2) | G62: =SUMIFS('D CCC'!$K$5:$K$100,'D CCC'!$B$5:$B$100,G$3,'D CCC'!$C$5:$C$100,"Utility Vehicle",'D CCC'!$D$5:$D$100,2) | H62: =SUMIFS('D CCC'!$K$5:$K$100,'D CCC'!$B$5:$B$100,H$3,'D CCC'!$C$5:$C$100,"Utility Vehicle",'D CCC'!$D$5:$D$100,2) | I62: =SUMIFS('D CCC'!$K$5:$K$100,'D CCC'!$B$5:$B$100,I$3,'D CCC'!$C$5:$C$100,"Utility Vehicle",'D CCC'!$D$5:$D$100,2) | J62: =SUMIFS('D CCC'!$K$5:$K$100,'D CCC'!$B$5:$B$100,J$3,'D CCC'!$C$5:$C$100,"Utility Vehicle",'D CCC'!$D$5:$D$100,2) | K62: – | L62: – | M62: – | N62: – | O62: – | P62: – | Q62: – | R62: –
B63: CCC-implied: Utility vehicle (SUV) — 7+ years | C63: % | D63: – | E63: =SUMIFS('D CCC'!$K$5:$K$100,'D CCC'!$B$5:$B$100,E$3,'D CCC'!$C$5:$C$100,"Utility Vehicle",'D CCC'!$D$5:$D$100,3) | F63: =SUMIFS('D CCC'!$K$5:$K$100,'D CCC'!$B$5:$B$100,F$3,'D CCC'!$C$5:$C$100,"Utility Vehicle",'D CCC'!$D$5:$D$100,3) | G63: =SUMIFS('D CCC'!$K$5:$K$100,'D CCC'!$B$5:$B$100,G$3,'D CCC'!$C$5:$C$100,"Utility Vehicle",'D CCC'!$D$5:$D$100,3) | H63: =SUMIFS('D CCC'!$K$5:$K$100,'D CCC'!$B$5:$B$100,H$3,'D CCC'!$C$5:$C$100,"Utility Vehicle",'D CCC'!$D$5:$D$100,3) | I63: =SUMIFS('D CCC'!$K$5:$K$100,'D CCC'!$B$5:$B$100,I$3,'D CCC'!$C$5:$C$100,"Utility Vehicle",'D CCC'!$D$5:$D$100,3) | J63: =SUMIFS('D CCC'!$K$5:$K$100,'D CCC'!$B$5:$B$100,J$3,'D CCC'!$C$5:$C$100,"Utility Vehicle",'D CCC'!$D$5:$D$100,3) | K63: – | L63: – | M63: – | N63: – | O63: – | P63: – | Q63: – | R63: –
B64: CCC-implied: Pickup — 0 (current or newer) | C64: % | D64: – | E64: =SUMIFS('D CCC'!$K$5:$K$100,'D CCC'!$B$5:$B$100,E$3,'D CCC'!$C$5:$C$100,"Pickup",'D CCC'!$D$5:$D$100,0) | F64: =SUMIFS('D CCC'!$K$5:$K$100,'D CCC'!$B$5:$B$100,F$3,'D CCC'!$C$5:$C$100,"Pickup",'D CCC'!$D$5:$D$100,0) | G64: =SUMIFS('D CCC'!$K$5:$K$100,'D CCC'!$B$5:$B$100,G$3,'D CCC'!$C$5:$C$100,"Pickup",'D CCC'!$D$5:$D$100,0) | H64: =SUMIFS('D CCC'!$K$5:$K$100,'D CCC'!$B$5:$B$100,H$3,'D CCC'!$C$5:$C$100,"Pickup",'D CCC'!$D$5:$D$100,0) | I64: =SUMIFS('D CCC'!$K$5:$K$100,'D CCC'!$B$5:$B$100,I$3,'D CCC'!$C$5:$C$100,"Pickup",'D CCC'!$D$5:$D$100,0) | J64: =SUMIFS('D CCC'!$K$5:$K$100,'D CCC'!$B$5:$B$100,J$3,'D CCC'!$C$5:$C$100,"Pickup",'D CCC'!$D$5:$D$100,0) | K64: – | L64: – | M64: – | N64: – | O64: – | P64: – | Q64: – | R64: –
B65: CCC-implied: Pickup — 1–3 years | C65: % | D65: – | E65: =SUMIFS('D CCC'!$K$5:$K$100,'D CCC'!$B$5:$B$100,E$3,'D CCC'!$C$5:$C$100,"Pickup",'D CCC'!$D$5:$D$100,1) | F65: =SUMIFS('D CCC'!$K$5:$K$100,'D CCC'!$B$5:$B$100,F$3,'D CCC'!$C$5:$C$100,"Pickup",'D CCC'!$D$5:$D$100,1) | G65: =SUMIFS('D CCC'!$K$5:$K$100,'D CCC'!$B$5:$B$100,G$3,'D CCC'!$C$5:$C$100,"Pickup",'D CCC'!$D$5:$D$100,1) | H65: =SUMIFS('D CCC'!$K$5:$K$100,'D CCC'!$B$5:$B$100,H$3,'D CCC'!$C$5:$C$100,"Pickup",'D CCC'!$D$5:$D$100,1) | I65: =SUMIFS('D CCC'!$K$5:$K$100,'D CCC'!$B$5:$B$100,I$3,'D CCC'!$C$5:$C$100,"Pickup",'D CCC'!$D$5:$D$100,1) | J65: =SUMIFS('D CCC'!$K$5:$K$100,'D CCC'!$B$5:$B$100,J$3,'D CCC'!$C$5:$C$100,"Pickup",'D CCC'!$D$5:$D$100,1) | K65: – | L65: – | M65: – | N65: – | O65: – | P65: – | Q65: – | R65: –
B66: CCC-implied: Pickup — 4–6 years | C66: % | D66: – | E66: =SUMIFS('D CCC'!$K$5:$K$100,'D CCC'!$B$5:$B$100,E$3,'D CCC'!$C$5:$C$100,"Pickup",'D CCC'!$D$5:$D$100,2) | F66: =SUMIFS('D CCC'!$K$5:$K$100,'D CCC'!$B$5:$B$100,F$3,'D CCC'!$C$5:$C$100,"Pickup",'D CCC'!$D$5:$D$100,2) | G66: =SUMIFS('D CCC'!$K$5:$K$100,'D CCC'!$B$5:$B$100,G$3,'D CCC'!$C$5:$C$100,"Pickup",'D CCC'!$D$5:$D$100,2) | H66: =SUMIFS('D CCC'!$K$5:$K$100,'D CCC'!$B$5:$B$100,H$3,'D CCC'!$C$5:$C$100,"Pickup",'D CCC'!$D$5:$D$100,2) | I66: =SUMIFS('D CCC'!$K$5:$K$100,'D CCC'!$B$5:$B$100,I$3,'D CCC'!$C$5:$C$100,"Pickup",'D CCC'!$D$5:$D$100,2) | J66: =SUMIFS('D CCC'!$K$5:$K$100,'D CCC'!$B$5:$B$100,J$3,'D CCC'!$C$5:$C$100,"Pickup",'D CCC'!$D$5:$D$100,2) | K66: – | L66: – | M66: – | N66: – | O66: – | P66: – | Q66: – | R66: –
B67: CCC-implied: Pickup — 7+ years | C67: % | D67: – | E67: =SUMIFS('D CCC'!$K$5:$K$100,'D CCC'!$B$5:$B$100,E$3,'D CCC'!$C$5:$C$100,"Pickup",'D CCC'!$D$5:$D$100,3) | F67: =SUMIFS('D CCC'!$K$5:$K$100,'D CCC'!$B$5:$B$100,F$3,'D CCC'!$C$5:$C$100,"Pickup",'D CCC'!$D$5:$D$100,3) | G67: =SUMIFS('D CCC'!$K$5:$K$100,'D CCC'!$B$5:$B$100,G$3,'D CCC'!$C$5:$C$100,"Pickup",'D CCC'!$D$5:$D$100,3) | H67: =SUMIFS('D CCC'!$K$5:$K$100,'D CCC'!$B$5:$B$100,H$3,'D CCC'!$C$5:$C$100,"Pickup",'D CCC'!$D$5:$D$100,3) | I67: =SUMIFS('D CCC'!$K$5:$K$100,'D CCC'!$B$5:$B$100,I$3,'D CCC'!$C$5:$C$100,"Pickup",'D CCC'!$D$5:$D$100,3) | J67: =SUMIFS('D CCC'!$K$5:$K$100,'D CCC'!$B$5:$B$100,J$3,'D CCC'!$C$5:$C$100,"Pickup",'D CCC'!$D$5:$D$100,3) | K67: – | L67: – | M67: – | N67: – | O67: – | P67: – | Q67: – | R67: –
B68: CCC-implied: Van / minivan — 0 (current or newer) | C68: % | D68: – | E68: =SUMIFS('D CCC'!$K$5:$K$100,'D CCC'!$B$5:$B$100,E$3,'D CCC'!$C$5:$C$100,"Van",'D CCC'!$D$5:$D$100,0) | F68: =SUMIFS('D CCC'!$K$5:$K$100,'D CCC'!$B$5:$B$100,F$3,'D CCC'!$C$5:$C$100,"Van",'D CCC'!$D$5:$D$100,0) | G68: =SUMIFS('D CCC'!$K$5:$K$100,'D CCC'!$B$5:$B$100,G$3,'D CCC'!$C$5:$C$100,"Van",'D CCC'!$D$5:$D$100,0) | H68: =SUMIFS('D CCC'!$K$5:$K$100,'D CCC'!$B$5:$B$100,H$3,'D CCC'!$C$5:$C$100,"Van",'D CCC'!$D$5:$D$100,0) | I68: =SUMIFS('D CCC'!$K$5:$K$100,'D CCC'!$B$5:$B$100,I$3,'D CCC'!$C$5:$C$100,"Van",'D CCC'!$D$5:$D$100,0) | J68: =SUMIFS('D CCC'!$K$5:$K$100,'D CCC'!$B$5:$B$100,J$3,'D CCC'!$C$5:$C$100,"Van",'D CCC'!$D$5:$D$100,0) | K68: – | L68: – | M68: – | N68: – | O68: – | P68: – | Q68: – | R68: –
B69: CCC-implied: Van / minivan — 1–3 years | C69: % | D69: – | E69: =SUMIFS('D CCC'!$K$5:$K$100,'D CCC'!$B$5:$B$100,E$3,'D CCC'!$C$5:$C$100,"Van",'D CCC'!$D$5:$D$100,1) | F69: =SUMIFS('D CCC'!$K$5:$K$100,'D CCC'!$B$5:$B$100,F$3,'D CCC'!$C$5:$C$100,"Van",'D CCC'!$D$5:$D$100,1) | G69: =SUMIFS('D CCC'!$K$5:$K$100,'D CCC'!$B$5:$B$100,G$3,'D CCC'!$C$5:$C$100,"Van",'D CCC'!$D$5:$D$100,1) | H69: =SUMIFS('D CCC'!$K$5:$K$100,'D CCC'!$B$5:$B$100,H$3,'D CCC'!$C$5:$C$100,"Van",'D CCC'!$D$5:$D$100,1) | I69: =SUMIFS('D CCC'!$K$5:$K$100,'D CCC'!$B$5:$B$100,I$3,'D CCC'!$C$5:$C$100,"Van",'D CCC'!$D$5:$D$100,1) | J69: =SUMIFS('D CCC'!$K$5:$K$100,'D CCC'!$B$5:$B$100,J$3,'D CCC'!$C$5:$C$100,"Van",'D CCC'!$D$5:$D$100,1) | K69: – | L69: – | M69: – | N69: – | O69: – | P69: – | Q69: – | R69: –
B70: CCC-implied: Van / minivan — 4–6 years | C70: % | D70: – | E70: =SUMIFS('D CCC'!$K$5:$K$100,'D CCC'!$B$5:$B$100,E$3,'D CCC'!$C$5:$C$100,"Van",'D CCC'!$D$5:$D$100,2) | F70: =SUMIFS('D CCC'!$K$5:$K$100,'D CCC'!$B$5:$B$100,F$3,'D CCC'!$C$5:$C$100,"Van",'D CCC'!$D$5:$D$100,2) | G70: =SUMIFS('D CCC'!$K$5:$K$100,'D CCC'!$B$5:$B$100,G$3,'D CCC'!$C$5:$C$100,"Van",'D CCC'!$D$5:$D$100,2) | H70: =SUMIFS('D CCC'!$K$5:$K$100,'D CCC'!$B$5:$B$100,H$3,'D CCC'!$C$5:$C$100,"Van",'D CCC'!$D$5:$D$100,2) | I70: =SUMIFS('D CCC'!$K$5:$K$100,'D CCC'!$B$5:$B$100,I$3,'D CCC'!$C$5:$C$100,"Van",'D CCC'!$D$5:$D$100,2) | J70: =SUMIFS('D CCC'!$K$5:$K$100,'D CCC'!$B$5:$B$100,J$3,'D CCC'!$C$5:$C$100,"Van",'D CCC'!$D$5:$D$100,2) | K70: – | L70: – | M70: – | N70: – | O70: – | P70: – | Q70: – | R70: –
B71: CCC-implied: Van / minivan — 7+ years | C71: % | D71: – | E71: =SUMIFS('D CCC'!$K$5:$K$100,'D CCC'!$B$5:$B$100,E$3,'D CCC'!$C$5:$C$100,"Van",'D CCC'!$D$5:$D$100,3) | F71: =SUMIFS('D CCC'!$K$5:$K$100,'D CCC'!$B$5:$B$100,F$3,'D CCC'!$C$5:$C$100,"Van",'D CCC'!$D$5:$D$100,3) | G71: =SUMIFS('D CCC'!$K$5:$K$100,'D CCC'!$B$5:$B$100,G$3,'D CCC'!$C$5:$C$100,"Van",'D CCC'!$D$5:$D$100,3) | H71: =SUMIFS('D CCC'!$K$5:$K$100,'D CCC'!$B$5:$B$100,H$3,'D CCC'!$C$5:$C$100,"Van",'D CCC'!$D$5:$D$100,3) | I71: =SUMIFS('D CCC'!$K$5:$K$100,'D CCC'!$B$5:$B$100,I$3,'D CCC'!$C$5:$C$100,"Van",'D CCC'!$D$5:$D$100,3) | J71: =SUMIFS('D CCC'!$K$5:$K$100,'D CCC'!$B$5:$B$100,J$3,'D CCC'!$C$5:$C$100,"Van",'D CCC'!$D$5:$D$100,3) | K71: – | L71: – | M71: – | N71: – | O71: – | P71: – | Q71: – | R71: –
B73: Gap, body total: Car (model − CCC) | C73: pp | D73: – | E73: =SUM(E40:E43)-SUM(E56:E59) | F73: =SUM(F40:F43)-SUM(F56:F59) | G73: =SUM(G40:G43)-SUM(G56:G59) | H73: =SUM(H40:H43)-SUM(H56:H59) | I73: =SUM(I40:I43)-SUM(I56:I59) | J73: =SUM(J40:J43)-SUM(J56:J59) | K73: – | L73: – | M73: – | N73: – | O73: – | P73: – | Q73: – | R73: –
B74: Gap, body total: Utility vehicle (SUV) (model − CCC) | C74: pp | D74: – | E74: =SUM(E44:E47)-SUM(E60:E63) | F74: =SUM(F44:F47)-SUM(F60:F63) | G74: =SUM(G44:G47)-SUM(G60:G63) | H74: =SUM(H44:H47)-SUM(H60:H63) | I74: =SUM(I44:I47)-SUM(I60:I63) | J74: =SUM(J44:J47)-SUM(J60:J63) | K74: – | L74: – | M74: – | N74: – | O74: – | P74: – | Q74: – | R74: –
B75: Gap, body total: Pickup (model − CCC) | C75: pp | D75: – | E75: =SUM(E48:E51)-SUM(E64:E67) | F75: =SUM(F48:F51)-SUM(F64:F67) | G75: =SUM(G48:G51)-SUM(G64:G67) | H75: =SUM(H48:H51)-SUM(H64:H67) | I75: =SUM(I48:I51)-SUM(I64:I67) | J75: =SUM(J48:J51)-SUM(J64:J67) | K75: – | L75: – | M75: – | N75: – | O75: – | P75: – | Q75: – | R75: –
B76: Gap, body total: Van / minivan (model − CCC) | C76: pp | D76: – | E76: =SUM(E52:E55)-SUM(E68:E71) | F76: =SUM(F52:F55)-SUM(F68:F71) | G76: =SUM(G52:G55)-SUM(G68:G71) | H76: =SUM(H52:H55)-SUM(H68:H71) | I76: =SUM(I52:I55)-SUM(I68:I71) | J76: =SUM(J52:J55)-SUM(J68:J71) | K76: – | L76: – | M76: – | N76: – | O76: – | P76: – | Q76: – | R76: –
B77: Largest single-cell gap, |model − CCC| | C77: pp | D77: – | E77: =MAX(ABS(E40-E56),ABS(E41-E57),ABS(E42-E58),ABS(E43-E59),ABS(E44-E60),ABS(E45-E61),ABS(E46-E62),ABS(E47-E63),ABS(E48-E64),ABS(E49-E65),ABS(E50-E66),ABS(E51-E67),ABS(E52-E68),ABS(E53-E69),ABS(E54-E70),ABS(E55-E71)) | F77: =MAX(ABS(F40-F56),ABS(F41-F57),ABS(F42-F58),ABS(F43-F59),ABS(F44-F60),ABS(F45-F61),ABS(F46-F62),ABS(F47-F63),ABS(F48-F64),ABS(F49-F65),ABS(F50-F66),ABS(F51-F67),ABS(F52-F68),ABS(F53-F69),ABS(F54-F70),ABS(F55-F71)) | G77: =MAX(ABS(G40-G56),ABS(G41-G57),ABS(G42-G58),ABS(G43-G59),ABS(G44-G60),ABS(G45-G61),ABS(G46-G62),ABS(G47-G63),ABS(G48-G64),ABS(G49-G65),ABS(G50-G66),ABS(G51-G67),ABS(G52-G68),ABS(G53-G69),ABS(G54-G70),ABS(G55-G71)) | H77: =MAX(ABS(H40-H56),ABS(H41-H57),ABS(H42-H58),ABS(H43-H59),ABS(H44-H60),ABS(H45-H61),ABS(H46-H62),ABS(H47-H63),ABS(H48-H64),ABS(H49-H65),ABS(H50-H66),ABS(H51-H67),ABS(H52-H68),ABS(H53-H69),ABS(H54-H70),ABS(H55-H71)) | I77: =MAX(ABS(I40-I56),ABS(I41-I57),ABS(I42-I58),ABS(I43-I59),ABS(I44-I60),ABS(I45-I61),ABS(I46-I62),ABS(I47-I63),ABS(I48-I64),ABS(I49-I65),ABS(I50-I66),ABS(I51-I67),ABS(I52-I68),ABS(I53-I69),ABS(I54-I70),ABS(I55-I71)) | J77: =MAX(ABS(J40-J56),ABS(J41-J57),ABS(J42-J58),ABS(J43-J59),ABS(J44-J60),ABS(J45-J61),ABS(J46-J62),ABS(J47-J63),ABS(J48-J64),ABS(J49-J65),ABS(J50-J66),ABS(J51-J67),ABS(J52-J68),ABS(J53-J69),ABS(J54-J70),ABS(J55-J71)) | K77: – | L77: – | M77: – | N77: – | O77: – | P77: – | Q77: – | R77: –
B80: E. Checks
B81: Total vehicles on the road, 2024 vs Experian anchor | C81: 000s | D81: =I35 | E81: =$D$95 | F81: =D81/E81-1 | G81: =IF(ABS(F81)<0.02,"PASS","FAIL") | H81: – | I81: – | J81: – | K81: – | L81: – | M81: – | N81: – | O81: – | P81: Anchor in Inputs; the roll is fitted to it via m(2024), so this is a reproduction check, not validation | Q81: – | R81: –
B82: Share aged 7+, 2024 vs S&P anchor | C82: % | D82: =I36 | E82: =$D$96 | F82: =D82-E82 | G82: =IF(ABS(F82)<0.02,"PASS","FAIL") | H82: – | I82: – | J82: – | K82: – | L82: – | M82: – | N82: – | O82: – | P82: – | Q82: – | R82: –
B83: Largest cell gap vs CCC claim mix, 2020–2025 (out of sample except body factors at 2025) | C83: pp | D83: =MAX(E77:J77) | E83: – | F83: – | G83: =IF(D83<0.035,"PASS","FAIL") | H83: – | I83: – | J83: – | K83: – | L83: – | M83: – | N83: – | O83: – | P83: PASS if every cell within 3.5 points and 2025 within 2.5; see docs/source_trace_2026-10-01/FLEET_VS_CCC.md | Q83: – | R83: –
B84: Largest body-total gap, 2020–2024 (body factors fitted on 2025 only) | C84: pp | D84: =MAX(ABS(E73),ABS(E74),ABS(E75),ABS(E76),ABS(F73),ABS(F74),ABS(F75),ABS(F76),ABS(G73),ABS(G74),ABS(G75),ABS(G76),ABS(H73),ABS(H74),ABS(H75),ABS(H76),ABS(I73),ABS(I74),ABS(I75),ABS(I76)) | E84: – | F84: – | G84: =IF(D84<0.015,"PASS","FAIL") | H84: – | I84: – | J84: – | K84: – | L84: – | M84: – | N84: – | O84: – | P84: – | Q84: – | R84: –
B86: Feeds → E2 Claims & Totals (vehicles by band × body, rows 19–34, mapped to fiscal quarters)
B88: Inputs (blue = typed value; every number here carries a label and a source) | D88: Value | E88: Label
B89: k_cars(2013): survival stretch, cars | D89: 1.064 | E89: FITTED | F89: – | G89: – | H89: – | I89: – | J89: – | K89: – | L89: – | M89: – | N89: – | O89: – | P89: docs/AGE_CURVES.md §2.3 — reproduces IHS 2013 census of cars by age (ORNL Table 3.11) | Q89: – | R89: –
B90: k_cars(2013) | D90: 1.064 | E90: FITTED | F90: – | G90: – | H90: – | I90: – | J90: – | K90: – | L90: – | M90: – | N90: – | O90: – | P90: same (duplicate row kept for formula anchoring) | Q90: – | R90: –
B91: k_light trucks(2013) | D91: 0.921 | E91: FITTED | F91: – | G91: – | H91: – | I91: – | J91: – | K91: – | L91: – | M91: – | N91: – | O91: – | P91: docs/AGE_CURVES.md §2.3 — IHS 2013 census of trucks (ORNL Table 3.12) | Q91: – | R91: –
B92: m(2024): drift multiplier | D92: 1.194 | E92: FITTED | F92: – | G92: – | H92: – | I92: – | J92: – | K92: – | L92: – | M92: – | N92: – | O92: – | P92: docs/AGE_CURVES.md §2.4 — fitted to the two 2024 anchors below; anchors themselves need sourcing | Q92: – | R92: –
B93: exposure(age 0): fraction of a claim-year for current-year vehicles | D93: 0.5 | E93: ASSUMED | F93: – | G93: – | H93: – | I93: – | J93: – | K93: – | L93: – | M93: – | N93: – | O93: – | P93: data/csv/age_curves.csv header; looks low versus CCC age-0 claim share (5.5% vs 4.0%) | Q93: – | R93: –
B94: Claims decay per year beyond age 6 (R(a) = exposure × e^(−decay·max(a−6,0))) | D94: 0.09027 | E94: FITTED | F94: – | G94: – | H94: – | I94: – | J94: – | K94: – | L94: – | M94: – | N94: – | O94: – | P94: scripts/age_curves.py — fitted jointly with P(a) to eight CCC 2024 statistics | Q94: – | R94: –
B95: Vehicles in operation, 2024 (thousands) | D95: ='D Facts'!$D$40 | E95: UNVERIFIED | F95: – | G95: – | H95: – | I95: – | J95: – | K95: – | L95: – | M95: – | N95: – | O95: – | P95: Experian figure on disk per PROVENANCE (file to be cited); the recalled S&P 289M is retired | Q95: – | R95: –
B96: Share aged 7+, 2024 | D96: ='D Facts'!$D$41 | E96: UNVERIFIED | F96: – | G96: – | H96: – | I96: – | J96: – | K96: – | L96: – | M96: – | N96: – | O96: – | P96: recalled S&P Global Mobility release; not on disk | Q96: – | R96: –
B97: Body factor: Car (claims per vehicle vs common curve) | D97: 1.11 | E97: CALIBRATED | F97: – | G97: – | H97: – | I97: – | J97: – | K97: – | L97: – | M97: – | N97: – | O97: – | P97: scripts/fleet_vs_ccc_backtest.py — fitted to 2025 CCC cells only; 2020–24 are the test | Q97: – | R97: –
B98: Body factor: Utility vehicle (SUV) | D98: 0.917 | E98: CALIBRATED | F98: – | G98: – | H98: – | I98: – | J98: – | K98: – | L98: – | M98: – | N98: – | O98: – | P98: same | Q98: – | R98: –
B99: Body factor: Pickup | D99: 1.028 | E99: CALIBRATED | F99: – | G99: – | H99: – | I99: – | J99: – | K99: – | L99: – | M99: – | N99: – | O99: – | P99: same | Q99: – | R99: –
B100: Body factor: Van / minivan | D100: 0.923 | E100: CALIBRATED | F100: – | G100: – | H100: – | I100: – | J100: – | K100: – | L100: – | M100: – | N100: – | O100: – | P100: same | Q100: – | R100: –

Sheet E1a Fleet (roll)
B1: E1a Fleet (roll) — single-age roll behind E1, by body (thousands) and claims mass
B2: Fleet cell = Births(CY − age, body) × S_body(age ÷ k_body(CY)), linear interpolation of the EPA schedule, zero beyond its last age. Claims mass = fleet × R(age) × body factor. Formulas only; collapse this tab in normal use.
D3: CY → | E3: 2019 | F3: 2020 | G3: 2021 | H3: 2022 | I3: 2023 | J3: 2024 | K3: 2025 | L3: 2026 | M3: 2027 | N3: 2028 | O3: claims mass → | P3: 2019 | Q3: 2020 | R3: 2021 | S3: 2022 | T3: 2023 | U3: 2024 | V3: 2025 | W3: 2026 | X3: 2027 | Y3: 2028
D4: k cars | E4: ='E1 Fleet'!D15 | F4: ='E1 Fleet'!E15 | G4: ='E1 Fleet'!F15 | H4: ='E1 Fleet'!G15 | I4: ='E1 Fleet'!H15 | J4: ='E1 Fleet'!I15 | K4: ='E1 Fleet'!J15 | L4: ='E1 Fleet'!K15 | ... N4: ='E1 Fleet'!M15
D5: k light trucks | E5: ='E1 Fleet'!D16 | F5: ='E1 Fleet'!E16 | G5: ='E1 Fleet'!F16 | H5: ='E1 Fleet'!G16 | I5: ='E1 Fleet'!H16 | J5: ='E1 Fleet'!I16 | K5: ='E1 Fleet'!J16 | L5: ='E1 Fleet'!K16 | ... N5: ='E1 Fleet'!M16
A6: Body | B6: Age | C6: Band | D6: R(age) | E6: Fleet CY2019 | F6: Fleet CY2020 | G6: Fleet CY2021 | H6: Fleet CY2022 | I6: Fleet CY2023 | J6: Fleet CY2024 | K6: Fleet CY2025 | L6: Fleet CY2026 | M6: Fleet CY2027 | N6: Fleet CY2028 | P6: Claims CY2019 | Q6: Claims CY2020 | R6: Claims CY2021 | S6: Claims CY2022 | T6: Claims CY2023 | U6: Claims CY2024 | V6: Claims CY2025 | W6: Claims CY2026 | X6: Claims CY2027 | Y6: Claims CY2028
A7: Car | B7: 0 | C7: 0 | D7: =IF($B7=0,'E1 Fleet'!$D$93,1)*EXP(-'E1 Fleet'!$D$94*MAX($B7-6,0)) | E7: =IFERROR(INDEX('D Fleet'!$C$5:$C$63,MATCH(E$3-$B7,'D Fleet'!$B$5:$B$63,0)),0)*IFERROR(INDEX('D Fleet'!$J$5:$J$36,INT(($B7/E$4))+1)+(($B7/E$4)-INT(($B7/E$4)))*(INDEX('D Fleet'!$J$5:$J$36,INT(($B7/E$4))+2)-INDEX('D Fleet'!$J$5:$J$36,INT(($B7/E$4))+1)),0) | F7: =IFERROR(INDEX('D Fleet'!$C$5:$C$63,MATCH(F$3-$B7,'D Fleet'!$B$5:$B$63,0)),0)*IFERROR(INDEX('D Fleet'!$J$5:$J$36,INT(($B7/F$4))+1)+(($B7/F$4)-INT(($B7/F$4)))*(INDEX('D Fleet'!$J$5:$J$36,INT(($B7/F$4))+2)-INDEX('D Fleet'!$J$5:$J$36,INT(($B7/F$4))+1)),0) | G7: =IFERROR(INDEX('D Fleet'!$C$5:$C$63,MATCH(G$3-$B7,'D Fleet'!$B$5:$B$63,0)),0)*IFERROR(INDEX('D Fleet'!$J$5:$J$36,INT(($B7/G$4))+1)+(($B7/G$4)-INT(($B7/G$4)))*(INDEX('D Fleet'!$J$5:$J$36,INT(($B7/G$4))+2)-INDEX('D Fleet'!$J$5:$J$36,INT(($B7/G$4))+1)),0) | H7: =IFERROR(INDEX('D Fleet'!$C$5:$C$63,MATCH(H$3-$B7,'D Fleet'!$B$5:$B$63,0)),0)*IFERROR(INDEX('D Fleet'!$J$5:$J$36,INT(($B7/H$4))+1)+(($B7/H$4)-INT(($B7/H$4)))*(INDEX('D Fleet'!$J$5:$J$36,INT(($B7/H$4))+2)-INDEX('D Fleet'!$J$5:$J$36,INT(($B7/H$4))+1)),0) | I7: =IFERROR(INDEX('D Fleet'!$C$5:$C$63,MATCH(I$3-$B7,'D Fleet'!$B$5:$B$63,0)),0)*IFERROR(INDEX('D Fleet'!$J$5:$J$36,INT(($B7/I$4))+1)+(($B7/I$4)-INT(($B7/I$4)))*(INDEX('D Fleet'!$J$5:$J$36,INT(($B7/I$4))+2)-INDEX('D Fleet'!$J$5:$J$36,INT(($B7/I$4))+1)),0) | J7: =IFERROR(INDEX('D Fleet'!$C$5:$C$63,MATCH(J$3-$B7,'D Fleet'!$B$5:$B$63,0)),0)*IFERROR(INDEX('D Fleet'!$J$5:$J$36,INT(($B7/J$4))+1)+(($B7/J$4)-INT(($B7/J$4)))*(INDEX('D Fleet'!$J$5:$J$36,INT(($B7/J$4))+2)-INDEX('D Fleet'!$J$5:$J$36,INT(($B7/J$4))+1)),0) | K7: =IFERROR(INDEX('D Fleet'!$C$5:$C$63,MATCH(K$3-$B7,'D Fleet'!$B$5:$B$63,0)),0)*IFERROR(INDEX('D Fleet'!$J$5:$J$36,INT(($B7/K$4))+1)+(($B7/K$4)-INT(($B7/K$4)))*(INDEX('D Fleet'!$J$5:$J$36,INT(($B7/K$4))+2)-INDEX('D Fleet'!$J$5:$J$36,INT(($B7/K$4))+1)),0) | L7: =IFERROR(INDEX('D Fleet'!$C$5:$C$63,MATCH(L$3-$B7,'D Fleet'!$B$5:$B$63,0)),0)*IFERROR(INDEX('D Fleet'!$J$5:$J$36,INT(($B7/L$4))+1)+(($B7/L$4)-INT(($B7/L$4)))*(INDEX('D Fleet'!$J$5:$J$36,INT(($B7/L$4))+2)-INDEX('D Fleet'!$J$5:$J$36,INT(($B7/L$4))+1)),0) | ... N7: =IFERROR(INDEX('D Fleet'!$C$5:$C$63,MATCH(N$3-$B7,'D Fleet'!$B$5:$B$63,0)),0)*IFERROR(INDEX('D Fleet'!$J$5:$J$36,INT(($B7/N$4))+1)+(($B7/N$4)-INT(($B7/N$4)))*(INDEX('D Fleet'!$J$5:$J$36,INT(($B7/N$4))+2)-INDEX('D Fleet'!$J$5:$J$36,INT(($B7/N$4))+1)),0) | P7: =E7*$D7*'E1 Fleet'!$D$97 | Q7: =F7*$D7*'E1 Fleet'!$D$97 | R7: =G7*$D7*'E1 Fleet'!$D$97 | S7: =H7*$D7*'E1 Fleet'!$D$97 | T7: =I7*$D7*'E1 Fleet'!$D$97 | U7: =J7*$D7*'E1 Fleet'!$D$97 | V7: =K7*$D7*'E1 Fleet'!$D$97 | W7: =L7*$D7*'E1 Fleet'!$D$97 | ... Y7: =N7*$D7*'E1 Fleet'!$D$97
A8: Car | B8: 1 | C8: 1 | D8: =IF($B8=0,'E1 Fleet'!$D$93,1)*EXP(-'E1 Fleet'!$D$94*MAX($B8-6,0)) | E8: =IFERROR(INDEX('D Fleet'!$C$5:$C$63,MATCH(E$3-$B8,'D Fleet'!$B$5:$B$63,0)),0)*IFERROR(INDEX('D Fleet'!$J$5:$J$36,INT(($B8/E$4))+1)+(($B8/E$4)-INT(($B8/E$4)))*(INDEX('D Fleet'!$J$5:$J$36,INT(($B8/E$4))+2)-INDEX('D Fleet'!$J$5:$J$36,INT(($B8/E$4))+1)),0) | F8: =IFERROR(INDEX('D Fleet'!$C$5:$C$63,MATCH(F$3-$B8,'D Fleet'!$B$5:$B$63,0)),0)*IFERROR(INDEX('D Fleet'!$J$5:$J$36,INT(($B8/F$4))+1)+(($B8/F$4)-INT(($B8/F$4)))*(INDEX('D Fleet'!$J$5:$J$36,INT(($B8/F$4))+2)-INDEX('D Fleet'!$J$5:$J$36,INT(($B8/F$4))+1)),0) | G8: =IFERROR(INDEX('D Fleet'!$C$5:$C$63,MATCH(G$3-$B8,'D Fleet'!$B$5:$B$63,0)),0)*IFERROR(INDEX('D Fleet'!$J$5:$J$36,INT(($B8/G$4))+1)+(($B8/G$4)-INT(($B8/G$4)))*(INDEX('D Fleet'!$J$5:$J$36,INT(($B8/G$4))+2)-INDEX('D Fleet'!$J$5:$J$36,INT(($B8/G$4))+1)),0) | H8: =IFERROR(INDEX('D Fleet'!$C$5:$C$63,MATCH(H$3-$B8,'D Fleet'!$B$5:$B$63,0)),0)*IFERROR(INDEX('D Fleet'!$J$5:$J$36,INT(($B8/H$4))+1)+(($B8/H$4)-INT(($B8/H$4)))*(INDEX('D Fleet'!$J$5:$J$36,INT(($B8/H$4))+2)-INDEX('D Fleet'!$J$5:$J$36,INT(($B8/H$4))+1)),0) | I8: =IFERROR(INDEX('D Fleet'!$C$5:$C$63,MATCH(I$3-$B8,'D Fleet'!$B$5:$B$63,0)),0)*IFERROR(INDEX('D Fleet'!$J$5:$J$36,INT(($B8/I$4))+1)+(($B8/I$4)-INT(($B8/I$4)))*(INDEX('D Fleet'!$J$5:$J$36,INT(($B8/I$4))+2)-INDEX('D Fleet'!$J$5:$J$36,INT(($B8/I$4))+1)),0) | J8: =IFERROR(INDEX('D Fleet'!$C$5:$C$63,MATCH(J$3-$B8,'D Fleet'!$B$5:$B$63,0)),0)*IFERROR(INDEX('D Fleet'!$J$5:$J$36,INT(($B8/J$4))+1)+(($B8/J$4)-INT(($B8/J$4)))*(INDEX('D Fleet'!$J$5:$J$36,INT(($B8/J$4))+2)-INDEX('D Fleet'!$J$5:$J$36,INT(($B8/J$4))+1)),0) | K8: =IFERROR(INDEX('D Fleet'!$C$5:$C$63,MATCH(K$3-$B8,'D Fleet'!$B$5:$B$63,0)),0)*IFERROR(INDEX('D Fleet'!$J$5:$J$36,INT(($B8/K$4))+1)+(($B8/K$4)-INT(($B8/K$4)))*(INDEX('D Fleet'!$J$5:$J$36,INT(($B8/K$4))+2)-INDEX('D Fleet'!$J$5:$J$36,INT(($B8/K$4))+1)),0) | L8: =IFERROR(INDEX('D Fleet'!$C$5:$C$63,MATCH(L$3-$B8,'D Fleet'!$B$5:$B$63,0)),0)*IFERROR(INDEX('D Fleet'!$J$5:$J$36,INT(($B8/L$4))+1)+(($B8/L$4)-INT(($B8/L$4)))*(INDEX('D Fleet'!$J$5:$J$36,INT(($B8/L$4))+2)-INDEX('D Fleet'!$J$5:$J$36,INT(($B8/L$4))+1)),0) | ... N8: =IFERROR(INDEX('D Fleet'!$C$5:$C$63,MATCH(N$3-$B8,'D Fleet'!$B$5:$B$63,0)),0)*IFERROR(INDEX('D Fleet'!$J$5:$J$36,INT(($B8/N$4))+1)+(($B8/N$4)-INT(($B8/N$4)))*(INDEX('D Fleet'!$J$5:$J$36,INT(($B8/N$4))+2)-INDEX('D Fleet'!$J$5:$J$36,INT(($B8/N$4))+1)),0) | P8: =E8*$D8*'E1 Fleet'!$D$97 | Q8: =F8*$D8*'E1 Fleet'!$D$97 | R8: =G8*$D8*'E1 Fleet'!$D$97 | S8: =H8*$D8*'E1 Fleet'!$D$97 | T8: =I8*$D8*'E1 Fleet'!$D$97 | U8: =J8*$D8*'E1 Fleet'!$D$97 | V8: =K8*$D8*'E1 Fleet'!$D$97 | W8: =L8*$D8*'E1 Fleet'!$D$97 | ... Y8: =N8*$D8*'E1 Fleet'!$D$97
A9: Car | B9: 2 | C9: 1 | D9: =IF($B9=0,'E1 Fleet'!$D$93,1)*EXP(-'E1 Fleet'!$D$94*MAX($B9-6,0)) | E9: =IFERROR(INDEX('D Fleet'!$C$5:$C$63,MATCH(E$3-$B9,'D Fleet'!$B$5:$B$63,0)),0)*IFERROR(INDEX('D Fleet'!$J$5:$J$36,INT(($B9/E$4))+1)+(($B9/E$4)-INT(($B9/E$4)))*(INDEX('D Fleet'!$J$5:$J$36,INT(($B9/E$4))+2)-INDEX('D Fleet'!$J$5:$J$36,INT(($B9/E$4))+1)),0) | F9: =IFERROR(INDEX('D Fleet'!$C$5:$C$63,MATCH(F$3-$B9,'D Fleet'!$B$5:$B$63,0)),0)*IFERROR(INDEX('D Fleet'!$J$5:$J$36,INT(($B9/F$4))+1)+(($B9/F$4)-INT(($B9/F$4)))*(INDEX('D Fleet'!$J$5:$J$36,INT(($B9/F$4))+2)-INDEX('D Fleet'!$J$5:$J$36,INT(($B9/F$4))+1)),0) | G9: =IFERROR(INDEX('D Fleet'!$C$5:$C$63,MATCH(G$3-$B9,'D Fleet'!$B$5:$B$63,0)),0)*IFERROR(INDEX('D Fleet'!$J$5:$J$36,INT(($B9/G$4))+1)+(($B9/G$4)-INT(($B9/G$4)))*(INDEX('D Fleet'!$J$5:$J$36,INT(($B9/G$4))+2)-INDEX('D Fleet'!$J$5:$J$36,INT(($B9/G$4))+1)),0) | H9: =IFERROR(INDEX('D Fleet'!$C$5:$C$63,MATCH(H$3-$B9,'D Fleet'!$B$5:$B$63,0)),0)*IFERROR(INDEX('D Fleet'!$J$5:$J$36,INT(($B9/H$4))+1)+(($B9/H$4)-INT(($B9/H$4)))*(INDEX('D Fleet'!$J$5:$J$36,INT(($B9/H$4))+2)-INDEX('D Fleet'!$J$5:$J$36,INT(($B9/H$4))+1)),0) | I9: =IFERROR(INDEX('D Fleet'!$C$5:$C$63,MATCH(I$3-$B9,'D Fleet'!$B$5:$B$63,0)),0)*IFERROR(INDEX('D Fleet'!$J$5:$J$36,INT(($B9/I$4))+1)+(($B9/I$4)-INT(($B9/I$4)))*(INDEX('D Fleet'!$J$5:$J$36,INT(($B9/I$4))+2)-INDEX('D Fleet'!$J$5:$J$36,INT(($B9/I$4))+1)),0) | J9: =IFERROR(INDEX('D Fleet'!$C$5:$C$63,MATCH(J$3-$B9,'D Fleet'!$B$5:$B$63,0)),0)*IFERROR(INDEX('D Fleet'!$J$5:$J$36,INT(($B9/J$4))+1)+(($B9/J$4)-INT(($B9/J$4)))*(INDEX('D Fleet'!$J$5:$J$36,INT(($B9/J$4))+2)-INDEX('D Fleet'!$J$5:$J$36,INT(($B9/J$4))+1)),0) | K9: =IFERROR(INDEX('D Fleet'!$C$5:$C$63,MATCH(K$3-$B9,'D Fleet'!$B$5:$B$63,0)),0)*IFERROR(INDEX('D Fleet'!$J$5:$J$36,INT(($B9/K$4))+1)+(($B9/K$4)-INT(($B9/K$4)))*(INDEX('D Fleet'!$J$5:$J$36,INT(($B9/K$4))+2)-INDEX('D Fleet'!$J$5:$J$36,INT(($B9/K$4))+1)),0) | L9: =IFERROR(INDEX('D Fleet'!$C$5:$C$63,MATCH(L$3-$B9,'D Fleet'!$B$5:$B$63,0)),0)*IFERROR(INDEX('D Fleet'!$J$5:$J$36,INT(($B9/L$4))+1)+(($B9/L$4)-INT(($B9/L$4)))*(INDEX('D Fleet'!$J$5:$J$36,INT(($B9/L$4))+2)-INDEX('D Fleet'!$J$5:$J$36,INT(($B9/L$4))+1)),0) | ... N9: =IFERROR(INDEX('D Fleet'!$C$5:$C$63,MATCH(N$3-$B9,'D Fleet'!$B$5:$B$63,0)),0)*IFERROR(INDEX('D Fleet'!$J$5:$J$36,INT(($B9/N$4))+1)+(($B9/N$4)-INT(($B9/N$4)))*(INDEX('D Fleet'!$J$5:$J$36,INT(($B9/N$4))+2)-INDEX('D Fleet'!$J$5:$J$36,INT(($B9/N$4))+1)),0) | P9: =E9*$D9*'E1 Fleet'!$D$97 | Q9: =F9*$D9*'E1 Fleet'!$D$97 | R9: =G9*$D9*'E1 Fleet'!$D$97 | S9: =H9*$D9*'E1 Fleet'!$D$97 | T9: =I9*$D9*'E1 Fleet'!$D$97 | U9: =J9*$D9*'E1 Fleet'!$D$97 | V9: =K9*$D9*'E1 Fleet'!$D$97 | W9: =L9*$D9*'E1 Fleet'!$D$97 | ... Y9: =N9*$D9*'E1 Fleet'!$D$97
A10: Car | B10: 3 | C10: 1 | D10: =IF($B10=0,'E1 Fleet'!$D$93,1)*EXP(-'E1 Fleet'!$D$94*MAX($B10-6,0)) | E10: =IFERROR(INDEX('D Fleet'!$C$5:$C$63,MATCH(E$3-$B10,'D Fleet'!$B$5:$B$63,0)),0)*IFERROR(INDEX('D Fleet'!$J$5:$J$36,INT(($B10/E$4))+1)+(($B10/E$4)-INT(($B10/E$4)))*(INDEX('D Fleet'!$J$5:$J$36,INT(($B10/E$4))+2)-INDEX('D Fleet'!$J$5:$J$36,INT(($B10/E$4))+1)),0) | F10: =IFERROR(INDEX('D Fleet'!$C$5:$C$63,MATCH(F$3-$B10,'D Fleet'!$B$5:$B$63,0)),0)*IFERROR(INDEX('D Fleet'!$J$5:$J$36,INT(($B10/F$4))+1)+(($B10/F$4)-INT(($B10/F$4)))*(INDEX('D Fleet'!$J$5:$J$36,INT(($B10/F$4))+2)-INDEX('D Fleet'!$J$5:$J$36,INT(($B10/F$4))+1)),0) | G10: =IFERROR(INDEX('D Fleet'!$C$5:$C$63,MATCH(G$3-$B10,'D Fleet'!$B$5:$B$63,0)),0)*IFERROR(INDEX('D Fleet'!$J$5:$J$36,INT(($B10/G$4))+1)+(($B10/G$4)-INT(($B10/G$4)))*(INDEX('D Fleet'!$J$5:$J$36,INT(($B10/G$4))+2)-INDEX('D Fleet'!$J$5:$J$36,INT(($B10/G$4))+1)),0) | H10: =IFERROR(INDEX('D Fleet'!$C$5:$C$63,MATCH(H$3-$B10,'D Fleet'!$B$5:$B$63,0)),0)*IFERROR(INDEX('D Fleet'!$J$5:$J$36,INT(($B10/H$4))+1)+(($B10/H$4)-INT(($B10/H$4)))*(INDEX('D Fleet'!$J$5:$J$36,INT(($B10/H$4))+2)-INDEX('D Fleet'!$J$5:$J$36,INT(($B10/H$4))+1)),0) | I10: =IFERROR(INDEX('D Fleet'!$C$5:$C$63,MATCH(I$3-$B10,'D Fleet'!$B$5:$B$63,0)),0)*IFERROR(INDEX('D Fleet'!$J$5:$J$36,INT(($B10/I$4))+1)+(($B10/I$4)-INT(($B10/I$4)))*(INDEX('D Fleet'!$J$5:$J$36,INT(($B10/I$4))+2)-INDEX('D Fleet'!$J$5:$J$36,INT(($B10/I$4))+1)),0) | J10: =IFERROR(INDEX('D Fleet'!$C$5:$C$63,MATCH(J$3-$B10,'D Fleet'!$B$5:$B$63,0)),0)*IFERROR(INDEX('D Fleet'!$J$5:$J$36,INT(($B10/J$4))+1)+(($B10/J$4)-INT(($B10/J$4)))*(INDEX('D Fleet'!$J$5:$J$36,INT(($B10/J$4))+2)-INDEX('D Fleet'!$J$5:$J$36,INT(($B10/J$4))+1)),0) | K10: =IFERROR(INDEX('D Fleet'!$C$5:$C$63,MATCH(K$3-$B10,'D Fleet'!$B$5:$B$63,0)),0)*IFERROR(INDEX('D Fleet'!$J$5:$J$36,INT(($B10/K$4))+1)+(($B10/K$4)-INT(($B10/K$4)))*(INDEX('D Fleet'!$J$5:$J$36,INT(($B10/K$4))+2)-INDEX('D Fleet'!$J$5:$J$36,INT(($B10/K$4))+1)),0) | L10: =IFERROR(INDEX('D Fleet'!$C$5:$C$63,MATCH(L$3-$B10,'D Fleet'!$B$5:$B$63,0)),0)*IFERROR(INDEX('D Fleet'!$J$5:$J$36,INT(($B10/L$4))+1)+(($B10/L$4)-INT(($B10/L$4)))*(INDEX('D Fleet'!$J$5:$J$36,INT(($B10/L$4))+2)-INDEX('D Fleet'!$J$5:$J$36,INT(($B10/L$4))+1)),0) | ... N10: =IFERROR(INDEX('D Fleet'!$C$5:$C$63,MATCH(N$3-$B10,'D Fleet'!$B$5:$B$63,0)),0)*IFERROR(INDEX('D Fleet'!$J$5:$J$36,INT(($B10/N$4))+1)+(($B10/N$4)-INT(($B10/N$4)))*(INDEX('D Fleet'!$J$5:$J$36,INT(($B10/N$4))+2)-INDEX('D Fleet'!$J$5:$J$36,INT(($B10/N$4))+1)),0) | P10: =E10*$D10*'E1 Fleet'!$D$97 | Q10: =F10*$D10*'E1 Fleet'!$D$97 | R10: =G10*$D10*'E1 Fleet'!$D$97 | S10: =H10*$D10*'E1 Fleet'!$D$97 | T10: =I10*$D10*'E1 Fleet'!$D$97 | U10: =J10*$D10*'E1 Fleet'!$D$97 | V10: =K10*$D10*'E1 Fleet'!$D$97 | W10: =L10*$D10*'E1 Fleet'!$D$97 | ... Y10: =N10*$D10*'E1 Fleet'!$D$97
A11: Car | B11: 4 | C11: 2 | D11: =IF($B11=0,'E1 Fleet'!$D$93,1)*EXP(-'E1 Fleet'!$D$94*MAX($B11-6,0)) | E11: =IFERROR(INDEX('D Fleet'!$C$5:$C$63,MATCH(E$3-$B11,'D Fleet'!$B$5:$B$63,0)),0)*IFERROR(INDEX('D Fleet'!$J$5:$J$36,INT(($B11/E$4))+1)+(($B11/E$4)-INT(($B11/E$4)))*(INDEX('D Fleet'!$J$5:$J$36,INT(($B11/E$4))+2)-INDEX('D Fleet'!$J$5:$J$36,INT(($B11/E$4))+1)),0) | F11: =IFERROR(INDEX('D Fleet'!$C$5:$C$63,MATCH(F$3-$B11,'D Fleet'!$B$5:$B$63,0)),0)*IFERROR(INDEX('D Fleet'!$J$5:$J$36,INT(($B11/F$4))+1)+(($B11/F$4)-INT(($B11/F$4)))*(INDEX('D Fleet'!$J$5:$J$36,INT(($B11/F$4))+2)-INDEX('D Fleet'!$J$5:$J$36,INT(($B11/F$4))+1)),0) | G11: =IFERROR(INDEX('D Fleet'!$C$5:$C$63,MATCH(G$3-$B11,'D Fleet'!$B$5:$B$63,0)),0)*IFERROR(INDEX('D Fleet'!$J$5:$J$36,INT(($B11/G$4))+1)+(($B11/G$4)-INT(($B11/G$4)))*(INDEX('D Fleet'!$J$5:$J$36,INT(($B11/G$4))+2)-INDEX('D Fleet'!$J$5:$J$36,INT(($B11/G$4))+1)),0) | H11: =IFERROR(INDEX('D Fleet'!$C$5:$C$63,MATCH(H$3-$B11,'D Fleet'!$B$5:$B$63,0)),0)*IFERROR(INDEX('D Fleet'!$J$5:$J$36,INT(($B11/H$4))+1)+(($B11/H$4)-INT(($B11/H$4)))*(INDEX('D Fleet'!$J$5:$J$36,INT(($B11/H$4))+2)-INDEX('D Fleet'!$J$5:$J$36,INT(($B11/H$4))+1)),0) | I11: =IFERROR(INDEX('D Fleet'!$C$5:$C$63,MATCH(I$3-$B11,'D Fleet'!$B$5:$B$63,0)),0)*IFERROR(INDEX('D Fleet'!$J$5:$J$36,INT(($B11/I$4))+1)+(($B11/I$4)-INT(($B11/I$4)))*(INDEX('D Fleet'!$J$5:$J$36,INT(($B11/I$4))+2)-INDEX('D Fleet'!$J$5:$J$36,INT(($B11/I$4))+1)),0) | J11: =IFERROR(INDEX('D Fleet'!$C$5:$C$63,MATCH(J$3-$B11,'D Fleet'!$B$5:$B$63,0)),0)*IFERROR(INDEX('D Fleet'!$J$5:$J$36,INT(($B11/J$4))+1)+(($B11/J$4)-INT(($B11/J$4)))*(INDEX('D Fleet'!$J$5:$J$36,INT(($B11/J$4))+2)-INDEX('D Fleet'!$J$5:$J$36,INT(($B11/J$4))+1)),0) | K11: =IFERROR(INDEX('D Fleet'!$C$5:$C$63,MATCH(K$3-$B11,'D Fleet'!$B$5:$B$63,0)),0)*IFERROR(INDEX('D Fleet'!$J$5:$J$36,INT(($B11/K$4))+1)+(($B11/K$4)-INT(($B11/K$4)))*(INDEX('D Fleet'!$J$5:$J$36,INT(($B11/K$4))+2)-INDEX('D Fleet'!$J$5:$J$36,INT(($B11/K$4))+1)),0) | L11: =IFERROR(INDEX('D Fleet'!$C$5:$C$63,MATCH(L$3-$B11,'D Fleet'!$B$5:$B$63,0)),0)*IFERROR(INDEX('D Fleet'!$J$5:$J$36,INT(($B11/L$4))+1)+(($B11/L$4)-INT(($B11/L$4)))*(INDEX('D Fleet'!$J$5:$J$36,INT(($B11/L$4))+2)-INDEX('D Fleet'!$J$5:$J$36,INT(($B11/L$4))+1)),0) | ... N11: =IFERROR(INDEX('D Fleet'!$C$5:$C$63,MATCH(N$3-$B11,'D Fleet'!$B$5:$B$63,0)),0)*IFERROR(INDEX('D Fleet'!$J$5:$J$36,INT(($B11/N$4))+1)+(($B11/N$4)-INT(($B11/N$4)))*(INDEX('D Fleet'!$J$5:$J$36,INT(($B11/N$4))+2)-INDEX('D Fleet'!$J$5:$J$36,INT(($B11/N$4))+1)),0) | P11: =E11*$D11*'E1 Fleet'!$D$97 | Q11: =F11*$D11*'E1 Fleet'!$D$97 | R11: =G11*$D11*'E1 Fleet'!$D$97 | S11: =H11*$D11*'E1 Fleet'!$D$97 | T11: =I11*$D11*'E1 Fleet'!$D$97 | U11: =J11*$D11*'E1 Fleet'!$D$97 | V11: =K11*$D11*'E1 Fleet'!$D$97 | W11: =L11*$D11*'E1 Fleet'!$D$97 | ... Y11: =N11*$D11*'E1 Fleet'!$D$97
A12: Car | B12: 5 | C12: 2 | D12: =IF($B12=0,'E1 Fleet'!$D$93,1)*EXP(-'E1 Fleet'!$D$94*MAX($B12-6,0)) | E12: =IFERROR(INDEX('D Fleet'!$C$5:$C$63,MATCH(E$3-$B12,'D Fleet'!$B$5:$B$63,0)),0)*IFERROR(INDEX('D Fleet'!$J$5:$J$36,INT(($B12/E$4))+1)+(($B12/E$4)-INT(($B12/E$4)))*(INDEX('D Fleet'!$J$5:$J$36,INT(($B12/E$4))+2)-INDEX('D Fleet'!$J$5:$J$36,INT(($B12/E$4))+1)),0) | F12: =IFERROR(INDEX('D Fleet'!$C$5:$C$63,MATCH(F$3-$B12,'D Fleet'!$B$5:$B$63,0)),0)*IFERROR(INDEX('D Fleet'!$J$5:$J$36,INT(($B12/F$4))+1)+(($B12/F$4)-INT(($B12/F$4)))*(INDEX('D Fleet'!$J$5:$J$36,INT(($B12/F$4))+2)-INDEX('D Fleet'!$J$5:$J$36,INT(($B12/F$4))+1)),0) | G12: =IFERROR(INDEX('D Fleet'!$C$5:$C$63,MATCH(G$3-$B12,'D Fleet'!$B$5:$B$63,0)),0)*IFERROR(INDEX('D Fleet'!$J$5:$J$36,INT(($B12/G$4))+1)+(($B12/G$4)-INT(($B12/G$4)))*(INDEX('D Fleet'!$J$5:$J$36,INT(($B12/G$4))+2)-INDEX('D Fleet'!$J$5:$J$36,INT(($B12/G$4))+1)),0) | H12: =IFERROR(INDEX('D Fleet'!$C$5:$C$63,MATCH(H$3-$B12,'D Fleet'!$B$5:$B$63,0)),0)*IFERROR(INDEX('D Fleet'!$J$5:$J$36,INT(($B12/H$4))+1)+(($B12/H$4)-INT(($B12/H$4)))*(INDEX('D Fleet'!$J$5:$J$36,INT(($B12/H$4))+2)-INDEX('D Fleet'!$J$5:$J$36,INT(($B12/H$4))+1)),0) | I12: =IFERROR(INDEX('D Fleet'!$C$5:$C$63,MATCH(I$3-$B12,'D Fleet'!$B$5:$B$63,0)),0)*IFERROR(INDEX('D Fleet'!$J$5:$J$36,INT(($B12/I$4))+1)+(($B12/I$4)-INT(($B12/I$4)))*(INDEX('D Fleet'!$J$5:$J$36,INT(($B12/I$4))+2)-INDEX('D Fleet'!$J$5:$J$36,INT(($B12/I$4))+1)),0) | J12: =IFERROR(INDEX('D Fleet'!$C$5:$C$63,MATCH(J$3-$B12,'D Fleet'!$B$5:$B$63,0)),0)*IFERROR(INDEX('D Fleet'!$J$5:$J$36,INT(($B12/J$4))+1)+(($B12/J$4)-INT(($B12/J$4)))*(INDEX('D Fleet'!$J$5:$J$36,INT(($B12/J$4))+2)-INDEX('D Fleet'!$J$5:$J$36,INT(($B12/J$4))+1)),0) | K12: =IFERROR(INDEX('D Fleet'!$C$5:$C$63,MATCH(K$3-$B12,'D Fleet'!$B$5:$B$63,0)),0)*IFERROR(INDEX('D Fleet'!$J$5:$J$36,INT(($B12/K$4))+1)+(($B12/K$4)-INT(($B12/K$4)))*(INDEX('D Fleet'!$J$5:$J$36,INT(($B12/K$4))+2)-INDEX('D Fleet'!$J$5:$J$36,INT(($B12/K$4))+1)),0) | L12: =IFERROR(INDEX('D Fleet'!$C$5:$C$63,MATCH(L$3-$B12,'D Fleet'!$B$5:$B$63,0)),0)*IFERROR(INDEX('D Fleet'!$J$5:$J$36,INT(($B12/L$4))+1)+(($B12/L$4)-INT(($B12/L$4)))*(INDEX('D Fleet'!$J$5:$J$36,INT(($B12/L$4))+2)-INDEX('D Fleet'!$J$5:$J$36,INT(($B12/L$4))+1)),0) | ... N12: =IFERROR(INDEX('D Fleet'!$C$5:$C$63,MATCH(N$3-$B12,'D Fleet'!$B$5:$B$63,0)),0)*IFERROR(INDEX('D Fleet'!$J$5:$J$36,INT(($B12/N$4))+1)+(($B12/N$4)-INT(($B12/N$4)))*(INDEX('D Fleet'!$J$5:$J$36,INT(($B12/N$4))+2)-INDEX('D Fleet'!$J$5:$J$36,INT(($B12/N$4))+1)),0) | P12: =E12*$D12*'E1 Fleet'!$D$97 | Q12: =F12*$D12*'E1 Fleet'!$D$97 | R12: =G12*$D12*'E1 Fleet'!$D$97 | S12: =H12*$D12*'E1 Fleet'!$D$97 | T12: =I12*$D12*'E1 Fleet'!$D$97 | U12: =J12*$D12*'E1 Fleet'!$D$97 | V12: =K12*$D12*'E1 Fleet'!$D$97 | W12: =L12*$D12*'E1 Fleet'!$D$97 | ... Y12: =N12*$D12*'E1 Fleet'!$D$97
A13: Car | B13: 6 | C13: 2 | D13: =IF($B13=0,'E1 Fleet'!$D$93,1)*EXP(-'E1 Fleet'!$D$94*MAX($B13-6,0)) | E13: =IFERROR(INDEX('D Fleet'!$C$5:$C$63,MATCH(E$3-$B13,'D Fleet'!$B$5:$B$63,0)),0)*IFERROR(INDEX('D Fleet'!$J$5:$J$36,INT(($B13/E$4))+1)+(($B13/E$4)-INT(($B13/E$4)))*(INDEX('D Fleet'!$J$5:$J$36,INT(($B13/E$4))+2)-INDEX('D Fleet'!$J$5:$J$36,INT(($B13/E$4))+1)),0) | F13: =IFERROR(INDEX('D Fleet'!$C$5:$C$63,MATCH(F$3-$B13,'D Fleet'!$B$5:$B$63,0)),0)*IFERROR(INDEX('D Fleet'!$J$5:$J$36,INT(($B13/F$4))+1)+(($B13/F$4)-INT(($B13/F$4)))*(INDEX('D Fleet'!$J$5:$J$36,INT(($B13/F$4))+2)-INDEX('D Fleet'!$J$5:$J$36,INT(($B13/F$4))+1)),0) | G13: =IFERROR(INDEX('D Fleet'!$C$5:$C$63,MATCH(G$3-$B13,'D Fleet'!$B$5:$B$63,0)),0)*IFERROR(INDEX('D Fleet'!$J$5:$J$36,INT(($B13/G$4))+1)+(($B13/G$4)-INT(($B13/G$4)))*(INDEX('D Fleet'!$J$5:$J$36,INT(($B13/G$4))+2)-INDEX('D Fleet'!$J$5:$J$36,INT(($B13/G$4))+1)),0) | H13: =IFERROR(INDEX('D Fleet'!$C$5:$C$63,MATCH(H$3-$B13,'D Fleet'!$B$5:$B$63,0)),0)*IFERROR(INDEX('D Fleet'!$J$5:$J$36,INT(($B13/H$4))+1)+(($B13/H$4)-INT(($B13/H$4)))*(INDEX('D Fleet'!$J$5:$J$36,INT(($B13/H$4))+2)-INDEX('D Fleet'!$J$5:$J$36,INT(($B13/H$4))+1)),0) | I13: =IFERROR(INDEX('D Fleet'!$C$5:$C$63,MATCH(I$3-$B13,'D Fleet'!$B$5:$B$63,0)),0)*IFERROR(INDEX('D Fleet'!$J$5:$J$36,INT(($B13/I$4))+1)+(($B13/I$4)-INT(($B13/I$4)))*(INDEX('D Fleet'!$J$5:$J$36,INT(($B13/I$4))+2)-INDEX('D Fleet'!$J$5:$J$36,INT(($B13/I$4))+1)),0) | J13: =IFERROR(INDEX('D Fleet'!$C$5:$C$63,MATCH(J$3-$B13,'D Fleet'!$B$5:$B$63,0)),0)*IFERROR(INDEX('D Fleet'!$J$5:$J$36,INT(($B13/J$4))+1)+(($B13/J$4)-INT(($B13/J$4)))*(INDEX('D Fleet'!$J$5:$J$36,INT(($B13/J$4))+2)-INDEX('D Fleet'!$J$5:$J$36,INT(($B13/J$4))+1)),0) | K13: =IFERROR(INDEX('D Fleet'!$C$5:$C$63,MATCH(K$3-$B13,'D Fleet'!$B$5:$B$63,0)),0)*IFERROR(INDEX('D Fleet'!$J$5:$J$36,INT(($B13/K$4))+1)+(($B13/K$4)-INT(($B13/K$4)))*(INDEX('D Fleet'!$J$5:$J$36,INT(($B13/K$4))+2)-INDEX('D Fleet'!$J$5:$J$36,INT(($B13/K$4))+1)),0) | L13: =IFERROR(INDEX('D Fleet'!$C$5:$C$63,MATCH(L$3-$B13,'D Fleet'!$B$5:$B$63,0)),0)*IFERROR(INDEX('D Fleet'!$J$5:$J$36,INT(($B13/L$4))+1)+(($B13/L$4)-INT(($B13/L$4)))*(INDEX('D Fleet'!$J$5:$J$36,INT(($B13/L$4))+2)-INDEX('D Fleet'!$J$5:$J$36,INT(($B13/L$4))+1)),0) | ... N13: =IFERROR(INDEX('D Fleet'!$C$5:$C$63,MATCH(N$3-$B13,'D Fleet'!$B$5:$B$63,0)),0)*IFERROR(INDEX('D Fleet'!$J$5:$J$36,INT(($B13/N$4))+1)+(($B13/N$4)-INT(($B13/N$4)))*(INDEX('D Fleet'!$J$5:$J$36,INT(($B13/N$4))+2)-INDEX('D Fleet'!$J$5:$J$36,INT(($B13/N$4))+1)),0) | P13: =E13*$D13*'E1 Fleet'!$D$97 | Q13: =F13*$D13*'E1 Fleet'!$D$97 | R13: =G13*$D13*'E1 Fleet'!$D$97 | S13: =H13*$D13*'E1 Fleet'!$D$97 | T13: =I13*$D13*'E1 Fleet'!$D$97 | U13: =J13*$D13*'E1 Fleet'!$D$97 | V13: =K13*$D13*'E1 Fleet'!$D$97 | W13: =L13*$D13*'E1 Fleet'!$D$97 | ... Y13: =N13*$D13*'E1 Fleet'!$D$97
A14: Car | B14: 7 | C14: 3 | D14: =IF($B14=0,'E1 Fleet'!$D$93,1)*EXP(-'E1 Fleet'!$D$94*MAX($B14-6,0)) | E14: =IFERROR(INDEX('D Fleet'!$C$5:$C$63,MATCH(E$3-$B14,'D Fleet'!$B$5:$B$63,0)),0)*IFERROR(INDEX('D Fleet'!$J$5:$J$36,INT(($B14/E$4))+1)+(($B14/E$4)-INT(($B14/E$4)))*(INDEX('D Fleet'!$J$5:$J$36,INT(($B14/E$4))+2)-INDEX('D Fleet'!$J$5:$J$36,INT(($B14/E$4))+1)),0) | F14: =IFERROR(INDEX('D Fleet'!$C$5:$C$63,MATCH(F$3-$B14,'D Fleet'!$B$5:$B$63,0)),0)*IFERROR(INDEX('D Fleet'!$J$5:$J$36,INT(($B14/F$4))+1)+(($B14/F$4)-INT(($B14/F$4)))*(INDEX('D Fleet'!$J$5:$J$36,INT(($B14/F$4))+2)-INDEX('D Fleet'!$J$5:$J$36,INT(($B14/F$4))+1)),0) | G14: =IFERROR(INDEX('D Fleet'!$C$5:$C$63,MATCH(G$3-$B14,'D Fleet'!$B$5:$B$63,0)),0)*IFERROR(INDEX('D Fleet'!$J$5:$J$36,INT(($B14/G$4))+1)+(($B14/G$4)-INT(($B14/G$4)))*(INDEX('D Fleet'!$J$5:$J$36,INT(($B14/G$4))+2)-INDEX('D Fleet'!$J$5:$J$36,INT(($B14/G$4))+1)),0) | H14: =IFERROR(INDEX('D Fleet'!$C$5:$C$63,MATCH(H$3-$B14,'D Fleet'!$B$5:$B$63,0)),0)*IFERROR(INDEX('D Fleet'!$J$5:$J$36,INT(($B14/H$4))+1)+(($B14/H$4)-INT(($B14/H$4)))*(INDEX('D Fleet'!$J$5:$J$36,INT(($B14/H$4))+2)-INDEX('D Fleet'!$J$5:$J$36,INT(($B14/H$4))+1)),0) | I14: =IFERROR(INDEX('D Fleet'!$C$5:$C$63,MATCH(I$3-$B14,'D Fleet'!$B$5:$B$63,0)),0)*IFERROR(INDEX('D Fleet'!$J$5:$J$36,INT(($B14/I$4))+1)+(($B14/I$4)-INT(($B14/I$4)))*(INDEX('D Fleet'!$J$5:$J$36,INT(($B14/I$4))+2)-INDEX('D Fleet'!$J$5:$J$36,INT(($B14/I$4))+1)),0) | J14: =IFERROR(INDEX('D Fleet'!$C$5:$C$63,MATCH(J$3-$B14,'D Fleet'!$B$5:$B$63,0)),0)*IFERROR(INDEX('D Fleet'!$J$5:$J$36,INT(($B14/J$4))+1)+(($B14/J$4)-INT(($B14/J$4)))*(INDEX('D Fleet'!$J$5:$J$36,INT(($B14/J$4))+2)-INDEX('D Fleet'!$J$5:$J$36,INT(($B14/J$4))+1)),0) | K14: =IFERROR(INDEX('D Fleet'!$C$5:$C$63,MATCH(K$3-$B14,'D Fleet'!$B$5:$B$63,0)),0)*IFERROR(INDEX('D Fleet'!$J$5:$J$36,INT(($B14/K$4))+1)+(($B14/K$4)-INT(($B14/K$4)))*(INDEX('D Fleet'!$J$5:$J$36,INT(($B14/K$4))+2)-INDEX('D Fleet'!$J$5:$J$36,INT(($B14/K$4))+1)),0) | L14: =IFERROR(INDEX('D Fleet'!$C$5:$C$63,MATCH(L$3-$B14,'D Fleet'!$B$5:$B$63,0)),0)*IFERROR(INDEX('D Fleet'!$J$5:$J$36,INT(($B14/L$4))+1)+(($B14/L$4)-INT(($B14/L$4)))*(INDEX('D Fleet'!$J$5:$J$36,INT(($B14/L$4))+2)-INDEX('D Fleet'!$J$5:$J$36,INT(($B14/L$4))+1)),0) | ... N14: =IFERROR(INDEX('D Fleet'!$C$5:$C$63,MATCH(N$3-$B14,'D Fleet'!$B$5:$B$63,0)),0)*IFERROR(INDEX('D Fleet'!$J$5:$J$36,INT(($B14/N$4))+1)+(($B14/N$4)-INT(($B14/N$4)))*(INDEX('D Fleet'!$J$5:$J$36,INT(($B14/N$4))+2)-INDEX('D Fleet'!$J$5:$J$36,INT(($B14/N$4))+1)),0) | P14: =E14*$D14*'E1 Fleet'!$D$97 | Q14: =F14*$D14*'E1 Fleet'!$D$97 | R14: =G14*$D14*'E1 Fleet'!$D$97 | S14: =H14*$D14*'E1 Fleet'!$D$97 | T14: =I14*$D14*'E1 Fleet'!$D$97 | U14: =J14*$D14*'E1 Fleet'!$D$97 | V14: =K14*$D14*'E1 Fleet'!$D$97 | W14: =L14*$D14*'E1 Fleet'!$D$97 | ... Y14: =N14*$D14*'E1 Fleet'!$D$97
A15: Car | B15: 8 | C15: 3 | D15: =IF($B15=0,'E1 Fleet'!$D$93,1)*EXP(-'E1 Fleet'!$D$94*MAX($B15-6,0)) | E15: =IFERROR(INDEX('D Fleet'!$C$5:$C$63,MATCH(E$3-$B15,'D Fleet'!$B$5:$B$63,0)),0)*IFERROR(INDEX('D Fleet'!$J$5:$J$36,INT(($B15/E$4))+1)+(($B15/E$4)-INT(($B15/E$4)))*(INDEX('D Fleet'!$J$5:$J$36,INT(($B15/E$4))+2)-INDEX('D Fleet'!$J$5:$J$36,INT(($B15/E$4))+1)),0) | F15: =IFERROR(INDEX('D Fleet'!$C$5:$C$63,MATCH(F$3-$B15,'D Fleet'!$B$5:$B$63,0)),0)*IFERROR(INDEX('D Fleet'!$J$5:$J$36,INT(($B15/F$4))+1)+(($B15/F$4)-INT(($B15/F$4)))*(INDEX('D Fleet'!$J$5:$J$36,INT(($B15/F$4))+2)-INDEX('D Fleet'!$J$5:$J$36,INT(($B15/F$4))+1)),0) | G15: =IFERROR(INDEX('D Fleet'!$C$5:$C$63,MATCH(G$3-$B15,'D Fleet'!$B$5:$B$63,0)),0)*IFERROR(INDEX('D Fleet'!$J$5:$J$36,INT(($B15/G$4))+1)+(($B15/G$4)-INT(($B15/G$4)))*(INDEX('D Fleet'!$J$5:$J$36,INT(($B15/G$4))+2)-INDEX('D Fleet'!$J$5:$J$36,INT(($B15/G$4))+1)),0) | H15: =IFERROR(INDEX('D Fleet'!$C$5:$C$63,MATCH(H$3-$B15,'D Fleet'!$B$5:$B$63,0)),0)*IFERROR(INDEX('D Fleet'!$J$5:$J$36,INT(($B15/H$4))+1)+(($B15/H$4)-INT(($B15/H$4)))*(INDEX('D Fleet'!$J$5:$J$36,INT(($B15/H$4))+2)-INDEX('D Fleet'!$J$5:$J$36,INT(($B15/H$4))+1)),0) | I15: =IFERROR(INDEX('D Fleet'!$C$5:$C$63,MATCH(I$3-$B15,'D Fleet'!$B$5:$B$63,0)),0)*IFERROR(INDEX('D Fleet'!$J$5:$J$36,INT(($B15/I$4))+1)+(($B15/I$4)-INT(($B15/I$4)))*(INDEX('D Fleet'!$J$5:$J$36,INT(($B15/I$4))+2)-INDEX('D Fleet'!$J$5:$J$36,INT(($B15/I$4))+1)),0) | J15: =IFERROR(INDEX('D Fleet'!$C$5:$C$63,MATCH(J$3-$B15,'D Fleet'!$B$5:$B$63,0)),0)*IFERROR(INDEX('D Fleet'!$J$5:$J$36,INT(($B15/J$4))+1)+(($B15/J$4)-INT(($B15/J$4)))*(INDEX('D Fleet'!$J$5:$J$36,INT(($B15/J$4))+2)-INDEX('D Fleet'!$J$5:$J$36,INT(($B15/J$4))+1)),0) | K15: =IFERROR(INDEX('D Fleet'!$C$5:$C$63,MATCH(K$3-$B15,'D Fleet'!$B$5:$B$63,0)),0)*IFERROR(INDEX('D Fleet'!$J$5:$J$36,INT(($B15/K$4))+1)+(($B15/K$4)-INT(($B15/K$4)))*(INDEX('D Fleet'!$J$5:$J$36,INT(($B15/K$4))+2)-INDEX('D Fleet'!$J$5:$J$36,INT(($B15/K$4))+1)),0) | L15: =IFERROR(INDEX('D Fleet'!$C$5:$C$63,MATCH(L$3-$B15,'D Fleet'!$B$5:$B$63,0)),0)*IFERROR(INDEX('D Fleet'!$J$5:$J$36,INT(($B15/L$4))+1)+(($B15/L$4)-INT(($B15/L$4)))*(INDEX('D Fleet'!$J$5:$J$36,INT(($B15/L$4))+2)-INDEX('D Fleet'!$J$5:$J$36,INT(($B15/L$4))+1)),0) | ... N15: =IFERROR(INDEX('D Fleet'!$C$5:$C$63,MATCH(N$3-$B15,'D Fleet'!$B$5:$B$63,0)),0)*IFERROR(INDEX('D Fleet'!$J$5:$J$36,INT(($B15/N$4))+1)+(($B15/N$4)-INT(($B15/N$4)))*(INDEX('D Fleet'!$J$5:$J$36,INT(($B15/N$4))+2)-INDEX('D Fleet'!$J$5:$J$36,INT(($B15/N$4))+1)),0) | P15: =E15*$D15*'E1 Fleet'!$D$97 | Q15: =F15*$D15*'E1 Fleet'!$D$97 | R15: =G15*$D15*'E1 Fleet'!$D$97 | S15: =H15*$D15*'E1 Fleet'!$D$97 | T15: =I15*$D15*'E1 Fleet'!$D$97 | U15: =J15*$D15*'E1 Fleet'!$D$97 | V15: =K15*$D15*'E1 Fleet'!$D$97 | W15: =L15*$D15*'E1 Fleet'!$D$97 | ... Y15: =N15*$D15*'E1 Fleet'!$D$97
A16: Car | B16: 9 | C16: 3 | D16: =IF($B16=0,'E1 Fleet'!$D$93,1)*EXP(-'E1 Fleet'!$D$94*MAX($B16-6,0)) | E16: =IFERROR(INDEX('D Fleet'!$C$5:$C$63,MATCH(E$3-$B16,'D Fleet'!$B$5:$B$63,0)),0)*IFERROR(INDEX('D Fleet'!$J$5:$J$36,INT(($B16/E$4))+1)+(($B16/E$4)-INT(($B16/E$4)))*(INDEX('D Fleet'!$J$5:$J$36,INT(($B16/E$4))+2)-INDEX('D Fleet'!$J$5:$J$36,INT(($B16/E$4))+1)),0) | F16: =IFERROR(INDEX('D Fleet'!$C$5:$C$63,MATCH(F$3-$B16,'D Fleet'!$B$5:$B$63,0)),0)*IFERROR(INDEX('D Fleet'!$J$5:$J$36,INT(($B16/F$4))+1)+(($B16/F$4)-INT(($B16/F$4)))*(INDEX('D Fleet'!$J$5:$J$36,INT(($B16/F$4))+2)-INDEX('D Fleet'!$J$5:$J$36,INT(($B16/F$4))+1)),0) | G16: =IFERROR(INDEX('D Fleet'!$C$5:$C$63,MATCH(G$3-$B16,'D Fleet'!$B$5:$B$63,0)),0)*IFERROR(INDEX('D Fleet'!$J$5:$J$36,INT(($B16/G$4))+1)+(($B16/G$4)-INT(($B16/G$4)))*(INDEX('D Fleet'!$J$5:$J$36,INT(($B16/G$4))+2)-INDEX('D Fleet'!$J$5:$J$36,INT(($B16/G$4))+1)),0) | H16: =IFERROR(INDEX('D Fleet'!$C$5:$C$63,MATCH(H$3-$B16,'D Fleet'!$B$5:$B$63,0)),0)*IFERROR(INDEX('D Fleet'!$J$5:$J$36,INT(($B16/H$4))+1)+(($B16/H$4)-INT(($B16/H$4)))*(INDEX('D Fleet'!$J$5:$J$36,INT(($B16/H$4))+2)-INDEX('D Fleet'!$J$5:$J$36,INT(($B16/H$4))+1)),0) | I16: =IFERROR(INDEX('D Fleet'!$C$5:$C$63,MATCH(I$3-$B16,'D Fleet'!$B$5:$B$63,0)),0)*IFERROR(INDEX('D Fleet'!$J$5:$J$36,INT(($B16/I$4))+1)+(($B16/I$4)-INT(($B16/I$4)))*(INDEX('D Fleet'!$J$5:$J$36,INT(($B16/I$4))+2)-INDEX('D Fleet'!$J$5:$J$36,INT(($B16/I$4))+1)),0) | J16: =IFERROR(INDEX('D Fleet'!$C$5:$C$63,MATCH(J$3-$B16,'D Fleet'!$B$5:$B$63,0)),0)*IFERROR(INDEX('D Fleet'!$J$5:$J$36,INT(($B16/J$4))+1)+(($B16/J$4)-INT(($B16/J$4)))*(INDEX('D Fleet'!$J$5:$J$36,INT(($B16/J$4))+2)-INDEX('D Fleet'!$J$5:$J$36,INT(($B16/J$4))+1)),0) | K16: =IFERROR(INDEX('D Fleet'!$C$5:$C$63,MATCH(K$3-$B16,'D Fleet'!$B$5:$B$63,0)),0)*IFERROR(INDEX('D Fleet'!$J$5:$J$36,INT(($B16/K$4))+1)+(($B16/K$4)-INT(($B16/K$4)))*(INDEX('D Fleet'!$J$5:$J$36,INT(($B16/K$4))+2)-INDEX('D Fleet'!$J$5:$J$36,INT(($B16/K$4))+1)),0) | L16: =IFERROR(INDEX('D Fleet'!$C$5:$C$63,MATCH(L$3-$B16,'D Fleet'!$B$5:$B$63,0)),0)*IFERROR(INDEX('D Fleet'!$J$5:$J$36,INT(($B16/L$4))+1)+(($B16/L$4)-INT(($B16/L$4)))*(INDEX('D Fleet'!$J$5:$J$36,INT(($B16/L$4))+2)-INDEX('D Fleet'!$J$5:$J$36,INT(($B16/L$4))+1)),0) | ... N16: =IFERROR(INDEX('D Fleet'!$C$5:$C$63,MATCH(N$3-$B16,'D Fleet'!$B$5:$B$63,0)),0)*IFERROR(INDEX('D Fleet'!$J$5:$J$36,INT(($B16/N$4))+1)+(($B16/N$4)-INT(($B16/N$4)))*(INDEX('D Fleet'!$J$5:$J$36,INT(($B16/N$4))+2)-INDEX('D Fleet'!$J$5:$J$36,INT(($B16/N$4))+1)),0) | P16: =E16*$D16*'E1 Fleet'!$D$97 | Q16: =F16*$D16*'E1 Fleet'!$D$97 | R16: =G16*$D16*'E1 Fleet'!$D$97 | S16: =H16*$D16*'E1 Fleet'!$D$97 | T16: =I16*$D16*'E1 Fleet'!$D$97 | U16: =J16*$D16*'E1 Fleet'!$D$97 | V16: =K16*$D16*'E1 Fleet'!$D$97 | W16: =L16*$D16*'E1 Fleet'!$D$97 | ... Y16: =N16*$D16*'E1 Fleet'!$D$97
A17: Car | B17: 10 | C17: 3 | D17: =IF($B17=0,'E1 Fleet'!$D$93,1)*EXP(-'E1 Fleet'!$D$94*MAX($B17-6,0)) | E17: =IFERROR(INDEX('D Fleet'!$C$5:$C$63,MATCH(E$3-$B17,'D Fleet'!$B$5:$B$63,0)),0)*IFERROR(INDEX('D Fleet'!$J$5:$J$36,INT(($B17/E$4))+1)+(($B17/E$4)-INT(($B17/E$4)))*(INDEX('D Fleet'!$J$5:$J$36,INT(($B17/E$4))+2)-INDEX('D Fleet'!$J$5:$J$36,INT(($B17/E$4))+1)),0) | F17: =IFERROR(INDEX('D Fleet'!$C$5:$C$63,MATCH(F$3-$B17,'D Fleet'!$B$5:$B$63,0)),0)*IFERROR(INDEX('D Fleet'!$J$5:$J$36,INT(($B17/F$4))+1)+(($B17/F$4)-INT(($B17/F$4)))*(INDEX('D Fleet'!$J$5:$J$36,INT(($B17/F$4))+2)-INDEX('D Fleet'!$J$5:$J$36,INT(($B17/F$4))+1)),0) | G17: =IFERROR(INDEX('D Fleet'!$C$5:$C$63,MATCH(G$3-$B17,'D Fleet'!$B$5:$B$63,0)),0)*IFERROR(INDEX('D Fleet'!$J$5:$J$36,INT(($B17/G$4))+1)+(($B17/G$4)-INT(($B17/G$4)))*(INDEX('D Fleet'!$J$5:$J$36,INT(($B17/G$4))+2)-INDEX('D Fleet'!$J$5:$J$36,INT(($B17/G$4))+1)),0) | H17: =IFERROR(INDEX('D Fleet'!$C$5:$C$63,MATCH(H$3-$B17,'D Fleet'!$B$5:$B$63,0)),0)*IFERROR(INDEX('D Fleet'!$J$5:$J$36,INT(($B17/H$4))+1)+(($B17/H$4)-INT(($B17/H$4)))*(INDEX('D Fleet'!$J$5:$J$36,INT(($B17/H$4))+2)-INDEX('D Fleet'!$J$5:$J$36,INT(($B17/H$4))+1)),0) | I17: =IFERROR(INDEX('D Fleet'!$C$5:$C$63,MATCH(I$3-$B17,'D Fleet'!$B$5:$B$63,0)),0)*IFERROR(INDEX('D Fleet'!$J$5:$J$36,INT(($B17/I$4))+1)+(($B17/I$4)-INT(($B17/I$4)))*(INDEX('D Fleet'!$J$5:$J$36,INT(($B17/I$4))+2)-INDEX('D Fleet'!$J$5:$J$36,INT(($B17/I$4))+1)),0) | J17: =IFERROR(INDEX('D Fleet'!$C$5:$C$63,MATCH(J$3-$B17,'D Fleet'!$B$5:$B$63,0)),0)*IFERROR(INDEX('D Fleet'!$J$5:$J$36,INT(($B17/J$4))+1)+(($B17/J$4)-INT(($B17/J$4)))*(INDEX('D Fleet'!$J$5:$J$36,INT(($B17/J$4))+2)-INDEX('D Fleet'!$J$5:$J$36,INT(($B17/J$4))+1)),0) | K17: =IFERROR(INDEX('D Fleet'!$C$5:$C$63,MATCH(K$3-$B17,'D Fleet'!$B$5:$B$63,0)),0)*IFERROR(INDEX('D Fleet'!$J$5:$J$36,INT(($B17/K$4))+1)+(($B17/K$4)-INT(($B17/K$4)))*(INDEX('D Fleet'!$J$5:$J$36,INT(($B17/K$4))+2)-INDEX('D Fleet'!$J$5:$J$36,INT(($B17/K$4))+1)),0) | L17: =IFERROR(INDEX('D Fleet'!$C$5:$C$63,MATCH(L$3-$B17,'D Fleet'!$B$5:$B$63,0)),0)*IFERROR(INDEX('D Fleet'!$J$5:$J$36,INT(($B17/L$4))+1)+(($B17/L$4)-INT(($B17/L$4)))*(INDEX('D Fleet'!$J$5:$J$36,INT(($B17/L$4))+2)-INDEX('D Fleet'!$J$5:$J$36,INT(($B17/L$4))+1)),0) | ... N17: =IFERROR(INDEX('D Fleet'!$C$5:$C$63,MATCH(N$3-$B17,'D Fleet'!$B$5:$B$63,0)),0)*IFERROR(INDEX('D Fleet'!$J$5:$J$36,INT(($B17/N$4))+1)+(($B17/N$4)-INT(($B17/N$4)))*(INDEX('D Fleet'!$J$5:$J$36,INT(($B17/N$4))+2)-INDEX('D Fleet'!$J$5:$J$36,INT(($B17/N$4))+1)),0) | P17: =E17*$D17*'E1 Fleet'!$D$97 | Q17: =F17*$D17*'E1 Fleet'!$D$97 | R17: =G17*$D17*'E1 Fleet'!$D$97 | S17: =H17*$D17*'E1 Fleet'!$D$97 | T17: =I17*$D17*'E1 Fleet'!$D$97 | U17: =J17*$D17*'E1 Fleet'!$D$97 | V17: =K17*$D17*'E1 Fleet'!$D$97 | W17: =L17*$D17*'E1 Fleet'!$D$97 | ... Y17: =N17*$D17*'E1 Fleet'!$D$97
A18: Car | B18: 11 | C18: 3 | D18: =IF($B18=0,'E1 Fleet'!$D$93,1)*EXP(-'E1 Fleet'!$D$94*MAX($B18-6,0)) | E18: =IFERROR(INDEX('D Fleet'!$C$5:$C$63,MATCH(E$3-$B18,'D Fleet'!$B$5:$B$63,0)),0)*IFERROR(INDEX('D Fleet'!$J$5:$J$36,INT(($B18/E$4))+1)+(($B18/E$4)-INT(($B18/E$4)))*(INDEX('D Fleet'!$J$5:$J$36,INT(($B18/E$4))+2)-INDEX('D Fleet'!$J$5:$J$36,INT(($B18/E$4))+1)),0) | F18: =IFERROR(INDEX('D Fleet'!$C$5:$C$63,MATCH(F$3-$B18,'D Fleet'!$B$5:$B$63,0)),0)*IFERROR(INDEX('D Fleet'!$J$5:$J$36,INT(($B18/F$4))+1)+(($B18/F$4)-INT(($B18/F$4)))*(INDEX('D Fleet'!$J$5:$J$36,INT(($B18/F$4))+2)-INDEX('D Fleet'!$J$5:$J$36,INT(($B18/F$4))+1)),0) | G18: =IFERROR(INDEX('D Fleet'!$C$5:$C$63,MATCH(G$3-$B18,'D Fleet'!$B$5:$B$63,0)),0)*IFERROR(INDEX('D Fleet'!$J$5:$J$36,INT(($B18/G$4))+1)+(($B18/G$4)-INT(($B18/G$4)))*(INDEX('D Fleet'!$J$5:$J$36,INT(($B18/G$4))+2)-INDEX('D Fleet'!$J$5:$J$36,INT(($B18/G$4))+1)),0) | H18: =IFERROR(INDEX('D Fleet'!$C$5:$C$63,MATCH(H$3-$B18,'D Fleet'!$B$5:$B$63,0)),0)*IFERROR(INDEX('D Fleet'!$J$5:$J$36,INT(($B18/H$4))+1)+(($B18/H$4)-INT(($B18/H$4)))*(INDEX('D Fleet'!$J$5:$J$36,INT(($B18/H$4))+2)-INDEX('D Fleet'!$J$5:$J$36,INT(($B18/H$4))+1)),0) | I18: =IFERROR(INDEX('D Fleet'!$C$5:$C$63,MATCH(I$3-$B18,'D Fleet'!$B$5:$B$63,0)),0)*IFERROR(INDEX('D Fleet'!$J$5:$J$36,INT(($B18/I$4))+1)+(($B18/I$4)-INT(($B18/I$4)))*(INDEX('D Fleet'!$J$5:$J$36,INT(($B18/I$4))+2)-INDEX('D Fleet'!$J$5:$J$36,INT(($B18/I$4))+1)),0) | J18: =IFERROR(INDEX('D Fleet'!$C$5:$C$63,MATCH(J$3-$B18,'D Fleet'!$B$5:$B$63,0)),0)*IFERROR(INDEX('D Fleet'!$J$5:$J$36,INT(($B18/J$4))+1)+(($B18/J$4)-INT(($B18/J$4)))*(INDEX('D Fleet'!$J$5:$J$36,INT(($B18/J$4))+2)-INDEX('D Fleet'!$J$5:$J$36,INT(($B18/J$4))+1)),0) | K18: =IFERROR(INDEX('D Fleet'!$C$5:$C$63,MATCH(K$3-$B18,'D Fleet'!$B$5:$B$63,0)),0)*IFERROR(INDEX('D Fleet'!$J$5:$J$36,INT(($B18/K$4))+1)+(($B18/K$4)-INT(($B18/K$4)))*(INDEX('D Fleet'!$J$5:$J$36,INT(($B18/K$4))+2)-INDEX('D Fleet'!$J$5:$J$36,INT(($B18/K$4))+1)),0) | L18: =IFERROR(INDEX('D Fleet'!$C$5:$C$63,MATCH(L$3-$B18,'D Fleet'!$B$5:$B$63,0)),0)*IFERROR(INDEX('D Fleet'!$J$5:$J$36,INT(($B18/L$4))+1)+(($B18/L$4)-INT(($B18/L$4)))*(INDEX('D Fleet'!$J$5:$J$36,INT(($B18/L$4))+2)-INDEX('D Fleet'!$J$5:$J$36,INT(($B18/L$4))+1)),0) | ... N18: =IFERROR(INDEX('D Fleet'!$C$5:$C$63,MATCH(N$3-$B18,'D Fleet'!$B$5:$B$63,0)),0)*IFERROR(INDEX('D Fleet'!$J$5:$J$36,INT(($B18/N$4))+1)+(($B18/N$4)-INT(($B18/N$4)))*(INDEX('D Fleet'!$J$5:$J$36,INT(($B18/N$4))+2)-INDEX('D Fleet'!$J$5:$J$36,INT(($B18/N$4))+1)),0) | P18: =E18*$D18*'E1 Fleet'!$D$97 | Q18: =F18*$D18*'E1 Fleet'!$D$97 | R18: =G18*$D18*'E1 Fleet'!$D$97 | S18: =H18*$D18*'E1 Fleet'!$D$97 | T18: =I18*$D18*'E1 Fleet'!$D$97 | U18: =J18*$D18*'E1 Fleet'!$D$97 | V18: =K18*$D18*'E1 Fleet'!$D$97 | W18: =L18*$D18*'E1 Fleet'!$D$97 | ... Y18: =N18*$D18*'E1 Fleet'!$D$97
... A52: Car | B52: 45 | C52: 3 | D52: =IF($B52=0,'E1 Fleet'!$D$93,1)*EXP(-'E1 Fleet'!$D$94*MAX($B52-6,0)) | E52: =IFERROR(INDEX('D Fleet'!$C$5:$C$63,MATCH(E$3-$B52,'D Fleet'!$B$5:$B$63,0)),0)*IFERROR(INDEX('D Fleet'!$J$5:$J$36,INT(($B52/E$4))+1)+(($B52/E$4)-INT(($B52/E$4)))*(INDEX('D Fleet'!$J$5:$J$36,INT(($B52/E$4))+2)-INDEX('D Fleet'!$J$5:$J$36,INT(($B52/E$4))+1)),0) | F52: =IFERROR(INDEX('D Fleet'!$C$5:$C$63,MATCH(F$3-$B52,'D Fleet'!$B$5:$B$63,0)),0)*IFERROR(INDEX('D Fleet'!$J$5:$J$36,INT(($B52/F$4))+1)+(($B52/F$4)-INT(($B52/F$4)))*(INDEX('D Fleet'!$J$5:$J$36,INT(($B52/F$4))+2)-INDEX('D Fleet'!$J$5:$J$36,INT(($B52/F$4))+1)),0) | G52: =IFERROR(INDEX('D Fleet'!$C$5:$C$63,MATCH(G$3-$B52,'D Fleet'!$B$5:$B$63,0)),0)*IFERROR(INDEX('D Fleet'!$J$5:$J$36,INT(($B52/G$4))+1)+(($B52/G$4)-INT(($B52/G$4)))*(INDEX('D Fleet'!$J$5:$J$36,INT(($B52/G$4))+2)-INDEX('D Fleet'!$J$5:$J$36,INT(($B52/G$4))+1)),0) | H52: =IFERROR(INDEX('D Fleet'!$C$5:$C$63,MATCH(H$3-$B52,'D Fleet'!$B$5:$B$63,0)),0)*IFERROR(INDEX('D Fleet'!$J$5:$J$36,INT(($B52/H$4))+1)+(($B52/H$4)-INT(($B52/H$4)))*(INDEX('D Fleet'!$J$5:$J$36,INT(($B52/H$4))+2)-INDEX('D Fleet'!$J$5:$J$36,INT(($B52/H$4))+1)),0) | I52: =IFERROR(INDEX('D Fleet'!$C$5:$C$63,MATCH(I$3-$B52,'D Fleet'!$B$5:$B$63,0)),0)*IFERROR(INDEX('D Fleet'!$J$5:$J$36,INT(($B52/I$4))+1)+(($B52/I$4)-INT(($B52/I$4)))*(INDEX('D Fleet'!$J$5:$J$36,INT(($B52/I$4))+2)-INDEX('D Fleet'!$J$5:$J$36,INT(($B52/I$4))+1)),0) | J52: =IFERROR(INDEX('D Fleet'!$C$5:$C$63,MATCH(J$3-$B52,'D Fleet'!$B$5:$B$63,0)),0)*IFERROR(INDEX('D Fleet'!$J$5:$J$36,INT(($B52/J$4))+1)+(($B52/J$4)-INT(($B52/J$4)))*(INDEX('D Fleet'!$J$5:$J$36,INT(($B52/J$4))+2)-INDEX('D Fleet'!$J$5:$J$36,INT(($B52/J$4))+1)),0) | K52: =IFERROR(INDEX('D Fleet'!$C$5:$C$63,MATCH(K$3-$B52,'D Fleet'!$B$5:$B$63,0)),0)*IFERROR(INDEX('D Fleet'!$J$5:$J$36,INT(($B52/K$4))+1)+(($B52/K$4)-INT(($B52/K$4)))*(INDEX('D Fleet'!$J$5:$J$36,INT(($B52/K$4))+2)-INDEX('D Fleet'!$J$5:$J$36,INT(($B52/K$4))+1)),0) | L52: =IFERROR(INDEX('D Fleet'!$C$5:$C$63,MATCH(L$3-$B52,'D Fleet'!$B$5:$B$63,0)),0)*IFERROR(INDEX('D Fleet'!$J$5:$J$36,INT(($B52/L$4))+1)+(($B52/L$4)-INT(($B52/L$4)))*(INDEX('D Fleet'!$J$5:$J$36,INT(($B52/L$4))+2)-INDEX('D Fleet'!$J$5:$J$36,INT(($B52/L$4))+1)),0) | ... N52: =IFERROR(INDEX('D Fleet'!$C$5:$C$63,MATCH(N$3-$B52,'D Fleet'!$B$5:$B$63,0)),0)*IFERROR(INDEX('D Fleet'!$J$5:$J$36,INT(($B52/N$4))+1)+(($B52/N$4)-INT(($B52/N$4)))*(INDEX('D Fleet'!$J$5:$J$36,INT(($B52/N$4))+2)-INDEX('D Fleet'!$J$5:$J$36,INT(($B52/N$4))+1)),0) | P52: =E52*$D52*'E1 Fleet'!$D$97 | Q52: =F52*$D52*'E1 Fleet'!$D$97 | R52: =G52*$D52*'E1 Fleet'!$D$97 | S52: =H52*$D52*'E1 Fleet'!$D$97 | T52: =I52*$D52*'E1 Fleet'!$D$97 | U52: =J52*$D52*'E1 Fleet'!$D$97 | V52: =K52*$D52*'E1 Fleet'!$D$97 | W52: =L52*$D52*'E1 Fleet'!$D$97 | ... Y52: =N52*$D52*'E1 Fleet'!$D$97
A53: SUV | B53: 0 | C53: 0 | D53: =IF($B53=0,'E1 Fleet'!$D$93,1)*EXP(-'E1 Fleet'!$D$94*MAX($B53-6,0)) | E53: =IFERROR(INDEX('D Fleet'!$D$5:$D$63,MATCH(E$3-$B53,'D Fleet'!$B$5:$B$63,0)),0)*IFERROR(INDEX('D Fleet'!$K$5:$K$36,INT(($B53/E$5))+1)+(($B53/E$5)-INT(($B53/E$5)))*(INDEX('D Fleet'!$K$5:$K$36,INT(($B53/E$5))+2)-INDEX('D Fleet'!$K$5:$K$36,INT(($B53/E$5))+1)),0) | F53: =IFERROR(INDEX('D Fleet'!$D$5:$D$63,MATCH(F$3-$B53,'D Fleet'!$B$5:$B$63,0)),0)*IFERROR(INDEX('D Fleet'!$K$5:$K$36,INT(($B53/F$5))+1)+(($B53/F$5)-INT(($B53/F$5)))*(INDEX('D Fleet'!$K$5:$K$36,INT(($B53/F$5))+2)-INDEX('D Fleet'!$K$5:$K$36,INT(($B53/F$5))+1)),0) | G53: =IFERROR(INDEX('D Fleet'!$D$5:$D$63,MATCH(G$3-$B53,'D Fleet'!$B$5:$B$63,0)),0)*IFERROR(INDEX('D Fleet'!$K$5:$K$36,INT(($B53/G$5))+1)+(($B53/G$5)-INT(($B53/G$5)))*(INDEX('D Fleet'!$K$5:$K$36,INT(($B53/G$5))+2)-INDEX('D Fleet'!$K$5:$K$36,INT(($B53/G$5))+1)),0) | H53: =IFERROR(INDEX('D Fleet'!$D$5:$D$63,MATCH(H$3-$B53,'D Fleet'!$B$5:$B$63,0)),0)*IFERROR(INDEX('D Fleet'!$K$5:$K$36,INT(($B53/H$5))+1)+(($B53/H$5)-INT(($B53/H$5)))*(INDEX('D Fleet'!$K$5:$K$36,INT(($B53/H$5))+2)-INDEX('D Fleet'!$K$5:$K$36,INT(($B53/H$5))+1)),0) | I53: =IFERROR(INDEX('D Fleet'!$D$5:$D$63,MATCH(I$3-$B53,'D Fleet'!$B$5:$B$63,0)),0)*IFERROR(INDEX('D Fleet'!$K$5:$K$36,INT(($B53/I$5))+1)+(($B53/I$5)-INT(($B53/I$5)))*(INDEX('D Fleet'!$K$5:$K$36,INT(($B53/I$5))+2)-INDEX('D Fleet'!$K$5:$K$36,INT(($B53/I$5))+1)),0) | J53: =IFERROR(INDEX('D Fleet'!$D$5:$D$63,MATCH(J$3-$B53,'D Fleet'!$B$5:$B$63,0)),0)*IFERROR(INDEX('D Fleet'!$K$5:$K$36,INT(($B53/J$5))+1)+(($B53/J$5)-INT(($B53/J$5)))*(INDEX('D Fleet'!$K$5:$K$36,INT(($B53/J$5))+2)-INDEX('D Fleet'!$K$5:$K$36,INT(($B53/J$5))+1)),0) | K53: =IFERROR(INDEX('D Fleet'!$D$5:$D$63,MATCH(K$3-$B53,'D Fleet'!$B$5:$B$63,0)),0)*IFERROR(INDEX('D Fleet'!$K$5:$K$36,INT(($B53/K$5))+1)+(($B53/K$5)-INT(($B53/K$5)))*(INDEX('D Fleet'!$K$5:$K$36,INT(($B53/K$5))+2)-INDEX('D Fleet'!$K$5:$K$36,INT(($B53/K$5))+1)),0) | L53: =IFERROR(INDEX('D Fleet'!$D$5:$D$63,MATCH(L$3-$B53,'D Fleet'!$B$5:$B$63,0)),0)*IFERROR(INDEX('D Fleet'!$K$5:$K$36,INT(($B53/L$5))+1)+(($B53/L$5)-INT(($B53/L$5)))*(INDEX('D Fleet'!$K$5:$K$36,INT(($B53/L$5))+2)-INDEX('D Fleet'!$K$5:$K$36,INT(($B53/L$5))+1)),0) | ... N53: =IFERROR(INDEX('D Fleet'!$D$5:$D$63,MATCH(N$3-$B53,'D Fleet'!$B$5:$B$63,0)),0)*IFERROR(INDEX('D Fleet'!$K$5:$K$36,INT(($B53/N$5))+1)+(($B53/N$5)-INT(($B53/N$5)))*(INDEX('D Fleet'!$K$5:$K$36,INT(($B53/N$5))+2)-INDEX('D Fleet'!$K$5:$K$36,INT(($B53/N$5))+1)),0) | P53: =E53*$D53*'E1 Fleet'!$D$98 | Q53: =F53*$D53*'E1 Fleet'!$D$98 | R53: =G53*$D53*'E1 Fleet'!$D$98 | S53: =H53*$D53*'E1 Fleet'!$D$98 | T53: =I53*$D53*'E1 Fleet'!$D$98 | U53: =J53*$D53*'E1 Fleet'!$D$98 | V53: =K53*$D53*'E1 Fleet'!$D$98 | W53: =L53*$D53*'E1 Fleet'!$D$98 | ... Y53: =N53*$D53*'E1 Fleet'!$D$98
A54: SUV | B54: 1 | C54: 1 | D54: =IF($B54=0,'E1 Fleet'!$D$93,1)*EXP(-'E1 Fleet'!$D$94*MAX($B54-6,0)) | E54: =IFERROR(INDEX('D Fleet'!$D$5:$D$63,MATCH(E$3-$B54,'D Fleet'!$B$5:$B$63,0)),0)*IFERROR(INDEX('D Fleet'!$K$5:$K$36,INT(($B54/E$5))+1)+(($B54/E$5)-INT(($B54/E$5)))*(INDEX('D Fleet'!$K$5:$K$36,INT(($B54/E$5))+2)-INDEX('D Fleet'!$K$5:$K$36,INT(($B54/E$5))+1)),0) | F54: =IFERROR(INDEX('D Fleet'!$D$5:$D$63,MATCH(F$3-$B54,'D Fleet'!$B$5:$B$63,0)),0)*IFERROR(INDEX('D Fleet'!$K$5:$K$36,INT(($B54/F$5))+1)+(($B54/F$5)-INT(($B54/F$5)))*(INDEX('D Fleet'!$K$5:$K$36,INT(($B54/F$5))+2)-INDEX('D Fleet'!$K$5:$K$36,INT(($B54/F$5))+1)),0) | G54: =IFERROR(INDEX('D Fleet'!$D$5:$D$63,MATCH(G$3-$B54,'D Fleet'!$B$5:$B$63,0)),0)*IFERROR(INDEX('D Fleet'!$K$5:$K$36,INT(($B54/G$5))+1)+(($B54/G$5)-INT(($B54/G$5)))*(INDEX('D Fleet'!$K$5:$K$36,INT(($B54/G$5))+2)-INDEX('D Fleet'!$K$5:$K$36,INT(($B54/G$5))+1)),0) | H54: =IFERROR(INDEX('D Fleet'!$D$5:$D$63,MATCH(H$3-$B54,'D Fleet'!$B$5:$B$63,0)),0)*IFERROR(INDEX('D Fleet'!$K$5:$K$36,INT(($B54/H$5))+1)+(($B54/H$5)-INT(($B54/H$5)))*(INDEX('D Fleet'!$K$5:$K$36,INT(($B54/H$5))+2)-INDEX('D Fleet'!$K$5:$K$36,INT(($B54/H$5))+1)),0) | I54: =IFERROR(INDEX('D Fleet'!$D$5:$D$63,MATCH(I$3-$B54,'D Fleet'!$B$5:$B$63,0)),0)*IFERROR(INDEX('D Fleet'!$K$5:$K$36,INT(($B54/I$5))+1)+(($B54/I$5)-INT(($B54/I$5)))*(INDEX('D Fleet'!$K$5:$K$36,INT(($B54/I$5))+2)-INDEX('D Fleet'!$K$5:$K$36,INT(($B54/I$5))+1)),0) | J54: =IFERROR(INDEX('D Fleet'!$D$5:$D$63,MATCH(J$3-$B54,'D Fleet'!$B$5:$B$63,0)),0)*IFERROR(INDEX('D Fleet'!$K$5:$K$36,INT(($B54/J$5))+1)+(($B54/J$5)-INT(($B54/J$5)))*(INDEX('D Fleet'!$K$5:$K$36,INT(($B54/J$5))+2)-INDEX('D Fleet'!$K$5:$K$36,INT(($B54/J$5))+1)),0) | K54: =IFERROR(INDEX('D Fleet'!$D$5:$D$63,MATCH(K$3-$B54,'D Fleet'!$B$5:$B$63,0)),0)*IFERROR(INDEX('D Fleet'!$K$5:$K$36,INT(($B54/K$5))+1)+(($B54/K$5)-INT(($B54/K$5)))*(INDEX('D Fleet'!$K$5:$K$36,INT(($B54/K$5))+2)-INDEX('D Fleet'!$K$5:$K$36,INT(($B54/K$5))+1)),0) | L54: =IFERROR(INDEX('D Fleet'!$D$5:$D$63,MATCH(L$3-$B54,'D Fleet'!$B$5:$B$63,0)),0)*IFERROR(INDEX('D Fleet'!$K$5:$K$36,INT(($B54/L$5))+1)+(($B54/L$5)-INT(($B54/L$5)))*(INDEX('D Fleet'!$K$5:$K$36,INT(($B54/L$5))+2)-INDEX('D Fleet'!$K$5:$K$36,INT(($B54/L$5))+1)),0) | ... N54: =IFERROR(INDEX('D Fleet'!$D$5:$D$63,MATCH(N$3-$B54,'D Fleet'!$B$5:$B$63,0)),0)*IFERROR(INDEX('D Fleet'!$K$5:$K$36,INT(($B54/N$5))+1)+(($B54/N$5)-INT(($B54/N$5)))*(INDEX('D Fleet'!$K$5:$K$36,INT(($B54/N$5))+2)-INDEX('D Fleet'!$K$5:$K$36,INT(($B54/N$5))+1)),0) | P54: =E54*$D54*'E1 Fleet'!$D$98 | Q54: =F54*$D54*'E1 Fleet'!$D$98 | R54: =G54*$D54*'E1 Fleet'!$D$98 | S54: =H54*$D54*'E1 Fleet'!$D$98 | T54: =I54*$D54*'E1 Fleet'!$D$98 | U54: =J54*$D54*'E1 Fleet'!$D$98 | V54: =K54*$D54*'E1 Fleet'!$D$98 | W54: =L54*$D54*'E1 Fleet'!$D$98 | ... Y54: =N54*$D54*'E1 Fleet'!$D$98
