Workbook

Sheet README
A1: CPRT Intermediate — data and formulas to copy into "CPRT Model"
A2: Built 2026-09-15 by scripts/build_intermediate_xlsx.py from the committed CSVs in data/csv/. Rebuild after any data update; do not hand-edit Data_* tabs.
A4: HOW TO USE
A5: Copy whole sheets, not cells | B5: Right-click a tab → Move or Copy → To book: CPRT Model → tick Create a copy. Copy the tabs a formula sheet depends on FIRST (Inputs, Data_Sales, Data_EPA_Survival, Data_EPA_Miles, Data_CCC_Targets, then Survival, Fleet, FleetByAge, Curves, then TLF_Roll / Calibration). References are explicit sheet names, no named ranges, so they survive the copy as long as the tab names are unchanged.
A6: Colour legend | B6: BLUE = hard-coded input · BLACK = formula · GREEN = link to another sheet · YELLOW fill = calibrated parameter (fitted; reproducible on Calibration / Spread_Reg / RPU_Reg).
A7: One assumption per cell | B7: Every parameter lives once, on Inputs. Formula tabs never contain a typed number except the fixed 2024 cross-section on Calibration and Curves I:K.
A8: Check before you trust | B8: Checks tab must read OK everywhere after Excel recalculates (it does on open). If a check FAILs, a reference broke in the copy.
A10: TAB INDEX
A11: Inputs | B11: All parameters (survival stretch, R/P, exposure, future sales, anchors) + the k(t) path by year.
A12: Data_Sales | B12: Cohort sizes: new light-vehicle sales by model year, cars and light trucks, 1970–2030 (2026+ from Inputs).
A13: Data_EPA_Survival | B13: EPA survival schedule by age (ORNL TEDB Ed.40 T3.15). Data_EPA_Miles: EPA miles by age (T3.14).
A14: Data_CCC_Targets | B14: The CCC statistics R and P are fitted to (FIT), tested against (OOS), and the fleet-count anchors (S), each with its verbatim quote and page.
A15: Survival | B15: S(a,t) = EPA(a/k(t)) for cars and light trucks, ages 0–45 × years 2013–2030.
A16: Fleet | B16: Vehicles on the road by model year × calendar year (thousands). Row 68 = VIO.
A17: FleetByAge | B17: Same fleet re-indexed by age; VIO, share 7+/15+, count ≤6, average age.
A18: Curves | B18: R(a), P(a), miles by age, flags; the 7+ vs 0–6 miles/coverage decomposition.
A19: Calibration | B19: Solver set-up: five parameters → eight CCC 2024 statistics → LOSS. Instructions on the sheet.
A20: TLF_Roll | B20: Baseline TLF from demographics by year, its YoY drift, claim/TL age mix, and the out-of-sample checks vs CCC 2019/2020/2025.
A21: Spread_Reg | B21: ΔTLF = a + b·spread(t−1): pairs built by formula from Data_Spread and Data_CCC_TLF_Quarterly; SLOPE/INTERCEPT/RSQ; prediction and the live 2Q26 test.
A22: RPU_Reg | B22: ASP ~ used-car CPI by fiscal quarter (formulas on Data_CPI, Data_ReportedUnits); service and total RPU ~ ASP (Data_Elasticity); the chain calculator.
... A27: NOT IN THIS WORKBOOK | B27: Licensed material (S&P transcripts, Stephens preview, SOLS model) and the IHS-sourced ORNL tables (3.11/3.12/3.13, "further reproduction prohibited") — cited by table number only. Lot-level sitemap rows (1.3M) — in data/cprt.db.

Sheet Inputs
A1: Inputs — every parameter of the fleet roll in one place
A2: BLUE = hard-coded input (change freely) · YELLOW = calibrated (fitted on the Calibration tab / scripts/age_curves.py; copy new Solver results here) · model tabs reference ONLY this sheet for parameters.
A3: Parameter | B3: Value | C3: Source / note
A4: Survival stretch k, cars, 2013 | B4: 1.064 | C4: fitted to the IHS/Polk 2013 census of cars by single year of age (ORNL TEDB40 T3.11); S_k(a)=S_EPA(a/k). docs/AGE_CURVES.md §2.2
A5: Survival stretch k, light trucks, 2013 | B5: 0.92 | C5: fitted to the IHS 2013 census of trucks (T3.12, includes heavy). §2.2
A6: k multiplier by drift-end year | B6: 1.194 | C6: fitted so the 2024 roll hits VIO anchor and 66% aged 7+. 289M anchor is unverified (from memory); Experian 292.1M (on disk) gives 1.204 — same downstream. §2.4
A7: Drift start year | B7: 2013 | C7: k = 2013 value up to here
A8: Drift end year | B8: 2024 | C8: k reaches k_2013 × multiplier here; FLAT after (base case). Sensitivity: keep drifting
A9: Exposure factor, age 0 | B9: 0.5 | C9: a model-year-t vehicle is on the road ~half of calendar year t. Necessary: without it the ≤3-yr repairable share fits at 36% vs CCC ~30%. §3.2
A10: R kink age | B10: 6 | C10: R is flat through this age (a free 0–6 slope is not identified by the CCC targets). §3.3
A11: R slope after kink (per year of age) | B11: 0.09027 | C11: R(a) = e(a)·exp(−slope·max(a−kink,0)). Solver-fitted on Calibration tab. §3.3
A12: P floor (pmin) | B12: 0.0483 | C12: P(a) = pmin + (pmax−pmin)/(1+exp(−(a−mid)/width)). Solver-fitted. §4.3
A13: P ceiling (pmax) | B13: 0.4804
A14: P midpoint age (mid) | B14: 9.216
A15: P width (yrs) | B15: 3.726
A16: Future new-vehicle sales, cars (thousands per year, 2026+) | B16: 2764.4 | C16: ASSUMED = 2025 level (Data_Sales). Flex for a sales-recovery case
A17: Future new-vehicle sales, light trucks (thousands per year, 2026+) | B17: 13090.5 | C17: ASSUMED = 2025 level
A18: VIO anchor, end-2024 (M light vehicles) | B18: 289 | C18: S&P Global Mobility 2025 avg-age release — NOT ON DISK, confirm; Experian Q3-2024 = 292.1M (Crash Course 2025/Q1)
A19: Share aged 7+ anchor, 2024 | B19: 0.66 | C19: '66% of vehicles in operation are seven years or older' — S&P via CCC Crash Course 2024/Q4
A22: Survival stretch by calendar year (formulas)
A23: Year | C23: 2013 | D23: 2014 | E23: 2015 | F23: 2016 | G23: 2017 | H23: 2018 | I23: 2019 | J23: 2020 | K23: 2021 | L23: 2022 | M23: 2023 | N23: 2024 | O23: 2025 | P23: 2026 | Q23: 2027 | R23: 2028 | S23: 2029 | T23: 2030
A24: k multiplier | C24: =1+($B$6-1)*MIN(MAX(C23-$B$7,0),$B$8-$B$7)/($B$8-$B$7) | D24: =1+($B$6-1)*MIN(MAX(D23-$B$7,0),$B$8-$B$7)/($B$8-$B$7) | E24: =1+($B$6-1)*MIN(MAX(E23-$B$7,0),$B$8-$B$7)/($B$8-$B$7) | F24: =1+($B$6-1)*MIN(MAX(F23-$B$7,0),$B$8-$B$7)/($B$8-$B$7) | G24: =1+($B$6-1)*MIN(MAX(G23-$B$7,0),$B$8-$B$7)/($B$8-$B$7) | H24: =1+($B$6-1)*MIN(MAX(H23-$B$7,0),$B$8-$B$7)/($B$8-$B$7) | I24: =1+($B$6-1)*MIN(MAX(I23-$B$7,0),$B$8-$B$7)/($B$8-$B$7) | J24: =1+($B$6-1)*MIN(MAX(J23-$B$7,0),$B$8-$B$7)/($B$8-$B$7) | ... T24: =1+($B$6-1)*MIN(MAX(T23-$B$7,0),$B$8-$B$7)/($B$8-$B$7)
A25: k cars | C25: =$B$4*C24 | D25: =$B$4*D24 | E25: =$B$4*E24 | F25: =$B$4*F24 | G25: =$B$4*G24 | H25: =$B$4*H24 | I25: =$B$4*I24 | J25: =$B$4*J24 | ... T25: =$B$4*T24
A26: k light trucks | C26: =$B$5*C24 | D26: =$B$5*D24 | E26: =$B$5*E24 | F26: =$B$5*F24 | G26: =$B$5*G24 | H26: =$B$5*H24 | I26: =$B$5*I24 | J26: =$B$5*J24 | ... T26: =$B$5*T24
A28: Sensitivity idea: set B8 = 2030 to let survival keep improving; set B6 = 1.0 for the raw EPA schedule. Baseline TLF drift moves 0.05–0.18pp/yr across that range; P buckets do not move. §6

Sheet Data_Sales
A1: Cohort sizes — new light-vehicle sales by model year (thousands of vehicles)
A2: Cohort sizes for the fleet roll. 1970-2021 Ward's via ORNL TEDB Ed.40 Table 3.6; 2022-2025 FRED TOTALNSA (light vehicles) and LTRUCKNSA (light trucks), NSA monthly summed by calendar year (fetched 2026-09-14), | rescaled to Ward's basis using the 2021 overlap (cars x0.8789, light trucks x0.9675); heavy trucks 2022-25 = FRED HTRUCKSNSA (BEA, >14,000 lb) x1.823 to Ward's >10,000 lb basis — estimates, used only for the 2013 truck-census check.
A3: Unit: thousands of vehicles (8,321 = 8,321,000 cars). Ward's reports to the single vehicle, so the source carries decimals (e.g. 8,720.3); they are kept in the cells and hidden by the format. Ward's via ORNL TEDB Ed.40 Table 3.6 for 1970–2021; FRED TOTALNSA / LTRUCKNSA / HTRUCKSNSA rescaled to Ward's basis on the 2021 overlap for 2022–2025 (estimates — the decimals there mean nothing); 2026+ = Inputs (green). Heavy trucks (>10,000 lb) are NOT in the fleet roll; the column exists for the 2013 census check only. data/csv/light_vehicle_sales_by_year.csv
A4: model year | B4: cars (thousands) | C4: light trucks (thousands) | D4: heavy trucks (thousands) | E4: source
A5: 1970 | B5: 8321 | C5: 1457 | D5: 334 | E5: Ward's (ORNL TEDB40 T3.6)
A6: 1971 | B6: 10144 | C6: 1673 | D6: 340 | E6: Ward's (ORNL TEDB40 T3.6)
A7: 1972 | B7: 10800.6 | C7: 2097 | D7: 438 | E7: Ward's (ORNL TEDB40 T3.6)
A8: 1973 | B8: 11276 | C8: 2512 | D8: 497 | E8: Ward's (ORNL TEDB40 T3.6)
A9: 1974 | B9: 8720.3 | C9: 2163 | D9: 424 | E9: Ward's (ORNL TEDB40 T3.6)
A10: 1975 | B10: 8485.8 | C10: 2053 | D10: 298 | E10: Ward's (ORNL TEDB40 T3.6)
A11: 1976 | B11: 9956.8 | C11: 2719 | D11: 324 | E11: Ward's (ORNL TEDB40 T3.6)
A12: 1977 | B12: 11003.6 | C12: 3109 | D12: 376 | E12: Ward's (ORNL TEDB40 T3.6)
A13: 1978 | B13: 11107 | C13: 3474 | D13: 441 | E13: Ward's (ORNL TEDB40 T3.6)
A14: 1979 | B14: 10512 | C14: 2845 | D14: 391 | E14: Ward's (ORNL TEDB40 T3.6)
A15: 1980 | B15: 8948.8 | C15: 1960 | D15: 271 | E15: Ward's (ORNL TEDB40 T3.6)
A16: 1981 | B16: 8488.4 | C16: 1746 | D16: 226 | E16: Ward's (ORNL TEDB40 T3.6)
... A60: 2025 | B60: 2764.4 | C60: 13090.5 | D60: 758.9 | E60: FRED TOTALNSA/LTRUCKNSA/HTRUCKSNSA x Ward's-basis scale
A61: 2026 | B61: =Inputs!$B$16 | C61: =Inputs!$B$17 | E61: ASSUMED — Inputs B16/B17; heavy trucks not modelled (outside the light-vehicle roll)
A62: 2027 | B62: =Inputs!$B$16 | C62: =Inputs!$B$17 | E62: ASSUMED — Inputs B16/B17; heavy trucks not modelled (outside the light-vehicle roll)
A63: 2028 | B63: =Inputs!$B$16 | C63: =Inputs!$B$17 | E63: ASSUMED — Inputs B16/B17; heavy trucks not modelled (outside the light-vehicle roll)
A64: 2029 | B64: =Inputs!$B$16 | C64: =Inputs!$B$17 | E64: ASSUMED — Inputs B16/B17; heavy trucks not modelled (outside the light-vehicle roll)
A65: 2030 | B65: =Inputs!$B$16 | C65: =Inputs!$B$17 | E65: ASSUMED — Inputs B16/B17; heavy trucks not modelled (outside the light-vehicle roll)

Sheet Data_EPA_Survival
A1: EPA survival rates by vehicle age — cars and light trucks
A2: ORNL Transportation Energy Data Book Ed.40 (June 2022) spreadsheets, https://tedb.ornl.gov/wp-content/uploads/2022/06/TEDB_40_Spreadsheets_06012022.zip (robots-open, fetched 2026-09-14) | Table 3.15 (Table3_15_01312022.xlsx): EPA estimated survival rates by vehicle age, cars and light trucks (MY2015 rulemaking schedules)
A3: Primary: U.S. EPA, Draft Technical Assessment Report, Midterm Evaluation of LD GHG / CAFE Standards MY2022–2025, EPA-420-D-16-900, July 2016 — republished as ORNL Transportation Energy Data Book Ed.40 Table 3.15. Values verbatim.
A4: age | B4: survival_cars | C4: survival_light_trucks
A5: 0 | B5: 1 | C5: 1
A6: 1 | B6: 0.997 | C6: 0.991
A7: 2 | B7: 0.994 | C7: 0.982
A8: 3 | B8: 0.991 | C8: 0.973
A9: 4 | B9: 0.984 | C9: 0.96
A10: 5 | B10: 0.974 | C10: 0.941
A11: 6 | B11: 0.961 | C11: 0.919
A12: 7 | B12: 0.942 | C12: 0.891
A13: 8 | B13: 0.92 | C13: 0.859
A14: 9 | B14: 0.893 | C14: 0.823
A15: 10 | B15: 0.862 | C15: 0.784
A16: 11 | B16: 0.826 | C16: 0.741
... A36: 31 | B36: 0.002 | C36: 0.027

Sheet Data_CCC_Targets
A1: CCC Crash Course statistics used to fit and test R(age) and P(age)
A2: Quotes verbatim from the ungated report pages (PROVENANCE.md §5). FIT rows are used by the Calibration tab; OOS rows are the out-of-sample tests on TLF_Roll. Tolerance = the error that costs one unit of Solver loss.
A4: use | B4: year | C4: key | D4: statistic | E4: value | F4: tolerance | G4: quote | H4: page
A5: FIT | B5: 2024 | C5: tlf | D5: Total-loss frequency, all loss categories | E5: 0.223 | F5: 0.005 | G5: printed data label, chart "Total Loss Frequency Remains High as Vehicle Values Trend Up" (2024 = 22.3%) | H5: https://www.cccis.com/reports/crash-course-2026
A6: FIT | B6: 2024 | C6: tl7 | D6: Share of total-loss valuations on vehicles 7+ yrs | E6: 0.72 | F6: 0.01 | G6: almost 72% of valuations across all loss categories are for vehicles 7 years or older | H6: https://www.cccis.com/reports/crash-course-2024/q4
A7: FIT | B7: 2024 | C7: rp7 | D7: Share of repairable claims on vehicles 7+ yrs | E7: 0.45 | F7: 0.01 | G7: vehicles seven years or older now make up nearly 45% of all repairable claims, up from 35% in 2019 | H7: https://www.cccis.com/reports/crash-course-2024/q4
A8: FIT | B8: 2024 | C8: rp3 | D8: Share of repairable claims on vehicles ≤3 yrs (all fuel) | E8: 0.3 | F8: 0.02 | G8: Only 26.3% of repairable ICE vehicles are three years or newer (EVs 79.4% / hybrids 60.3% ≤3 yrs → all-fuel ≈30%) | H8: https://www.cccis.com/reports/crash-course-2024/q4
A9: FIT | B9: 2024 | C9: age_cl | D9: Average age of vehicles in claims (yrs) | E9: 7.6 | F9: 0.15 | G9: For claims, the average age of vehicles has increased to 7.6 years – up from 6.9 years in 2020 | H9: https://www.cccis.com/reports/crash-course-2025/q1
A10: FIT | B10: 2024 | C10: age_rp | D10: Average age of repairable vehicles (yrs) | E10: 6.8 | F10: 0.15 | G10: The average age of repairable vehicles was 6.8 years in 2024 (up from 6.1 years old in 2020) | H10: https://www.cccis.com/reports/crash-course-2025/q1
A11: FIT | B11: 2024 | C11: age_tl | D11: Average age of total-loss vehicles (yrs) | E11: 10.6 | F11: 0.15 | G11: ... and 10.6 years for total loss vehicles (up from 10.0 years old in 2020) | H11: https://www.cccis.com/reports/crash-course-2025/q1
A12: FIT | B12: 2024 | C12: p03 | D12: Total-loss rate for claims on vehicles ≤3 yrs | E12: 0.1 | F12: 0.01 | G12: For claims that are three years old or newer, 1 in 10 are flagged as a total loss by the insurer | H12: https://www.cccis.com/reports/crash-course-2026
A13: OOS | B13: 2019 | C13: rp7 | D13: Share of repairable claims on vehicles 7+ yrs | E13: 0.35 | G13: up from 35% in 2019 | H13: https://www.cccis.com/reports/crash-course-2024/q4
A14: OOS | B14: 2019 | C14: rp3 | D14: Share of repairable claims on vehicles ≤3 yrs | E14: 0.385 | G14: vehicles 3 years or newer represented 38.5% of the repairable mix in 2019 | H14: https://www.cccis.com/reports/crash-course-2025/q1
A15: OOS | B15: 2020 | C15: age_cl | D15: Average age of vehicles in claims (yrs) | E15: 6.9 | G15: up from 6.9 years in 2020 | H15: https://www.cccis.com/reports/crash-course-2025/q1
A16: OOS | B16: 2020 | C16: age_rp | D16: Average age of repairable vehicles (yrs) | E16: 6.1 | G16: up from 6.1 years old in 2020 | H16: https://www.cccis.com/reports/crash-course-2025/q1
A17: OOS | B17: 2020 | C17: age_tl | D17: Average age of total-loss vehicles (yrs) | E17: 10 | G17: up from 10.0 years old in 2020 | H17: https://www.cccis.com/reports/crash-course-2025/q1
A18: OOS | B18: 2025 | C18: tl7 | D18: Share of total-loss valuations on vehicles 7+ yrs | E18: 0.72 | G18: over 72% of total loss valuations are on vehicles 7 years or older | H18: https://www.cccis.com/reports/crash-course-2025/q4
A19: OOS | B19: 2025 | C19: rp7 | D19: Share of repairable claims on vehicles 7+ yrs | E19: 0.46 | G19: almost 46% of repairable vehicles are 7 years or older | H19: https://www.cccis.com/reports/crash-course-2025/q4
A20: OOS | B20: 2019 | C20: tlf | D20: TLF all loss categories (demographics-only model vs actual) | E20: 0.192 | G20: CCC annual 2019 = 19.2%; the gap is the non-demographic LEVEL (spread cycle, technology, filing) | H20: Data_CCC_TLF_Annual
A21: OOS | B21: 2020 | C21: tlf | D21: TLF all loss categories | E21: 0.206 | G21: CCC annual 2020 = 20.6% | H21: Data_CCC_TLF_Annual
A22: OOS | B22: 2025 | C22: tlf | D22: TLF all loss categories | E22: 0.231 | G22: CCC annual 2025 = 23.1% | H22: Data_CCC_TLF_Annual
A23: S | B23: 2024 | C23: vio | D23: Light vehicles in operation (M) | E23: 289 | G23: S&P 2025 release — NOT on disk (from memory); Experian 292.1M at Q3-2024 is on disk (Crash Course 2025/Q1) | H23: https://www.cccis.com/reports/crash-course-2025/q1
A24: S | B24: 2024 | C24: sh7 | D24: Share of fleet aged 7+ | E24: 0.66 | G24: 66% of vehicles in operation are seven years or older (S&P Mobility) | H24: https://www.cccis.com/reports/crash-course-2024/q4
A25: S | B25: 2025 | C25: viogr | D25: VIO growth 2020→Q3-2025 | E25: 0.051 | G25: Vehicles in operation reached almost 296 million as of Q3 2025 (Experian), +5.1% relative to 2020 | H25: https://www.cccis.com/reports/crash-course-2026

Sheet Survival
A1: Survival by age and calendar year — EPA schedule stretched by k(t)
A2: S(a,t) = S_EPA(a / k(t)), linearly interpolated between the table’s integer ages, zero beyond age 31·k. k(t) from Inputs row 25/26. Ages 0–45 (S is ~0 past 40).
A3: Year → | C3: =Inputs!C23 | D3: =Inputs!D23 | E3: =Inputs!E23 | F3: =Inputs!F23 | G3: =Inputs!G23 | H3: =Inputs!H23 | I3: =Inputs!I23 | J3: =Inputs!J23 | ... T3: =Inputs!T23
A4: k cars (Inputs) | C4: =Inputs!C25 | D4: =Inputs!D25 | E4: =Inputs!E25 | F4: =Inputs!F25 | G4: =Inputs!G25 | H4: =Inputs!H25 | I4: =Inputs!I25 | J4: =Inputs!J25 | ... T4: =Inputs!T25
A5: CARS: age | C5: =C3 | D5: =D3 | E5: =E3 | F5: =F3 | G5: =G3 | H5: =H3 | I5: =I3 | J5: =J3 | ... T5: =T3
A6: 0 | C6: =IF(($A6/C$4)>=31,0,INDEX(Data_EPA_Survival!$B$5:$B$36,INT(($A6/C$4))+1)+(($A6/C$4)-INT(($A6/C$4)))*(INDEX(Data_EPA_Survival!$B$5:$B$36,INT(($A6/C$4))+2)-INDEX(Data_EPA_Survival!$B$5:$B$36,INT(($A6/C$4))+1))) | D6: =IF(($A6/D$4)>=31,0,INDEX(Data_EPA_Survival!$B$5:$B$36,INT(($A6/D$4))+1)+(($A6/D$4)-INT(($A6/D$4)))*(INDEX(Data_EPA_Survival!$B$5:$B$36,INT(($A6/D$4))+2)-INDEX(Data_EPA_Survival!$B$5:$B$36,INT(($A6/D$4))+1))) | E6: =IF(($A6/E$4)>=31,0,INDEX(Data_EPA_Survival!$B$5:$B$36,INT(($A6/E$4))+1)+(($A6/E$4)-INT(($A6/E$4)))*(INDEX(Data_EPA_Survival!$B$5:$B$36,INT(($A6/E$4))+2)-INDEX(Data_EPA_Survival!$B$5:$B$36,INT(($A6/E$4))+1))) | F6: =IF(($A6/F$4)>=31,0,INDEX(Data_EPA_Survival!$B$5:$B$36,INT(($A6/F$4))+1)+(($A6/F$4)-INT(($A6/F$4)))*(INDEX(Data_EPA_Survival!$B$5:$B$36,INT(($A6/F$4))+2)-INDEX(Data_EPA_Survival!$B$5:$B$36,INT(($A6/F$4))+1))) | G6: =IF(($A6/G$4)>=31,0,INDEX(Data_EPA_Survival!$B$5:$B$36,INT(($A6/G$4))+1)+(($A6/G$4)-INT(($A6/G$4)))*(INDEX(Data_EPA_Survival!$B$5:$B$36,INT(($A6/G$4))+2)-INDEX(Data_EPA_Survival!$B$5:$B$36,INT(($A6/G$4))+1))) | H6: =IF(($A6/H$4)>=31,0,INDEX(Data_EPA_Survival!$B$5:$B$36,INT(($A6/H$4))+1)+(($A6/H$4)-INT(($A6/H$4)))*(INDEX(Data_EPA_Survival!$B$5:$B$36,INT(($A6/H$4))+2)-INDEX(Data_EPA_Survival!$B$5:$B$36,INT(($A6/H$4))+1))) | I6: =IF(($A6/I$4)>=31,0,INDEX(Data_EPA_Survival!$B$5:$B$36,INT(($A6/I$4))+1)+(($A6/I$4)-INT(($A6/I$4)))*(INDEX(Data_EPA_Survival!$B$5:$B$36,INT(($A6/I$4))+2)-INDEX(Data_EPA_Survival!$B$5:$B$36,INT(($A6/I$4))+1))) | J6: =IF(($A6/J$4)>=31,0,INDEX(Data_EPA_Survival!$B$5:$B$36,INT(($A6/J$4))+1)+(($A6/J$4)-INT(($A6/J$4)))*(INDEX(Data_EPA_Survival!$B$5:$B$36,INT(($A6/J$4))+2)-INDEX(Data_EPA_Survival!$B$5:$B$36,INT(($A6/J$4))+1))) | ... T6: =IF(($A6/T$4)>=31,0,INDEX(Data_EPA_Survival!$B$5:$B$36,INT(($A6/T$4))+1)+(($A6/T$4)-INT(($A6/T$4)))*(INDEX(Data_EPA_Survival!$B$5:$B$36,INT(($A6/T$4))+2)-INDEX(Data_EPA_Survival!$B$5:$B$36,INT(($A6/T$4))+1)))
A7: 1 | C7: =IF(($A7/C$4)>=31,0,INDEX(Data_EPA_Survival!$B$5:$B$36,INT(($A7/C$4))+1)+(($A7/C$4)-INT(($A7/C$4)))*(INDEX(Data_EPA_Survival!$B$5:$B$36,INT(($A7/C$4))+2)-INDEX(Data_EPA_Survival!$B$5:$B$36,INT(($A7/C$4))+1))) | D7: =IF(($A7/D$4)>=31,0,INDEX(Data_EPA_Survival!$B$5:$B$36,INT(($A7/D$4))+1)+(($A7/D$4)-INT(($A7/D$4)))*(INDEX(Data_EPA_Survival!$B$5:$B$36,INT(($A7/D$4))+2)-INDEX(Data_EPA_Survival!$B$5:$B$36,INT(($A7/D$4))+1))) | E7: =IF(($A7/E$4)>=31,0,INDEX(Data_EPA_Survival!$B$5:$B$36,INT(($A7/E$4))+1)+(($A7/E$4)-INT(($A7/E$4)))*(INDEX(Data_EPA_Survival!$B$5:$B$36,INT(($A7/E$4))+2)-INDEX(Data_EPA_Survival!$B$5:$B$36,INT(($A7/E$4))+1))) | F7: =IF(($A7/F$4)>=31,0,INDEX(Data_EPA_Survival!$B$5:$B$36,INT(($A7/F$4))+1)+(($A7/F$4)-INT(($A7/F$4)))*(INDEX(Data_EPA_Survival!$B$5:$B$36,INT(($A7/F$4))+2)-INDEX(Data_EPA_Survival!$B$5:$B$36,INT(($A7/F$4))+1))) | G7: =IF(($A7/G$4)>=31,0,INDEX(Data_EPA_Survival!$B$5:$B$36,INT(($A7/G$4))+1)+(($A7/G$4)-INT(($A7/G$4)))*(INDEX(Data_EPA_Survival!$B$5:$B$36,INT(($A7/G$4))+2)-INDEX(Data_EPA_Survival!$B$5:$B$36,INT(($A7/G$4))+1))) | H7: =IF(($A7/H$4)>=31,0,INDEX(Data_EPA_Survival!$B$5:$B$36,INT(($A7/H$4))+1)+(($A7/H$4)-INT(($A7/H$4)))*(INDEX(Data_EPA_Survival!$B$5:$B$36,INT(($A7/H$4))+2)-INDEX(Data_EPA_Survival!$B$5:$B$36,INT(($A7/H$4))+1))) | I7: =IF(($A7/I$4)>=31,0,INDEX(Data_EPA_Survival!$B$5:$B$36,INT(($A7/I$4))+1)+(($A7/I$4)-INT(($A7/I$4)))*(INDEX(Data_EPA_Survival!$B$5:$B$36,INT(($A7/I$4))+2)-INDEX(Data_EPA_Survival!$B$5:$B$36,INT(($A7/I$4))+1))) | J7: =IF(($A7/J$4)>=31,0,INDEX(Data_EPA_Survival!$B$5:$B$36,INT(($A7/J$4))+1)+(($A7/J$4)-INT(($A7/J$4)))*(INDEX(Data_EPA_Survival!$B$5:$B$36,INT(($A7/J$4))+2)-INDEX(Data_EPA_Survival!$B$5:$B$36,INT(($A7/J$4))+1))) | ... T7: =IF(($A7/T$4)>=31,0,INDEX(Data_EPA_Survival!$B$5:$B$36,INT(($A7/T$4))+1)+(($A7/T$4)-INT(($A7/T$4)))*(INDEX(Data_EPA_Survival!$B$5:$B$36,INT(($A7/T$4))+2)-INDEX(Data_EPA_Survival!$B$5:$B$36,INT(($A7/T$4))+1)))
A8: 2 | C8: =IF(($A8/C$4)>=31,0,INDEX(Data_EPA_Survival!$B$5:$B$36,INT(($A8/C$4))+1)+(($A8/C$4)-INT(($A8/C$4)))*(INDEX(Data_EPA_Survival!$B$5:$B$36,INT(($A8/C$4))+2)-INDEX(Data_EPA_Survival!$B$5:$B$36,INT(($A8/C$4))+1))) | D8: =IF(($A8/D$4)>=31,0,INDEX(Data_EPA_Survival!$B$5:$B$36,INT(($A8/D$4))+1)+(($A8/D$4)-INT(($A8/D$4)))*(INDEX(Data_EPA_Survival!$B$5:$B$36,INT(($A8/D$4))+2)-INDEX(Data_EPA_Survival!$B$5:$B$36,INT(($A8/D$4))+1))) | E8: =IF(($A8/E$4)>=31,0,INDEX(Data_EPA_Survival!$B$5:$B$36,INT(($A8/E$4))+1)+(($A8/E$4)-INT(($A8/E$4)))*(INDEX(Data_EPA_Survival!$B$5:$B$36,INT(($A8/E$4))+2)-INDEX(Data_EPA_Survival!$B$5:$B$36,INT(($A8/E$4))+1))) | F8: =IF(($A8/F$4)>=31,0,INDEX(Data_EPA_Survival!$B$5:$B$36,INT(($A8/F$4))+1)+(($A8/F$4)-INT(($A8/F$4)))*(INDEX(Data_EPA_Survival!$B$5:$B$36,INT(($A8/F$4))+2)-INDEX(Data_EPA_Survival!$B$5:$B$36,INT(($A8/F$4))+1))) | G8: =IF(($A8/G$4)>=31,0,INDEX(Data_EPA_Survival!$B$5:$B$36,INT(($A8/G$4))+1)+(($A8/G$4)-INT(($A8/G$4)))*(INDEX(Data_EPA_Survival!$B$5:$B$36,INT(($A8/G$4))+2)-INDEX(Data_EPA_Survival!$B$5:$B$36,INT(($A8/G$4))+1))) | H8: =IF(($A8/H$4)>=31,0,INDEX(Data_EPA_Survival!$B$5:$B$36,INT(($A8/H$4))+1)+(($A8/H$4)-INT(($A8/H$4)))*(INDEX(Data_EPA_Survival!$B$5:$B$36,INT(($A8/H$4))+2)-INDEX(Data_EPA_Survival!$B$5:$B$36,INT(($A8/H$4))+1))) | I8: =IF(($A8/I$4)>=31,0,INDEX(Data_EPA_Survival!$B$5:$B$36,INT(($A8/I$4))+1)+(($A8/I$4)-INT(($A8/I$4)))*(INDEX(Data_EPA_Survival!$B$5:$B$36,INT(($A8/I$4))+2)-INDEX(Data_EPA_Survival!$B$5:$B$36,INT(($A8/I$4))+1))) | J8: =IF(($A8/J$4)>=31,0,INDEX(Data_EPA_Survival!$B$5:$B$36,INT(($A8/J$4))+1)+(($A8/J$4)-INT(($A8/J$4)))*(INDEX(Data_EPA_Survival!$B$5:$B$36,INT(($A8/J$4))+2)-INDEX(Data_EPA_Survival!$B$5:$B$36,INT(($A8/J$4))+1))) | ... T8: =IF(($A8/T$4)>=31,0,INDEX(Data_EPA_Survival!$B$5:$B$36,INT(($A8/T$4))+1)+(($A8/T$4)-INT(($A8/T$4)))*(INDEX(Data_EPA_Survival!$B$5:$B$36,INT(($A8/T$4))+2)-INDEX(Data_EPA_Survival!$B$5:$B$36,INT(($A8/T$4))+1)))
A9: 3 | C9: =IF(($A9/C$4)>=31,0,INDEX(Data_EPA_Survival!$B$5:$B$36,INT(($A9/C$4))+1)+(($A9/C$4)-INT(($A9/C$4)))*(INDEX(Data_EPA_Survival!$B$5:$B$36,INT(($A9/C$4))+2)-INDEX(Data_EPA_Survival!$B$5:$B$36,INT(($A9/C$4))+1))) | D9: =IF(($A9/D$4)>=31,0,INDEX(Data_EPA_Survival!$B$5:$B$36,INT(($A9/D$4))+1)+(($A9/D$4)-INT(($A9/D$4)))*(INDEX(Data_EPA_Survival!$B$5:$B$36,INT(($A9/D$4))+2)-INDEX(Data_EPA_Survival!$B$5:$B$36,INT(($A9/D$4))+1))) | E9: =IF(($A9/E$4)>=31,0,INDEX(Data_EPA_Survival!$B$5:$B$36,INT(($A9/E$4))+1)+(($A9/E$4)-INT(($A9/E$4)))*(INDEX(Data_EPA_Survival!$B$5:$B$36,INT(($A9/E$4))+2)-INDEX(Data_EPA_Survival!$B$5:$B$36,INT(($A9/E$4))+1))) | F9: =IF(($A9/F$4)>=31,0,INDEX(Data_EPA_Survival!$B$5:$B$36,INT(($A9/F$4))+1)+(($A9/F$4)-INT(($A9/F$4)))*(INDEX(Data_EPA_Survival!$B$5:$B$36,INT(($A9/F$4))+2)-INDEX(Data_EPA_Survival!$B$5:$B$36,INT(($A9/F$4))+1))) | G9: =IF(($A9/G$4)>=31,0,INDEX(Data_EPA_Survival!$B$5:$B$36,INT(($A9/G$4))+1)+(($A9/G$4)-INT(($A9/G$4)))*(INDEX(Data_EPA_Survival!$B$5:$B$36,INT(($A9/G$4))+2)-INDEX(Data_EPA_Survival!$B$5:$B$36,INT(($A9/G$4))+1))) | H9: =IF(($A9/H$4)>=31,0,INDEX(Data_EPA_Survival!$B$5:$B$36,INT(($A9/H$4))+1)+(($A9/H$4)-INT(($A9/H$4)))*(INDEX(Data_EPA_Survival!$B$5:$B$36,INT(($A9/H$4))+2)-INDEX(Data_EPA_Survival!$B$5:$B$36,INT(($A9/H$4))+1))) | I9: =IF(($A9/I$4)>=31,0,INDEX(Data_EPA_Survival!$B$5:$B$36,INT(($A9/I$4))+1)+(($A9/I$4)-INT(($A9/I$4)))*(INDEX(Data_EPA_Survival!$B$5:$B$36,INT(($A9/I$4))+2)-INDEX(Data_EPA_Survival!$B$5:$B$36,INT(($A9/I$4))+1))) | J9: =IF(($A9/J$4)>=31,0,INDEX(Data_EPA_Survival!$B$5:$B$36,INT(($A9/J$4))+1)+(($A9/J$4)-INT(($A9/J$4)))*(INDEX(Data_EPA_Survival!$B$5:$B$36,INT(($A9/J$4))+2)-INDEX(Data_EPA_Survival!$B$5:$B$36,INT(($A9/J$4))+1))) | ... T9: =IF(($A9/T$4)>=31,0,INDEX(Data_EPA_Survival!$B$5:$B$36,INT(($A9/T$4))+1)+(($A9/T$4)-INT(($A9/T$4)))*(INDEX(Data_EPA_Survival!$B$5:$B$36,INT(($A9/T$4))+2)-INDEX(Data_EPA_Survival!$B$5:$B$36,INT(($A9/T$4))+1)))
A10: 4 | C10: =IF(($A10/C$4)>=31,0,INDEX(Data_EPA_Survival!$B$5:$B$36,INT(($A10/C$4))+1)+(($A10/C$4)-INT(($A10/C$4)))*(INDEX(Data_EPA_Survival!$B$5:$B$36,INT(($A10/C$4))+2)-INDEX(Data_EPA_Survival!$B$5:$B$36,INT(($A10/C$4))+1))) | D10: =IF(($A10/D$4)>=31,0,INDEX(Data_EPA_Survival!$B$5:$B$36,INT(($A10/D$4))+1)+(($A10/D$4)-INT(($A10/D$4)))*(INDEX(Data_EPA_Survival!$B$5:$B$36,INT(($A10/D$4))+2)-INDEX(Data_EPA_Survival!$B$5:$B$36,INT(($A10/D$4))+1))) | E10: =IF(($A10/E$4)>=31,0,INDEX(Data_EPA_Survival!$B$5:$B$36,INT(($A10/E$4))+1)+(($A10/E$4)-INT(($A10/E$4)))*(INDEX(Data_EPA_Survival!$B$5:$B$36,INT(($A10/E$4))+2)-INDEX(Data_EPA_Survival!$B$5:$B$36,INT(($A10/E$4))+1))) | F10: =IF(($A10/F$4)>=31,0,INDEX(Data_EPA_Survival!$B$5:$B$36,INT(($A10/F$4))+1)+(($A10/F$4)-INT(($A10/F$4)))*(INDEX(Data_EPA_Survival!$B$5:$B$36,INT(($A10/F$4))+2)-INDEX(Data_EPA_Survival!$B$5:$B$36,INT(($A10/F$4))+1))) | G10: =IF(($A10/G$4)>=31,0,INDEX(Data_EPA_Survival!$B$5:$B$36,INT(($A10/G$4))+1)+(($A10/G$4)-INT(($A10/G$4)))*(INDEX(Data_EPA_Survival!$B$5:$B$36,INT(($A10/G$4))+2)-INDEX(Data_EPA_Survival!$B$5:$B$36,INT(($A10/G$4))+1))) | H10: =IF(($A10/H$4)>=31,0,INDEX(Data_EPA_Survival!$B$5:$B$36,INT(($A10/H$4))+1)+(($A10/H$4)-INT(($A10/H$4)))*(INDEX(Data_EPA_Survival!$B$5:$B$36,INT(($A10/H$4))+2)-INDEX(Data_EPA_Survival!$B$5:$B$36,INT(($A10/H$4))+1))) | I10: =IF(($A10/I$4)>=31,0,INDEX(Data_EPA_Survival!$B$5:$B$36,INT(($A10/I$4))+1)+(($A10/I$4)-INT(($A10/I$4)))*(INDEX(Data_EPA_Survival!$B$5:$B$36,INT(($A10/I$4))+2)-INDEX(Data_EPA_Survival!$B$5:$B$36,INT(($A10/I$4))+1))) | J10: =IF(($A10/J$4)>=31,0,INDEX(Data_EPA_Survival!$B$5:$B$36,INT(($A10/J$4))+1)+(($A10/J$4)-INT(($A10/J$4)))*(INDEX(Data_EPA_Survival!$B$5:$B$36,INT(($A10/J$4))+2)-INDEX(Data_EPA_Survival!$B$5:$B$36,INT(($A10/J$4))+1))) | ... T10: =IF(($A10/T$4)>=31,0,INDEX(Data_EPA_Survival!$B$5:$B$36,INT(($A10/T$4))+1)+(($A10/T$4)-INT(($A10/T$4)))*(INDEX(Data_EPA_Survival!$B$5:$B$36,INT(($A10/T$4))+2)-INDEX(Data_EPA_Survival!$B$5:$B$36,INT(($A10/T$4))+1)))
A11: 5 | C11: =IF(($A11/C$4)>=31,0,INDEX(Data_EPA_Survival!$B$5:$B$36,INT(($A11/C$4))+1)+(($A11/C$4)-INT(($A11/C$4)))*(INDEX(Data_EPA_Survival!$B$5:$B$36,INT(($A11/C$4))+2)-INDEX(Data_EPA_Survival!$B$5:$B$36,INT(($A11/C$4))+1))) | D11: =IF(($A11/D$4)>=31,0,INDEX(Data_EPA_Survival!$B$5:$B$36,INT(($A11/D$4))+1)+(($A11/D$4)-INT(($A11/D$4)))*(INDEX(Data_EPA_Survival!$B$5:$B$36,INT(($A11/D$4))+2)-INDEX(Data_EPA_Survival!$B$5:$B$36,INT(($A11/D$4))+1))) | E11: =IF(($A11/E$4)>=31,0,INDEX(Data_EPA_Survival!$B$5:$B$36,INT(($A11/E$4))+1)+(($A11/E$4)-INT(($A11/E$4)))*(INDEX(Data_EPA_Survival!$B$5:$B$36,INT(($A11/E$4))+2)-INDEX(Data_EPA_Survival!$B$5:$B$36,INT(($A11/E$4))+1))) | F11: =IF(($A11/F$4)>=31,0,INDEX(Data_EPA_Survival!$B$5:$B$36,INT(($A11/F$4))+1)+(($A11/F$4)-INT(($A11/F$4)))*(INDEX(Data_EPA_Survival!$B$5:$B$36,INT(($A11/F$4))+2)-INDEX(Data_EPA_Survival!$B$5:$B$36,INT(($A11/F$4))+1))) | G11: =IF(($A11/G$4)>=31,0,INDEX(Data_EPA_Survival!$B$5:$B$36,INT(($A11/G$4))+1)+(($A11/G$4)-INT(($A11/G$4)))*(INDEX(Data_EPA_Survival!$B$5:$B$36,INT(($A11/G$4))+2)-INDEX(Data_EPA_Survival!$B$5:$B$36,INT(($A11/G$4))+1))) | H11: =IF(($A11/H$4)>=31,0,INDEX(Data_EPA_Survival!$B$5:$B$36,INT(($A11/H$4))+1)+(($A11/H$4)-INT(($A11/H$4)))*(INDEX(Data_EPA_Survival!$B$5:$B$36,INT(($A11/H$4))+2)-INDEX(Data_EPA_Survival!$B$5:$B$36,INT(($A11/H$4))+1))) | I11: =IF(($A11/I$4)>=31,0,INDEX(Data_EPA_Survival!$B$5:$B$36,INT(($A11/I$4))+1)+(($A11/I$4)-INT(($A11/I$4)))*(INDEX(Data_EPA_Survival!$B$5:$B$36,INT(($A11/I$4))+2)-INDEX(Data_EPA_Survival!$B$5:$B$36,INT(($A11/I$4))+1))) | J11: =IF(($A11/J$4)>=31,0,INDEX(Data_EPA_Survival!$B$5:$B$36,INT(($A11/J$4))+1)+(($A11/J$4)-INT(($A11/J$4)))*(INDEX(Data_EPA_Survival!$B$5:$B$36,INT(($A11/J$4))+2)-INDEX(Data_EPA_Survival!$B$5:$B$36,INT(($A11/J$4))+1))) | ... T11: =IF(($A11/T$4)>=31,0,INDEX(Data_EPA_Survival!$B$5:$B$36,INT(($A11/T$4))+1)+(($A11/T$4)-INT(($A11/T$4)))*(INDEX(Data_EPA_Survival!$B$5:$B$36,INT(($A11/T$4))+2)-INDEX(Data_EPA_Survival!$B$5:$B$36,INT(($A11/T$4))+1)))
A12: 6 | C12: =IF(($A12/C$4)>=31,0,INDEX(Data_EPA_Survival!$B$5:$B$36,INT(($A12/C$4))+1)+(($A12/C$4)-INT(($A12/C$4)))*(INDEX(Data_EPA_Survival!$B$5:$B$36,INT(($A12/C$4))+2)-INDEX(Data_EPA_Survival!$B$5:$B$36,INT(($A12/C$4))+1))) | D12: =IF(($A12/D$4)>=31,0,INDEX(Data_EPA_Survival!$B$5:$B$36,INT(($A12/D$4))+1)+(($A12/D$4)-INT(($A12/D$4)))*(INDEX(Data_EPA_Survival!$B$5:$B$36,INT(($A12/D$4))+2)-INDEX(Data_EPA_Survival!$B$5:$B$36,INT(($A12/D$4))+1))) | E12: =IF(($A12/E$4)>=31,0,INDEX(Data_EPA_Survival!$B$5:$B$36,INT(($A12/E$4))+1)+(($A12/E$4)-INT(($A12/E$4)))*(INDEX(Data_EPA_Survival!$B$5:$B$36,INT(($A12/E$4))+2)-INDEX(Data_EPA_Survival!$B$5:$B$36,INT(($A12/E$4))+1))) | F12: =IF(($A12/F$4)>=31,0,INDEX(Data_EPA_Survival!$B$5:$B$36,INT(($A12/F$4))+1)+(($A12/F$4)-INT(($A12/F$4)))*(INDEX(Data_EPA_Survival!$B$5:$B$36,INT(($A12/F$4))+2)-INDEX(Data_EPA_Survival!$B$5:$B$36,INT(($A12/F$4))+1))) | G12: =IF(($A12/G$4)>=31,0,INDEX(Data_EPA_Survival!$B$5:$B$36,INT(($A12/G$4))+1)+(($A12/G$4)-INT(($A12/G$4)))*(INDEX(Data_EPA_Survival!$B$5:$B$36,INT(($A12/G$4))+2)-INDEX(Data_EPA_Survival!$B$5:$B$36,INT(($A12/G$4))+1))) | H12: =IF(($A12/H$4)>=31,0,INDEX(Data_EPA_Survival!$B$5:$B$36,INT(($A12/H$4))+1)+(($A12/H$4)-INT(($A12/H$4)))*(INDEX(Data_EPA_Survival!$B$5:$B$36,INT(($A12/H$4))+2)-INDEX(Data_EPA_Survival!$B$5:$B$36,INT(($A12/H$4))+1))) | I12: =IF(($A12/I$4)>=31,0,INDEX(Data_EPA_Survival!$B$5:$B$36,INT(($A12/I$4))+1)+(($A12/I$4)-INT(($A12/I$4)))*(INDEX(Data_EPA_Survival!$B$5:$B$36,INT(($A12/I$4))+2)-INDEX(Data_EPA_Survival!$B$5:$B$36,INT(($A12/I$4))+1))) | J12: =IF(($A12/J$4)>=31,0,INDEX(Data_EPA_Survival!$B$5:$B$36,INT(($A12/J$4))+1)+(($A12/J$4)-INT(($A12/J$4)))*(INDEX(Data_EPA_Survival!$B$5:$B$36,INT(($A12/J$4))+2)-INDEX(Data_EPA_Survival!$B$5:$B$36,INT(($A12/J$4))+1))) | ... T12: =IF(($A12/T$4)>=31,0,INDEX(Data_EPA_Survival!$B$5:$B$36,INT(($A12/T$4))+1)+(($A12/T$4)-INT(($A12/T$4)))*(INDEX(Data_EPA_Survival!$B$5:$B$36,INT(($A12/T$4))+2)-INDEX(Data_EPA_Survival!$B$5:$B$36,INT(($A12/T$4))+1)))
A13: 7 | C13: =IF(($A13/C$4)>=31,0,INDEX(Data_EPA_Survival!$B$5:$B$36,INT(($A13/C$4))+1)+(($A13/C$4)-INT(($A13/C$4)))*(INDEX(Data_EPA_Survival!$B$5:$B$36,INT(($A13/C$4))+2)-INDEX(Data_EPA_Survival!$B$5:$B$36,INT(($A13/C$4))+1))) | D13: =IF(($A13/D$4)>=31,0,INDEX(Data_EPA_Survival!$B$5:$B$36,INT(($A13/D$4))+1)+(($A13/D$4)-INT(($A13/D$4)))*(INDEX(Data_EPA_Survival!$B$5:$B$36,INT(($A13/D$4))+2)-INDEX(Data_EPA_Survival!$B$5:$B$36,INT(($A13/D$4))+1))) | E13: =IF(($A13/E$4)>=31,0,INDEX(Data_EPA_Survival!$B$5:$B$36,INT(($A13/E$4))+1)+(($A13/E$4)-INT(($A13/E$4)))*(INDEX(Data_EPA_Survival!$B$5:$B$36,INT(($A13/E$4))+2)-INDEX(Data_EPA_Survival!$B$5:$B$36,INT(($A13/E$4))+1))) | F13: =IF(($A13/F$4)>=31,0,INDEX(Data_EPA_Survival!$B$5:$B$36,INT(($A13/F$4))+1)+(($A13/F$4)-INT(($A13/F$4)))*(INDEX(Data_EPA_Survival!$B$5:$B$36,INT(($A13/F$4))+2)-INDEX(Data_EPA_Survival!$B$5:$B$36,INT(($A13/F$4))+1))) | G13: =IF(($A13/G$4)>=31,0,INDEX(Data_EPA_Survival!$B$5:$B$36,INT(($A13/G$4))+1)+(($A13/G$4)-INT(($A13/G$4)))*(INDEX(Data_EPA_Survival!$B$5:$B$36,INT(($A13/G$4))+2)-INDEX(Data_EPA_Survival!$B$5:$B$36,INT(($A13/G$4))+1))) | H13: =IF(($A13/H$4)>=31,0,INDEX(Data_EPA_Survival!$B$5:$B$36,INT(($A13/H$4))+1)+(($A13/H$4)-INT(($A13/H$4)))*(INDEX(Data_EPA_Survival!$B$5:$B$36,INT(($A13/H$4))+2)-INDEX(Data_EPA_Survival!$B$5:$B$36,INT(($A13/H$4))+1))) | I13: =IF(($A13/I$4)>=31,0,INDEX(Data_EPA_Survival!$B$5:$B$36,INT(($A13/I$4))+1)+(($A13/I$4)-INT(($A13/I$4)))*(INDEX(Data_EPA_Survival!$B$5:$B$36,INT(($A13/I$4))+2)-INDEX(Data_EPA_Survival!$B$5:$B$36,INT(($A13/I$4))+1))) | J13: =IF(($A13/J$4)>=31,0,INDEX(Data_EPA_Survival!$B$5:$B$36,INT(($A13/J$4))+1)+(($A13/J$4)-INT(($A13/J$4)))*(INDEX(Data_EPA_Survival!$B$5:$B$36,INT(($A13/J$4))+2)-INDEX(Data_EPA_Survival!$B$5:$B$36,INT(($A13/J$4))+1))) | ... T13: =IF(($A13/T$4)>=31,0,INDEX(Data_EPA_Survival!$B$5:$B$36,INT(($A13/T$4))+1)+(($A13/T$4)-INT(($A13/T$4)))*(INDEX(Data_EPA_Survival!$B$5:$B$36,INT(($A13/T$4))+2)-INDEX(Data_EPA_Survival!$B$5:$B$36,INT(($A13/T$4))+1)))
A14: 8 | C14: =IF(($A14/C$4)>=31,0,INDEX(Data_EPA_Survival!$B$5:$B$36,INT(($A14/C$4))+1)+(($A14/C$4)-INT(($A14/C$4)))*(INDEX(Data_EPA_Survival!$B$5:$B$36,INT(($A14/C$4))+2)-INDEX(Data_EPA_Survival!$B$5:$B$36,INT(($A14/C$4))+1))) | D14: =IF(($A14/D$4)>=31,0,INDEX(Data_EPA_Survival!$B$5:$B$36,INT(($A14/D$4))+1)+(($A14/D$4)-INT(($A14/D$4)))*(INDEX(Data_EPA_Survival!$B$5:$B$36,INT(($A14/D$4))+2)-INDEX(Data_EPA_Survival!$B$5:$B$36,INT(($A14/D$4))+1))) | E14: =IF(($A14/E$4)>=31,0,INDEX(Data_EPA_Survival!$B$5:$B$36,INT(($A14/E$4))+1)+(($A14/E$4)-INT(($A14/E$4)))*(INDEX(Data_EPA_Survival!$B$5:$B$36,INT(($A14/E$4))+2)-INDEX(Data_EPA_Survival!$B$5:$B$36,INT(($A14/E$4))+1))) | F14: =IF(($A14/F$4)>=31,0,INDEX(Data_EPA_Survival!$B$5:$B$36,INT(($A14/F$4))+1)+(($A14/F$4)-INT(($A14/F$4)))*(INDEX(Data_EPA_Survival!$B$5:$B$36,INT(($A14/F$4))+2)-INDEX(Data_EPA_Survival!$B$5:$B$36,INT(($A14/F$4))+1))) | G14: =IF(($A14/G$4)>=31,0,INDEX(Data_EPA_Survival!$B$5:$B$36,INT(($A14/G$4))+1)+(($A14/G$4)-INT(($A14/G$4)))*(INDEX(Data_EPA_Survival!$B$5:$B$36,INT(($A14/G$4))+2)-INDEX(Data_EPA_Survival!$B$5:$B$36,INT(($A14/G$4))+1))) | H14: =IF(($A14/H$4)>=31,0,INDEX(Data_EPA_Survival!$B$5:$B$36,INT(($A14/H$4))+1)+(($A14/H$4)-INT(($A14/H$4)))*(INDEX(Data_EPA_Survival!$B$5:$B$36,INT(($A14/H$4))+2)-INDEX(Data_EPA_Survival!$B$5:$B$36,INT(($A14/H$4))+1))) | I14: =IF(($A14/I$4)>=31,0,INDEX(Data_EPA_Survival!$B$5:$B$36,INT(($A14/I$4))+1)+(($A14/I$4)-INT(($A14/I$4)))*(INDEX(Data_EPA_Survival!$B$5:$B$36,INT(($A14/I$4))+2)-INDEX(Data_EPA_Survival!$B$5:$B$36,INT(($A14/I$4))+1))) | J14: =IF(($A14/J$4)>=31,0,INDEX(Data_EPA_Survival!$B$5:$B$36,INT(($A14/J$4))+1)+(($A14/J$4)-INT(($A14/J$4)))*(INDEX(Data_EPA_Survival!$B$5:$B$36,INT(($A14/J$4))+2)-INDEX(Data_EPA_Survival!$B$5:$B$36,INT(($A14/J$4))+1))) | ... T14: =IF(($A14/T$4)>=31,0,INDEX(Data_EPA_Survival!$B$5:$B$36,INT(($A14/T$4))+1)+(($A14/T$4)-INT(($A14/T$4)))*(INDEX(Data_EPA_Survival!$B$5:$B$36,INT(($A14/T$4))+2)-INDEX(Data_EPA_Survival!$B$5:$B$36,INT(($A14/T$4))+1)))
A15: 9 | C15: =IF(($A15/C$4)>=31,0,INDEX(Data_EPA_Survival!$B$5:$B$36,INT(($A15/C$4))+1)+(($A15/C$4)-INT(($A15/C$4)))*(INDEX(Data_EPA_Survival!$B$5:$B$36,INT(($A15/C$4))+2)-INDEX(Data_EPA_Survival!$B$5:$B$36,INT(($A15/C$4))+1))) | D15: =IF(($A15/D$4)>=31,0,INDEX(Data_EPA_Survival!$B$5:$B$36,INT(($A15/D$4))+1)+(($A15/D$4)-INT(($A15/D$4)))*(INDEX(Data_EPA_Survival!$B$5:$B$36,INT(($A15/D$4))+2)-INDEX(Data_EPA_Survival!$B$5:$B$36,INT(($A15/D$4))+1))) | E15: =IF(($A15/E$4)>=31,0,INDEX(Data_EPA_Survival!$B$5:$B$36,INT(($A15/E$4))+1)+(($A15/E$4)-INT(($A15/E$4)))*(INDEX(Data_EPA_Survival!$B$5:$B$36,INT(($A15/E$4))+2)-INDEX(Data_EPA_Survival!$B$5:$B$36,INT(($A15/E$4))+1))) | F15: =IF(($A15/F$4)>=31,0,INDEX(Data_EPA_Survival!$B$5:$B$36,INT(($A15/F$4))+1)+(($A15/F$4)-INT(($A15/F$4)))*(INDEX(Data_EPA_Survival!$B$5:$B$36,INT(($A15/F$4))+2)-INDEX(Data_EPA_Survival!$B$5:$B$36,INT(($A15/F$4))+1))) | G15: =IF(($A15/G$4)>=31,0,INDEX(Data_EPA_Survival!$B$5:$B$36,INT(($A15/G$4))+1)+(($A15/G$4)-INT(($A15/G$4)))*(INDEX(Data_EPA_Survival!$B$5:$B$36,INT(($A15/G$4))+2)-INDEX(Data_EPA_Survival!$B$5:$B$36,INT(($A15/G$4))+1))) | H15: =IF(($A15/H$4)>=31,0,INDEX(Data_EPA_Survival!$B$5:$B$36,INT(($A15/H$4))+1)+(($A15/H$4)-INT(($A15/H$4)))*(INDEX(Data_EPA_Survival!$B$5:$B$36,INT(($A15/H$4))+2)-INDEX(Data_EPA_Survival!$B$5:$B$36,INT(($A15/H$4))+1))) | I15: =IF(($A15/I$4)>=31,0,INDEX(Data_EPA_Survival!$B$5:$B$36,INT(($A15/I$4))+1)+(($A15/I$4)-INT(($A15/I$4)))*(INDEX(Data_EPA_Survival!$B$5:$B$36,INT(($A15/I$4))+2)-INDEX(Data_EPA_Survival!$B$5:$B$36,INT(($A15/I$4))+1))) | J15: =IF(($A15/J$4)>=31,0,INDEX(Data_EPA_Survival!$B$5:$B$36,INT(($A15/J$4))+1)+(($A15/J$4)-INT(($A15/J$4)))*(INDEX(Data_EPA_Survival!$B$5:$B$36,INT(($A15/J$4))+2)-INDEX(Data_EPA_Survival!$B$5:$B$36,INT(($A15/J$4))+1))) | ... T15: =IF(($A15/T$4)>=31,0,INDEX(Data_EPA_Survival!$B$5:$B$36,INT(($A15/T$4))+1)+(($A15/T$4)-INT(($A15/T$4)))*(INDEX(Data_EPA_Survival!$B$5:$B$36,INT(($A15/T$4))+2)-INDEX(Data_EPA_Survival!$B$5:$B$36,INT(($A15/T$4))+1)))
A16: 10 | C16: =IF(($A16/C$4)>=31,0,INDEX(Data_EPA_Survival!$B$5:$B$36,INT(($A16/C$4))+1)+(($A16/C$4)-INT(($A16/C$4)))*(INDEX(Data_EPA_Survival!$B$5:$B$36,INT(($A16/C$4))+2)-INDEX(Data_EPA_Survival!$B$5:$B$36,INT(($A16/C$4))+1))) | D16: =IF(($A16/D$4)>=31,0,INDEX(Data_EPA_Survival!$B$5:$B$36,INT(($A16/D$4))+1)+(($A16/D$4)-INT(($A16/D$4)))*(INDEX(Data_EPA_Survival!$B$5:$B$36,INT(($A16/D$4))+2)-INDEX(Data_EPA_Survival!$B$5:$B$36,INT(($A16/D$4))+1))) | E16: =IF(($A16/E$4)>=31,0,INDEX(Data_EPA_Survival!$B$5:$B$36,INT(($A16/E$4))+1)+(($A16/E$4)-INT(($A16/E$4)))*(INDEX(Data_EPA_Survival!$B$5:$B$36,INT(($A16/E$4))+2)-INDEX(Data_EPA_Survival!$B$5:$B$36,INT(($A16/E$4))+1))) | F16: =IF(($A16/F$4)>=31,0,INDEX(Data_EPA_Survival!$B$5:$B$36,INT(($A16/F$4))+1)+(($A16/F$4)-INT(($A16/F$4)))*(INDEX(Data_EPA_Survival!$B$5:$B$36,INT(($A16/F$4))+2)-INDEX(Data_EPA_Survival!$B$5:$B$36,INT(($A16/F$4))+1))) | G16: =IF(($A16/G$4)>=31,0,INDEX(Data_EPA_Survival!$B$5:$B$36,INT(($A16/G$4))+1)+(($A16/G$4)-INT(($A16/G$4)))*(INDEX(Data_EPA_Survival!$B$5:$B$36,INT(($A16/G$4))+2)-INDEX(Data_EPA_Survival!$B$5:$B$36,INT(($A16/G$4))+1))) | H16: =IF(($A16/H$4)>=31,0,INDEX(Data_EPA_Survival!$B$5:$B$36,INT(($A16/H$4))+1)+(($A16/H$4)-INT(($A16/H$4)))*(INDEX(Data_EPA_Survival!$B$5:$B$36,INT(($A16/H$4))+2)-INDEX(Data_EPA_Survival!$B$5:$B$36,INT(($A16/H$4))+1))) | I16: =IF(($A16/I$4)>=31,0,INDEX(Data_EPA_Survival!$B$5:$B$36,INT(($A16/I$4))+1)+(($A16/I$4)-INT(($A16/I$4)))*(INDEX(Data_EPA_Survival!$B$5:$B$36,INT(($A16/I$4))+2)-INDEX(Data_EPA_Survival!$B$5:$B$36,INT(($A16/I$4))+1))) | J16: =IF(($A16/J$4)>=31,0,INDEX(Data_EPA_Survival!$B$5:$B$36,INT(($A16/J$4))+1)+(($A16/J$4)-INT(($A16/J$4)))*(INDEX(Data_EPA_Survival!$B$5:$B$36,INT(($A16/J$4))+2)-INDEX(Data_EPA_Survival!$B$5:$B$36,INT(($A16/J$4))+1))) | ... T16: =IF(($A16/T$4)>=31,0,INDEX(Data_EPA_Survival!$B$5:$B$36,INT(($A16/T$4))+1)+(($A16/T$4)-INT(($A16/T$4)))*(INDEX(Data_EPA_Survival!$B$5:$B$36,INT(($A16/T$4))+2)-INDEX(Data_EPA_Survival!$B$5:$B$36,INT(($A16/T$4))+1)))
A17: 11 | C17: =IF(($A17/C$4)>=31,0,INDEX(Data_EPA_Survival!$B$5:$B$36,INT(($A17/C$4))+1)+(($A17/C$4)-INT(($A17/C$4)))*(INDEX(Data_EPA_Survival!$B$5:$B$36,INT(($A17/C$4))+2)-INDEX(Data_EPA_Survival!$B$5:$B$36,INT(($A17/C$4))+1))) | D17: =IF(($A17/D$4)>=31,0,INDEX(Data_EPA_Survival!$B$5:$B$36,INT(($A17/D$4))+1)+(($A17/D$4)-INT(($A17/D$4)))*(INDEX(Data_EPA_Survival!$B$5:$B$36,INT(($A17/D$4))+2)-INDEX(Data_EPA_Survival!$B$5:$B$36,INT(($A17/D$4))+1))) | E17: =IF(($A17/E$4)>=31,0,INDEX(Data_EPA_Survival!$B$5:$B$36,INT(($A17/E$4))+1)+(($A17/E$4)-INT(($A17/E$4)))*(INDEX(Data_EPA_Survival!$B$5:$B$36,INT(($A17/E$4))+2)-INDEX(Data_EPA_Survival!$B$5:$B$36,INT(($A17/E$4))+1))) | F17: =IF(($A17/F$4)>=31,0,INDEX(Data_EPA_Survival!$B$5:$B$36,INT(($A17/F$4))+1)+(($A17/F$4)-INT(($A17/F$4)))*(INDEX(Data_EPA_Survival!$B$5:$B$36,INT(($A17/F$4))+2)-INDEX(Data_EPA_Survival!$B$5:$B$36,INT(($A17/F$4))+1))) | G17: =IF(($A17/G$4)>=31,0,INDEX(Data_EPA_Survival!$B$5:$B$36,INT(($A17/G$4))+1)+(($A17/G$4)-INT(($A17/G$4)))*(INDEX(Data_EPA_Survival!$B$5:$B$36,INT(($A17/G$4))+2)-INDEX(Data_EPA_Survival!$B$5:$B$36,INT(($A17/G$4))+1))) | H17: =IF(($A17/H$4)>=31,0,INDEX(Data_EPA_Survival!$B$5:$B$36,INT(($A17/H$4))+1)+(($A17/H$4)-INT(($A17/H$4)))*(INDEX(Data_EPA_Survival!$B$5:$B$36,INT(($A17/H$4))+2)-INDEX(Data_EPA_Survival!$B$5:$B$36,INT(($A17/H$4))+1))) | I17: =IF(($A17/I$4)>=31,0,INDEX(Data_EPA_Survival!$B$5:$B$36,INT(($A17/I$4))+1)+(($A17/I$4)-INT(($A17/I$4)))*(INDEX(Data_EPA_Survival!$B$5:$B$36,INT(($A17/I$4))+2)-INDEX(Data_EPA_Survival!$B$5:$B$36,INT(($A17/I$4))+1))) | J17: =IF(($A17/J$4)>=31,0,INDEX(Data_EPA_Survival!$B$5:$B$36,INT(($A17/J$4))+1)+(($A17/J$4)-INT(($A17/J$4)))*(INDEX(Data_EPA_Survival!$B$5:$B$36,INT(($A17/J$4))+2)-INDEX(Data_EPA_Survival!$B$5:$B$36,INT(($A17/J$4))+1))) | ... T17: =IF(($A17/T$4)>=31,0,INDEX(Data_EPA_Survival!$B$5:$B$36,INT(($A17/T$4))+1)+(($A17/T$4)-INT(($A17/T$4)))*(INDEX(Data_EPA_Survival!$B$5:$B$36,INT(($A17/T$4))+2)-INDEX(Data_EPA_Survival!$B$5:$B$36,INT(($A17/T$4))+1)))
... A51: 45 | C51: =IF(($A51/C$4)>=31,0,INDEX(Data_EPA_Survival!$B$5:$B$36,INT(($A51/C$4))+1)+(($A51/C$4)-INT(($A51/C$4)))*(INDEX(Data_EPA_Survival!$B$5:$B$36,INT(($A51/C$4))+2)-INDEX(Data_EPA_Survival!$B$5:$B$36,INT(($A51/C$4))+1))) | D51: =IF(($A51/D$4)>=31,0,INDEX(Data_EPA_Survival!$B$5:$B$36,INT(($A51/D$4))+1)+(($A51/D$4)-INT(($A51/D$4)))*(INDEX(Data_EPA_Survival!$B$5:$B$36,INT(($A51/D$4))+2)-INDEX(Data_EPA_Survival!$B$5:$B$36,INT(($A51/D$4))+1))) | E51: =IF(($A51/E$4)>=31,0,INDEX(Data_EPA_Survival!$B$5:$B$36,INT(($A51/E$4))+1)+(($A51/E$4)-INT(($A51/E$4)))*(INDEX(Data_EPA_Survival!$B$5:$B$36,INT(($A51/E$4))+2)-INDEX(Data_EPA_Survival!$B$5:$B$36,INT(($A51/E$4))+1))) | F51: =IF(($A51/F$4)>=31,0,INDEX(Data_EPA_Survival!$B$5:$B$36,INT(($A51/F$4))+1)+(($A51/F$4)-INT(($A51/F$4)))*(INDEX(Data_EPA_Survival!$B$5:$B$36,INT(($A51/F$4))+2)-INDEX(Data_EPA_Survival!$B$5:$B$36,INT(($A51/F$4))+1))) | G51: =IF(($A51/G$4)>=31,0,INDEX(Data_EPA_Survival!$B$5:$B$36,INT(($A51/G$4))+1)+(($A51/G$4)-INT(($A51/G$4)))*(INDEX(Data_EPA_Survival!$B$5:$B$36,INT(($A51/G$4))+2)-INDEX(Data_EPA_Survival!$B$5:$B$36,INT(($A51/G$4))+1))) | H51: =IF(($A51/H$4)>=31,0,INDEX(Data_EPA_Survival!$B$5:$B$36,INT(($A51/H$4))+1)+(($A51/H$4)-INT(($A51/H$4)))*(INDEX(Data_EPA_Survival!$B$5:$B$36,INT(($A51/H$4))+2)-INDEX(Data_EPA_Survival!$B$5:$B$36,INT(($A51/H$4))+1))) | I51: =IF(($A51/I$4)>=31,0,INDEX(Data_EPA_Survival!$B$5:$B$36,INT(($A51/I$4))+1)+(($A51/I$4)-INT(($A51/I$4)))*(INDEX(Data_EPA_Survival!$B$5:$B$36,INT(($A51/I$4))+2)-INDEX(Data_EPA_Survival!$B$5:$B$36,INT(($A51/I$4))+1))) | J51: =IF(($A51/J$4)>=31,0,INDEX(Data_EPA_Survival!$B$5:$B$36,INT(($A51/J$4))+1)+(($A51/J$4)-INT(($A51/J$4)))*(INDEX(Data_EPA_Survival!$B$5:$B$36,INT(($A51/J$4))+2)-INDEX(Data_EPA_Survival!$B$5:$B$36,INT(($A51/J$4))+1))) | ... T51: =IF(($A51/T$4)>=31,0,INDEX(Data_EPA_Survival!$B$5:$B$36,INT(($A51/T$4))+1)+(($A51/T$4)-INT(($A51/T$4)))*(INDEX(Data_EPA_Survival!$B$5:$B$36,INT(($A51/T$4))+2)-INDEX(Data_EPA_Survival!$B$5:$B$36,INT(($A51/T$4))+1)))
A53: k light trucks (Inputs) | C53: =Inputs!C26 | D53: =Inputs!D26 | E53: =Inputs!E26 | F53: =Inputs!F26 | G53: =Inputs!G26 | H53: =Inputs!H26 | I53: =Inputs!I26 | J53: =Inputs!J26 | ... T53: =Inputs!T26
A54: LIGHT TRUCKS: age | C54: =C3 | D54: =D3 | E54: =E3 | F54: =F3 | G54: =G3 | H54: =H3 | I54: =I3 | J54: =J3 | ... T54: =T3
A55: 0 | C55: =IF(($A55/C$53)>=31,0,INDEX(Data_EPA_Survival!$C$5:$C$36,INT(($A55/C$53))+1)+(($A55/C$53)-INT(($A55/C$53)))*(INDEX(Data_EPA_Survival!$C$5:$C$36,INT(($A55/C$53))+2)-INDEX(Data_EPA_Survival!$C$5:$C$36,INT(($A55/C$53))+1))) | D55: =IF(($A55/D$53)>=31,0,INDEX(Data_EPA_Survival!$C$5:$C$36,INT(($A55/D$53))+1)+(($A55/D$53)-INT(($A55/D$53)))*(INDEX(Data_EPA_Survival!$C$5:$C$36,INT(($A55/D$53))+2)-INDEX(Data_EPA_Survival!$C$5:$C$36,INT(($A55/D$53))+1))) | E55: =IF(($A55/E$53)>=31,0,INDEX(Data_EPA_Survival!$C$5:$C$36,INT(($A55/E$53))+1)+(($A55/E$53)-INT(($A55/E$53)))*(INDEX(Data_EPA_Survival!$C$5:$C$36,INT(($A55/E$53))+2)-INDEX(Data_EPA_Survival!$C$5:$C$36,INT(($A55/E$53))+1))) | F55: =IF(($A55/F$53)>=31,0,INDEX(Data_EPA_Survival!$C$5:$C$36,INT(($A55/F$53))+1)+(($A55/F$53)-INT(($A55/F$53)))*(INDEX(Data_EPA_Survival!$C$5:$C$36,INT(($A55/F$53))+2)-INDEX(Data_EPA_Survival!$C$5:$C$36,INT(($A55/F$53))+1))) | G55: =IF(($A55/G$53)>=31,0,INDEX(Data_EPA_Survival!$C$5:$C$36,INT(($A55/G$53))+1)+(($A55/G$53)-INT(($A55/G$53)))*(INDEX(Data_EPA_Survival!$C$5:$C$36,INT(($A55/G$53))+2)-INDEX(Data_EPA_Survival!$C$5:$C$36,INT(($A55/G$53))+1))) | H55: =IF(($A55/H$53)>=31,0,INDEX(Data_EPA_Survival!$C$5:$C$36,INT(($A55/H$53))+1)+(($A55/H$53)-INT(($A55/H$53)))*(INDEX(Data_EPA_Survival!$C$5:$C$36,INT(($A55/H$53))+2)-INDEX(Data_EPA_Survival!$C$5:$C$36,INT(($A55/H$53))+1))) | I55: =IF(($A55/I$53)>=31,0,INDEX(Data_EPA_Survival!$C$5:$C$36,INT(($A55/I$53))+1)+(($A55/I$53)-INT(($A55/I$53)))*(INDEX(Data_EPA_Survival!$C$5:$C$36,INT(($A55/I$53))+2)-INDEX(Data_EPA_Survival!$C$5:$C$36,INT(($A55/I$53))+1))) | J55: =IF(($A55/J$53)>=31,0,INDEX(Data_EPA_Survival!$C$5:$C$36,INT(($A55/J$53))+1)+(($A55/J$53)-INT(($A55/J$53)))*(INDEX(Data_EPA_Survival!$C$5:$C$36,INT(($A55/J$53))+2)-INDEX(Data_EPA_Survival!$C$5:$C$36,INT(($A55/J$53))+1))) | ... T55: =IF(($A55/T$53)>=31,0,INDEX(Data_EPA_Survival!$C$5:$C$36,INT(($A55/T$53))+1)+(($A55/T$53)-INT(($A55/T$53)))*(INDEX(Data_EPA_Survival!$C$5:$C$36,INT(($A55/T$53))+2)-INDEX(Data_EPA_Survival!$C$5:$C$36,INT(($A55/T$53))+1)))
A56: 1 | C56: =IF(($A56/C$53)>=31,0,INDEX(Data_EPA_Survival!$C$5:$C$36,INT(($A56/C$53))+1)+(($A56/C$53)-INT(($A56/C$53)))*(INDEX(Data_EPA_Survival!$C$5:$C$36,INT(($A56/C$53))+2)-INDEX(Data_EPA_Survival!$C$5:$C$36,INT(($A56/C$53))+1))) | D56: =IF(($A56/D$53)>=31,0,INDEX(Data_EPA_Survival!$C$5:$C$36,INT(($A56/D$53))+1)+(($A56/D$53)-INT(($A56/D$53)))*(INDEX(Data_EPA_Survival!$C$5:$C$36,INT(($A56/D$53))+2)-INDEX(Data_EPA_Survival!$C$5:$C$36,INT(($A56/D$53))+1))) | E56: =IF(($A56/E$53)>=31,0,INDEX(Data_EPA_Survival!$C$5:$C$36,INT(($A56/E$53))+1)+(($A56/E$53)-INT(($A56/E$53)))*(INDEX(Data_EPA_Survival!$C$5:$C$36,INT(($A56/E$53))+2)-INDEX(Data_EPA_Survival!$C$5:$C$36,INT(($A56/E$53))+1))) | F56: =IF(($A56/F$53)>=31,0,INDEX(Data_EPA_Survival!$C$5:$C$36,INT(($A56/F$53))+1)+(($A56/F$53)-INT(($A56/F$53)))*(INDEX(Data_EPA_Survival!$C$5:$C$36,INT(($A56/F$53))+2)-INDEX(Data_EPA_Survival!$C$5:$C$36,INT(($A56/F$53))+1))) | G56: =IF(($A56/G$53)>=31,0,INDEX(Data_EPA_Survival!$C$5:$C$36,INT(($A56/G$53))+1)+(($A56/G$53)-INT(($A56/G$53)))*(INDEX(Data_EPA_Survival!$C$5:$C$36,INT(($A56/G$53))+2)-INDEX(Data_EPA_Survival!$C$5:$C$36,INT(($A56/G$53))+1))) | H56: =IF(($A56/H$53)>=31,0,INDEX(Data_EPA_Survival!$C$5:$C$36,INT(($A56/H$53))+1)+(($A56/H$53)-INT(($A56/H$53)))*(INDEX(Data_EPA_Survival!$C$5:$C$36,INT(($A56/H$53))+2)-INDEX(Data_EPA_Survival!$C$5:$C$36,INT(($A56/H$53))+1))) | I56: =IF(($A56/I$53)>=31,0,INDEX(Data_EPA_Survival!$C$5:$C$36,INT(($A56/I$53))+1)+(($A56/I$53)-INT(($A56/I$53)))*(INDEX(Data_EPA_Survival!$C$5:$C$36,INT(($A56/I$53))+2)-INDEX(Data_EPA_Survival!$C$5:$C$36,INT(($A56/I$53))+1))) | J56: =IF(($A56/J$53)>=31,0,INDEX(Data_EPA_Survival!$C$5:$C$36,INT(($A56/J$53))+1)+(($A56/J$53)-INT(($A56/J$53)))*(INDEX(Data_EPA_Survival!$C$5:$C$36,INT(($A56/J$53))+2)-INDEX(Data_EPA_Survival!$C$5:$C$36,INT(($A56/J$53))+1))) | ... T56: =IF(($A56/T$53)>=31,0,INDEX(Data_EPA_Survival!$C$5:$C$36,INT(($A56/T$53))+1)+(($A56/T$53)-INT(($A56/T$53)))*(INDEX(Data_EPA_Survival!$C$5:$C$36,INT(($A56/T$53))+2)-INDEX(Data_EPA_Survival!$C$5:$C$36,INT(($A56/T$53))+1)))
A57: 2 | C57: =IF(($A57/C$53)>=31,0,INDEX(Data_EPA_Survival!$C$5:$C$36,INT(($A57/C$53))+1)+(($A57/C$53)-INT(($A57/C$53)))*(INDEX(Data_EPA_Survival!$C$5:$C$36,INT(($A57/C$53))+2)-INDEX(Data_EPA_Survival!$C$5:$C$36,INT(($A57/C$53))+1))) | D57: =IF(($A57/D$53)>=31,0,INDEX(Data_EPA_Survival!$C$5:$C$36,INT(($A57/D$53))+1)+(($A57/D$53)-INT(($A57/D$53)))*(INDEX(Data_EPA_Survival!$C$5:$C$36,INT(($A57/D$53))+2)-INDEX(Data_EPA_Survival!$C$5:$C$36,INT(($A57/D$53))+1))) | E57: =IF(($A57/E$53)>=31,0,INDEX(Data_EPA_Survival!$C$5:$C$36,INT(($A57/E$53))+1)+(($A57/E$53)-INT(($A57/E$53)))*(INDEX(Data_EPA_Survival!$C$5:$C$36,INT(($A57/E$53))+2)-INDEX(Data_EPA_Survival!$C$5:$C$36,INT(($A57/E$53))+1))) | F57: =IF(($A57/F$53)>=31,0,INDEX(Data_EPA_Survival!$C$5:$C$36,INT(($A57/F$53))+1)+(($A57/F$53)-INT(($A57/F$53)))*(INDEX(Data_EPA_Survival!$C$5:$C$36,INT(($A57/F$53))+2)-INDEX(Data_EPA_Survival!$C$5:$C$36,INT(($A57/F$53))+1))) | G57: =IF(($A57/G$53)>=31,0,INDEX(Data_EPA_Survival!$C$5:$C$36,INT(($A57/G$53))+1)+(($A57/G$53)-INT(($A57/G$53)))*(INDEX(Data_EPA_Survival!$C$5:$C$36,INT(($A57/G$53))+2)-INDEX(Data_EPA_Survival!$C$5:$C$36,INT(($A57/G$53))+1))) | H57: =IF(($A57/H$53)>=31,0,INDEX(Data_EPA_Survival!$C$5:$C$36,INT(($A57/H$53))+1)+(($A57/H$53)-INT(($A57/H$53)))*(INDEX(Data_EPA_Survival!$C$5:$C$36,INT(($A57/H$53))+2)-INDEX(Data_EPA_Survival!$C$5:$C$36,INT(($A57/H$53))+1))) | I57: =IF(($A57/I$53)>=31,0,INDEX(Data_EPA_Survival!$C$5:$C$36,INT(($A57/I$53))+1)+(($A57/I$53)-INT(($A57/I$53)))*(INDEX(Data_EPA_Survival!$C$5:$C$36,INT(($A57/I$53))+2)-INDEX(Data_EPA_Survival!$C$5:$C$36,INT(($A57/I$53))+1))) | J57: =IF(($A57/J$53)>=31,0,INDEX(Data_EPA_Survival!$C$5:$C$36,INT(($A57/J$53))+1)+(($A57/J$53)-INT(($A57/J$53)))*(INDEX(Data_EPA_Survival!$C$5:$C$36,INT(($A57/J$53))+2)-INDEX(Data_EPA_Survival!$C$5:$C$36,INT(($A57/J$53))+1))) | ... T57: =IF(($A57/T$53)>=31,0,INDEX(Data_EPA_Survival!$C$5:$C$36,INT(($A57/T$53))+1)+(($A57/T$53)-INT(($A57/T$53)))*(INDEX(Data_EPA_Survival!$C$5:$C$36,INT(($A57/T$53))+2)-INDEX(Data_EPA_Survival!$C$5:$C$36,INT(($A57/T$53))+1)))
A58: 3 | C58: =IF(($A58/C$53)>=31,0,INDEX(Data_EPA_Survival!$C$5:$C$36,INT(($A58/C$53))+1)+(($A58/C$53)-INT(($A58/C$53)))*(INDEX(Data_EPA_Survival!$C$5:$C$36,INT(($A58/C$53))+2)-INDEX(Data_EPA_Survival!$C$5:$C$36,INT(($A58/C$53))+1))) | D58: =IF(($A58/D$53)>=31,0,INDEX(Data_EPA_Survival!$C$5:$C$36,INT(($A58/D$53))+1)+(($A58/D$53)-INT(($A58/D$53)))*(INDEX(Data_EPA_Survival!$C$5:$C$36,INT(($A58/D$53))+2)-INDEX(Data_EPA_Survival!$C$5:$C$36,INT(($A58/D$53))+1))) | E58: =IF(($A58/E$53)>=31,0,INDEX(Data_EPA_Survival!$C$5:$C$36,INT(($A58/E$53))+1)+(($A58/E$53)-INT(($A58/E$53)))*(INDEX(Data_EPA_Survival!$C$5:$C$36,INT(($A58/E$53))+2)-INDEX(Data_EPA_Survival!$C$5:$C$36,INT(($A58/E$53))+1))) | F58: =IF(($A58/F$53)>=31,0,INDEX(Data_EPA_Survival!$C$5:$C$36,INT(($A58/F$53))+1)+(($A58/F$53)-INT(($A58/F$53)))*(INDEX(Data_EPA_Survival!$C$5:$C$36,INT(($A58/F$53))+2)-INDEX(Data_EPA_Survival!$C$5:$C$36,INT(($A58/F$53))+1))) | G58: =IF(($A58/G$53)>=31,0,INDEX(Data_EPA_Survival!$C$5:$C$36,INT(($A58/G$53))+1)+(($A58/G$53)-INT(($A58/G$53)))*(INDEX(Data_EPA_Survival!$C$5:$C$36,INT(($A58/G$53))+2)-INDEX(Data_EPA_Survival!$C$5:$C$36,INT(($A58/G$53))+1))) | H58: =IF(($A58/H$53)>=31,0,INDEX(Data_EPA_Survival!$C$5:$C$36,INT(($A58/H$53))+1)+(($A58/H$53)-INT(($A58/H$53)))*(INDEX(Data_EPA_Survival!$C$5:$C$36,INT(($A58/H$53))+2)-INDEX(Data_EPA_Survival!$C$5:$C$36,INT(($A58/H$53))+1))) | I58: =IF(($A58/I$53)>=31,0,INDEX(Data_EPA_Survival!$C$5:$C$36,INT(($A58/I$53))+1)+(($A58/I$53)-INT(($A58/I$53)))*(INDEX(Data_EPA_Survival!$C$5:$C$36,INT(($A58/I$53))+2)-INDEX(Data_EPA_Survival!$C$5:$C$36,INT(($A58/I$53))+1))) | J58: =IF(($A58/J$53)>=31,0,INDEX(Data_EPA_Survival!$C$5:$C$36,INT(($A58/J$53))+1)+(($A58/J$53)-INT(($A58/J$53)))*(INDEX(Data_EPA_Survival!$C$5:$C$36,INT(($A58/J$53))+2)-INDEX(Data_EPA_Survival!$C$5:$C$36,INT(($A58/J$53))+1))) | ... T58: =IF(($A58/T$53)>=31,0,INDEX(Data_EPA_Survival!$C$5:$C$36,INT(($A58/T$53))+1)+(($A58/T$53)-INT(($A58/T$53)))*(INDEX(Data_EPA_Survival!$C$5:$C$36,INT(($A58/T$53))+2)-INDEX(Data_EPA_Survival!$C$5:$C$36,INT(($A58/T$53))+1)))
A59: 4 | C59: =IF(($A59/C$53)>=31,0,INDEX(Data_EPA_Survival!$C$5:$C$36,INT(($A59/C$53))+1)+(($A59/C$53)-INT(($A59/C$53)))*(INDEX(Data_EPA_Survival!$C$5:$C$36,INT(($A59/C$53))+2)-INDEX(Data_EPA_Survival!$C$5:$C$36,INT(($A59/C$53))+1))) | D59: =IF(($A59/D$53)>=31,0,INDEX(Data_EPA_Survival!$C$5:$C$36,INT(($A59/D$53))+1)+(($A59/D$53)-INT(($A59/D$53)))*(INDEX(Data_EPA_Survival!$C$5:$C$36,INT(($A59/D$53))+2)-INDEX(Data_EPA_Survival!$C$5:$C$36,INT(($A59/D$53))+1))) | E59: =IF(($A59/E$53)>=31,0,INDEX(Data_EPA_Survival!$C$5:$C$36,INT(($A59/E$53))+1)+(($A59/E$53)-INT(($A59/E$53)))*(INDEX(Data_EPA_Survival!$C$5:$C$36,INT(($A59/E$53))+2)-INDEX(Data_EPA_Survival!$C$5:$C$36,INT(($A59/E$53))+1))) | F59: =IF(($A59/F$53)>=31,0,INDEX(Data_EPA_Survival!$C$5:$C$36,INT(($A59/F$53))+1)+(($A59/F$53)-INT(($A59/F$53)))*(INDEX(Data_EPA_Survival!$C$5:$C$36,INT(($A59/F$53))+2)-INDEX(Data_EPA_Survival!$C$5:$C$36,INT(($A59/F$53))+1))) | G59: =IF(($A59/G$53)>=31,0,INDEX(Data_EPA_Survival!$C$5:$C$36,INT(($A59/G$53))+1)+(($A59/G$53)-INT(($A59/G$53)))*(INDEX(Data_EPA_Survival!$C$5:$C$36,INT(($A59/G$53))+2)-INDEX(Data_EPA_Survival!$C$5:$C$36,INT(($A59/G$53))+1))) | H59: =IF(($A59/H$53)>=31,0,INDEX(Data_EPA_Survival!$C$5:$C$36,INT(($A59/H$53))+1)+(($A59/H$53)-INT(($A59/H$53)))*(INDEX(Data_EPA_Survival!$C$5:$C$36,INT(($A59/H$53))+2)-INDEX(Data_EPA_Survival!$C$5:$C$36,INT(($A59/H$53))+1))) | I59: =IF(($A59/I$53)>=31,0,INDEX(Data_EPA_Survival!$C$5:$C$36,INT(($A59/I$53))+1)+(($A59/I$53)-INT(($A59/I$53)))*(INDEX(Data_EPA_Survival!$C$5:$C$36,INT(($A59/I$53))+2)-INDEX(Data_EPA_Survival!$C$5:$C$36,INT(($A59/I$53))+1))) | J59: =IF(($A59/J$53)>=31,0,INDEX(Data_EPA_Survival!$C$5:$C$36,INT(($A59/J$53))+1)+(($A59/J$53)-INT(($A59/J$53)))*(INDEX(Data_EPA_Survival!$C$5:$C$36,INT(($A59/J$53))+2)-INDEX(Data_EPA_Survival!$C$5:$C$36,INT(($A59/J$53))+1))) | ... T59: =IF(($A59/T$53)>=31,0,INDEX(Data_EPA_Survival!$C$5:$C$36,INT(($A59/T$53))+1)+(($A59/T$53)-INT(($A59/T$53)))*(INDEX(Data_EPA_Survival!$C$5:$C$36,INT(($A59/T$53))+2)-INDEX(Data_EPA_Survival!$C$5:$C$36,INT(($A59/T$53))+1)))
A60: 5 | C60: =IF(($A60/C$53)>=31,0,INDEX(Data_EPA_Survival!$C$5:$C$36,INT(($A60/C$53))+1)+(($A60/C$53)-INT(($A60/C$53)))*(INDEX(Data_EPA_Survival!$C$5:$C$36,INT(($A60/C$53))+2)-INDEX(Data_EPA_Survival!$C$5:$C$36,INT(($A60/C$53))+1))) | D60: =IF(($A60/D$53)>=31,0,INDEX(Data_EPA_Survival!$C$5:$C$36,INT(($A60/D$53))+1)+(($A60/D$53)-INT(($A60/D$53)))*(INDEX(Data_EPA_Survival!$C$5:$C$36,INT(($A60/D$53))+2)-INDEX(Data_EPA_Survival!$C$5:$C$36,INT(($A60/D$53))+1))) | E60: =IF(($A60/E$53)>=31,0,INDEX(Data_EPA_Survival!$C$5:$C$36,INT(($A60/E$53))+1)+(($A60/E$53)-INT(($A60/E$53)))*(INDEX(Data_EPA_Survival!$C$5:$C$36,INT(($A60/E$53))+2)-INDEX(Data_EPA_Survival!$C$5:$C$36,INT(($A60/E$53))+1))) | F60: =IF(($A60/F$53)>=31,0,INDEX(Data_EPA_Survival!$C$5:$C$36,INT(($A60/F$53))+1)+(($A60/F$53)-INT(($A60/F$53)))*(INDEX(Data_EPA_Survival!$C$5:$C$36,INT(($A60/F$53))+2)-INDEX(Data_EPA_Survival!$C$5:$C$36,INT(($A60/F$53))+1))) | G60: =IF(($A60/G$53)>=31,0,INDEX(Data_EPA_Survival!$C$5:$C$36,INT(($A60/G$53))+1)+(($A60/G$53)-INT(($A60/G$53)))*(INDEX(Data_EPA_Survival!$C$5:$C$36,INT(($A60/G$53))+2)-INDEX(Data_EPA_Survival!$C$5:$C$36,INT(($A60/G$53))+1))) | H60: =IF(($A60/H$53)>=31,0,INDEX(Data_EPA_Survival!$C$5:$C$36,INT(($A60/H$53))+1)+(($A60/H$53)-INT(($A60/H$53)))*(INDEX(Data_EPA_Survival!$C$5:$C$36,INT(($A60/H$53))+2)-INDEX(Data_EPA_Survival!$C$5:$C$36,INT(($A60/H$53))+1))) | I60: =IF(($A60/I$53)>=31,0,INDEX(Data_EPA_Survival!$C$5:$C$36,INT(($A60/I$53))+1)+(($A60/I$53)-INT(($A60/I$53)))*(INDEX(Data_EPA_Survival!$C$5:$C$36,INT(($A60/I$53))+2)-INDEX(Data_EPA_Survival!$C$5:$C$36,INT(($A60/I$53))+1))) | J60: =IF(($A60/J$53)>=31,0,INDEX(Data_EPA_Survival!$C$5:$C$36,INT(($A60/J$53))+1)+(($A60/J$53)-INT(($A60/J$53)))*(INDEX(Data_EPA_Survival!$C$5:$C$36,INT(($A60/J$53))+2)-INDEX(Data_EPA_Survival!$C$5:$C$36,INT(($A60/J$53))+1))) | ... T60: =IF(($A60/T$53)>=31,0,INDEX(Data_EPA_Survival!$C$5:$C$36,INT(($A60/T$53))+1)+(($A60/T$53)-INT(($A60/T$53)))*(INDEX(Data_EPA_Survival!$C$5:$C$36,INT(($A60/T$53))+2)-INDEX(Data_EPA_Survival!$C$5:$C$36,INT(($A60/T$53))+1)))
A61: 6 | C61: =IF(($A61/C$53)>=31,0,INDEX(Data_EPA_Survival!$C$5:$C$36,INT(($A61/C$53))+1)+(($A61/C$53)-INT(($A61/C$53)))*(INDEX(Data_EPA_Survival!$C$5:$C$36,INT(($A61/C$53))+2)-INDEX(Data_EPA_Survival!$C$5:$C$36,INT(($A61/C$53))+1))) | D61: =IF(($A61/D$53)>=31,0,INDEX(Data_EPA_Survival!$C$5:$C$36,INT(($A61/D$53))+1)+(($A61/D$53)-INT(($A61/D$53)))*(INDEX(Data_EPA_Survival!$C$5:$C$36,INT(($A61/D$53))+2)-INDEX(Data_EPA_Survival!$C$5:$C$36,INT(($A61/D$53))+1))) | E61: =IF(($A61/E$53)>=31,0,INDEX(Data_EPA_Survival!$C$5:$C$36,INT(($A61/E$53))+1)+(($A61/E$53)-INT(($A61/E$53)))*(INDEX(Data_EPA_Survival!$C$5:$C$36,INT(($A61/E$53))+2)-INDEX(Data_EPA_Survival!$C$5:$C$36,INT(($A61/E$53))+1))) | F61: =IF(($A61/F$53)>=31,0,INDEX(Data_EPA_Survival!$C$5:$C$36,INT(($A61/F$53))+1)+(($A61/F$53)-INT(($A61/F$53)))*(INDEX(Data_EPA_Survival!$C$5:$C$36,INT(($A61/F$53))+2)-INDEX(Data_EPA_Survival!$C$5:$C$36,INT(($A61/F$53))+1))) | G61: =IF(($A61/G$53)>=31,0,INDEX(Data_EPA_Survival!$C$5:$C$36,INT(($A61/G$53))+1)+(($A61/G$53)-INT(($A61/G$53)))*(INDEX(Data_EPA_Survival!$C$5:$C$36,INT(($A61/G$53))+2)-INDEX(Data_EPA_Survival!$C$5:$C$36,INT(($A61/G$53))+1))) | H61: =IF(($A61/H$53)>=31,0,INDEX(Data_EPA_Survival!$C$5:$C$36,INT(($A61/H$53))+1)+(($A61/H$53)-INT(($A61/H$53)))*(INDEX(Data_EPA_Survival!$C$5:$C$36,INT(($A61/H$53))+2)-INDEX(Data_EPA_Survival!$C$5:$C$36,INT(($A61/H$53))+1))) | I61: =IF(($A61/I$53)>=31,0,INDEX(Data_EPA_Survival!$C$5:$C$36,INT(($A61/I$53))+1)+(($A61/I$53)-INT(($A61/I$53)))*(INDEX(Data_EPA_Survival!$C$5:$C$36,INT(($A61/I$53))+2)-INDEX(Data_EPA_Survival!$C$5:$C$36,INT(($A61/I$53))+1))) | J61: =IF(($A61/J$53)>=31,0,INDEX(Data_EPA_Survival!$C$5:$C$36,INT(($A61/J$53))+1)+(($A61/J$53)-INT(($A61/J$53)))*(INDEX(Data_EPA_Survival!$C$5:$C$36,INT(($A61/J$53))+2)-INDEX(Data_EPA_Survival!$C$5:$C$36,INT(($A61/J$53))+1))) | ... T61: =IF(($A61/T$53)>=31,0,INDEX(Data_EPA_Survival!$C$5:$C$36,INT(($A61/T$53))+1)+(($A61/T$53)-INT(($A61/T$53)))*(INDEX(Data_EPA_Survival!$C$5:$C$36,INT(($A61/T$53))+2)-INDEX(Data_EPA_Survival!$C$5:$C$36,INT(($A61/T$53))+1)))
A62: 7 | C62: =IF(($A62/C$53)>=31,0,INDEX(Data_EPA_Survival!$C$5:$C$36,INT(($A62/C$53))+1)+(($A62/C$53)-INT(($A62/C$53)))*(INDEX(Data_EPA_Survival!$C$5:$C$36,INT(($A62/C$53))+2)-INDEX(Data_EPA_Survival!$C$5:$C$36,INT(($A62/C$53))+1))) | D62: =IF(($A62/D$53)>=31,0,INDEX(Data_EPA_Survival!$C$5:$C$36,INT(($A62/D$53))+1)+(($A62/D$53)-INT(($A62/D$53)))*(INDEX(Data_EPA_Survival!$C$5:$C$36,INT(($A62/D$53))+2)-INDEX(Data_EPA_Survival!$C$5:$C$36,INT(($A62/D$53))+1))) | E62: =IF(($A62/E$53)>=31,0,INDEX(Data_EPA_Survival!$C$5:$C$36,INT(($A62/E$53))+1)+(($A62/E$53)-INT(($A62/E$53)))*(INDEX(Data_EPA_Survival!$C$5:$C$36,INT(($A62/E$53))+2)-INDEX(Data_EPA_Survival!$C$5:$C$36,INT(($A62/E$53))+1))) | F62: =IF(($A62/F$53)>=31,0,INDEX(Data_EPA_Survival!$C$5:$C$36,INT(($A62/F$53))+1)+(($A62/F$53)-INT(($A62/F$53)))*(INDEX(Data_EPA_Survival!$C$5:$C$36,INT(($A62/F$53))+2)-INDEX(Data_EPA_Survival!$C$5:$C$36,INT(($A62/F$53))+1))) | G62: =IF(($A62/G$53)>=31,0,INDEX(Data_EPA_Survival!$C$5:$C$36,INT(($A62/G$53))+1)+(($A62/G$53)-INT(($A62/G$53)))*(INDEX(Data_EPA_Survival!$C$5:$C$36,INT(($A62/G$53))+2)-INDEX(Data_EPA_Survival!$C$5:$C$36,INT(($A62/G$53))+1))) | H62: =IF(($A62/H$53)>=31,0,INDEX(Data_EPA_Survival!$C$5:$C$36,INT(($A62/H$53))+1)+(($A62/H$53)-INT(($A62/H$53)))*(INDEX(Data_EPA_Survival!$C$5:$C$36,INT(($A62/H$53))+2)-INDEX(Data_EPA_Survival!$C$5:$C$36,INT(($A62/H$53))+1))) | I62: =IF(($A62/I$53)>=31,0,INDEX(Data_EPA_Survival!$C$5:$C$36,INT(($A62/I$53))+1)+(($A62/I$53)-INT(($A62/I$53)))*(INDEX(Data_EPA_Survival!$C$5:$C$36,INT(($A62/I$53))+2)-INDEX(Data_EPA_Survival!$C$5:$C$36,INT(($A62/I$53))+1))) | J62: =IF(($A62/J$53)>=31,0,INDEX(Data_EPA_Survival!$C$5:$C$36,INT(($A62/J$53))+1)+(($A62/J$53)-INT(($A62/J$53)))*(INDEX(Data_EPA_Survival!$C$5:$C$36,INT(($A62/J$53))+2)-INDEX(Data_EPA_Survival!$C$5:$C$36,INT(($A62/J$53))+1))) | ... T62: =IF(($A62/T$53)>=31,0,INDEX(Data_EPA_Survival!$C$5:$C$36,INT(($A62/T$53))+1)+(($A62/T$53)-INT(($A62/T$53)))*(INDEX(Data_EPA_Survival!$C$5:$C$36,INT(($A62/T$53))+2)-INDEX(Data_EPA_Survival!$C$5:$C$36,INT(($A62/T$53))+1)))
A63: 8 | C63: =IF(($A63/C$53)>=31,0,INDEX(Data_EPA_Survival!$C$5:$C$36,INT(($A63/C$53))+1)+(($A63/C$53)-INT(($A63/C$53)))*(INDEX(Data_EPA_Survival!$C$5:$C$36,INT(($A63/C$53))+2)-INDEX(Data_EPA_Survival!$C$5:$C$36,INT(($A63/C$53))+1))) | D63: =IF(($A63/D$53)>=31,0,INDEX(Data_EPA_Survival!$C$5:$C$36,INT(($A63/D$53))+1)+(($A63/D$53)-INT(($A63/D$53)))*(INDEX(Data_EPA_Survival!$C$5:$C$36,INT(($A63/D$53))+2)-INDEX(Data_EPA_Survival!$C$5:$C$36,INT(($A63/D$53))+1))) | E63: =IF(($A63/E$53)>=31,0,INDEX(Data_EPA_Survival!$C$5:$C$36,INT(($A63/E$53))+1)+(($A63/E$53)-INT(($A63/E$53)))*(INDEX(Data_EPA_Survival!$C$5:$C$36,INT(($A63/E$53))+2)-INDEX(Data_EPA_Survival!$C$5:$C$36,INT(($A63/E$53))+1))) | F63: =IF(($A63/F$53)>=31,0,INDEX(Data_EPA_Survival!$C$5:$C$36,INT(($A63/F$53))+1)+(($A63/F$53)-INT(($A63/F$53)))*(INDEX(Data_EPA_Survival!$C$5:$C$36,INT(($A63/F$53))+2)-INDEX(Data_EPA_Survival!$C$5:$C$36,INT(($A63/F$53))+1))) | G63: =IF(($A63/G$53)>=31,0,INDEX(Data_EPA_Survival!$C$5:$C$36,INT(($A63/G$53))+1)+(($A63/G$53)-INT(($A63/G$53)))*(INDEX(Data_EPA_Survival!$C$5:$C$36,INT(($A63/G$53))+2)-INDEX(Data_EPA_Survival!$C$5:$C$36,INT(($A63/G$53))+1))) | H63: =IF(($A63/H$53)>=31,0,INDEX(Data_EPA_Survival!$C$5:$C$36,INT(($A63/H$53))+1)+(($A63/H$53)-INT(($A63/H$53)))*(INDEX(Data_EPA_Survival!$C$5:$C$36,INT(($A63/H$53))+2)-INDEX(Data_EPA_Survival!$C$5:$C$36,INT(($A63/H$53))+1))) | I63: =IF(($A63/I$53)>=31,0,INDEX(Data_EPA_Survival!$C$5:$C$36,INT(($A63/I$53))+1)+(($A63/I$53)-INT(($A63/I$53)))*(INDEX(Data_EPA_Survival!$C$5:$C$36,INT(($A63/I$53))+2)-INDEX(Data_EPA_Survival!$C$5:$C$36,INT(($A63/I$53))+1))) | J63: =IF(($A63/J$53)>=31,0,INDEX(Data_EPA_Survival!$C$5:$C$36,INT(($A63/J$53))+1)+(($A63/J$53)-INT(($A63/J$53)))*(INDEX(Data_EPA_Survival!$C$5:$C$36,INT(($A63/J$53))+2)-INDEX(Data_EPA_Survival!$C$5:$C$36,INT(($A63/J$53))+1))) | ... T63: =IF(($A63/T$53)>=31,0,INDEX(Data_EPA_Survival!$C$5:$C$36,INT(($A63/T$53))+1)+(($A63/T$53)-INT(($A63/T$53)))*(INDEX(Data_EPA_Survival!$C$5:$C$36,INT(($A63/T$53))+2)-INDEX(Data_EPA_Survival!$C$5:$C$36,INT(($A63/T$53))+1)))
A64: 9 | C64: =IF(($A64/C$53)>=31,0,INDEX(Data_EPA_Survival!$C$5:$C$36,INT(($A64/C$53))+1)+(($A64/C$53)-INT(($A64/C$53)))*(INDEX(Data_EPA_Survival!$C$5:$C$36,INT(($A64/C$53))+2)-INDEX(Data_EPA_Survival!$C$5:$C$36,INT(($A64/C$53))+1))) | D64: =IF(($A64/D$53)>=31,0,INDEX(Data_EPA_Survival!$C$5:$C$36,INT(($A64/D$53))+1)+(($A64/D$53)-INT(($A64/D$53)))*(INDEX(Data_EPA_Survival!$C$5:$C$36,INT(($A64/D$53))+2)-INDEX(Data_EPA_Survival!$C$5:$C$36,INT(($A64/D$53))+1))) | E64: =IF(($A64/E$53)>=31,0,INDEX(Data_EPA_Survival!$C$5:$C$36,INT(($A64/E$53))+1)+(($A64/E$53)-INT(($A64/E$53)))*(INDEX(Data_EPA_Survival!$C$5:$C$36,INT(($A64/E$53))+2)-INDEX(Data_EPA_Survival!$C$5:$C$36,INT(($A64/E$53))+1))) | F64: =IF(($A64/F$53)>=31,0,INDEX(Data_EPA_Survival!$C$5:$C$36,INT(($A64/F$53))+1)+(($A64/F$53)-INT(($A64/F$53)))*(INDEX(Data_EPA_Survival!$C$5:$C$36,INT(($A64/F$53))+2)-INDEX(Data_EPA_Survival!$C$5:$C$36,INT(($A64/F$53))+1))) | G64: =IF(($A64/G$53)>=31,0,INDEX(Data_EPA_Survival!$C$5:$C$36,INT(($A64/G$53))+1)+(($A64/G$53)-INT(($A64/G$53)))*(INDEX(Data_EPA_Survival!$C$5:$C$36,INT(($A64/G$53))+2)-INDEX(Data_EPA_Survival!$C$5:$C$36,INT(($A64/G$53))+1))) | H64: =IF(($A64/H$53)>=31,0,INDEX(Data_EPA_Survival!$C$5:$C$36,INT(($A64/H$53))+1)+(($A64/H$53)-INT(($A64/H$53)))*(INDEX(Data_EPA_Survival!$C$5:$C$36,INT(($A64/H$53))+2)-INDEX(Data_EPA_Survival!$C$5:$C$36,INT(($A64/H$53))+1))) | I64: =IF(($A64/I$53)>=31,0,INDEX(Data_EPA_Survival!$C$5:$C$36,INT(($A64/I$53))+1)+(($A64/I$53)-INT(($A64/I$53)))*(INDEX(Data_EPA_Survival!$C$5:$C$36,INT(($A64/I$53))+2)-INDEX(Data_EPA_Survival!$C$5:$C$36,INT(($A64/I$53))+1))) | J64: =IF(($A64/J$53)>=31,0,INDEX(Data_EPA_Survival!$C$5:$C$36,INT(($A64/J$53))+1)+(($A64/J$53)-INT(($A64/J$53)))*(INDEX(Data_EPA_Survival!$C$5:$C$36,INT(($A64/J$53))+2)-INDEX(Data_EPA_Survival!$C$5:$C$36,INT(($A64/J$53))+1))) | ... T64: =IF(($A64/T$53)>=31,0,INDEX(Data_EPA_Survival!$C$5:$C$36,INT(($A64/T$53))+1)+(($A64/T$53)-INT(($A64/T$53)))*(INDEX(Data_EPA_Survival!$C$5:$C$36,INT(($A64/T$53))+2)-INDEX(Data_EPA_Survival!$C$5:$C$36,INT(($A64/T$53))+1)))
A65: 10 | C65: =IF(($A65/C$53)>=31,0,INDEX(Data_EPA_Survival!$C$5:$C$36,INT(($A65/C$53))+1)+(($A65/C$53)-INT(($A65/C$53)))*(INDEX(Data_EPA_Survival!$C$5:$C$36,INT(($A65/C$53))+2)-INDEX(Data_EPA_Survival!$C$5:$C$36,INT(($A65/C$53))+1))) | D65: =IF(($A65/D$53)>=31,0,INDEX(Data_EPA_Survival!$C$5:$C$36,INT(($A65/D$53))+1)+(($A65/D$53)-INT(($A65/D$53)))*(INDEX(Data_EPA_Survival!$C$5:$C$36,INT(($A65/D$53))+2)-INDEX(Data_EPA_Survival!$C$5:$C$36,INT(($A65/D$53))+1))) | E65: =IF(($A65/E$53)>=31,0,INDEX(Data_EPA_Survival!$C$5:$C$36,INT(($A65/E$53))+1)+(($A65/E$53)-INT(($A65/E$53)))*(INDEX(Data_EPA_Survival!$C$5:$C$36,INT(($A65/E$53))+2)-INDEX(Data_EPA_Survival!$C$5:$C$36,INT(($A65/E$53))+1))) | F65: =IF(($A65/F$53)>=31,0,INDEX(Data_EPA_Survival!$C$5:$C$36,INT(($A65/F$53))+1)+(($A65/F$53)-INT(($A65/F$53)))*(INDEX(Data_EPA_Survival!$C$5:$C$36,INT(($A65/F$53))+2)-INDEX(Data_EPA_Survival!$C$5:$C$36,INT(($A65/F$53))+1))) | G65: =IF(($A65/G$53)>=31,0,INDEX(Data_EPA_Survival!$C$5:$C$36,INT(($A65/G$53))+1)+(($A65/G$53)-INT(($A65/G$53)))*(INDEX(Data_EPA_Survival!$C$5:$C$36,INT(($A65/G$53))+2)-INDEX(Data_EPA_Survival!$C$5:$C$36,INT(($A65/G$53))+1))) | H65: =IF(($A65/H$53)>=31,0,INDEX(Data_EPA_Survival!$C$5:$C$36,INT(($A65/H$53))+1)+(($A65/H$53)-INT(($A65/H$53)))*(INDEX(Data_EPA_Survival!$C$5:$C$36,INT(($A65/H$53))+2)-INDEX(Data_EPA_Survival!$C$5:$C$36,INT(($A65/H$53))+1))) | I65: =IF(($A65/I$53)>=31,0,INDEX(Data_EPA_Survival!$C$5:$C$36,INT(($A65/I$53))+1)+(($A65/I$53)-INT(($A65/I$53)))*(INDEX(Data_EPA_Survival!$C$5:$C$36,INT(($A65/I$53))+2)-INDEX(Data_EPA_Survival!$C$5:$C$36,INT(($A65/I$53))+1))) | J65: =IF(($A65/J$53)>=31,0,INDEX(Data_EPA_Survival!$C$5:$C$36,INT(($A65/J$53))+1)+(($A65/J$53)-INT(($A65/J$53)))*(INDEX(Data_EPA_Survival!$C$5:$C$36,INT(($A65/J$53))+2)-INDEX(Data_EPA_Survival!$C$5:$C$36,INT(($A65/J$53))+1))) | ... T65: =IF(($A65/T$53)>=31,0,INDEX(Data_EPA_Survival!$C$5:$C$36,INT(($A65/T$53))+1)+(($A65/T$53)-INT(($A65/T$53)))*(INDEX(Data_EPA_Survival!$C$5:$C$36,INT(($A65/T$53))+2)-INDEX(Data_EPA_Survival!$C$5:$C$36,INT(($A65/T$53))+1)))
A66: 11 | C66: =IF(($A66/C$53)>=31,0,INDEX(Data_EPA_Survival!$C$5:$C$36,INT(($A66/C$53))+1)+(($A66/C$53)-INT(($A66/C$53)))*(INDEX(Data_EPA_Survival!$C$5:$C$36,INT(($A66/C$53))+2)-INDEX(Data_EPA_Survival!$C$5:$C$36,INT(($A66/C$53))+1))) | D66: =IF(($A66/D$53)>=31,0,INDEX(Data_EPA_Survival!$C$5:$C$36,INT(($A66/D$53))+1)+(($A66/D$53)-INT(($A66/D$53)))*(INDEX(Data_EPA_Survival!$C$5:$C$36,INT(($A66/D$53))+2)-INDEX(Data_EPA_Survival!$C$5:$C$36,INT(($A66/D$53))+1))) | E66: =IF(($A66/E$53)>=31,0,INDEX(Data_EPA_Survival!$C$5:$C$36,INT(($A66/E$53))+1)+(($A66/E$53)-INT(($A66/E$53)))*(INDEX(Data_EPA_Survival!$C$5:$C$36,INT(($A66/E$53))+2)-INDEX(Data_EPA_Survival!$C$5:$C$36,INT(($A66/E$53))+1))) | F66: =IF(($A66/F$53)>=31,0,INDEX(Data_EPA_Survival!$C$5:$C$36,INT(($A66/F$53))+1)+(($A66/F$53)-INT(($A66/F$53)))*(INDEX(Data_EPA_Survival!$C$5:$C$36,INT(($A66/F$53))+2)-INDEX(Data_EPA_Survival!$C$5:$C$36,INT(($A66/F$53))+1))) | G66: =IF(($A66/G$53)>=31,0,INDEX(Data_EPA_Survival!$C$5:$C$36,INT(($A66/G$53))+1)+(($A66/G$53)-INT(($A66/G$53)))*(INDEX(Data_EPA_Survival!$C$5:$C$36,INT(($A66/G$53))+2)-INDEX(Data_EPA_Survival!$C$5:$C$36,INT(($A66/G$53))+1))) | H66: =IF(($A66/H$53)>=31,0,INDEX(Data_EPA_Survival!$C$5:$C$36,INT(($A66/H$53))+1)+(($A66/H$53)-INT(($A66/H$53)))*(INDEX(Data_EPA_Survival!$C$5:$C$36,INT(($A66/H$53))+2)-INDEX(Data_EPA_Survival!$C$5:$C$36,INT(($A66/H$53))+1))) | I66: =IF(($A66/I$53)>=31,0,INDEX(Data_EPA_Survival!$C$5:$C$36,INT(($A66/I$53))+1)+(($A66/I$53)-INT(($A66/I$53)))*(INDEX(Data_EPA_Survival!$C$5:$C$36,INT(($A66/I$53))+2)-INDEX(Data_EPA_Survival!$C$5:$C$36,INT(($A66/I$53))+1))) | J66: =IF(($A66/J$53)>=31,0,INDEX(Data_EPA_Survival!$C$5:$C$36,INT(($A66/J$53))+1)+(($A66/J$53)-INT(($A66/J$53)))*(INDEX(Data_EPA_Survival!$C$5:$C$36,INT(($A66/J$53))+2)-INDEX(Data_EPA_Survival!$C$5:$C$36,INT(($A66/J$53))+1))) | ... T66: =IF(($A66/T$53)>=31,0,INDEX(Data_EPA_Survival!$C$5:$C$36,INT(($A66/T$53))+1)+(($A66/T$53)-INT(($A66/T$53)))*(INDEX(Data_EPA_Survival!$C$5:$C$36,INT(($A66/T$53))+2)-INDEX(Data_EPA_Survival!$C$5:$C$36,INT(($A66/T$53))+1)))
... A100: 45 | C100: =IF(($A100/C$53)>=31,0,INDEX(Data_EPA_Survival!$C$5:$C$36,INT(($A100/C$53))+1)+(($A100/C$53)-INT(($A100/C$53)))*(INDEX(Data_EPA_Survival!$C$5:$C$36,INT(($A100/C$53))+2)-INDEX(Data_EPA_Survival!$C$5:$C$36,INT(($A100/C$53))+1))) | D100: =IF(($A100/D$53)>=31,0,INDEX(Data_EPA_Survival!$C$5:$C$36,INT(($A100/D$53))+1)+(($A100/D$53)-INT(($A100/D$53)))*(INDEX(Data_EPA_Survival!$C$5:$C$36,INT(($A100/D$53))+2)-INDEX(Data_EPA_Survival!$C$5:$C$36,INT(($A100/D$53))+1))) | E100: =IF(($A100/E$53)>=31,0,INDEX(Data_EPA_Survival!$C$5:$C$36,INT(($A100/E$53))+1)+(($A100/E$53)-INT(($A100/E$53)))*(INDEX(Data_EPA_Survival!$C$5:$C$36,INT(($A100/E$53))+2)-INDEX(Data_EPA_Survival!$C$5:$C$36,INT(($A100/E$53))+1))) | F100: =IF(($A100/F$53)>=31,0,INDEX(Data_EPA_Survival!$C$5:$C$36,INT(($A100/F$53))+1)+(($A100/F$53)-INT(($A100/F$53)))*(INDEX(Data_EPA_Survival!$C$5:$C$36,INT(($A100/F$53))+2)-INDEX(Data_EPA_Survival!$C$5:$C$36,INT(($A100/F$53))+1))) | G100: =IF(($A100/G$53)>=31,0,INDEX(Data_EPA_Survival!$C$5:$C$36,INT(($A100/G$53))+1)+(($A100/G$53)-INT(($A100/G$53)))*(INDEX(Data_EPA_Survival!$C$5:$C$36,INT(($A100/G$53))+2)-INDEX(Data_EPA_Survival!$C$5:$C$36,INT(($A100/G$53))+1))) | H100: =IF(($A100/H$53)>=31,0,INDEX(Data_EPA_Survival!$C$5:$C$36,INT(($A100/H$53))+1)+(($A100/H$53)-INT(($A100/H$53)))*(INDEX(Data_EPA_Survival!$C$5:$C$36,INT(($A100/H$53))+2)-INDEX(Data_EPA_Survival!$C$5:$C$36,INT(($A100/H$53))+1))) | I100: =IF(($A100/I$53)>=31,0,INDEX(Data_EPA_Survival!$C$5:$C$36,INT(($A100/I$53))+1)+(($A100/I$53)-INT(($A100/I$53)))*(INDEX(Data_EPA_Survival!$C$5:$C$36,INT(($A100/I$53))+2)-INDEX(Data_EPA_Survival!$C$5:$C$36,INT(($A100/I$53))+1))) | J100: =IF(($A100/J$53)>=31,0,INDEX(Data_EPA_Survival!$C$5:$C$36,INT(($A100/J$53))+1)+(($A100/J$53)-INT(($A100/J$53)))*(INDEX(Data_EPA_Survival!$C$5:$C$36,INT(($A100/J$53))+2)-INDEX(Data_EPA_Survival!$C$5:$C$36,INT(($A100/J$53))+1))) | ... T100: =IF(($A100/T$53)>=31,0,INDEX(Data_EPA_Survival!$C$5:$C$36,INT(($A100/T$53))+1)+(($A100/T$53)-INT(($A100/T$53)))*(INDEX(Data_EPA_Survival!$C$5:$C$36,INT(($A100/T$53))+2)-INDEX(Data_EPA_Survival!$C$5:$C$36,INT(($A100/T$53))+1)))

Sheet Fleet
A1: Fleet roll — vehicles on the road by model year and calendar year (thousands, cars + light trucks)
A2: cell = sales_cars(MY) × S_cars(t−MY, t) + sales_LT(MY) × S_LT(t−MY, t). Blank where the model year is after the calendar year. Row 68 = total VIO.
A4: Model year ↓ / Year → | C4: =Inputs!C23 | D4: =Inputs!D23 | E4: =Inputs!E23 | F4: =Inputs!F23 | G4: =Inputs!G23 | H4: =Inputs!H23 | I4: =Inputs!I23 | J4: =Inputs!J23 | ... T4: =Inputs!T23
A6: 1970 | C6: =IF(C$4<$A6,"",IF((C$4-$A6)>45,0,INDEX(Data_Sales!$B$5:$B$65,MATCH($A6,Data_Sales!$A$5:$A$65,0))*INDEX(Survival!$C$6:$T$51,(C$4-$A6)+1,MATCH(C$4,Survival!$C$3:$T$3,0))+INDEX(Data_Sales!$C$5:$C$65,MATCH($A6,Data_Sales!$A$5:$A$65,0))*INDEX(Survival!$C$55:$T$100,(C$4-$A6)+1,MATCH(C$4,Survival!$C$3:$T$3,0)))) | D6: =IF(D$4<$A6,"",IF((D$4-$A6)>45,0,INDEX(Data_Sales!$B$5:$B$65,MATCH($A6,Data_Sales!$A$5:$A$65,0))*INDEX(Survival!$C$6:$T$51,(D$4-$A6)+1,MATCH(D$4,Survival!$C$3:$T$3,0))+INDEX(Data_Sales!$C$5:$C$65,MATCH($A6,Data_Sales!$A$5:$A$65,0))*INDEX(Survival!$C$55:$T$100,(D$4-$A6)+1,MATCH(D$4,Survival!$C$3:$T$3,0)))) | E6: =IF(E$4<$A6,"",IF((E$4-$A6)>45,0,INDEX(Data_Sales!$B$5:$B$65,MATCH($A6,Data_Sales!$A$5:$A$65,0))*INDEX(Survival!$C$6:$T$51,(E$4-$A6)+1,MATCH(E$4,Survival!$C$3:$T$3,0))+INDEX(Data_Sales!$C$5:$C$65,MATCH($A6,Data_Sales!$A$5:$A$65,0))*INDEX(Survival!$C$55:$T$100,(E$4-$A6)+1,MATCH(E$4,Survival!$C$3:$T$3,0)))) | F6: =IF(F$4<$A6,"",IF((F$4-$A6)>45,0,INDEX(Data_Sales!$B$5:$B$65,MATCH($A6,Data_Sales!$A$5:$A$65,0))*INDEX(Survival!$C$6:$T$51,(F$4-$A6)+1,MATCH(F$4,Survival!$C$3:$T$3,0))+INDEX(Data_Sales!$C$5:$C$65,MATCH($A6,Data_Sales!$A$5:$A$65,0))*INDEX(Survival!$C$55:$T$100,(F$4-$A6)+1,MATCH(F$4,Survival!$C$3:$T$3,0)))) | G6: =IF(G$4<$A6,"",IF((G$4-$A6)>45,0,INDEX(Data_Sales!$B$5:$B$65,MATCH($A6,Data_Sales!$A$5:$A$65,0))*INDEX(Survival!$C$6:$T$51,(G$4-$A6)+1,MATCH(G$4,Survival!$C$3:$T$3,0))+INDEX(Data_Sales!$C$5:$C$65,MATCH($A6,Data_Sales!$A$5:$A$65,0))*INDEX(Survival!$C$55:$T$100,(G$4-$A6)+1,MATCH(G$4,Survival!$C$3:$T$3,0)))) | H6: =IF(H$4<$A6,"",IF((H$4-$A6)>45,0,INDEX(Data_Sales!$B$5:$B$65,MATCH($A6,Data_Sales!$A$5:$A$65,0))*INDEX(Survival!$C$6:$T$51,(H$4-$A6)+1,MATCH(H$4,Survival!$C$3:$T$3,0))+INDEX(Data_Sales!$C$5:$C$65,MATCH($A6,Data_Sales!$A$5:$A$65,0))*INDEX(Survival!$C$55:$T$100,(H$4-$A6)+1,MATCH(H$4,Survival!$C$3:$T$3,0)))) | I6: =IF(I$4<$A6,"",IF((I$4-$A6)>45,0,INDEX(Data_Sales!$B$5:$B$65,MATCH($A6,Data_Sales!$A$5:$A$65,0))*INDEX(Survival!$C$6:$T$51,(I$4-$A6)+1,MATCH(I$4,Survival!$C$3:$T$3,0))+INDEX(Data_Sales!$C$5:$C$65,MATCH($A6,Data_Sales!$A$5:$A$65,0))*INDEX(Survival!$C$55:$T$100,(I$4-$A6)+1,MATCH(I$4,Survival!$C$3:$T$3,0)))) | J6: =IF(J$4<$A6,"",IF((J$4-$A6)>45,0,INDEX(Data_Sales!$B$5:$B$65,MATCH($A6,Data_Sales!$A$5:$A$65,0))*INDEX(Survival!$C$6:$T$51,(J$4-$A6)+1,MATCH(J$4,Survival!$C$3:$T$3,0))+INDEX(Data_Sales!$C$5:$C$65,MATCH($A6,Data_Sales!$A$5:$A$65,0))*INDEX(Survival!$C$55:$T$100,(J$4-$A6)+1,MATCH(J$4,Survival!$C$3:$T$3,0)))) | ... T6: =IF(T$4<$A6,"",IF((T$4-$A6)>45,0,INDEX(Data_Sales!$B$5:$B$65,MATCH($A6,Data_Sales!$A$5:$A$65,0))*INDEX(Survival!$C$6:$T$51,(T$4-$A6)+1,MATCH(T$4,Survival!$C$3:$T$3,0))+INDEX(Data_Sales!$C$5:$C$65,MATCH($A6,Data_Sales!$A$5:$A$65,0))*INDEX(Survival!$C$55:$T$100,(T$4-$A6)+1,MATCH(T$4,Survival!$C$3:$T$3,0))))
A7: 1971 | C7: =IF(C$4<$A7,"",IF((C$4-$A7)>45,0,INDEX(Data_Sales!$B$5:$B$65,MATCH($A7,Data_Sales!$A$5:$A$65,0))*INDEX(Survival!$C$6:$T$51,(C$4-$A7)+1,MATCH(C$4,Survival!$C$3:$T$3,0))+INDEX(Data_Sales!$C$5:$C$65,MATCH($A7,Data_Sales!$A$5:$A$65,0))*INDEX(Survival!$C$55:$T$100,(C$4-$A7)+1,MATCH(C$4,Survival!$C$3:$T$3,0)))) | D7: =IF(D$4<$A7,"",IF((D$4-$A7)>45,0,INDEX(Data_Sales!$B$5:$B$65,MATCH($A7,Data_Sales!$A$5:$A$65,0))*INDEX(Survival!$C$6:$T$51,(D$4-$A7)+1,MATCH(D$4,Survival!$C$3:$T$3,0))+INDEX(Data_Sales!$C$5:$C$65,MATCH($A7,Data_Sales!$A$5:$A$65,0))*INDEX(Survival!$C$55:$T$100,(D$4-$A7)+1,MATCH(D$4,Survival!$C$3:$T$3,0)))) | E7: =IF(E$4<$A7,"",IF((E$4-$A7)>45,0,INDEX(Data_Sales!$B$5:$B$65,MATCH($A7,Data_Sales!$A$5:$A$65,0))*INDEX(Survival!$C$6:$T$51,(E$4-$A7)+1,MATCH(E$4,Survival!$C$3:$T$3,0))+INDEX(Data_Sales!$C$5:$C$65,MATCH($A7,Data_Sales!$A$5:$A$65,0))*INDEX(Survival!$C$55:$T$100,(E$4-$A7)+1,MATCH(E$4,Survival!$C$3:$T$3,0)))) | F7: =IF(F$4<$A7,"",IF((F$4-$A7)>45,0,INDEX(Data_Sales!$B$5:$B$65,MATCH($A7,Data_Sales!$A$5:$A$65,0))*INDEX(Survival!$C$6:$T$51,(F$4-$A7)+1,MATCH(F$4,Survival!$C$3:$T$3,0))+INDEX(Data_Sales!$C$5:$C$65,MATCH($A7,Data_Sales!$A$5:$A$65,0))*INDEX(Survival!$C$55:$T$100,(F$4-$A7)+1,MATCH(F$4,Survival!$C$3:$T$3,0)))) | G7: =IF(G$4<$A7,"",IF((G$4-$A7)>45,0,INDEX(Data_Sales!$B$5:$B$65,MATCH($A7,Data_Sales!$A$5:$A$65,0))*INDEX(Survival!$C$6:$T$51,(G$4-$A7)+1,MATCH(G$4,Survival!$C$3:$T$3,0))+INDEX(Data_Sales!$C$5:$C$65,MATCH($A7,Data_Sales!$A$5:$A$65,0))*INDEX(Survival!$C$55:$T$100,(G$4-$A7)+1,MATCH(G$4,Survival!$C$3:$T$3,0)))) | H7: =IF(H$4<$A7,"",IF((H$4-$A7)>45,0,INDEX(Data_Sales!$B$5:$B$65,MATCH($A7,Data_Sales!$A$5:$A$65,0))*INDEX(Survival!$C$6:$T$51,(H$4-$A7)+1,MATCH(H$4,Survival!$C$3:$T$3,0))+INDEX(Data_Sales!$C$5:$C$65,MATCH($A7,Data_Sales!$A$5:$A$65,0))*INDEX(Survival!$C$55:$T$100,(H$4-$A7)+1,MATCH(H$4,Survival!$C$3:$T$3,0)))) | I7: =IF(I$4<$A7,"",IF((I$4-$A7)>45,0,INDEX(Data_Sales!$B$5:$B$65,MATCH($A7,Data_Sales!$A$5:$A$65,0))*INDEX(Survival!$C$6:$T$51,(I$4-$A7)+1,MATCH(I$4,Survival!$C$3:$T$3,0))+INDEX(Data_Sales!$C$5:$C$65,MATCH($A7,Data_Sales!$A$5:$A$65,0))*INDEX(Survival!$C$55:$T$100,(I$4-$A7)+1,MATCH(I$4,Survival!$C$3:$T$3,0)))) | J7: =IF(J$4<$A7,"",IF((J$4-$A7)>45,0,INDEX(Data_Sales!$B$5:$B$65,MATCH($A7,Data_Sales!$A$5:$A$65,0))*INDEX(Survival!$C$6:$T$51,(J$4-$A7)+1,MATCH(J$4,Survival!$C$3:$T$3,0))+INDEX(Data_Sales!$C$5:$C$65,MATCH($A7,Data_Sales!$A$5:$A$65,0))*INDEX(Survival!$C$55:$T$100,(J$4-$A7)+1,MATCH(J$4,Survival!$C$3:$T$3,0)))) | ... T7: =IF(T$4<$A7,"",IF((T$4-$A7)>45,0,INDEX(Data_Sales!$B$5:$B$65,MATCH($A7,Data_Sales!$A$5:$A$65,0))*INDEX(Survival!$C$6:$T$51,(T$4-$A7)+1,MATCH(T$4,Survival!$C$3:$T$3,0))+INDEX(Data_Sales!$C$5:$C$65,MATCH($A7,Data_Sales!$A$5:$A$65,0))*INDEX(Survival!$C$55:$T$100,(T$4-$A7)+1,MATCH(T$4,Survival!$C$3:$T$3,0))))
A8: 1972 | C8: =IF(C$4<$A8,"",IF((C$4-$A8)>45,0,INDEX(Data_Sales!$B$5:$B$65,MATCH($A8,Data_Sales!$A$5:$A$65,0))*INDEX(Survival!$C$6:$T$51,(C$4-$A8)+1,MATCH(C$4,Survival!$C$3:$T$3,0))+INDEX(Data_Sales!$C$5:$C$65,MATCH($A8,Data_Sales!$A$5:$A$65,0))*INDEX(Survival!$C$55:$T$100,(C$4-$A8)+1,MATCH(C$4,Survival!$C$3:$T$3,0)))) | D8: =IF(D$4<$A8,"",IF((D$4-$A8)>45,0,INDEX(Data_Sales!$B$5:$B$65,MATCH($A8,Data_Sales!$A$5:$A$65,0))*INDEX(Survival!$C$6:$T$51,(D$4-$A8)+1,MATCH(D$4,Survival!$C$3:$T$3,0))+INDEX(Data_Sales!$C$5:$C$65,MATCH($A8,Data_Sales!$A$5:$A$65,0))*INDEX(Survival!$C$55:$T$100,(D$4-$A8)+1,MATCH(D$4,Survival!$C$3:$T$3,0)))) | E8: =IF(E$4<$A8,"",IF((E$4-$A8)>45,0,INDEX(Data_Sales!$B$5:$B$65,MATCH($A8,Data_Sales!$A$5:$A$65,0))*INDEX(Survival!$C$6:$T$51,(E$4-$A8)+1,MATCH(E$4,Survival!$C$3:$T$3,0))+INDEX(Data_Sales!$C$5:$C$65,MATCH($A8,Data_Sales!$A$5:$A$65,0))*INDEX(Survival!$C$55:$T$100,(E$4-$A8)+1,MATCH(E$4,Survival!$C$3:$T$3,0)))) | F8: =IF(F$4<$A8,"",IF((F$4-$A8)>45,0,INDEX(Data_Sales!$B$5:$B$65,MATCH($A8,Data_Sales!$A$5:$A$65,0))*INDEX(Survival!$C$6:$T$51,(F$4-$A8)+1,MATCH(F$4,Survival!$C$3:$T$3,0))+INDEX(Data_Sales!$C$5:$C$65,MATCH($A8,Data_Sales!$A$5:$A$65,0))*INDEX(Survival!$C$55:$T$100,(F$4-$A8)+1,MATCH(F$4,Survival!$C$3:$T$3,0)))) | G8: =IF(G$4<$A8,"",IF((G$4-$A8)>45,0,INDEX(Data_Sales!$B$5:$B$65,MATCH($A8,Data_Sales!$A$5:$A$65,0))*INDEX(Survival!$C$6:$T$51,(G$4-$A8)+1,MATCH(G$4,Survival!$C$3:$T$3,0))+INDEX(Data_Sales!$C$5:$C$65,MATCH($A8,Data_Sales!$A$5:$A$65,0))*INDEX(Survival!$C$55:$T$100,(G$4-$A8)+1,MATCH(G$4,Survival!$C$3:$T$3,0)))) | H8: =IF(H$4<$A8,"",IF((H$4-$A8)>45,0,INDEX(Data_Sales!$B$5:$B$65,MATCH($A8,Data_Sales!$A$5:$A$65,0))*INDEX(Survival!$C$6:$T$51,(H$4-$A8)+1,MATCH(H$4,Survival!$C$3:$T$3,0))+INDEX(Data_Sales!$C$5:$C$65,MATCH($A8,Data_Sales!$A$5:$A$65,0))*INDEX(Survival!$C$55:$T$100,(H$4-$A8)+1,MATCH(H$4,Survival!$C$3:$T$3,0)))) | I8: =IF(I$4<$A8,"",IF((I$4-$A8)>45,0,INDEX(Data_Sales!$B$5:$B$65,MATCH($A8,Data_Sales!$A$5:$A$65,0))*INDEX(Survival!$C$6:$T$51,(I$4-$A8)+1,MATCH(I$4,Survival!$C$3:$T$3,0))+INDEX(Data_Sales!$C$5:$C$65,MATCH($A8,Data_Sales!$A$5:$A$65,0))*INDEX(Survival!$C$55:$T$100,(I$4-$A8)+1,MATCH(I$4,Survival!$C$3:$T$3,0)))) | J8: =IF(J$4<$A8,"",IF((J$4-$A8)>45,0,INDEX(Data_Sales!$B$5:$B$65,MATCH($A8,Data_Sales!$A$5:$A$65,0))*INDEX(Survival!$C$6:$T$51,(J$4-$A8)+1,MATCH(J$4,Survival!$C$3:$T$3,0))+INDEX(Data_Sales!$C$5:$C$65,MATCH($A8,Data_Sales!$A$5:$A$65,0))*INDEX(Survival!$C$55:$T$100,(J$4-$A8)+1,MATCH(J$4,Survival!$C$3:$T$3,0)))) | ... T8: =IF(T$4<$A8,"",IF((T$4-$A8)>45,0,INDEX(Data_Sales!$B$5:$B$65,MATCH($A8,Data_Sales!$A$5:$A$65,0))*INDEX(Survival!$C$6:$T$51,(T$4-$A8)+1,MATCH(T$4,Survival!$C$3:$T$3,0))+INDEX(Data_Sales!$C$5:$C$65,MATCH($A8,Data_Sales!$A$5:$A$65,0))*INDEX(Survival!$C$55:$T$100,(T$4-$A8)+1,MATCH(T$4,Survival!$C$3:$T$3,0))))
A9: 1973 | C9: =IF(C$4<$A9,"",IF((C$4-$A9)>45,0,INDEX(Data_Sales!$B$5:$B$65,MATCH($A9,Data_Sales!$A$5:$A$65,0))*INDEX(Survival!$C$6:$T$51,(C$4-$A9)+1,MATCH(C$4,Survival!$C$3:$T$3,0))+INDEX(Data_Sales!$C$5:$C$65,MATCH($A9,Data_Sales!$A$5:$A$65,0))*INDEX(Survival!$C$55:$T$100,(C$4-$A9)+1,MATCH(C$4,Survival!$C$3:$T$3,0)))) | D9: =IF(D$4<$A9,"",IF((D$4-$A9)>45,0,INDEX(Data_Sales!$B$5:$B$65,MATCH($A9,Data_Sales!$A$5:$A$65,0))*INDEX(Survival!$C$6:$T$51,(D$4-$A9)+1,MATCH(D$4,Survival!$C$3:$T$3,0))+INDEX(Data_Sales!$C$5:$C$65,MATCH($A9,Data_Sales!$A$5:$A$65,0))*INDEX(Survival!$C$55:$T$100,(D$4-$A9)+1,MATCH(D$4,Survival!$C$3:$T$3,0)))) | E9: =IF(E$4<$A9,"",IF((E$4-$A9)>45,0,INDEX(Data_Sales!$B$5:$B$65,MATCH($A9,Data_Sales!$A$5:$A$65,0))*INDEX(Survival!$C$6:$T$51,(E$4-$A9)+1,MATCH(E$4,Survival!$C$3:$T$3,0))+INDEX(Data_Sales!$C$5:$C$65,MATCH($A9,Data_Sales!$A$5:$A$65,0))*INDEX(Survival!$C$55:$T$100,(E$4-$A9)+1,MATCH(E$4,Survival!$C$3:$T$3,0)))) | F9: =IF(F$4<$A9,"",IF((F$4-$A9)>45,0,INDEX(Data_Sales!$B$5:$B$65,MATCH($A9,Data_Sales!$A$5:$A$65,0))*INDEX(Survival!$C$6:$T$51,(F$4-$A9)+1,MATCH(F$4,Survival!$C$3:$T$3,0))+INDEX(Data_Sales!$C$5:$C$65,MATCH($A9,Data_Sales!$A$5:$A$65,0))*INDEX(Survival!$C$55:$T$100,(F$4-$A9)+1,MATCH(F$4,Survival!$C$3:$T$3,0)))) | G9: =IF(G$4<$A9,"",IF((G$4-$A9)>45,0,INDEX(Data_Sales!$B$5:$B$65,MATCH($A9,Data_Sales!$A$5:$A$65,0))*INDEX(Survival!$C$6:$T$51,(G$4-$A9)+1,MATCH(G$4,Survival!$C$3:$T$3,0))+INDEX(Data_Sales!$C$5:$C$65,MATCH($A9,Data_Sales!$A$5:$A$65,0))*INDEX(Survival!$C$55:$T$100,(G$4-$A9)+1,MATCH(G$4,Survival!$C$3:$T$3,0)))) | H9: =IF(H$4<$A9,"",IF((H$4-$A9)>45,0,INDEX(Data_Sales!$B$5:$B$65,MATCH($A9,Data_Sales!$A$5:$A$65,0))*INDEX(Survival!$C$6:$T$51,(H$4-$A9)+1,MATCH(H$4,Survival!$C$3:$T$3,0))+INDEX(Data_Sales!$C$5:$C$65,MATCH($A9,Data_Sales!$A$5:$A$65,0))*INDEX(Survival!$C$55:$T$100,(H$4-$A9)+1,MATCH(H$4,Survival!$C$3:$T$3,0)))) | I9: =IF(I$4<$A9,"",IF((I$4-$A9)>45,0,INDEX(Data_Sales!$B$5:$B$65,MATCH($A9,Data_Sales!$A$5:$A$65,0))*INDEX(Survival!$C$6:$T$51,(I$4-$A9)+1,MATCH(I$4,Survival!$C$3:$T$3,0))+INDEX(Data_Sales!$C$5:$C$65,MATCH($A9,Data_Sales!$A$5:$A$65,0))*INDEX(Survival!$C$55:$T$100,(I$4-$A9)+1,MATCH(I$4,Survival!$C$3:$T$3,0)))) | J9: =IF(J$4<$A9,"",IF((J$4-$A9)>45,0,INDEX(Data_Sales!$B$5:$B$65,MATCH($A9,Data_Sales!$A$5:$A$65,0))*INDEX(Survival!$C$6:$T$51,(J$4-$A9)+1,MATCH(J$4,Survival!$C$3:$T$3,0))+INDEX(Data_Sales!$C$5:$C$65,MATCH($A9,Data_Sales!$A$5:$A$65,0))*INDEX(Survival!$C$55:$T$100,(J$4-$A9)+1,MATCH(J$4,Survival!$C$3:$T$3,0)))) | ... T9: =IF(T$4<$A9,"",IF((T$4-$A9)>45,0,INDEX(Data_Sales!$B$5:$B$65,MATCH($A9,Data_Sales!$A$5:$A$65,0))*INDEX(Survival!$C$6:$T$51,(T$4-$A9)+1,MATCH(T$4,Survival!$C$3:$T$3,0))+INDEX(Data_Sales!$C$5:$C$65,MATCH($A9,Data_Sales!$A$5:$A$65,0))*INDEX(Survival!$C$55:$T$100,(T$4-$A9)+1,MATCH(T$4,Survival!$C$3:$T$3,0))))
A10: 1974 | C10: =IF(C$4<$A10,"",IF((C$4-$A10)>45,0,INDEX(Data_Sales!$B$5:$B$65,MATCH($A10,Data_Sales!$A$5:$A$65,0))*INDEX(Survival!$C$6:$T$51,(C$4-$A10)+1,MATCH(C$4,Survival!$C$3:$T$3,0))+INDEX(Data_Sales!$C$5:$C$65,MATCH($A10,Data_Sales!$A$5:$A$65,0))*INDEX(Survival!$C$55:$T$100,(C$4-$A10)+1,MATCH(C$4,Survival!$C$3:$T$3,0)))) | D10: =IF(D$4<$A10,"",IF((D$4-$A10)>45,0,INDEX(Data_Sales!$B$5:$B$65,MATCH($A10,Data_Sales!$A$5:$A$65,0))*INDEX(Survival!$C$6:$T$51,(D$4-$A10)+1,MATCH(D$4,Survival!$C$3:$T$3,0))+INDEX(Data_Sales!$C$5:$C$65,MATCH($A10,Data_Sales!$A$5:$A$65,0))*INDEX(Survival!$C$55:$T$100,(D$4-$A10)+1,MATCH(D$4,Survival!$C$3:$T$3,0)))) | E10: =IF(E$4<$A10,"",IF((E$4-$A10)>45,0,INDEX(Data_Sales!$B$5:$B$65,MATCH($A10,Data_Sales!$A$5:$A$65,0))*INDEX(Survival!$C$6:$T$51,(E$4-$A10)+1,MATCH(E$4,Survival!$C$3:$T$3,0))+INDEX(Data_Sales!$C$5:$C$65,MATCH($A10,Data_Sales!$A$5:$A$65,0))*INDEX(Survival!$C$55:$T$100,(E$4-$A10)+1,MATCH(E$4,Survival!$C$3:$T$3,0)))) | F10: =IF(F$4<$A10,"",IF((F$4-$A10)>45,0,INDEX(Data_Sales!$B$5:$B$65,MATCH($A10,Data_Sales!$A$5:$A$65,0))*INDEX(Survival!$C$6:$T$51,(F$4-$A10)+1,MATCH(F$4,Survival!$C$3:$T$3,0))+INDEX(Data_Sales!$C$5:$C$65,MATCH($A10,Data_Sales!$A$5:$A$65,0))*INDEX(Survival!$C$55:$T$100,(F$4-$A10)+1,MATCH(F$4,Survival!$C$3:$T$3,0)))) | G10: =IF(G$4<$A10,"",IF((G$4-$A10)>45,0,INDEX(Data_Sales!$B$5:$B$65,MATCH($A10,Data_Sales!$A$5:$A$65,0))*INDEX(Survival!$C$6:$T$51,(G$4-$A10)+1,MATCH(G$4,Survival!$C$3:$T$3,0))+INDEX(Data_Sales!$C$5:$C$65,MATCH($A10,Data_Sales!$A$5:$A$65,0))*INDEX(Survival!$C$55:$T$100,(G$4-$A10)+1,MATCH(G$4,Survival!$C$3:$T$3,0)))) | H10: =IF(H$4<$A10,"",IF((H$4-$A10)>45,0,INDEX(Data_Sales!$B$5:$B$65,MATCH($A10,Data_Sales!$A$5:$A$65,0))*INDEX(Survival!$C$6:$T$51,(H$4-$A10)+1,MATCH(H$4,Survival!$C$3:$T$3,0))+INDEX(Data_Sales!$C$5:$C$65,MATCH($A10,Data_Sales!$A$5:$A$65,0))*INDEX(Survival!$C$55:$T$100,(H$4-$A10)+1,MATCH(H$4,Survival!$C$3:$T$3,0)))) | I10: =IF(I$4<$A10,"",IF((I$4-$A10)>45,0,INDEX(Data_Sales!$B$5:$B$65,MATCH($A10,Data_Sales!$A$5:$A$65,0))*INDEX(Survival!$C$6:$T$51,(I$4-$A10)+1,MATCH(I$4,Survival!$C$3:$T$3,0))+INDEX(Data_Sales!$C$5:$C$65,MATCH($A10,Data_Sales!$A$5:$A$65,0))*INDEX(Survival!$C$55:$T$100,(I$4-$A10)+1,MATCH(I$4,Survival!$C$3:$T$3,0)))) | J10: =IF(J$4<$A10,"",IF((J$4-$A10)>45,0,INDEX(Data_Sales!$B$5:$B$65,MATCH($A10,Data_Sales!$A$5:$A$65,0))*INDEX(Survival!$C$6:$T$51,(J$4-$A10)+1,MATCH(J$4,Survival!$C$3:$T$3,0))+INDEX(Data_Sales!$C$5:$C$65,MATCH($A10,Data_Sales!$A$5:$A$65,0))*INDEX(Survival!$C$55:$T$100,(J$4-$A10)+1,MATCH(J$4,Survival!$C$3:$T$3,0)))) | ... T10: =IF(T$4<$A10,"",IF((T$4-$A10)>45,0,INDEX(Data_Sales!$B$5:$B$65,MATCH($A10,Data_Sales!$A$5:$A$65,0))*INDEX(Survival!$C$6:$T$51,(T$4-$A10)+1,MATCH(T$4,Survival!$C$3:$T$3,0))+INDEX(Data_Sales!$C$5:$C$65,MATCH($A10,Data_Sales!$A$5:$A$65,0))*INDEX(Survival!$C$55:$T$100,(T$4-$A10)+1,MATCH(T$4,Survival!$C$3:$T$3,0))))
A11: 1975 | C11: =IF(C$4<$A11,"",IF((C$4-$A11)>45,0,INDEX(Data_Sales!$B$5:$B$65,MATCH($A11,Data_Sales!$A$5:$A$65,0))*INDEX(Survival!$C$6:$T$51,(C$4-$A11)+1,MATCH(C$4,Survival!$C$3:$T$3,0))+INDEX(Data_Sales!$C$5:$C$65,MATCH($A11,Data_Sales!$A$5:$A$65,0))*INDEX(Survival!$C$55:$T$100,(C$4-$A11)+1,MATCH(C$4,Survival!$C$3:$T$3,0)))) | D11: =IF(D$4<$A11,"",IF((D$4-$A11)>45,0,INDEX(Data_Sales!$B$5:$B$65,MATCH($A11,Data_Sales!$A$5:$A$65,0))*INDEX(Survival!$C$6:$T$51,(D$4-$A11)+1,MATCH(D$4,Survival!$C$3:$T$3,0))+INDEX(Data_Sales!$C$5:$C$65,MATCH($A11,Data_Sales!$A$5:$A$65,0))*INDEX(Survival!$C$55:$T$100,(D$4-$A11)+1,MATCH(D$4,Survival!$C$3:$T$3,0)))) | E11: =IF(E$4<$A11,"",IF((E$4-$A11)>45,0,INDEX(Data_Sales!$B$5:$B$65,MATCH($A11,Data_Sales!$A$5:$A$65,0))*INDEX(Survival!$C$6:$T$51,(E$4-$A11)+1,MATCH(E$4,Survival!$C$3:$T$3,0))+INDEX(Data_Sales!$C$5:$C$65,MATCH($A11,Data_Sales!$A$5:$A$65,0))*INDEX(Survival!$C$55:$T$100,(E$4-$A11)+1,MATCH(E$4,Survival!$C$3:$T$3,0)))) | F11: =IF(F$4<$A11,"",IF((F$4-$A11)>45,0,INDEX(Data_Sales!$B$5:$B$65,MATCH($A11,Data_Sales!$A$5:$A$65,0))*INDEX(Survival!$C$6:$T$51,(F$4-$A11)+1,MATCH(F$4,Survival!$C$3:$T$3,0))+INDEX(Data_Sales!$C$5:$C$65,MATCH($A11,Data_Sales!$A$5:$A$65,0))*INDEX(Survival!$C$55:$T$100,(F$4-$A11)+1,MATCH(F$4,Survival!$C$3:$T$3,0)))) | G11: =IF(G$4<$A11,"",IF((G$4-$A11)>45,0,INDEX(Data_Sales!$B$5:$B$65,MATCH($A11,Data_Sales!$A$5:$A$65,0))*INDEX(Survival!$C$6:$T$51,(G$4-$A11)+1,MATCH(G$4,Survival!$C$3:$T$3,0))+INDEX(Data_Sales!$C$5:$C$65,MATCH($A11,Data_Sales!$A$5:$A$65,0))*INDEX(Survival!$C$55:$T$100,(G$4-$A11)+1,MATCH(G$4,Survival!$C$3:$T$3,0)))) | H11: =IF(H$4<$A11,"",IF((H$4-$A11)>45,0,INDEX(Data_Sales!$B$5:$B$65,MATCH($A11,Data_Sales!$A$5:$A$65,0))*INDEX(Survival!$C$6:$T$51,(H$4-$A11)+1,MATCH(H$4,Survival!$C$3:$T$3,0))+INDEX(Data_Sales!$C$5:$C$65,MATCH($A11,Data_Sales!$A$5:$A$65,0))*INDEX(Survival!$C$55:$T$100,(H$4-$A11)+1,MATCH(H$4,Survival!$C$3:$T$3,0)))) | I11: =IF(I$4<$A11,"",IF((I$4-$A11)>45,0,INDEX(Data_Sales!$B$5:$B$65,MATCH($A11,Data_Sales!$A$5:$A$65,0))*INDEX(Survival!$C$6:$T$51,(I$4-$A11)+1,MATCH(I$4,Survival!$C$3:$T$3,0))+INDEX(Data_Sales!$C$5:$C$65,MATCH($A11,Data_Sales!$A$5:$A$65,0))*INDEX(Survival!$C$55:$T$100,(I$4-$A11)+1,MATCH(I$4,Survival!$C$3:$T$3,0)))) | J11: =IF(J$4<$A11,"",IF((J$4-$A11)>45,0,INDEX(Data_Sales!$B$5:$B$65,MATCH($A11,Data_Sales!$A$5:$A$65,0))*INDEX(Survival!$C$6:$T$51,(J$4-$A11)+1,MATCH(J$4,Survival!$C$3:$T$3,0))+INDEX(Data_Sales!$C$5:$C$65,MATCH($A11,Data_Sales!$A$5:$A$65,0))*INDEX(Survival!$C$55:$T$100,(J$4-$A11)+1,MATCH(J$4,Survival!$C$3:$T$3,0)))) | ... T11: =IF(T$4<$A11,"",IF((T$4-$A11)>45,0,INDEX(Data_Sales!$B$5:$B$65,MATCH($A11,Data_Sales!$A$5:$A$65,0))*INDEX(Survival!$C$6:$T$51,(T$4-$A11)+1,MATCH(T$4,Survival!$C$3:$T$3,0))+INDEX(Data_Sales!$C$5:$C$65,MATCH($A11,Data_Sales!$A$5:$A$65,0))*INDEX(Survival!$C$55:$T$100,(T$4-$A11)+1,MATCH(T$4,Survival!$C$3:$T$3,0))))
A12: 1976 | C12: =IF(C$4<$A12,"",IF((C$4-$A12)>45,0,INDEX(Data_Sales!$B$5:$B$65,MATCH($A12,Data_Sales!$A$5:$A$65,0))*INDEX(Survival!$C$6:$T$51,(C$4-$A12)+1,MATCH(C$4,Survival!$C$3:$T$3,0))+INDEX(Data_Sales!$C$5:$C$65,MATCH($A12,Data_Sales!$A$5:$A$65,0))*INDEX(Survival!$C$55:$T$100,(C$4-$A12)+1,MATCH(C$4,Survival!$C$3:$T$3,0)))) | D12: =IF(D$4<$A12,"",IF((D$4-$A12)>45,0,INDEX(Data_Sales!$B$5:$B$65,MATCH($A12,Data_Sales!$A$5:$A$65,0))*INDEX(Survival!$C$6:$T$51,(D$4-$A12)+1,MATCH(D$4,Survival!$C$3:$T$3,0))+INDEX(Data_Sales!$C$5:$C$65,MATCH($A12,Data_Sales!$A$5:$A$65,0))*INDEX(Survival!$C$55:$T$100,(D$4-$A12)+1,MATCH(D$4,Survival!$C$3:$T$3,0)))) | E12: =IF(E$4<$A12,"",IF((E$4-$A12)>45,0,INDEX(Data_Sales!$B$5:$B$65,MATCH($A12,Data_Sales!$A$5:$A$65,0))*INDEX(Survival!$C$6:$T$51,(E$4-$A12)+1,MATCH(E$4,Survival!$C$3:$T$3,0))+INDEX(Data_Sales!$C$5:$C$65,MATCH($A12,Data_Sales!$A$5:$A$65,0))*INDEX(Survival!$C$55:$T$100,(E$4-$A12)+1,MATCH(E$4,Survival!$C$3:$T$3,0)))) | F12: =IF(F$4<$A12,"",IF((F$4-$A12)>45,0,INDEX(Data_Sales!$B$5:$B$65,MATCH($A12,Data_Sales!$A$5:$A$65,0))*INDEX(Survival!$C$6:$T$51,(F$4-$A12)+1,MATCH(F$4,Survival!$C$3:$T$3,0))+INDEX(Data_Sales!$C$5:$C$65,MATCH($A12,Data_Sales!$A$5:$A$65,0))*INDEX(Survival!$C$55:$T$100,(F$4-$A12)+1,MATCH(F$4,Survival!$C$3:$T$3,0)))) | G12: =IF(G$4<$A12,"",IF((G$4-$A12)>45,0,INDEX(Data_Sales!$B$5:$B$65,MATCH($A12,Data_Sales!$A$5:$A$65,0))*INDEX(Survival!$C$6:$T$51,(G$4-$A12)+1,MATCH(G$4,Survival!$C$3:$T$3,0))+INDEX(Data_Sales!$C$5:$C$65,MATCH($A12,Data_Sales!$A$5:$A$65,0))*INDEX(Survival!$C$55:$T$100,(G$4-$A12)+1,MATCH(G$4,Survival!$C$3:$T$3,0)))) | H12: =IF(H$4<$A12,"",IF((H$4-$A12)>45,0,INDEX(Data_Sales!$B$5:$B$65,MATCH($A12,Data_Sales!$A$5:$A$65,0))*INDEX(Survival!$C$6:$T$51,(H$4-$A12)+1,MATCH(H$4,Survival!$C$3:$T$3,0))+INDEX(Data_Sales!$C$5:$C$65,MATCH($A12,Data_Sales!$A$5:$A$65,0))*INDEX(Survival!$C$55:$T$100,(H$4-$A12)+1,MATCH(H$4,Survival!$C$3:$T$3,0)))) | I12: =IF(I$4<$A12,"",IF((I$4-$A12)>45,0,INDEX(Data_Sales!$B$5:$B$65,MATCH($A12,Data_Sales!$A$5:$A$65,0))*INDEX(Survival!$C$6:$T$51,(I$4-$A12)+1,MATCH(I$4,Survival!$C$3:$T$3,0))+INDEX(Data_Sales!$C$5:$C$65,MATCH($A12,Data_Sales!$A$5:$A$65,0))*INDEX(Survival!$C$55:$T$100,(I$4-$A12)+1,MATCH(I$4,Survival!$C$3:$T$3,0)))) | J12: =IF(J$4<$A12,"",IF((J$4-$A12)>45,0,INDEX(Data_Sales!$B$5:$B$65,MATCH($A12,Data_Sales!$A$5:$A$65,0))*INDEX(Survival!$C$6:$T$51,(J$4-$A12)+1,MATCH(J$4,Survival!$C$3:$T$3,0))+INDEX(Data_Sales!$C$5:$C$65,MATCH($A12,Data_Sales!$A$5:$A$65,0))*INDEX(Survival!$C$55:$T$100,(J$4-$A12)+1,MATCH(J$4,Survival!$C$3:$T$3,0)))) | ... T12: =IF(T$4<$A12,"",IF((T$4-$A12)>45,0,INDEX(Data_Sales!$B$5:$B$65,MATCH($A12,Data_Sales!$A$5:$A$65,0))*INDEX(Survival!$C$6:$T$51,(T$4-$A12)+1,MATCH(T$4,Survival!$C$3:$T$3,0))+INDEX(Data_Sales!$C$5:$C$65,MATCH($A12,Data_Sales!$A$5:$A$65,0))*INDEX(Survival!$C$55:$T$100,(T$4-$A12)+1,MATCH(T$4,Survival!$C$3:$T$3,0))))
A13: 1977 | C13: =IF(C$4<$A13,"",IF((C$4-$A13)>45,0,INDEX(Data_Sales!$B$5:$B$65,MATCH($A13,Data_Sales!$A$5:$A$65,0))*INDEX(Survival!$C$6:$T$51,(C$4-$A13)+1,MATCH(C$4,Survival!$C$3:$T$3,0))+INDEX(Data_Sales!$C$5:$C$65,MATCH($A13,Data_Sales!$A$5:$A$65,0))*INDEX(Survival!$C$55:$T$100,(C$4-$A13)+1,MATCH(C$4,Survival!$C$3:$T$3,0)))) | D13: =IF(D$4<$A13,"",IF((D$4-$A13)>45,0,INDEX(Data_Sales!$B$5:$B$65,MATCH($A13,Data_Sales!$A$5:$A$65,0))*INDEX(Survival!$C$6:$T$51,(D$4-$A13)+1,MATCH(D$4,Survival!$C$3:$T$3,0))+INDEX(Data_Sales!$C$5:$C$65,MATCH($A13,Data_Sales!$A$5:$A$65,0))*INDEX(Survival!$C$55:$T$100,(D$4-$A13)+1,MATCH(D$4,Survival!$C$3:$T$3,0)))) | E13: =IF(E$4<$A13,"",IF((E$4-$A13)>45,0,INDEX(Data_Sales!$B$5:$B$65,MATCH($A13,Data_Sales!$A$5:$A$65,0))*INDEX(Survival!$C$6:$T$51,(E$4-$A13)+1,MATCH(E$4,Survival!$C$3:$T$3,0))+INDEX(Data_Sales!$C$5:$C$65,MATCH($A13,Data_Sales!$A$5:$A$65,0))*INDEX(Survival!$C$55:$T$100,(E$4-$A13)+1,MATCH(E$4,Survival!$C$3:$T$3,0)))) | F13: =IF(F$4<$A13,"",IF((F$4-$A13)>45,0,INDEX(Data_Sales!$B$5:$B$65,MATCH($A13,Data_Sales!$A$5:$A$65,0))*INDEX(Survival!$C$6:$T$51,(F$4-$A13)+1,MATCH(F$4,Survival!$C$3:$T$3,0))+INDEX(Data_Sales!$C$5:$C$65,MATCH($A13,Data_Sales!$A$5:$A$65,0))*INDEX(Survival!$C$55:$T$100,(F$4-$A13)+1,MATCH(F$4,Survival!$C$3:$T$3,0)))) | G13: =IF(G$4<$A13,"",IF((G$4-$A13)>45,0,INDEX(Data_Sales!$B$5:$B$65,MATCH($A13,Data_Sales!$A$5:$A$65,0))*INDEX(Survival!$C$6:$T$51,(G$4-$A13)+1,MATCH(G$4,Survival!$C$3:$T$3,0))+INDEX(Data_Sales!$C$5:$C$65,MATCH($A13,Data_Sales!$A$5:$A$65,0))*INDEX(Survival!$C$55:$T$100,(G$4-$A13)+1,MATCH(G$4,Survival!$C$3:$T$3,0)))) | H13: =IF(H$4<$A13,"",IF((H$4-$A13)>45,0,INDEX(Data_Sales!$B$5:$B$65,MATCH($A13,Data_Sales!$A$5:$A$65,0))*INDEX(Survival!$C$6:$T$51,(H$4-$A13)+1,MATCH(H$4,Survival!$C$3:$T$3,0))+INDEX(Data_Sales!$C$5:$C$65,MATCH($A13,Data_Sales!$A$5:$A$65,0))*INDEX(Survival!$C$55:$T$100,(H$4-$A13)+1,MATCH(H$4,Survival!$C$3:$T$3,0)))) | I13: =IF(I$4<$A13,"",IF((I$4-$A13)>45,0,INDEX(Data_Sales!$B$5:$B$65,MATCH($A13,Data_Sales!$A$5:$A$65,0))*INDEX(Survival!$C$6:$T$51,(I$4-$A13)+1,MATCH(I$4,Survival!$C$3:$T$3,0))+INDEX(Data_Sales!$C$5:$C$65,MATCH($A13,Data_Sales!$A$5:$A$65,0))*INDEX(Survival!$C$55:$T$100,(I$4-$A13)+1,MATCH(I$4,Survival!$C$3:$T$3,0)))) | J13: =IF(J$4<$A13,"",IF((J$4-$A13)>45,0,INDEX(Data_Sales!$B$5:$B$65,MATCH($A13,Data_Sales!$A$5:$A$65,0))*INDEX(Survival!$C$6:$T$51,(J$4-$A13)+1,MATCH(J$4,Survival!$C$3:$T$3,0))+INDEX(Data_Sales!$C$5:$C$65,MATCH($A13,Data_Sales!$A$5:$A$65,0))*INDEX(Survival!$C$55:$T$100,(J$4-$A13)+1,MATCH(J$4,Survival!$C$3:$T$3,0)))) | ... T13: =IF(T$4<$A13,"",IF((T$4-$A13)>45,0,INDEX(Data_Sales!$B$5:$B$65,MATCH($A13,Data_Sales!$A$5:$A$65,0))*INDEX(Survival!$C$6:$T$51,(T$4-$A13)+1,MATCH(T$4,Survival!$C$3:$T$3,0))+INDEX(Data_Sales!$C$5:$C$65,MATCH($A13,Data_Sales!$A$5:$A$65,0))*INDEX(Survival!$C$55:$T$100,(T$4-$A13)+1,MATCH(T$4,Survival!$C$3:$T$3,0))))
A14: 1978 | C14: =IF(C$4<$A14,"",IF((C$4-$A14)>45,0,INDEX(Data_Sales!$B$5:$B$65,MATCH($A14,Data_Sales!$A$5:$A$65,0))*INDEX(Survival!$C$6:$T$51,(C$4-$A14)+1,MATCH(C$4,Survival!$C$3:$T$3,0))+INDEX(Data_Sales!$C$5:$C$65,MATCH($A14,Data_Sales!$A$5:$A$65,0))*INDEX(Survival!$C$55:$T$100,(C$4-$A14)+1,MATCH(C$4,Survival!$C$3:$T$3,0)))) | D14: =IF(D$4<$A14,"",IF((D$4-$A14)>45,0,INDEX(Data_Sales!$B$5:$B$65,MATCH($A14,Data_Sales!$A$5:$A$65,0))*INDEX(Survival!$C$6:$T$51,(D$4-$A14)+1,MATCH(D$4,Survival!$C$3:$T$3,0))+INDEX(Data_Sales!$C$5:$C$65,MATCH($A14,Data_Sales!$A$5:$A$65,0))*INDEX(Survival!$C$55:$T$100,(D$4-$A14)+1,MATCH(D$4,Survival!$C$3:$T$3,0)))) | E14: =IF(E$4<$A14,"",IF((E$4-$A14)>45,0,INDEX(Data_Sales!$B$5:$B$65,MATCH($A14,Data_Sales!$A$5:$A$65,0))*INDEX(Survival!$C$6:$T$51,(E$4-$A14)+1,MATCH(E$4,Survival!$C$3:$T$3,0))+INDEX(Data_Sales!$C$5:$C$65,MATCH($A14,Data_Sales!$A$5:$A$65,0))*INDEX(Survival!$C$55:$T$100,(E$4-$A14)+1,MATCH(E$4,Survival!$C$3:$T$3,0)))) | F14: =IF(F$4<$A14,"",IF((F$4-$A14)>45,0,INDEX(Data_Sales!$B$5:$B$65,MATCH($A14,Data_Sales!$A$5:$A$65,0))*INDEX(Survival!$C$6:$T$51,(F$4-$A14)+1,MATCH(F$4,Survival!$C$3:$T$3,0))+INDEX(Data_Sales!$C$5:$C$65,MATCH($A14,Data_Sales!$A$5:$A$65,0))*INDEX(Survival!$C$55:$T$100,(F$4-$A14)+1,MATCH(F$4,Survival!$C$3:$T$3,0)))) | G14: =IF(G$4<$A14,"",IF((G$4-$A14)>45,0,INDEX(Data_Sales!$B$5:$B$65,MATCH($A14,Data_Sales!$A$5:$A$65,0))*INDEX(Survival!$C$6:$T$51,(G$4-$A14)+1,MATCH(G$4,Survival!$C$3:$T$3,0))+INDEX(Data_Sales!$C$5:$C$65,MATCH($A14,Data_Sales!$A$5:$A$65,0))*INDEX(Survival!$C$55:$T$100,(G$4-$A14)+1,MATCH(G$4,Survival!$C$3:$T$3,0)))) | H14: =IF(H$4<$A14,"",IF((H$4-$A14)>45,0,INDEX(Data_Sales!$B$5:$B$65,MATCH($A14,Data_Sales!$A$5:$A$65,0))*INDEX(Survival!$C$6:$T$51,(H$4-$A14)+1,MATCH(H$4,Survival!$C$3:$T$3,0))+INDEX(Data_Sales!$C$5:$C$65,MATCH($A14,Data_Sales!$A$5:$A$65,0))*INDEX(Survival!$C$55:$T$100,(H$4-$A14)+1,MATCH(H$4,Survival!$C$3:$T$3,0)))) | I14: =IF(I$4<$A14,"",IF((I$4-$A14)>45,0,INDEX(Data_Sales!$B$5:$B$65,MATCH($A14,Data_Sales!$A$5:$A$65,0))*INDEX(Survival!$C$6:$T$51,(I$4-$A14)+1,MATCH(I$4,Survival!$C$3:$T$3,0))+INDEX(Data_Sales!$C$5:$C$65,MATCH($A14,Data_Sales!$A$5:$A$65,0))*INDEX(Survival!$C$55:$T$100,(I$4-$A14)+1,MATCH(I$4,Survival!$C$3:$T$3,0)))) | J14: =IF(J$4<$A14,"",IF((J$4-$A14)>45,0,INDEX(Data_Sales!$B$5:$B$65,MATCH($A14,Data_Sales!$A$5:$A$65,0))*INDEX(Survival!$C$6:$T$51,(J$4-$A14)+1,MATCH(J$4,Survival!$C$3:$T$3,0))+INDEX(Data_Sales!$C$5:$C$65,MATCH($A14,Data_Sales!$A$5:$A$65,0))*INDEX(Survival!$C$55:$T$100,(J$4-$A14)+1,MATCH(J$4,Survival!$C$3:$T$3,0)))) | ... T14: =IF(T$4<$A14,"",IF((T$4-$A14)>45,0,INDEX(Data_Sales!$B$5:$B$65,MATCH($A14,Data_Sales!$A$5:$A$65,0))*INDEX(Survival!$C$6:$T$51,(T$4-$A14)+1,MATCH(T$4,Survival!$C$3:$T$3,0))+INDEX(Data_Sales!$C$5:$C$65,MATCH($A14,Data_Sales!$A$5:$A$65,0))*INDEX(Survival!$C$55:$T$100,(T$4-$A14)+1,MATCH(T$4,Survival!$C$3:$T$3,0))))
A15: 1979 | C15: =IF(C$4<$A15,"",IF((C$4-$A15)>45,0,INDEX(Data_Sales!$B$5:$B$65,MATCH($A15,Data_Sales!$A$5:$A$65,0))*INDEX(Survival!$C$6:$T$51,(C$4-$A15)+1,MATCH(C$4,Survival!$C$3:$T$3,0))+INDEX(Data_Sales!$C$5:$C$65,MATCH($A15,Data_Sales!$A$5:$A$65,0))*INDEX(Survival!$C$55:$T$100,(C$4-$A15)+1,MATCH(C$4,Survival!$C$3:$T$3,0)))) | D15: =IF(D$4<$A15,"",IF((D$4-$A15)>45,0,INDEX(Data_Sales!$B$5:$B$65,MATCH($A15,Data_Sales!$A$5:$A$65,0))*INDEX(Survival!$C$6:$T$51,(D$4-$A15)+1,MATCH(D$4,Survival!$C$3:$T$3,0))+INDEX(Data_Sales!$C$5:$C$65,MATCH($A15,Data_Sales!$A$5:$A$65,0))*INDEX(Survival!$C$55:$T$100,(D$4-$A15)+1,MATCH(D$4,Survival!$C$3:$T$3,0)))) | E15: =IF(E$4<$A15,"",IF((E$4-$A15)>45,0,INDEX(Data_Sales!$B$5:$B$65,MATCH($A15,Data_Sales!$A$5:$A$65,0))*INDEX(Survival!$C$6:$T$51,(E$4-$A15)+1,MATCH(E$4,Survival!$C$3:$T$3,0))+INDEX(Data_Sales!$C$5:$C$65,MATCH($A15,Data_Sales!$A$5:$A$65,0))*INDEX(Survival!$C$55:$T$100,(E$4-$A15)+1,MATCH(E$4,Survival!$C$3:$T$3,0)))) | F15: =IF(F$4<$A15,"",IF((F$4-$A15)>45,0,INDEX(Data_Sales!$B$5:$B$65,MATCH($A15,Data_Sales!$A$5:$A$65,0))*INDEX(Survival!$C$6:$T$51,(F$4-$A15)+1,MATCH(F$4,Survival!$C$3:$T$3,0))+INDEX(Data_Sales!$C$5:$C$65,MATCH($A15,Data_Sales!$A$5:$A$65,0))*INDEX(Survival!$C$55:$T$100,(F$4-$A15)+1,MATCH(F$4,Survival!$C$3:$T$3,0)))) | G15: =IF(G$4<$A15,"",IF((G$4-$A15)>45,0,INDEX(Data_Sales!$B$5:$B$65,MATCH($A15,Data_Sales!$A$5:$A$65,0))*INDEX(Survival!$C$6:$T$51,(G$4-$A15)+1,MATCH(G$4,Survival!$C$3:$T$3,0))+INDEX(Data_Sales!$C$5:$C$65,MATCH($A15,Data_Sales!$A$5:$A$65,0))*INDEX(Survival!$C$55:$T$100,(G$4-$A15)+1,MATCH(G$4,Survival!$C$3:$T$3,0)))) | H15: =IF(H$4<$A15,"",IF((H$4-$A15)>45,0,INDEX(Data_Sales!$B$5:$B$65,MATCH($A15,Data_Sales!$A$5:$A$65,0))*INDEX(Survival!$C$6:$T$51,(H$4-$A15)+1,MATCH(H$4,Survival!$C$3:$T$3,0))+INDEX(Data_Sales!$C$5:$C$65,MATCH($A15,Data_Sales!$A$5:$A$65,0))*INDEX(Survival!$C$55:$T$100,(H$4-$A15)+1,MATCH(H$4,Survival!$C$3:$T$3,0)))) | I15: =IF(I$4<$A15,"",IF((I$4-$A15)>45,0,INDEX(Data_Sales!$B$5:$B$65,MATCH($A15,Data_Sales!$A$5:$A$65,0))*INDEX(Survival!$C$6:$T$51,(I$4-$A15)+1,MATCH(I$4,Survival!$C$3:$T$3,0))+INDEX(Data_Sales!$C$5:$C$65,MATCH($A15,Data_Sales!$A$5:$A$65,0))*INDEX(Survival!$C$55:$T$100,(I$4-$A15)+1,MATCH(I$4,Survival!$C$3:$T$3,0)))) | J15: =IF(J$4<$A15,"",IF((J$4-$A15)>45,0,INDEX(Data_Sales!$B$5:$B$65,MATCH($A15,Data_Sales!$A$5:$A$65,0))*INDEX(Survival!$C$6:$T$51,(J$4-$A15)+1,MATCH(J$4,Survival!$C$3:$T$3,0))+INDEX(Data_Sales!$C$5:$C$65,MATCH($A15,Data_Sales!$A$5:$A$65,0))*INDEX(Survival!$C$55:$T$100,(J$4-$A15)+1,MATCH(J$4,Survival!$C$3:$T$3,0)))) | ... T15: =IF(T$4<$A15,"",IF((T$4-$A15)>45,0,INDEX(Data_Sales!$B$5:$B$65,MATCH($A15,Data_Sales!$A$5:$A$65,0))*INDEX(Survival!$C$6:$T$51,(T$4-$A15)+1,MATCH(T$4,Survival!$C$3:$T$3,0))+INDEX(Data_Sales!$C$5:$C$65,MATCH($A15,Data_Sales!$A$5:$A$65,0))*INDEX(Survival!$C$55:$T$100,(T$4-$A15)+1,MATCH(T$4,Survival!$C$3:$T$3,0))))
A16: 1980 | C16: =IF(C$4<$A16,"",IF((C$4-$A16)>45,0,INDEX(Data_Sales!$B$5:$B$65,MATCH($A16,Data_Sales!$A$5:$A$65,0))*INDEX(Survival!$C$6:$T$51,(C$4-$A16)+1,MATCH(C$4,Survival!$C$3:$T$3,0))+INDEX(Data_Sales!$C$5:$C$65,MATCH($A16,Data_Sales!$A$5:$A$65,0))*INDEX(Survival!$C$55:$T$100,(C$4-$A16)+1,MATCH(C$4,Survival!$C$3:$T$3,0)))) | D16: =IF(D$4<$A16,"",IF((D$4-$A16)>45,0,INDEX(Data_Sales!$B$5:$B$65,MATCH($A16,Data_Sales!$A$5:$A$65,0))*INDEX(Survival!$C$6:$T$51,(D$4-$A16)+1,MATCH(D$4,Survival!$C$3:$T$3,0))+INDEX(Data_Sales!$C$5:$C$65,MATCH($A16,Data_Sales!$A$5:$A$65,0))*INDEX(Survival!$C$55:$T$100,(D$4-$A16)+1,MATCH(D$4,Survival!$C$3:$T$3,0)))) | E16: =IF(E$4<$A16,"",IF((E$4-$A16)>45,0,INDEX(Data_Sales!$B$5:$B$65,MATCH($A16,Data_Sales!$A$5:$A$65,0))*INDEX(Survival!$C$6:$T$51,(E$4-$A16)+1,MATCH(E$4,Survival!$C$3:$T$3,0))+INDEX(Data_Sales!$C$5:$C$65,MATCH($A16,Data_Sales!$A$5:$A$65,0))*INDEX(Survival!$C$55:$T$100,(E$4-$A16)+1,MATCH(E$4,Survival!$C$3:$T$3,0)))) | F16: =IF(F$4<$A16,"",IF((F$4-$A16)>45,0,INDEX(Data_Sales!$B$5:$B$65,MATCH($A16,Data_Sales!$A$5:$A$65,0))*INDEX(Survival!$C$6:$T$51,(F$4-$A16)+1,MATCH(F$4,Survival!$C$3:$T$3,0))+INDEX(Data_Sales!$C$5:$C$65,MATCH($A16,Data_Sales!$A$5:$A$65,0))*INDEX(Survival!$C$55:$T$100,(F$4-$A16)+1,MATCH(F$4,Survival!$C$3:$T$3,0)))) | G16: =IF(G$4<$A16,"",IF((G$4-$A16)>45,0,INDEX(Data_Sales!$B$5:$B$65,MATCH($A16,Data_Sales!$A$5:$A$65,0))*INDEX(Survival!$C$6:$T$51,(G$4-$A16)+1,MATCH(G$4,Survival!$C$3:$T$3,0))+INDEX(Data_Sales!$C$5:$C$65,MATCH($A16,Data_Sales!$A$5:$A$65,0))*INDEX(Survival!$C$55:$T$100,(G$4-$A16)+1,MATCH(G$4,Survival!$C$3:$T$3,0)))) | H16: =IF(H$4<$A16,"",IF((H$4-$A16)>45,0,INDEX(Data_Sales!$B$5:$B$65,MATCH($A16,Data_Sales!$A$5:$A$65,0))*INDEX(Survival!$C$6:$T$51,(H$4-$A16)+1,MATCH(H$4,Survival!$C$3:$T$3,0))+INDEX(Data_Sales!$C$5:$C$65,MATCH($A16,Data_Sales!$A$5:$A$65,0))*INDEX(Survival!$C$55:$T$100,(H$4-$A16)+1,MATCH(H$4,Survival!$C$3:$T$3,0)))) | I16: =IF(I$4<$A16,"",IF((I$4-$A16)>45,0,INDEX(Data_Sales!$B$5:$B$65,MATCH($A16,Data_Sales!$A$5:$A$65,0))*INDEX(Survival!$C$6:$T$51,(I$4-$A16)+1,MATCH(I$4,Survival!$C$3:$T$3,0))+INDEX(Data_Sales!$C$5:$C$65,MATCH($A16,Data_Sales!$A$5:$A$65,0))*INDEX(Survival!$C$55:$T$100,(I$4-$A16)+1,MATCH(I$4,Survival!$C$3:$T$3,0)))) | J16: =IF(J$4<$A16,"",IF((J$4-$A16)>45,0,INDEX(Data_Sales!$B$5:$B$65,MATCH($A16,Data_Sales!$A$5:$A$65,0))*INDEX(Survival!$C$6:$T$51,(J$4-$A16)+1,MATCH(J$4,Survival!$C$3:$T$3,0))+INDEX(Data_Sales!$C$5:$C$65,MATCH($A16,Data_Sales!$A$5:$A$65,0))*INDEX(Survival!$C$55:$T$100,(J$4-$A16)+1,MATCH(J$4,Survival!$C$3:$T$3,0)))) | ... T16: =IF(T$4<$A16,"",IF((T$4-$A16)>45,0,INDEX(Data_Sales!$B$5:$B$65,MATCH($A16,Data_Sales!$A$5:$A$65,0))*INDEX(Survival!$C$6:$T$51,(T$4-$A16)+1,MATCH(T$4,Survival!$C$3:$T$3,0))+INDEX(Data_Sales!$C$5:$C$65,MATCH($A16,Data_Sales!$A$5:$A$65,0))*INDEX(Survival!$C$55:$T$100,(T$4-$A16)+1,MATCH(T$4,Survival!$C$3:$T$3,0))))
A17: 1981 | C17: =IF(C$4<$A17,"",IF((C$4-$A17)>45,0,INDEX(Data_Sales!$B$5:$B$65,MATCH($A17,Data_Sales!$A$5:$A$65,0))*INDEX(Survival!$C$6:$T$51,(C$4-$A17)+1,MATCH(C$4,Survival!$C$3:$T$3,0))+INDEX(Data_Sales!$C$5:$C$65,MATCH($A17,Data_Sales!$A$5:$A$65,0))*INDEX(Survival!$C$55:$T$100,(C$4-$A17)+1,MATCH(C$4,Survival!$C$3:$T$3,0)))) | D17: =IF(D$4<$A17,"",IF((D$4-$A17)>45,0,INDEX(Data_Sales!$B$5:$B$65,MATCH($A17,Data_Sales!$A$5:$A$65,0))*INDEX(Survival!$C$6:$T$51,(D$4-$A17)+1,MATCH(D$4,Survival!$C$3:$T$3,0))+INDEX(Data_Sales!$C$5:$C$65,MATCH($A17,Data_Sales!$A$5:$A$65,0))*INDEX(Survival!$C$55:$T$100,(D$4-$A17)+1,MATCH(D$4,Survival!$C$3:$T$3,0)))) | E17: =IF(E$4<$A17,"",IF((E$4-$A17)>45,0,INDEX(Data_Sales!$B$5:$B$65,MATCH($A17,Data_Sales!$A$5:$A$65,0))*INDEX(Survival!$C$6:$T$51,(E$4-$A17)+1,MATCH(E$4,Survival!$C$3:$T$3,0))+INDEX(Data_Sales!$C$5:$C$65,MATCH($A17,Data_Sales!$A$5:$A$65,0))*INDEX(Survival!$C$55:$T$100,(E$4-$A17)+1,MATCH(E$4,Survival!$C$3:$T$3,0)))) | F17: =IF(F$4<$A17,"",IF((F$4-$A17)>45,0,INDEX(Data_Sales!$B$5:$B$65,MATCH($A17,Data_Sales!$A$5:$A$65,0))*INDEX(Survival!$C$6:$T$51,(F$4-$A17)+1,MATCH(F$4,Survival!$C$3:$T$3,0))+INDEX(Data_Sales!$C$5:$C$65,MATCH($A17,Data_Sales!$A$5:$A$65,0))*INDEX(Survival!$C$55:$T$100,(F$4-$A17)+1,MATCH(F$4,Survival!$C$3:$T$3,0)))) | G17: =IF(G$4<$A17,"",IF((G$4-$A17)>45,0,INDEX(Data_Sales!$B$5:$B$65,MATCH($A17,Data_Sales!$A$5:$A$65,0))*INDEX(Survival!$C$6:$T$51,(G$4-$A17)+1,MATCH(G$4,Survival!$C$3:$T$3,0))+INDEX(Data_Sales!$C$5:$C$65,MATCH($A17,Data_Sales!$A$5:$A$65,0))*INDEX(Survival!$C$55:$T$100,(G$4-$A17)+1,MATCH(G$4,Survival!$C$3:$T$3,0)))) | H17: =IF(H$4<$A17,"",IF((H$4-$A17)>45,0,INDEX(Data_Sales!$B$5:$B$65,MATCH($A17,Data_Sales!$A$5:$A$65,0))*INDEX(Survival!$C$6:$T$51,(H$4-$A17)+1,MATCH(H$4,Survival!$C$3:$T$3,0))+INDEX(Data_Sales!$C$5:$C$65,MATCH($A17,Data_Sales!$A$5:$A$65,0))*INDEX(Survival!$C$55:$T$100,(H$4-$A17)+1,MATCH(H$4,Survival!$C$3:$T$3,0)))) | I17: =IF(I$4<$A17,"",IF((I$4-$A17)>45,0,INDEX(Data_Sales!$B$5:$B$65,MATCH($A17,Data_Sales!$A$5:$A$65,0))*INDEX(Survival!$C$6:$T$51,(I$4-$A17)+1,MATCH(I$4,Survival!$C$3:$T$3,0))+INDEX(Data_Sales!$C$5:$C$65,MATCH($A17,Data_Sales!$A$5:$A$65,0))*INDEX(Survival!$C$55:$T$100,(I$4-$A17)+1,MATCH(I$4,Survival!$C$3:$T$3,0)))) | J17: =IF(J$4<$A17,"",IF((J$4-$A17)>45,0,INDEX(Data_Sales!$B$5:$B$65,MATCH($A17,Data_Sales!$A$5:$A$65,0))*INDEX(Survival!$C$6:$T$51,(J$4-$A17)+1,MATCH(J$4,Survival!$C$3:$T$3,0))+INDEX(Data_Sales!$C$5:$C$65,MATCH($A17,Data_Sales!$A$5:$A$65,0))*INDEX(Survival!$C$55:$T$100,(J$4-$A17)+1,MATCH(J$4,Survival!$C$3:$T$3,0)))) | ... T17: =IF(T$4<$A17,"",IF((T$4-$A17)>45,0,INDEX(Data_Sales!$B$5:$B$65,MATCH($A17,Data_Sales!$A$5:$A$65,0))*INDEX(Survival!$C$6:$T$51,(T$4-$A17)+1,MATCH(T$4,Survival!$C$3:$T$3,0))+INDEX(Data_Sales!$C$5:$C$65,MATCH($A17,Data_Sales!$A$5:$A$65,0))*INDEX(Survival!$C$55:$T$100,(T$4-$A17)+1,MATCH(T$4,Survival!$C$3:$T$3,0))))
... A66: 2030 | C66: =IF(C$4<$A66,"",IF((C$4-$A66)>45,0,INDEX(Data_Sales!$B$5:$B$65,MATCH($A66,Data_Sales!$A$5:$A$65,0))*INDEX(Survival!$C$6:$T$51,(C$4-$A66)+1,MATCH(C$4,Survival!$C$3:$T$3,0))+INDEX(Data_Sales!$C$5:$C$65,MATCH($A66,Data_Sales!$A$5:$A$65,0))*INDEX(Survival!$C$55:$T$100,(C$4-$A66)+1,MATCH(C$4,Survival!$C$3:$T$3,0)))) | D66: =IF(D$4<$A66,"",IF((D$4-$A66)>45,0,INDEX(Data_Sales!$B$5:$B$65,MATCH($A66,Data_Sales!$A$5:$A$65,0))*INDEX(Survival!$C$6:$T$51,(D$4-$A66)+1,MATCH(D$4,Survival!$C$3:$T$3,0))+INDEX(Data_Sales!$C$5:$C$65,MATCH($A66,Data_Sales!$A$5:$A$65,0))*INDEX(Survival!$C$55:$T$100,(D$4-$A66)+1,MATCH(D$4,Survival!$C$3:$T$3,0)))) | E66: =IF(E$4<$A66,"",IF((E$4-$A66)>45,0,INDEX(Data_Sales!$B$5:$B$65,MATCH($A66,Data_Sales!$A$5:$A$65,0))*INDEX(Survival!$C$6:$T$51,(E$4-$A66)+1,MATCH(E$4,Survival!$C$3:$T$3,0))+INDEX(Data_Sales!$C$5:$C$65,MATCH($A66,Data_Sales!$A$5:$A$65,0))*INDEX(Survival!$C$55:$T$100,(E$4-$A66)+1,MATCH(E$4,Survival!$C$3:$T$3,0)))) | F66: =IF(F$4<$A66,"",IF((F$4-$A66)>45,0,INDEX(Data_Sales!$B$5:$B$65,MATCH($A66,Data_Sales!$A$5:$A$65,0))*INDEX(Survival!$C$6:$T$51,(F$4-$A66)+1,MATCH(F$4,Survival!$C$3:$T$3,0))+INDEX(Data_Sales!$C$5:$C$65,MATCH($A66,Data_Sales!$A$5:$A$65,0))*INDEX(Survival!$C$55:$T$100,(F$4-$A66)+1,MATCH(F$4,Survival!$C$3:$T$3,0)))) | G66: =IF(G$4<$A66,"",IF((G$4-$A66)>45,0,INDEX(Data_Sales!$B$5:$B$65,MATCH($A66,Data_Sales!$A$5:$A$65,0))*INDEX(Survival!$C$6:$T$51,(G$4-$A66)+1,MATCH(G$4,Survival!$C$3:$T$3,0))+INDEX(Data_Sales!$C$5:$C$65,MATCH($A66,Data_Sales!$A$5:$A$65,0))*INDEX(Survival!$C$55:$T$100,(G$4-$A66)+1,MATCH(G$4,Survival!$C$3:$T$3,0)))) | H66: =IF(H$4<$A66,"",IF((H$4-$A66)>45,0,INDEX(Data_Sales!$B$5:$B$65,MATCH($A66,Data_Sales!$A$5:$A$65,0))*INDEX(Survival!$C$6:$T$51,(H$4-$A66)+1,MATCH(H$4,Survival!$C$3:$T$3,0))+INDEX(Data_Sales!$C$5:$C$65,MATCH($A66,Data_Sales!$A$5:$A$65,0))*INDEX(Survival!$C$55:$T$100,(H$4-$A66)+1,MATCH(H$4,Survival!$C$3:$T$3,0)))) | I66: =IF(I$4<$A66,"",IF((I$4-$A66)>45,0,INDEX(Data_Sales!$B$5:$B$65,MATCH($A66,Data_Sales!$A$5:$A$65,0))*INDEX(Survival!$C$6:$T$51,(I$4-$A66)+1,MATCH(I$4,Survival!$C$3:$T$3,0))+INDEX(Data_Sales!$C$5:$C$65,MATCH($A66,Data_Sales!$A$5:$A$65,0))*INDEX(Survival!$C$55:$T$100,(I$4-$A66)+1,MATCH(I$4,Survival!$C$3:$T$3,0)))) | J66: =IF(J$4<$A66,"",IF((J$4-$A66)>45,0,INDEX(Data_Sales!$B$5:$B$65,MATCH($A66,Data_Sales!$A$5:$A$65,0))*INDEX(Survival!$C$6:$T$51,(J$4-$A66)+1,MATCH(J$4,Survival!$C$3:$T$3,0))+INDEX(Data_Sales!$C$5:$C$65,MATCH($A66,Data_Sales!$A$5:$A$65,0))*INDEX(Survival!$C$55:$T$100,(J$4-$A66)+1,MATCH(J$4,Survival!$C$3:$T$3,0)))) | ... T66: =IF(T$4<$A66,"",IF((T$4-$A66)>45,0,INDEX(Data_Sales!$B$5:$B$65,MATCH($A66,Data_Sales!$A$5:$A$65,0))*INDEX(Survival!$C$6:$T$51,(T$4-$A66)+1,MATCH(T$4,Survival!$C$3:$T$3,0))+INDEX(Data_Sales!$C$5:$C$65,MATCH($A66,Data_Sales!$A$5:$A$65,0))*INDEX(Survival!$C$55:$T$100,(T$4-$A66)+1,MATCH(T$4,Survival!$C$3:$T$3,0))))
A68: Total VIO (thousands) | C68: =SUM(C6:C66) | D68: =SUM(D6:D66) | E68: =SUM(E6:E66) | F68: =SUM(F6:F66) | G68: =SUM(G6:G66) | H68: =SUM(H6:H66) | I68: =SUM(I6:I66) | J68: =SUM(J6:J66) | ... T68: =SUM(T6:T66)

Sheet FleetByAge
A1: Fleet by age and calendar year (thousands) + fleet statistics
A2: fleet(a,t) = Fleet[MY = t−a, t]. Rows 53–57: VIO, share 7+, share 15+, count ≤6, average age (t−MY+0.5). Compare with Data_CCC_Targets rows marked S.
A4: Age ↓ / Year → | B4: age+0.5 | C4: =Inputs!C23 | D4: =Inputs!D23 | E4: =Inputs!E23 | F4: =Inputs!F23 | G4: =Inputs!G23 | H4: =Inputs!H23 | I4: =Inputs!I23 | J4: =Inputs!J23 | ... T4: =Inputs!T23
A6: 0 | B6: =A6+0.5 | C6: =IF(C$4-$A6<1970,0,INDEX(Fleet!$C$6:$T$66,MATCH(C$4-$A6,Fleet!$A$6:$A$66,0),MATCH(C$4,Fleet!$C$4:$T$4,0))) | D6: =IF(D$4-$A6<1970,0,INDEX(Fleet!$C$6:$T$66,MATCH(D$4-$A6,Fleet!$A$6:$A$66,0),MATCH(D$4,Fleet!$C$4:$T$4,0))) | E6: =IF(E$4-$A6<1970,0,INDEX(Fleet!$C$6:$T$66,MATCH(E$4-$A6,Fleet!$A$6:$A$66,0),MATCH(E$4,Fleet!$C$4:$T$4,0))) | F6: =IF(F$4-$A6<1970,0,INDEX(Fleet!$C$6:$T$66,MATCH(F$4-$A6,Fleet!$A$6:$A$66,0),MATCH(F$4,Fleet!$C$4:$T$4,0))) | G6: =IF(G$4-$A6<1970,0,INDEX(Fleet!$C$6:$T$66,MATCH(G$4-$A6,Fleet!$A$6:$A$66,0),MATCH(G$4,Fleet!$C$4:$T$4,0))) | H6: =IF(H$4-$A6<1970,0,INDEX(Fleet!$C$6:$T$66,MATCH(H$4-$A6,Fleet!$A$6:$A$66,0),MATCH(H$4,Fleet!$C$4:$T$4,0))) | I6: =IF(I$4-$A6<1970,0,INDEX(Fleet!$C$6:$T$66,MATCH(I$4-$A6,Fleet!$A$6:$A$66,0),MATCH(I$4,Fleet!$C$4:$T$4,0))) | J6: =IF(J$4-$A6<1970,0,INDEX(Fleet!$C$6:$T$66,MATCH(J$4-$A6,Fleet!$A$6:$A$66,0),MATCH(J$4,Fleet!$C$4:$T$4,0))) | ... T6: =IF(T$4-$A6<1970,0,INDEX(Fleet!$C$6:$T$66,MATCH(T$4-$A6,Fleet!$A$6:$A$66,0),MATCH(T$4,Fleet!$C$4:$T$4,0)))
A7: 1 | B7: =A7+0.5 | C7: =IF(C$4-$A7<1970,0,INDEX(Fleet!$C$6:$T$66,MATCH(C$4-$A7,Fleet!$A$6:$A$66,0),MATCH(C$4,Fleet!$C$4:$T$4,0))) | D7: =IF(D$4-$A7<1970,0,INDEX(Fleet!$C$6:$T$66,MATCH(D$4-$A7,Fleet!$A$6:$A$66,0),MATCH(D$4,Fleet!$C$4:$T$4,0))) | E7: =IF(E$4-$A7<1970,0,INDEX(Fleet!$C$6:$T$66,MATCH(E$4-$A7,Fleet!$A$6:$A$66,0),MATCH(E$4,Fleet!$C$4:$T$4,0))) | F7: =IF(F$4-$A7<1970,0,INDEX(Fleet!$C$6:$T$66,MATCH(F$4-$A7,Fleet!$A$6:$A$66,0),MATCH(F$4,Fleet!$C$4:$T$4,0))) | G7: =IF(G$4-$A7<1970,0,INDEX(Fleet!$C$6:$T$66,MATCH(G$4-$A7,Fleet!$A$6:$A$66,0),MATCH(G$4,Fleet!$C$4:$T$4,0))) | H7: =IF(H$4-$A7<1970,0,INDEX(Fleet!$C$6:$T$66,MATCH(H$4-$A7,Fleet!$A$6:$A$66,0),MATCH(H$4,Fleet!$C$4:$T$4,0))) | I7: =IF(I$4-$A7<1970,0,INDEX(Fleet!$C$6:$T$66,MATCH(I$4-$A7,Fleet!$A$6:$A$66,0),MATCH(I$4,Fleet!$C$4:$T$4,0))) | J7: =IF(J$4-$A7<1970,0,INDEX(Fleet!$C$6:$T$66,MATCH(J$4-$A7,Fleet!$A$6:$A$66,0),MATCH(J$4,Fleet!$C$4:$T$4,0))) | ... T7: =IF(T$4-$A7<1970,0,INDEX(Fleet!$C$6:$T$66,MATCH(T$4-$A7,Fleet!$A$6:$A$66,0),MATCH(T$4,Fleet!$C$4:$T$4,0)))
A8: 2 | B8: =A8+0.5 | C8: =IF(C$4-$A8<1970,0,INDEX(Fleet!$C$6:$T$66,MATCH(C$4-$A8,Fleet!$A$6:$A$66,0),MATCH(C$4,Fleet!$C$4:$T$4,0))) | D8: =IF(D$4-$A8<1970,0,INDEX(Fleet!$C$6:$T$66,MATCH(D$4-$A8,Fleet!$A$6:$A$66,0),MATCH(D$4,Fleet!$C$4:$T$4,0))) | E8: =IF(E$4-$A8<1970,0,INDEX(Fleet!$C$6:$T$66,MATCH(E$4-$A8,Fleet!$A$6:$A$66,0),MATCH(E$4,Fleet!$C$4:$T$4,0))) | F8: =IF(F$4-$A8<1970,0,INDEX(Fleet!$C$6:$T$66,MATCH(F$4-$A8,Fleet!$A$6:$A$66,0),MATCH(F$4,Fleet!$C$4:$T$4,0))) | G8: =IF(G$4-$A8<1970,0,INDEX(Fleet!$C$6:$T$66,MATCH(G$4-$A8,Fleet!$A$6:$A$66,0),MATCH(G$4,Fleet!$C$4:$T$4,0))) | H8: =IF(H$4-$A8<1970,0,INDEX(Fleet!$C$6:$T$66,MATCH(H$4-$A8,Fleet!$A$6:$A$66,0),MATCH(H$4,Fleet!$C$4:$T$4,0))) | I8: =IF(I$4-$A8<1970,0,INDEX(Fleet!$C$6:$T$66,MATCH(I$4-$A8,Fleet!$A$6:$A$66,0),MATCH(I$4,Fleet!$C$4:$T$4,0))) | J8: =IF(J$4-$A8<1970,0,INDEX(Fleet!$C$6:$T$66,MATCH(J$4-$A8,Fleet!$A$6:$A$66,0),MATCH(J$4,Fleet!$C$4:$T$4,0))) | ... T8: =IF(T$4-$A8<1970,0,INDEX(Fleet!$C$6:$T$66,MATCH(T$4-$A8,Fleet!$A$6:$A$66,0),MATCH(T$4,Fleet!$C$4:$T$4,0)))
A9: 3 | B9: =A9+0.5 | C9: =IF(C$4-$A9<1970,0,INDEX(Fleet!$C$6:$T$66,MATCH(C$4-$A9,Fleet!$A$6:$A$66,0),MATCH(C$4,Fleet!$C$4:$T$4,0))) | D9: =IF(D$4-$A9<1970,0,INDEX(Fleet!$C$6:$T$66,MATCH(D$4-$A9,Fleet!$A$6:$A$66,0),MATCH(D$4,Fleet!$C$4:$T$4,0))) | E9: =IF(E$4-$A9<1970,0,INDEX(Fleet!$C$6:$T$66,MATCH(E$4-$A9,Fleet!$A$6:$A$66,0),MATCH(E$4,Fleet!$C$4:$T$4,0))) | F9: =IF(F$4-$A9<1970,0,INDEX(Fleet!$C$6:$T$66,MATCH(F$4-$A9,Fleet!$A$6:$A$66,0),MATCH(F$4,Fleet!$C$4:$T$4,0))) | G9: =IF(G$4-$A9<1970,0,INDEX(Fleet!$C$6:$T$66,MATCH(G$4-$A9,Fleet!$A$6:$A$66,0),MATCH(G$4,Fleet!$C$4:$T$4,0))) | H9: =IF(H$4-$A9<1970,0,INDEX(Fleet!$C$6:$T$66,MATCH(H$4-$A9,Fleet!$A$6:$A$66,0),MATCH(H$4,Fleet!$C$4:$T$4,0))) | I9: =IF(I$4-$A9<1970,0,INDEX(Fleet!$C$6:$T$66,MATCH(I$4-$A9,Fleet!$A$6:$A$66,0),MATCH(I$4,Fleet!$C$4:$T$4,0))) | J9: =IF(J$4-$A9<1970,0,INDEX(Fleet!$C$6:$T$66,MATCH(J$4-$A9,Fleet!$A$6:$A$66,0),MATCH(J$4,Fleet!$C$4:$T$4,0))) | ... T9: =IF(T$4-$A9<1970,0,INDEX(Fleet!$C$6:$T$66,MATCH(T$4-$A9,Fleet!$A$6:$A$66,0),MATCH(T$4,Fleet!$C$4:$T$4,0)))
A10: 4 | B10: =A10+0.5 | C10: =IF(C$4-$A10<1970,0,INDEX(Fleet!$C$6:$T$66,MATCH(C$4-$A10,Fleet!$A$6:$A$66,0),MATCH(C$4,Fleet!$C$4:$T$4,0))) | D10: =IF(D$4-$A10<1970,0,INDEX(Fleet!$C$6:$T$66,MATCH(D$4-$A10,Fleet!$A$6:$A$66,0),MATCH(D$4,Fleet!$C$4:$T$4,0))) | E10: =IF(E$4-$A10<1970,0,INDEX(Fleet!$C$6:$T$66,MATCH(E$4-$A10,Fleet!$A$6:$A$66,0),MATCH(E$4,Fleet!$C$4:$T$4,0))) | F10: =IF(F$4-$A10<1970,0,INDEX(Fleet!$C$6:$T$66,MATCH(F$4-$A10,Fleet!$A$6:$A$66,0),MATCH(F$4,Fleet!$C$4:$T$4,0))) | G10: =IF(G$4-$A10<1970,0,INDEX(Fleet!$C$6:$T$66,MATCH(G$4-$A10,Fleet!$A$6:$A$66,0),MATCH(G$4,Fleet!$C$4:$T$4,0))) | H10: =IF(H$4-$A10<1970,0,INDEX(Fleet!$C$6:$T$66,MATCH(H$4-$A10,Fleet!$A$6:$A$66,0),MATCH(H$4,Fleet!$C$4:$T$4,0))) | I10: =IF(I$4-$A10<1970,0,INDEX(Fleet!$C$6:$T$66,MATCH(I$4-$A10,Fleet!$A$6:$A$66,0),MATCH(I$4,Fleet!$C$4:$T$4,0))) | J10: =IF(J$4-$A10<1970,0,INDEX(Fleet!$C$6:$T$66,MATCH(J$4-$A10,Fleet!$A$6:$A$66,0),MATCH(J$4,Fleet!$C$4:$T$4,0))) | ... T10: =IF(T$4-$A10<1970,0,INDEX(Fleet!$C$6:$T$66,MATCH(T$4-$A10,Fleet!$A$6:$A$66,0),MATCH(T$4,Fleet!$C$4:$T$4,0)))
A11: 5 | B11: =A11+0.5 | C11: =IF(C$4-$A11<1970,0,INDEX(Fleet!$C$6:$T$66,MATCH(C$4-$A11,Fleet!$A$6:$A$66,0),MATCH(C$4,Fleet!$C$4:$T$4,0))) | D11: =IF(D$4-$A11<1970,0,INDEX(Fleet!$C$6:$T$66,MATCH(D$4-$A11,Fleet!$A$6:$A$66,0),MATCH(D$4,Fleet!$C$4:$T$4,0))) | E11: =IF(E$4-$A11<1970,0,INDEX(Fleet!$C$6:$T$66,MATCH(E$4-$A11,Fleet!$A$6:$A$66,0),MATCH(E$4,Fleet!$C$4:$T$4,0))) | F11: =IF(F$4-$A11<1970,0,INDEX(Fleet!$C$6:$T$66,MATCH(F$4-$A11,Fleet!$A$6:$A$66,0),MATCH(F$4,Fleet!$C$4:$T$4,0))) | G11: =IF(G$4-$A11<1970,0,INDEX(Fleet!$C$6:$T$66,MATCH(G$4-$A11,Fleet!$A$6:$A$66,0),MATCH(G$4,Fleet!$C$4:$T$4,0))) | H11: =IF(H$4-$A11<1970,0,INDEX(Fleet!$C$6:$T$66,MATCH(H$4-$A11,Fleet!$A$6:$A$66,0),MATCH(H$4,Fleet!$C$4:$T$4,0))) | I11: =IF(I$4-$A11<1970,0,INDEX(Fleet!$C$6:$T$66,MATCH(I$4-$A11,Fleet!$A$6:$A$66,0),MATCH(I$4,Fleet!$C$4:$T$4,0))) | J11: =IF(J$4-$A11<1970,0,INDEX(Fleet!$C$6:$T$66,MATCH(J$4-$A11,Fleet!$A$6:$A$66,0),MATCH(J$4,Fleet!$C$4:$T$4,0))) | ... T11: =IF(T$4-$A11<1970,0,INDEX(Fleet!$C$6:$T$66,MATCH(T$4-$A11,Fleet!$A$6:$A$66,0),MATCH(T$4,Fleet!$C$4:$T$4,0)))
A12: 6 | B12: =A12+0.5 | C12: =IF(C$4-$A12<1970,0,INDEX(Fleet!$C$6:$T$66,MATCH(C$4-$A12,Fleet!$A$6:$A$66,0),MATCH(C$4,Fleet!$C$4:$T$4,0))) | D12: =IF(D$4-$A12<1970,0,INDEX(Fleet!$C$6:$T$66,MATCH(D$4-$A12,Fleet!$A$6:$A$66,0),MATCH(D$4,Fleet!$C$4:$T$4,0))) | E12: =IF(E$4-$A12<1970,0,INDEX(Fleet!$C$6:$T$66,MATCH(E$4-$A12,Fleet!$A$6:$A$66,0),MATCH(E$4,Fleet!$C$4:$T$4,0))) | F12: =IF(F$4-$A12<1970,0,INDEX(Fleet!$C$6:$T$66,MATCH(F$4-$A12,Fleet!$A$6:$A$66,0),MATCH(F$4,Fleet!$C$4:$T$4,0))) | G12: =IF(G$4-$A12<1970,0,INDEX(Fleet!$C$6:$T$66,MATCH(G$4-$A12,Fleet!$A$6:$A$66,0),MATCH(G$4,Fleet!$C$4:$T$4,0))) | H12: =IF(H$4-$A12<1970,0,INDEX(Fleet!$C$6:$T$66,MATCH(H$4-$A12,Fleet!$A$6:$A$66,0),MATCH(H$4,Fleet!$C$4:$T$4,0))) | I12: =IF(I$4-$A12<1970,0,INDEX(Fleet!$C$6:$T$66,MATCH(I$4-$A12,Fleet!$A$6:$A$66,0),MATCH(I$4,Fleet!$C$4:$T$4,0))) | J12: =IF(J$4-$A12<1970,0,INDEX(Fleet!$C$6:$T$66,MATCH(J$4-$A12,Fleet!$A$6:$A$66,0),MATCH(J$4,Fleet!$C$4:$T$4,0))) | ... T12: =IF(T$4-$A12<1970,0,INDEX(Fleet!$C$6:$T$66,MATCH(T$4-$A12,Fleet!$A$6:$A$66,0),MATCH(T$4,Fleet!$C$4:$T$4,0)))
A13: 7 | B13: =A13+0.5 | C13: =IF(C$4-$A13<1970,0,INDEX(Fleet!$C$6:$T$66,MATCH(C$4-$A13,Fleet!$A$6:$A$66,0),MATCH(C$4,Fleet!$C$4:$T$4,0))) | D13: =IF(D$4-$A13<1970,0,INDEX(Fleet!$C$6:$T$66,MATCH(D$4-$A13,Fleet!$A$6:$A$66,0),MATCH(D$4,Fleet!$C$4:$T$4,0))) | E13: =IF(E$4-$A13<1970,0,INDEX(Fleet!$C$6:$T$66,MATCH(E$4-$A13,Fleet!$A$6:$A$66,0),MATCH(E$4,Fleet!$C$4:$T$4,0))) | F13: =IF(F$4-$A13<1970,0,INDEX(Fleet!$C$6:$T$66,MATCH(F$4-$A13,Fleet!$A$6:$A$66,0),MATCH(F$4,Fleet!$C$4:$T$4,0))) | G13: =IF(G$4-$A13<1970,0,INDEX(Fleet!$C$6:$T$66,MATCH(G$4-$A13,Fleet!$A$6:$A$66,0),MATCH(G$4,Fleet!$C$4:$T$4,0))) | H13: =IF(H$4-$A13<1970,0,INDEX(Fleet!$C$6:$T$66,MATCH(H$4-$A13,Fleet!$A$6:$A$66,0),MATCH(H$4,Fleet!$C$4:$T$4,0))) | I13: =IF(I$4-$A13<1970,0,INDEX(Fleet!$C$6:$T$66,MATCH(I$4-$A13,Fleet!$A$6:$A$66,0),MATCH(I$4,Fleet!$C$4:$T$4,0))) | J13: =IF(J$4-$A13<1970,0,INDEX(Fleet!$C$6:$T$66,MATCH(J$4-$A13,Fleet!$A$6:$A$66,0),MATCH(J$4,Fleet!$C$4:$T$4,0))) | ... T13: =IF(T$4-$A13<1970,0,INDEX(Fleet!$C$6:$T$66,MATCH(T$4-$A13,Fleet!$A$6:$A$66,0),MATCH(T$4,Fleet!$C$4:$T$4,0)))
A14: 8 | B14: =A14+0.5 | C14: =IF(C$4-$A14<1970,0,INDEX(Fleet!$C$6:$T$66,MATCH(C$4-$A14,Fleet!$A$6:$A$66,0),MATCH(C$4,Fleet!$C$4:$T$4,0))) | D14: =IF(D$4-$A14<1970,0,INDEX(Fleet!$C$6:$T$66,MATCH(D$4-$A14,Fleet!$A$6:$A$66,0),MATCH(D$4,Fleet!$C$4:$T$4,0))) | E14: =IF(E$4-$A14<1970,0,INDEX(Fleet!$C$6:$T$66,MATCH(E$4-$A14,Fleet!$A$6:$A$66,0),MATCH(E$4,Fleet!$C$4:$T$4,0))) | F14: =IF(F$4-$A14<1970,0,INDEX(Fleet!$C$6:$T$66,MATCH(F$4-$A14,Fleet!$A$6:$A$66,0),MATCH(F$4,Fleet!$C$4:$T$4,0))) | G14: =IF(G$4-$A14<1970,0,INDEX(Fleet!$C$6:$T$66,MATCH(G$4-$A14,Fleet!$A$6:$A$66,0),MATCH(G$4,Fleet!$C$4:$T$4,0))) | H14: =IF(H$4-$A14<1970,0,INDEX(Fleet!$C$6:$T$66,MATCH(H$4-$A14,Fleet!$A$6:$A$66,0),MATCH(H$4,Fleet!$C$4:$T$4,0))) | I14: =IF(I$4-$A14<1970,0,INDEX(Fleet!$C$6:$T$66,MATCH(I$4-$A14,Fleet!$A$6:$A$66,0),MATCH(I$4,Fleet!$C$4:$T$4,0))) | J14: =IF(J$4-$A14<1970,0,INDEX(Fleet!$C$6:$T$66,MATCH(J$4-$A14,Fleet!$A$6:$A$66,0),MATCH(J$4,Fleet!$C$4:$T$4,0))) | ... T14: =IF(T$4-$A14<1970,0,INDEX(Fleet!$C$6:$T$66,MATCH(T$4-$A14,Fleet!$A$6:$A$66,0),MATCH(T$4,Fleet!$C$4:$T$4,0)))
A15: 9 | B15: =A15+0.5 | C15: =IF(C$4-$A15<1970,0,INDEX(Fleet!$C$6:$T$66,MATCH(C$4-$A15,Fleet!$A$6:$A$66,0),MATCH(C$4,Fleet!$C$4:$T$4,0))) | D15: =IF(D$4-$A15<1970,0,INDEX(Fleet!$C$6:$T$66,MATCH(D$4-$A15,Fleet!$A$6:$A$66,0),MATCH(D$4,Fleet!$C$4:$T$4,0))) | E15: =IF(E$4-$A15<1970,0,INDEX(Fleet!$C$6:$T$66,MATCH(E$4-$A15,Fleet!$A$6:$A$66,0),MATCH(E$4,Fleet!$C$4:$T$4,0))) | F15: =IF(F$4-$A15<1970,0,INDEX(Fleet!$C$6:$T$66,MATCH(F$4-$A15,Fleet!$A$6:$A$66,0),MATCH(F$4,Fleet!$C$4:$T$4,0))) | G15: =IF(G$4-$A15<1970,0,INDEX(Fleet!$C$6:$T$66,MATCH(G$4-$A15,Fleet!$A$6:$A$66,0),MATCH(G$4,Fleet!$C$4:$T$4,0))) | H15: =IF(H$4-$A15<1970,0,INDEX(Fleet!$C$6:$T$66,MATCH(H$4-$A15,Fleet!$A$6:$A$66,0),MATCH(H$4,Fleet!$C$4:$T$4,0))) | I15: =IF(I$4-$A15<1970,0,INDEX(Fleet!$C$6:$T$66,MATCH(I$4-$A15,Fleet!$A$6:$A$66,0),MATCH(I$4,Fleet!$C$4:$T$4,0))) | J15: =IF(J$4-$A15<1970,0,INDEX(Fleet!$C$6:$T$66,MATCH(J$4-$A15,Fleet!$A$6:$A$66,0),MATCH(J$4,Fleet!$C$4:$T$4,0))) | ... T15: =IF(T$4-$A15<1970,0,INDEX(Fleet!$C$6:$T$66,MATCH(T$4-$A15,Fleet!$A$6:$A$66,0),MATCH(T$4,Fleet!$C$4:$T$4,0)))
A16: 10 | B16: =A16+0.5 | C16: =IF(C$4-$A16<1970,0,INDEX(Fleet!$C$6:$T$66,MATCH(C$4-$A16,Fleet!$A$6:$A$66,0),MATCH(C$4,Fleet!$C$4:$T$4,0))) | D16: =IF(D$4-$A16<1970,0,INDEX(Fleet!$C$6:$T$66,MATCH(D$4-$A16,Fleet!$A$6:$A$66,0),MATCH(D$4,Fleet!$C$4:$T$4,0))) | E16: =IF(E$4-$A16<1970,0,INDEX(Fleet!$C$6:$T$66,MATCH(E$4-$A16,Fleet!$A$6:$A$66,0),MATCH(E$4,Fleet!$C$4:$T$4,0))) | F16: =IF(F$4-$A16<1970,0,INDEX(Fleet!$C$6:$T$66,MATCH(F$4-$A16,Fleet!$A$6:$A$66,0),MATCH(F$4,Fleet!$C$4:$T$4,0))) | G16: =IF(G$4-$A16<1970,0,INDEX(Fleet!$C$6:$T$66,MATCH(G$4-$A16,Fleet!$A$6:$A$66,0),MATCH(G$4,Fleet!$C$4:$T$4,0))) | H16: =IF(H$4-$A16<1970,0,INDEX(Fleet!$C$6:$T$66,MATCH(H$4-$A16,Fleet!$A$6:$A$66,0),MATCH(H$4,Fleet!$C$4:$T$4,0))) | I16: =IF(I$4-$A16<1970,0,INDEX(Fleet!$C$6:$T$66,MATCH(I$4-$A16,Fleet!$A$6:$A$66,0),MATCH(I$4,Fleet!$C$4:$T$4,0))) | J16: =IF(J$4-$A16<1970,0,INDEX(Fleet!$C$6:$T$66,MATCH(J$4-$A16,Fleet!$A$6:$A$66,0),MATCH(J$4,Fleet!$C$4:$T$4,0))) | ... T16: =IF(T$4-$A16<1970,0,INDEX(Fleet!$C$6:$T$66,MATCH(T$4-$A16,Fleet!$A$6:$A$66,0),MATCH(T$4,Fleet!$C$4:$T$4,0)))
A17: 11 | B17: =A17+0.5 | C17: =IF(C$4-$A17<1970,0,INDEX(Fleet!$C$6:$T$66,MATCH(C$4-$A17,Fleet!$A$6:$A$66,0),MATCH(C$4,Fleet!$C$4:$T$4,0))) | D17: =IF(D$4-$A17<1970,0,INDEX(Fleet!$C$6:$T$66,MATCH(D$4-$A17,Fleet!$A$6:$A$66,0),MATCH(D$4,Fleet!$C$4:$T$4,0))) | E17: =IF(E$4-$A17<1970,0,INDEX(Fleet!$C$6:$T$66,MATCH(E$4-$A17,Fleet!$A$6:$A$66,0),MATCH(E$4,Fleet!$C$4:$T$4,0))) | F17: =IF(F$4-$A17<1970,0,INDEX(Fleet!$C$6:$T$66,MATCH(F$4-$A17,Fleet!$A$6:$A$66,0),MATCH(F$4,Fleet!$C$4:$T$4,0))) | G17: =IF(G$4-$A17<1970,0,INDEX(Fleet!$C$6:$T$66,MATCH(G$4-$A17,Fleet!$A$6:$A$66,0),MATCH(G$4,Fleet!$C$4:$T$4,0))) | H17: =IF(H$4-$A17<1970,0,INDEX(Fleet!$C$6:$T$66,MATCH(H$4-$A17,Fleet!$A$6:$A$66,0),MATCH(H$4,Fleet!$C$4:$T$4,0))) | I17: =IF(I$4-$A17<1970,0,INDEX(Fleet!$C$6:$T$66,MATCH(I$4-$A17,Fleet!$A$6:$A$66,0),MATCH(I$4,Fleet!$C$4:$T$4,0))) | J17: =IF(J$4-$A17<1970,0,INDEX(Fleet!$C$6:$T$66,MATCH(J$4-$A17,Fleet!$A$6:$A$66,0),MATCH(J$4,Fleet!$C$4:$T$4,0))) | ... T17: =IF(T$4-$A17<1970,0,INDEX(Fleet!$C$6:$T$66,MATCH(T$4-$A17,Fleet!$A$6:$A$66,0),MATCH(T$4,Fleet!$C$4:$T$4,0)))
... A51: 45 | B51: =A51+0.5 | C51: =IF(C$4-$A51<1970,0,INDEX(Fleet!$C$6:$T$66,MATCH(C$4-$A51,Fleet!$A$6:$A$66,0),MATCH(C$4,Fleet!$C$4:$T$4,0))) | D51: =IF(D$4-$A51<1970,0,INDEX(Fleet!$C$6:$T$66,MATCH(D$4-$A51,Fleet!$A$6:$A$66,0),MATCH(D$4,Fleet!$C$4:$T$4,0))) | E51: =IF(E$4-$A51<1970,0,INDEX(Fleet!$C$6:$T$66,MATCH(E$4-$A51,Fleet!$A$6:$A$66,0),MATCH(E$4,Fleet!$C$4:$T$4,0))) | F51: =IF(F$4-$A51<1970,0,INDEX(Fleet!$C$6:$T$66,MATCH(F$4-$A51,Fleet!$A$6:$A$66,0),MATCH(F$4,Fleet!$C$4:$T$4,0))) | G51: =IF(G$4-$A51<1970,0,INDEX(Fleet!$C$6:$T$66,MATCH(G$4-$A51,Fleet!$A$6:$A$66,0),MATCH(G$4,Fleet!$C$4:$T$4,0))) | H51: =IF(H$4-$A51<1970,0,INDEX(Fleet!$C$6:$T$66,MATCH(H$4-$A51,Fleet!$A$6:$A$66,0),MATCH(H$4,Fleet!$C$4:$T$4,0))) | I51: =IF(I$4-$A51<1970,0,INDEX(Fleet!$C$6:$T$66,MATCH(I$4-$A51,Fleet!$A$6:$A$66,0),MATCH(I$4,Fleet!$C$4:$T$4,0))) | J51: =IF(J$4-$A51<1970,0,INDEX(Fleet!$C$6:$T$66,MATCH(J$4-$A51,Fleet!$A$6:$A$66,0),MATCH(J$4,Fleet!$C$4:$T$4,0))) | ... T51: =IF(T$4-$A51<1970,0,INDEX(Fleet!$C$6:$T$66,MATCH(T$4-$A51,Fleet!$A$6:$A$66,0),MATCH(T$4,Fleet!$C$4:$T$4,0)))
A53: VIO (M) | C53: =SUM(C6:C51)/1000 | D53: =SUM(D6:D51)/1000 | E53: =SUM(E6:E51)/1000 | F53: =SUM(F6:F51)/1000 | G53: =SUM(G6:G51)/1000 | H53: =SUM(H6:H51)/1000 | I53: =SUM(I6:I51)/1000 | J53: =SUM(J6:J51)/1000 | ... T53: =SUM(T6:T51)/1000
A54: Share aged 7+ | C54: =SUMIF($A$6:$A$51,">=7",C6:C51)/SUM(C6:C51) | D54: =SUMIF($A$6:$A$51,">=7",D6:D51)/SUM(D6:D51) | E54: =SUMIF($A$6:$A$51,">=7",E6:E51)/SUM(E6:E51) | F54: =SUMIF($A$6:$A$51,">=7",F6:F51)/SUM(F6:F51) | G54: =SUMIF($A$6:$A$51,">=7",G6:G51)/SUM(G6:G51) | H54: =SUMIF($A$6:$A$51,">=7",H6:H51)/SUM(H6:H51) | I54: =SUMIF($A$6:$A$51,">=7",I6:I51)/SUM(I6:I51) | J54: =SUMIF($A$6:$A$51,">=7",J6:J51)/SUM(J6:J51) | ... T54: =SUMIF($A$6:$A$51,">=7",T6:T51)/SUM(T6:T51)
A55: Share aged 15+ | C55: =SUMIF($A$6:$A$51,">=15",C6:C51)/SUM(C6:C51) | D55: =SUMIF($A$6:$A$51,">=15",D6:D51)/SUM(D6:D51) | E55: =SUMIF($A$6:$A$51,">=15",E6:E51)/SUM(E6:E51) | F55: =SUMIF($A$6:$A$51,">=15",F6:F51)/SUM(F6:F51) | G55: =SUMIF($A$6:$A$51,">=15",G6:G51)/SUM(G6:G51) | H55: =SUMIF($A$6:$A$51,">=15",H6:H51)/SUM(H6:H51) | I55: =SUMIF($A$6:$A$51,">=15",I6:I51)/SUM(I6:I51) | J55: =SUMIF($A$6:$A$51,">=15",J6:J51)/SUM(J6:J51) | ... T55: =SUMIF($A$6:$A$51,">=15",T6:T51)/SUM(T6:T51)
A56: Count aged ≤6 (M) | C56: =SUMIF($A$6:$A$51,"<=6",C6:C51)/1000 | D56: =SUMIF($A$6:$A$51,"<=6",D6:D51)/1000 | E56: =SUMIF($A$6:$A$51,"<=6",E6:E51)/1000 | F56: =SUMIF($A$6:$A$51,"<=6",F6:F51)/1000 | G56: =SUMIF($A$6:$A$51,"<=6",G6:G51)/1000 | H56: =SUMIF($A$6:$A$51,"<=6",H6:H51)/1000 | I56: =SUMIF($A$6:$A$51,"<=6",I6:I51)/1000 | J56: =SUMIF($A$6:$A$51,"<=6",J6:J51)/1000 | ... T56: =SUMIF($A$6:$A$51,"<=6",T6:T51)/1000
A57: Average age (t−MY+0.5) | C57: =SUMPRODUCT($B$6:$B$51,C6:C51)/SUM(C6:C51) | D57: =SUMPRODUCT($B$6:$B$51,D6:D51)/SUM(D6:D51) | E57: =SUMPRODUCT($B$6:$B$51,E6:E51)/SUM(E6:E51) | F57: =SUMPRODUCT($B$6:$B$51,F6:F51)/SUM(F6:F51) | G57: =SUMPRODUCT($B$6:$B$51,G6:G51)/SUM(G6:G51) | H57: =SUMPRODUCT($B$6:$B$51,H6:H51)/SUM(H6:H51) | I57: =SUMPRODUCT($B$6:$B$51,I6:I51)/SUM(I6:I51) | J57: =SUMPRODUCT($B$6:$B$51,J6:J51)/SUM(J6:J51) | ... T57: =SUMPRODUCT($B$6:$B$51,T6:T51)/SUM(T6:T51)
A59: Average age here is NOT comparable to S&P's 12.8 (S&P's figure needs a 15+ tail averaging ~27 yrs — registrations that are barely driven). Calibrate to counts, not to average age. docs/AGE_CURVES.md §2.3

Sheet Curves
A1: Age curves — R(a) relative insured-claim frequency, P(a) total-loss propensity, miles by age
A2: R and P read their parameters from Inputs (yellow cells). Flags feed the SUMPRODUCTs on TLF_Roll. Miles: EPA schedule (Data_EPA_Miles), age>30 = age-30 value. Columns I–K: 2024 fleet split by body for the fleet-weighted miles ratio (docs/AGE_CURVES.md §3.4).
A4: age | B4: R(a) | C4: P(a) | D4: miles/yr cars | E4: miles/yr light trucks | F4: flag age≥7 | G4: flag age≤3 | H4: (unused) | I4: cars fleet 2024 (thousands) | J4: LT fleet 2024 (thousands) | K4: miles/yr fleet-weighted 2024
A6: 0 | B6: =IF($A6=0,Inputs!$B$9,1)*EXP(-Inputs!$B$11*MAX($A6-Inputs!$B$10,0)) | C6: =Inputs!$B$12+(Inputs!$B$13-Inputs!$B$12)/(1+EXP(-($A6-Inputs!$B$14)/Inputs!$B$15)) | D6: =INDEX(Data_EPA_Miles!$B$5:$B$35,MIN($A6,30)+1) | E6: =INDEX(Data_EPA_Miles!$C$5:$C$35,MIN($A6,30)+1) | F6: =IF($A6>=7,1,0) | G6: =IF($A6<=3,1,0) | I6: =IF(2024-$A6<1970,0,INDEX(Data_Sales!$B$5:$B$65,MATCH(2024-$A6,Data_Sales!$A$5:$A$65,0))*INDEX(Survival!$C$6:$T$51,$A6+1,MATCH(2024,Survival!$C$3:$T$3,0))) | J6: =IF(2024-$A6<1970,0,INDEX(Data_Sales!$C$5:$C$65,MATCH(2024-$A6,Data_Sales!$A$5:$A$65,0))*INDEX(Survival!$C$55:$T$100,$A6+1,MATCH(2024,Survival!$C$3:$T$3,0))) | K6: =IF(I6+J6=0,D6,(D6*I6+E6*J6)/(I6+J6))
A7: 1 | B7: =IF($A7=0,Inputs!$B$9,1)*EXP(-Inputs!$B$11*MAX($A7-Inputs!$B$10,0)) | C7: =Inputs!$B$12+(Inputs!$B$13-Inputs!$B$12)/(1+EXP(-($A7-Inputs!$B$14)/Inputs!$B$15)) | D7: =INDEX(Data_EPA_Miles!$B$5:$B$35,MIN($A7,30)+1) | E7: =INDEX(Data_EPA_Miles!$C$5:$C$35,MIN($A7,30)+1) | F7: =IF($A7>=7,1,0) | G7: =IF($A7<=3,1,0) | I7: =IF(2024-$A7<1970,0,INDEX(Data_Sales!$B$5:$B$65,MATCH(2024-$A7,Data_Sales!$A$5:$A$65,0))*INDEX(Survival!$C$6:$T$51,$A7+1,MATCH(2024,Survival!$C$3:$T$3,0))) | J7: =IF(2024-$A7<1970,0,INDEX(Data_Sales!$C$5:$C$65,MATCH(2024-$A7,Data_Sales!$A$5:$A$65,0))*INDEX(Survival!$C$55:$T$100,$A7+1,MATCH(2024,Survival!$C$3:$T$3,0))) | K7: =IF(I7+J7=0,D7,(D7*I7+E7*J7)/(I7+J7))
A8: 2 | B8: =IF($A8=0,Inputs!$B$9,1)*EXP(-Inputs!$B$11*MAX($A8-Inputs!$B$10,0)) | C8: =Inputs!$B$12+(Inputs!$B$13-Inputs!$B$12)/(1+EXP(-($A8-Inputs!$B$14)/Inputs!$B$15)) | D8: =INDEX(Data_EPA_Miles!$B$5:$B$35,MIN($A8,30)+1) | E8: =INDEX(Data_EPA_Miles!$C$5:$C$35,MIN($A8,30)+1) | F8: =IF($A8>=7,1,0) | G8: =IF($A8<=3,1,0) | I8: =IF(2024-$A8<1970,0,INDEX(Data_Sales!$B$5:$B$65,MATCH(2024-$A8,Data_Sales!$A$5:$A$65,0))*INDEX(Survival!$C$6:$T$51,$A8+1,MATCH(2024,Survival!$C$3:$T$3,0))) | J8: =IF(2024-$A8<1970,0,INDEX(Data_Sales!$C$5:$C$65,MATCH(2024-$A8,Data_Sales!$A$5:$A$65,0))*INDEX(Survival!$C$55:$T$100,$A8+1,MATCH(2024,Survival!$C$3:$T$3,0))) | K8: =IF(I8+J8=0,D8,(D8*I8+E8*J8)/(I8+J8))
A9: 3 | B9: =IF($A9=0,Inputs!$B$9,1)*EXP(-Inputs!$B$11*MAX($A9-Inputs!$B$10,0)) | C9: =Inputs!$B$12+(Inputs!$B$13-Inputs!$B$12)/(1+EXP(-($A9-Inputs!$B$14)/Inputs!$B$15)) | D9: =INDEX(Data_EPA_Miles!$B$5:$B$35,MIN($A9,30)+1) | E9: =INDEX(Data_EPA_Miles!$C$5:$C$35,MIN($A9,30)+1) | F9: =IF($A9>=7,1,0) | G9: =IF($A9<=3,1,0) | I9: =IF(2024-$A9<1970,0,INDEX(Data_Sales!$B$5:$B$65,MATCH(2024-$A9,Data_Sales!$A$5:$A$65,0))*INDEX(Survival!$C$6:$T$51,$A9+1,MATCH(2024,Survival!$C$3:$T$3,0))) | J9: =IF(2024-$A9<1970,0,INDEX(Data_Sales!$C$5:$C$65,MATCH(2024-$A9,Data_Sales!$A$5:$A$65,0))*INDEX(Survival!$C$55:$T$100,$A9+1,MATCH(2024,Survival!$C$3:$T$3,0))) | K9: =IF(I9+J9=0,D9,(D9*I9+E9*J9)/(I9+J9))
A10: 4 | B10: =IF($A10=0,Inputs!$B$9,1)*EXP(-Inputs!$B$11*MAX($A10-Inputs!$B$10,0)) | C10: =Inputs!$B$12+(Inputs!$B$13-Inputs!$B$12)/(1+EXP(-($A10-Inputs!$B$14)/Inputs!$B$15)) | D10: =INDEX(Data_EPA_Miles!$B$5:$B$35,MIN($A10,30)+1) | E10: =INDEX(Data_EPA_Miles!$C$5:$C$35,MIN($A10,30)+1) | F10: =IF($A10>=7,1,0) | G10: =IF($A10<=3,1,0) | I10: =IF(2024-$A10<1970,0,INDEX(Data_Sales!$B$5:$B$65,MATCH(2024-$A10,Data_Sales!$A$5:$A$65,0))*INDEX(Survival!$C$6:$T$51,$A10+1,MATCH(2024,Survival!$C$3:$T$3,0))) | J10: =IF(2024-$A10<1970,0,INDEX(Data_Sales!$C$5:$C$65,MATCH(2024-$A10,Data_Sales!$A$5:$A$65,0))*INDEX(Survival!$C$55:$T$100,$A10+1,MATCH(2024,Survival!$C$3:$T$3,0))) | K10: =IF(I10+J10=0,D10,(D10*I10+E10*J10)/(I10+J10))
A11: 5 | B11: =IF($A11=0,Inputs!$B$9,1)*EXP(-Inputs!$B$11*MAX($A11-Inputs!$B$10,0)) | C11: =Inputs!$B$12+(Inputs!$B$13-Inputs!$B$12)/(1+EXP(-($A11-Inputs!$B$14)/Inputs!$B$15)) | D11: =INDEX(Data_EPA_Miles!$B$5:$B$35,MIN($A11,30)+1) | E11: =INDEX(Data_EPA_Miles!$C$5:$C$35,MIN($A11,30)+1) | F11: =IF($A11>=7,1,0) | G11: =IF($A11<=3,1,0) | I11: =IF(2024-$A11<1970,0,INDEX(Data_Sales!$B$5:$B$65,MATCH(2024-$A11,Data_Sales!$A$5:$A$65,0))*INDEX(Survival!$C$6:$T$51,$A11+1,MATCH(2024,Survival!$C$3:$T$3,0))) | J11: =IF(2024-$A11<1970,0,INDEX(Data_Sales!$C$5:$C$65,MATCH(2024-$A11,Data_Sales!$A$5:$A$65,0))*INDEX(Survival!$C$55:$T$100,$A11+1,MATCH(2024,Survival!$C$3:$T$3,0))) | K11: =IF(I11+J11=0,D11,(D11*I11+E11*J11)/(I11+J11))
A12: 6 | B12: =IF($A12=0,Inputs!$B$9,1)*EXP(-Inputs!$B$11*MAX($A12-Inputs!$B$10,0)) | C12: =Inputs!$B$12+(Inputs!$B$13-Inputs!$B$12)/(1+EXP(-($A12-Inputs!$B$14)/Inputs!$B$15)) | D12: =INDEX(Data_EPA_Miles!$B$5:$B$35,MIN($A12,30)+1) | E12: =INDEX(Data_EPA_Miles!$C$5:$C$35,MIN($A12,30)+1) | F12: =IF($A12>=7,1,0) | G12: =IF($A12<=3,1,0) | I12: =IF(2024-$A12<1970,0,INDEX(Data_Sales!$B$5:$B$65,MATCH(2024-$A12,Data_Sales!$A$5:$A$65,0))*INDEX(Survival!$C$6:$T$51,$A12+1,MATCH(2024,Survival!$C$3:$T$3,0))) | J12: =IF(2024-$A12<1970,0,INDEX(Data_Sales!$C$5:$C$65,MATCH(2024-$A12,Data_Sales!$A$5:$A$65,0))*INDEX(Survival!$C$55:$T$100,$A12+1,MATCH(2024,Survival!$C$3:$T$3,0))) | K12: =IF(I12+J12=0,D12,(D12*I12+E12*J12)/(I12+J12))
A13: 7 | B13: =IF($A13=0,Inputs!$B$9,1)*EXP(-Inputs!$B$11*MAX($A13-Inputs!$B$10,0)) | C13: =Inputs!$B$12+(Inputs!$B$13-Inputs!$B$12)/(1+EXP(-($A13-Inputs!$B$14)/Inputs!$B$15)) | D13: =INDEX(Data_EPA_Miles!$B$5:$B$35,MIN($A13,30)+1) | E13: =INDEX(Data_EPA_Miles!$C$5:$C$35,MIN($A13,30)+1) | F13: =IF($A13>=7,1,0) | G13: =IF($A13<=3,1,0) | I13: =IF(2024-$A13<1970,0,INDEX(Data_Sales!$B$5:$B$65,MATCH(2024-$A13,Data_Sales!$A$5:$A$65,0))*INDEX(Survival!$C$6:$T$51,$A13+1,MATCH(2024,Survival!$C$3:$T$3,0))) | J13: =IF(2024-$A13<1970,0,INDEX(Data_Sales!$C$5:$C$65,MATCH(2024-$A13,Data_Sales!$A$5:$A$65,0))*INDEX(Survival!$C$55:$T$100,$A13+1,MATCH(2024,Survival!$C$3:$T$3,0))) | K13: =IF(I13+J13=0,D13,(D13*I13+E13*J13)/(I13+J13))
A14: 8 | B14: =IF($A14=0,Inputs!$B$9,1)*EXP(-Inputs!$B$11*MAX($A14-Inputs!$B$10,0)) | C14: =Inputs!$B$12+(Inputs!$B$13-Inputs!$B$12)/(1+EXP(-($A14-Inputs!$B$14)/Inputs!$B$15)) | D14: =INDEX(Data_EPA_Miles!$B$5:$B$35,MIN($A14,30)+1) | E14: =INDEX(Data_EPA_Miles!$C$5:$C$35,MIN($A14,30)+1) | F14: =IF($A14>=7,1,0) | G14: =IF($A14<=3,1,0) | I14: =IF(2024-$A14<1970,0,INDEX(Data_Sales!$B$5:$B$65,MATCH(2024-$A14,Data_Sales!$A$5:$A$65,0))*INDEX(Survival!$C$6:$T$51,$A14+1,MATCH(2024,Survival!$C$3:$T$3,0))) | J14: =IF(2024-$A14<1970,0,INDEX(Data_Sales!$C$5:$C$65,MATCH(2024-$A14,Data_Sales!$A$5:$A$65,0))*INDEX(Survival!$C$55:$T$100,$A14+1,MATCH(2024,Survival!$C$3:$T$3,0))) | K14: =IF(I14+J14=0,D14,(D14*I14+E14*J14)/(I14+J14))
A15: 9 | B15: =IF($A15=0,Inputs!$B$9,1)*EXP(-Inputs!$B$11*MAX($A15-Inputs!$B$10,0)) | C15: =Inputs!$B$12+(Inputs!$B$13-Inputs!$B$12)/(1+EXP(-($A15-Inputs!$B$14)/Inputs!$B$15)) | D15: =INDEX(Data_EPA_Miles!$B$5:$B$35,MIN($A15,30)+1) | E15: =INDEX(Data_EPA_Miles!$C$5:$C$35,MIN($A15,30)+1) | F15: =IF($A15>=7,1,0) | G15: =IF($A15<=3,1,0) | I15: =IF(2024-$A15<1970,0,INDEX(Data_Sales!$B$5:$B$65,MATCH(2024-$A15,Data_Sales!$A$5:$A$65,0))*INDEX(Survival!$C$6:$T$51,$A15+1,MATCH(2024,Survival!$C$3:$T$3,0))) | J15: =IF(2024-$A15<1970,0,INDEX(Data_Sales!$C$5:$C$65,MATCH(2024-$A15,Data_Sales!$A$5:$A$65,0))*INDEX(Survival!$C$55:$T$100,$A15+1,MATCH(2024,Survival!$C$3:$T$3,0))) | K15: =IF(I15+J15=0,D15,(D15*I15+E15*J15)/(I15+J15))
A16: 10 | B16: =IF($A16=0,Inputs!$B$9,1)*EXP(-Inputs!$B$11*MAX($A16-Inputs!$B$10,0)) | C16: =Inputs!$B$12+(Inputs!$B$13-Inputs!$B$12)/(1+EXP(-($A16-Inputs!$B$14)/Inputs!$B$15)) | D16: =INDEX(Data_EPA_Miles!$B$5:$B$35,MIN($A16,30)+1) | E16: =INDEX(Data_EPA_Miles!$C$5:$C$35,MIN($A16,30)+1) | F16: =IF($A16>=7,1,0) | G16: =IF($A16<=3,1,0) | I16: =IF(2024-$A16<1970,0,INDEX(Data_Sales!$B$5:$B$65,MATCH(2024-$A16,Data_Sales!$A$5:$A$65,0))*INDEX(Survival!$C$6:$T$51,$A16+1,MATCH(2024,Survival!$C$3:$T$3,0))) | J16: =IF(2024-$A16<1970,0,INDEX(Data_Sales!$C$5:$C$65,MATCH(2024-$A16,Data_Sales!$A$5:$A$65,0))*INDEX(Survival!$C$55:$T$100,$A16+1,MATCH(2024,Survival!$C$3:$T$3,0))) | K16: =IF(I16+J16=0,D16,(D16*I16+E16*J16)/(I16+J16))
A17: 11 | B17: =IF($A17=0,Inputs!$B$9,1)*EXP(-Inputs!$B$11*MAX($A17-Inputs!$B$10,0)) | C17: =Inputs!$B$12+(Inputs!$B$13-Inputs!$B$12)/(1+EXP(-($A17-Inputs!$B$14)/Inputs!$B$15)) | D17: =INDEX(Data_EPA_Miles!$B$5:$B$35,MIN($A17,30)+1) | E17: =INDEX(Data_EPA_Miles!$C$5:$C$35,MIN($A17,30)+1) | F17: =IF($A17>=7,1,0) | G17: =IF($A17<=3,1,0) | I17: =IF(2024-$A17<1970,0,INDEX(Data_Sales!$B$5:$B$65,MATCH(2024-$A17,Data_Sales!$A$5:$A$65,0))*INDEX(Survival!$C$6:$T$51,$A17+1,MATCH(2024,Survival!$C$3:$T$3,0))) | J17: =IF(2024-$A17<1970,0,INDEX(Data_Sales!$C$5:$C$65,MATCH(2024-$A17,Data_Sales!$A$5:$A$65,0))*INDEX(Survival!$C$55:$T$100,$A17+1,MATCH(2024,Survival!$C$3:$T$3,0))) | K17: =IF(I17+J17=0,D17,(D17*I17+E17*J17)/(I17+J17))
... A51: 45 | B51: =IF($A51=0,Inputs!$B$9,1)*EXP(-Inputs!$B$11*MAX($A51-Inputs!$B$10,0)) | C51: =Inputs!$B$12+(Inputs!$B$13-Inputs!$B$12)/(1+EXP(-($A51-Inputs!$B$14)/Inputs!$B$15)) | D51: =INDEX(Data_EPA_Miles!$B$5:$B$35,MIN($A51,30)+1) | E51: =INDEX(Data_EPA_Miles!$C$5:$C$35,MIN($A51,30)+1) | F51: =IF($A51>=7,1,0) | G51: =IF($A51<=3,1,0) | I51: =IF(2024-$A51<1970,0,INDEX(Data_Sales!$B$5:$B$65,MATCH(2024-$A51,Data_Sales!$A$5:$A$65,0))*INDEX(Survival!$C$6:$T$51,$A51+1,MATCH(2024,Survival!$C$3:$T$3,0))) | J51: =IF(2024-$A51<1970,0,INDEX(Data_Sales!$C$5:$C$65,MATCH(2024-$A51,Data_Sales!$A$5:$A$65,0))*INDEX(Survival!$C$55:$T$100,$A51+1,MATCH(2024,Survival!$C$3:$T$3,0))) | K51: =IF(I51+J51=0,D51,(D51*I51+E51*J51)/(I51+J51))
A53: R decomposition, 7+ vs 0–6 (2024 fleet weights)
A54: Fleet-weighted miles ratio 7+ / 0–6 | B54: =(SUMPRODUCT($K$6:$K$51,$F$6:$F$51,FleetByAge!N$6:N$51)/SUMPRODUCT($F$6:$F$51,FleetByAge!N$6:N$51))/(SUMPRODUCT($K$6:$K$51,1-$F$6:$F$51,FleetByAge!N$6:N$51)/SUMPRODUCT(1-$F$6:$F$51,FleetByAge!N$6:N$51)) | C54: EPA T3.14 miles × 2024 fleet (≈0.65)
A55: Fitted R ratio 7+ / 0–6 (claims per vehicle) | B55: =(SUMPRODUCT($B$6:$B$51,$F$6:$F$51,FleetByAge!N$6:N$51)/SUMPRODUCT($F$6:$F$51,FleetByAge!N$6:N$51))/(SUMPRODUCT($B$6:$B$51,1-$F$6:$F$51,FleetByAge!N$6:N$51)/SUMPRODUCT(1-$F$6:$F$51,FleetByAge!N$6:N$51)) | C55: claims per vehicle, 7+ vs 0–6 (≈0.56)
A56: Residual = coverage / filing | B56: =B55/B54 | C56: liability-only, higher deductibles, unfiled small claims on older cars (≈0.87)

Sheet Calibration
A1: Calibration — fit R(a) and P(a) to CCC 2024 with Solver
A2: Working parameters B4:B8 (yellow) are what Solver changes. They start at the fitted values. After a run, copy B4:B8 → Inputs!B11:B15 so the model does not depend on Solver being re-run.
A3: Working parameter | B3: Value | C3: Bounds for Solver
A4: R slope after kink | B4: 0.09027 | C4: 0 to 0.5
A5: P floor (pmin) | B5: 0.0483 | C5: 0.01 to 0.3
A6: P ceiling (pmax) | B6: 0.4804 | C6: 0.3 to 0.95, and ≥ B5
A7: P midpoint age | B7: 9.216 | C7: 0 to 30
A8: P width | B8: 3.726 | C8: 0.3 to 12
A9: Exposure age 0 (from Inputs) | B9: =Inputs!$B$9
A10: R kink age (from Inputs) | B10: =Inputs!$B$10
A12: age | B12: fleet 2024 (thousands) | C12: R(a) | D12: P(a) | E12: claims = fleet×R | F12: total losses = claims×P | G12: repairables = claims−TL | I12: key | J12: statistic (2024) | K12: model | L12: CCC target | M12: tolerance | N12: scaled sq. error | O12: source quote
A13: 0 | B13: =INDEX(FleetByAge!$C$6:$T$51,MATCH($A13,FleetByAge!$A$6:$A$51,0),MATCH(2024,FleetByAge!$C$4:$T$4,0)) | C13: =IF($A13=0,$B$9,1)*EXP(-$B$4*MAX($A13-$B$10,0)) | D13: =$B$5+($B$6-$B$5)/(1+EXP(-($A13-$B$7)/$B$8)) | E13: =B13*C13 | F13: =E13*D13 | G13: =E13-F13 | I13: tlf | J13: Total-loss frequency | K13: =SUM($F$13:$F$58)/SUM($E$13:$E$58) | L13: =Data_CCC_Targets!$E$5 | M13: =Data_CCC_Targets!$F$5 | N13: =((K13-L13)/M13)^2 | O13: =Data_CCC_Targets!$G$5
A14: 1 | B14: =INDEX(FleetByAge!$C$6:$T$51,MATCH($A14,FleetByAge!$A$6:$A$51,0),MATCH(2024,FleetByAge!$C$4:$T$4,0)) | C14: =IF($A14=0,$B$9,1)*EXP(-$B$4*MAX($A14-$B$10,0)) | D14: =$B$5+($B$6-$B$5)/(1+EXP(-($A14-$B$7)/$B$8)) | E14: =B14*C14 | F14: =E14*D14 | G14: =E14-F14 | I14: tl7 | J14: Total losses from vehicles 7+ | K14: =SUMIF($A$13:$A$58,">=7",$F$13:$F$58)/SUM($F$13:$F$58) | L14: =Data_CCC_Targets!$E$6 | M14: =Data_CCC_Targets!$F$6 | N14: =((K14-L14)/M14)^2 | O14: =Data_CCC_Targets!$G$6
A15: 2 | B15: =INDEX(FleetByAge!$C$6:$T$51,MATCH($A15,FleetByAge!$A$6:$A$51,0),MATCH(2024,FleetByAge!$C$4:$T$4,0)) | C15: =IF($A15=0,$B$9,1)*EXP(-$B$4*MAX($A15-$B$10,0)) | D15: =$B$5+($B$6-$B$5)/(1+EXP(-($A15-$B$7)/$B$8)) | E15: =B15*C15 | F15: =E15*D15 | G15: =E15-F15 | I15: rp7 | J15: Repairables from vehicles 7+ | K15: =SUMIF($A$13:$A$58,">=7",$G$13:$G$58)/SUM($G$13:$G$58) | L15: =Data_CCC_Targets!$E$7 | M15: =Data_CCC_Targets!$F$7 | N15: =((K15-L15)/M15)^2 | O15: =Data_CCC_Targets!$G$7
A16: 3 | B16: =INDEX(FleetByAge!$C$6:$T$51,MATCH($A16,FleetByAge!$A$6:$A$51,0),MATCH(2024,FleetByAge!$C$4:$T$4,0)) | C16: =IF($A16=0,$B$9,1)*EXP(-$B$4*MAX($A16-$B$10,0)) | D16: =$B$5+($B$6-$B$5)/(1+EXP(-($A16-$B$7)/$B$8)) | E16: =B16*C16 | F16: =E16*D16 | G16: =E16-F16 | I16: rp3 | J16: Repairables from vehicles ≤3 | K16: =SUMIF($A$13:$A$58,"<=3",$G$13:$G$58)/SUM($G$13:$G$58) | L16: =Data_CCC_Targets!$E$8 | M16: =Data_CCC_Targets!$F$8 | N16: =((K16-L16)/M16)^2 | O16: =Data_CCC_Targets!$G$8
A17: 4 | B17: =INDEX(FleetByAge!$C$6:$T$51,MATCH($A17,FleetByAge!$A$6:$A$51,0),MATCH(2024,FleetByAge!$C$4:$T$4,0)) | C17: =IF($A17=0,$B$9,1)*EXP(-$B$4*MAX($A17-$B$10,0)) | D17: =$B$5+($B$6-$B$5)/(1+EXP(-($A17-$B$7)/$B$8)) | E17: =B17*C17 | F17: =E17*D17 | G17: =E17-F17 | I17: age_cl | J17: Average age, claim vehicles | K17: =SUMPRODUCT($A$13:$A$58,$E$13:$E$58)/SUM($E$13:$E$58) | L17: =Data_CCC_Targets!$E$9 | M17: =Data_CCC_Targets!$F$9 | N17: =((K17-L17)/M17)^2 | O17: =Data_CCC_Targets!$G$9
A18: 5 | B18: =INDEX(FleetByAge!$C$6:$T$51,MATCH($A18,FleetByAge!$A$6:$A$51,0),MATCH(2024,FleetByAge!$C$4:$T$4,0)) | C18: =IF($A18=0,$B$9,1)*EXP(-$B$4*MAX($A18-$B$10,0)) | D18: =$B$5+($B$6-$B$5)/(1+EXP(-($A18-$B$7)/$B$8)) | E18: =B18*C18 | F18: =E18*D18 | G18: =E18-F18 | I18: age_rp | J18: Average age, repairables | K18: =SUMPRODUCT($A$13:$A$58,$G$13:$G$58)/SUM($G$13:$G$58) | L18: =Data_CCC_Targets!$E$10 | M18: =Data_CCC_Targets!$F$10 | N18: =((K18-L18)/M18)^2 | O18: =Data_CCC_Targets!$G$10
A19: 6 | B19: =INDEX(FleetByAge!$C$6:$T$51,MATCH($A19,FleetByAge!$A$6:$A$51,0),MATCH(2024,FleetByAge!$C$4:$T$4,0)) | C19: =IF($A19=0,$B$9,1)*EXP(-$B$4*MAX($A19-$B$10,0)) | D19: =$B$5+($B$6-$B$5)/(1+EXP(-($A19-$B$7)/$B$8)) | E19: =B19*C19 | F19: =E19*D19 | G19: =E19-F19 | I19: age_tl | J19: Average age, total losses | K19: =SUMPRODUCT($A$13:$A$58,$F$13:$F$58)/SUM($F$13:$F$58) | L19: =Data_CCC_Targets!$E$11 | M19: =Data_CCC_Targets!$F$11 | N19: =((K19-L19)/M19)^2 | O19: =Data_CCC_Targets!$G$11
A20: 7 | B20: =INDEX(FleetByAge!$C$6:$T$51,MATCH($A20,FleetByAge!$A$6:$A$51,0),MATCH(2024,FleetByAge!$C$4:$T$4,0)) | C20: =IF($A20=0,$B$9,1)*EXP(-$B$4*MAX($A20-$B$10,0)) | D20: =$B$5+($B$6-$B$5)/(1+EXP(-($A20-$B$7)/$B$8)) | E20: =B20*C20 | F20: =E20*D20 | G20: =E20-F20 | I20: p03 | J20: Total-loss rate, vehicles ≤3 | K20: =SUMIF($A$13:$A$58,"<=3",$F$13:$F$58)/SUMIF($A$13:$A$58,"<=3",$E$13:$E$58) | L20: =Data_CCC_Targets!$E$12 | M20: =Data_CCC_Targets!$F$12 | N20: =((K20-L20)/M20)^2 | O20: =Data_CCC_Targets!$G$12
A21: 8 | B21: =INDEX(FleetByAge!$C$6:$T$51,MATCH($A21,FleetByAge!$A$6:$A$51,0),MATCH(2024,FleetByAge!$C$4:$T$4,0)) | C21: =IF($A21=0,$B$9,1)*EXP(-$B$4*MAX($A21-$B$10,0)) | D21: =$B$5+($B$6-$B$5)/(1+EXP(-($A21-$B$7)/$B$8)) | E21: =B21*C21 | F21: =E21*D21 | G21: =E21-F21
A22: 9 | B22: =INDEX(FleetByAge!$C$6:$T$51,MATCH($A22,FleetByAge!$A$6:$A$51,0),MATCH(2024,FleetByAge!$C$4:$T$4,0)) | C22: =IF($A22=0,$B$9,1)*EXP(-$B$4*MAX($A22-$B$10,0)) | D22: =$B$5+($B$6-$B$5)/(1+EXP(-($A22-$B$7)/$B$8)) | E22: =B22*C22 | F22: =E22*D22 | G22: =E22-F22 | J22: LOSS (Solver objective → minimise) | N22: =SUM(N13:N20)
A23: 10 | B23: =INDEX(FleetByAge!$C$6:$T$51,MATCH($A23,FleetByAge!$A$6:$A$51,0),MATCH(2024,FleetByAge!$C$4:$T$4,0)) | C23: =IF($A23=0,$B$9,1)*EXP(-$B$4*MAX($A23-$B$10,0)) | D23: =$B$5+($B$6-$B$5)/(1+EXP(-($A23-$B$7)/$B$8)) | E23: =B23*C23 | F23: =E23*D23 | G23: =E23-F23 | J23: Reference: the Python fit (scripts/age_curves.py) lands at ~1.0. One unit = one statistic off by exactly its tolerance.
A24: 11 | B24: =INDEX(FleetByAge!$C$6:$T$51,MATCH($A24,FleetByAge!$A$6:$A$51,0),MATCH(2024,FleetByAge!$C$4:$T$4,0)) | C24: =IF($A24=0,$B$9,1)*EXP(-$B$4*MAX($A24-$B$10,0)) | D24: =$B$5+($B$6-$B$5)/(1+EXP(-($A24-$B$7)/$B$8)) | E24: =B24*C24 | F24: =E24*D24 | G24: =E24-F24
A25: 12 | B25: =INDEX(FleetByAge!$C$6:$T$51,MATCH($A25,FleetByAge!$A$6:$A$51,0),MATCH(2024,FleetByAge!$C$4:$T$4,0)) | C25: =IF($A25=0,$B$9,1)*EXP(-$B$4*MAX($A25-$B$10,0)) | D25: =$B$5+($B$6-$B$5)/(1+EXP(-($A25-$B$7)/$B$8)) | E25: =B25*C25 | F25: =E25*D25 | G25: =E25-F25 | I25: SOLVER SET-UP (Excel → Data → Solver; on Mac enable once via Tools → Excel Add-ins → Solver):
A26: 13 | B26: =INDEX(FleetByAge!$C$6:$T$51,MATCH($A26,FleetByAge!$A$6:$A$51,0),MATCH(2024,FleetByAge!$C$4:$T$4,0)) | C26: =IF($A26=0,$B$9,1)*EXP(-$B$4*MAX($A26-$B$10,0)) | D26: =$B$5+($B$6-$B$5)/(1+EXP(-($A26-$B$7)/$B$8)) | E26: =B26*C26 | F26: =E26*D26 | G26: =E26-F26 | I26: 1. Set Objective: $N$22, To: Min.
A27: 14 | B27: =INDEX(FleetByAge!$C$6:$T$51,MATCH($A27,FleetByAge!$A$6:$A$51,0),MATCH(2024,FleetByAge!$C$4:$T$4,0)) | C27: =IF($A27=0,$B$9,1)*EXP(-$B$4*MAX($A27-$B$10,0)) | D27: =$B$5+($B$6-$B$5)/(1+EXP(-($A27-$B$7)/$B$8)) | E27: =B27*C27 | F27: =E27*D27 | G27: =E27-F27 | I27: 2. By Changing Variable Cells: $B$4:$B$8.
A28: 15 | B28: =INDEX(FleetByAge!$C$6:$T$51,MATCH($A28,FleetByAge!$A$6:$A$51,0),MATCH(2024,FleetByAge!$C$4:$T$4,0)) | C28: =IF($A28=0,$B$9,1)*EXP(-$B$4*MAX($A28-$B$10,0)) | D28: =$B$5+($B$6-$B$5)/(1+EXP(-($A28-$B$7)/$B$8)) | E28: =B28*C28 | F28: =E28*D28 | G28: =E28-F28 | I28: 3. Constraints: B4 ≥ 0; B4 ≤ 0.5; B5 ≥ 0.01; B5 ≤ 0.3; B6 ≥ 0.3; B6 ≤ 0.95; B6 ≥ B5; B7 ≥ 0; B7 ≤ 30; B8 ≥ 0.3; B8 ≤ 12.
A29: 16 | B29: =INDEX(FleetByAge!$C$6:$T$51,MATCH($A29,FleetByAge!$A$6:$A$51,0),MATCH(2024,FleetByAge!$C$4:$T$4,0)) | C29: =IF($A29=0,$B$9,1)*EXP(-$B$4*MAX($A29-$B$10,0)) | D29: =$B$5+($B$6-$B$5)/(1+EXP(-($A29-$B$7)/$B$8)) | E29: =B29*C29 | F29: =E29*D29 | G29: =E29-F29 | I29: 4. Method: GRG Nonlinear. Options → GRG Nonlinear tab: tick Use Multistart, Population Size 100, Random Seed 7, tick Require Bounds on Variables. Untick 'Make Unconstrained Variables Non-Negative' (bounds are set explicitly).
A30: 17 | B30: =INDEX(FleetByAge!$C$6:$T$51,MATCH($A30,FleetByAge!$A$6:$A$51,0),MATCH(2024,FleetByAge!$C$4:$T$4,0)) | C30: =IF($A30=0,$B$9,1)*EXP(-$B$4*MAX($A30-$B$10,0)) | D30: =$B$5+($B$6-$B$5)/(1+EXP(-($A30-$B$7)/$B$8)) | E30: =B30*C30 | F30: =E30*D30 | G30: =E30-F30 | I30: 5. Solve. Expect LOSS ≈ 1.0 and B4:B8 within a few thousandths of the starting values. Copy B4:B8 → Inputs!B11:B15 (paste values).
A31: 18 | B31: =INDEX(FleetByAge!$C$6:$T$51,MATCH($A31,FleetByAge!$A$6:$A$51,0),MATCH(2024,FleetByAge!$C$4:$T$4,0)) | C31: =IF($A31=0,$B$9,1)*EXP(-$B$4*MAX($A31-$B$10,0)) | D31: =$B$5+($B$6-$B$5)/(1+EXP(-($A31-$B$7)/$B$8)) | E31: =B31*C31 | F31: =E31*D31 | G31: =E31-F31 | I31: What this does in words: turn the five knobs until the model's eight 2024 statistics match CCC's published ones. Multistart = try from many random starting points so Solver does not settle in a shallow dip.
A32: 19 | B32: =INDEX(FleetByAge!$C$6:$T$51,MATCH($A32,FleetByAge!$A$6:$A$51,0),MATCH(2024,FleetByAge!$C$4:$T$4,0)) | C32: =IF($A32=0,$B$9,1)*EXP(-$B$4*MAX($A32-$B$10,0)) | D32: =$B$5+($B$6-$B$5)/(1+EXP(-($A32-$B$7)/$B$8)) | E32: =B32*C32 | F32: =E32*D32 | G32: =E32-F32
A33: 20 | B33: =INDEX(FleetByAge!$C$6:$T$51,MATCH($A33,FleetByAge!$A$6:$A$51,0),MATCH(2024,FleetByAge!$C$4:$T$4,0)) | C33: =IF($A33=0,$B$9,1)*EXP(-$B$4*MAX($A33-$B$10,0)) | D33: =$B$5+($B$6-$B$5)/(1+EXP(-($A33-$B$7)/$B$8)) | E33: =B33*C33 | F33: =E33*D33 | G33: =E33-F33
A34: 21 | B34: =INDEX(FleetByAge!$C$6:$T$51,MATCH($A34,FleetByAge!$A$6:$A$51,0),MATCH(2024,FleetByAge!$C$4:$T$4,0)) | C34: =IF($A34=0,$B$9,1)*EXP(-$B$4*MAX($A34-$B$10,0)) | D34: =$B$5+($B$6-$B$5)/(1+EXP(-($A34-$B$7)/$B$8)) | E34: =B34*C34 | F34: =E34*D34 | G34: =E34-F34
A35: 22 | B35: =INDEX(FleetByAge!$C$6:$T$51,MATCH($A35,FleetByAge!$A$6:$A$51,0),MATCH(2024,FleetByAge!$C$4:$T$4,0)) | C35: =IF($A35=0,$B$9,1)*EXP(-$B$4*MAX($A35-$B$10,0)) | D35: =$B$5+($B$6-$B$5)/(1+EXP(-($A35-$B$7)/$B$8)) | E35: =B35*C35 | F35: =E35*D35 | G35: =E35-F35
A36: 23 | B36: =INDEX(FleetByAge!$C$6:$T$51,MATCH($A36,FleetByAge!$A$6:$A$51,0),MATCH(2024,FleetByAge!$C$4:$T$4,0)) | C36: =IF($A36=0,$B$9,1)*EXP(-$B$4*MAX($A36-$B$10,0)) | D36: =$B$5+($B$6-$B$5)/(1+EXP(-($A36-$B$7)/$B$8)) | E36: =B36*C36 | F36: =E36*D36 | G36: =E36-F36
A37: 24 | B37: =INDEX(FleetByAge!$C$6:$T$51,MATCH($A37,FleetByAge!$A$6:$A$51,0),MATCH(2024,FleetByAge!$C$4:$T$4,0)) | C37: =IF($A37=0,$B$9,1)*EXP(-$B$4*MAX($A37-$B$10,0)) | D37: =$B$5+($B$6-$B$5)/(1+EXP(-($A37-$B$7)/$B$8)) | E37: =B37*C37 | F37: =E37*D37 | G37: =E37-F37
A38: 25 | B38: =INDEX(FleetByAge!$C$6:$T$51,MATCH($A38,FleetByAge!$A$6:$A$51,0),MATCH(2024,FleetByAge!$C$4:$T$4,0)) | C38: =IF($A38=0,$B$9,1)*EXP(-$B$4*MAX($A38-$B$10,0)) | D38: =$B$5+($B$6-$B$5)/(1+EXP(-($A38-$B$7)/$B$8)) | E38: =B38*C38 | F38: =E38*D38 | G38: =E38-F38
A39: 26 | B39: =INDEX(FleetByAge!$C$6:$T$51,MATCH($A39,FleetByAge!$A$6:$A$51,0),MATCH(2024,FleetByAge!$C$4:$T$4,0)) | C39: =IF($A39=0,$B$9,1)*EXP(-$B$4*MAX($A39-$B$10,0)) | D39: =$B$5+($B$6-$B$5)/(1+EXP(-($A39-$B$7)/$B$8)) | E39: =B39*C39 | F39: =E39*D39 | G39: =E39-F39
A40: 27 | B40: =INDEX(FleetByAge!$C$6:$T$51,MATCH($A40,FleetByAge!$A$6:$A$51,0),MATCH(2024,FleetByAge!$C$4:$T$4,0)) | C40: =IF($A40=0,$B$9,1)*EXP(-$B$4*MAX($A40-$B$10,0)) | D40: =$B$5+($B$6-$B$5)/(1+EXP(-($A40-$B$7)/$B$8)) | E40: =B40*C40 | F40: =E40*D40 | G40: =E40-F40
A41: 28 | B41: =INDEX(FleetByAge!$C$6:$T$51,MATCH($A41,FleetByAge!$A$6:$A$51,0),MATCH(2024,FleetByAge!$C$4:$T$4,0)) | C41: =IF($A41=0,$B$9,1)*EXP(-$B$4*MAX($A41-$B$10,0)) | D41: =$B$5+($B$6-$B$5)/(1+EXP(-($A41-$B$7)/$B$8)) | E41: =B41*C41 | F41: =E41*D41 | G41: =E41-F41
A42: 29 | B42: =INDEX(FleetByAge!$C$6:$T$51,MATCH($A42,FleetByAge!$A$6:$A$51,0),MATCH(2024,FleetByAge!$C$4:$T$4,0)) | C42: =IF($A42=0,$B$9,1)*EXP(-$B$4*MAX($A42-$B$10,0)) | D42: =$B$5+($B$6-$B$5)/(1+EXP(-($A42-$B$7)/$B$8)) | E42: =B42*C42 | F42: =E42*D42 | G42: =E42-F42
A43: 30 | B43: =INDEX(FleetByAge!$C$6:$T$51,MATCH($A43,FleetByAge!$A$6:$A$51,0),MATCH(2024,FleetByAge!$C$4:$T$4,0)) | C43: =IF($A43=0,$B$9,1)*EXP(-$B$4*MAX($A43-$B$10,0)) | D43: =$B$5+($B$6-$B$5)/(1+EXP(-($A43-$B$7)/$B$8)) | E43: =B43*C43 | F43: =E43*D43 | G43: =E43-F43
... A58: 45 | B58: =INDEX(FleetByAge!$C$6:$T$51,MATCH($A58,FleetByAge!$A$6:$A$51,0),MATCH(2024,FleetByAge!$C$4:$T$4,0)) | C58: =IF($A58=0,$B$9,1)*EXP(-$B$4*MAX($A58-$B$10,0)) | D58: =$B$5+($B$6-$B$5)/(1+EXP(-($A58-$B$7)/$B$8)) | E58: =B58*C58 | F58: =E58*D58 | G58: =E58-F58

Sheet TLF_Roll
A1: Baseline total-loss frequency from demographics alone, by year — and the out-of-sample tests
A2: claims index = Σ_a fleet(a,t)·R(a); TL index = Σ_a fleet(a,t)·R(a)·P(a); baseline TLF = TL/claims. R and P are FROZEN (Inputs); only the fleet changes year to year. The YoY drift row is the demographic contribution to TLF; everything else in actual TLF is level (spread cycle, technology, filing).
A4: Year → | C4: =Inputs!C23 | D4: =Inputs!D23 | E4: =Inputs!E23 | F4: =Inputs!F23 | G4: =Inputs!G23 | H4: =Inputs!H23 | I4: =Inputs!I23 | J4: =Inputs!J23 | ... T4: =Inputs!T23
A6: Claims index Σ fleet·R (thousands) | C6: =SUMPRODUCT(FleetByAge!C$6:C$51,Curves!$B$6:$B$51) | D6: =SUMPRODUCT(FleetByAge!D$6:D$51,Curves!$B$6:$B$51) | E6: =SUMPRODUCT(FleetByAge!E$6:E$51,Curves!$B$6:$B$51) | F6: =SUMPRODUCT(FleetByAge!F$6:F$51,Curves!$B$6:$B$51) | G6: =SUMPRODUCT(FleetByAge!G$6:G$51,Curves!$B$6:$B$51) | H6: =SUMPRODUCT(FleetByAge!H$6:H$51,Curves!$B$6:$B$51) | I6: =SUMPRODUCT(FleetByAge!I$6:I$51,Curves!$B$6:$B$51) | J6: =SUMPRODUCT(FleetByAge!J$6:J$51,Curves!$B$6:$B$51) | ... T6: =SUMPRODUCT(FleetByAge!T$6:T$51,Curves!$B$6:$B$51)
A7: Total-loss index Σ fleet·R·P (thousands) | C7: =SUMPRODUCT(FleetByAge!C$6:C$51,Curves!$B$6:$B$51,Curves!$C$6:$C$51) | D7: =SUMPRODUCT(FleetByAge!D$6:D$51,Curves!$B$6:$B$51,Curves!$C$6:$C$51) | E7: =SUMPRODUCT(FleetByAge!E$6:E$51,Curves!$B$6:$B$51,Curves!$C$6:$C$51) | F7: =SUMPRODUCT(FleetByAge!F$6:F$51,Curves!$B$6:$B$51,Curves!$C$6:$C$51) | G7: =SUMPRODUCT(FleetByAge!G$6:G$51,Curves!$B$6:$B$51,Curves!$C$6:$C$51) | H7: =SUMPRODUCT(FleetByAge!H$6:H$51,Curves!$B$6:$B$51,Curves!$C$6:$C$51) | I7: =SUMPRODUCT(FleetByAge!I$6:I$51,Curves!$B$6:$B$51,Curves!$C$6:$C$51) | J7: =SUMPRODUCT(FleetByAge!J$6:J$51,Curves!$B$6:$B$51,Curves!$C$6:$C$51) | ... T7: =SUMPRODUCT(FleetByAge!T$6:T$51,Curves!$B$6:$B$51,Curves!$C$6:$C$51)
A8: Baseline TLF (demographics only) | C8: =C7/C6 | D8: =D7/D6 | E8: =E7/E6 | F8: =F7/F6 | G8: =G7/G6 | H8: =H7/H6 | I8: =I7/I6 | J8: =J7/J6 | ... T8: =T7/T6
A9: YoY change in baseline TLF (pp) | D9: =(D8-C8)*100 | E9: =(E8-D8)*100 | F9: =(F8-E8)*100 | G9: =(G8-F8)*100 | H9: =(H8-G8)*100 | I9: =(I8-H8)*100 | J9: =(J8-I8)*100 | K9: =(K8-J8)*100 | ... T9: =(T8-S8)*100
A10: Claims share, vehicles 7+ | C10: =SUMPRODUCT(FleetByAge!C$6:C$51,Curves!$B$6:$B$51,Curves!$F$6:$F$51)/C6 | D10: =SUMPRODUCT(FleetByAge!D$6:D$51,Curves!$B$6:$B$51,Curves!$F$6:$F$51)/D6 | E10: =SUMPRODUCT(FleetByAge!E$6:E$51,Curves!$B$6:$B$51,Curves!$F$6:$F$51)/E6 | F10: =SUMPRODUCT(FleetByAge!F$6:F$51,Curves!$B$6:$B$51,Curves!$F$6:$F$51)/F6 | G10: =SUMPRODUCT(FleetByAge!G$6:G$51,Curves!$B$6:$B$51,Curves!$F$6:$F$51)/G6 | H10: =SUMPRODUCT(FleetByAge!H$6:H$51,Curves!$B$6:$B$51,Curves!$F$6:$F$51)/H6 | I10: =SUMPRODUCT(FleetByAge!I$6:I$51,Curves!$B$6:$B$51,Curves!$F$6:$F$51)/I6 | J10: =SUMPRODUCT(FleetByAge!J$6:J$51,Curves!$B$6:$B$51,Curves!$F$6:$F$51)/J6 | ... T10: =SUMPRODUCT(FleetByAge!T$6:T$51,Curves!$B$6:$B$51,Curves!$F$6:$F$51)/T6
A11: Total-loss share, vehicles 7+ | C11: =SUMPRODUCT(FleetByAge!C$6:C$51,Curves!$B$6:$B$51,Curves!$C$6:$C$51,Curves!$F$6:$F$51)/C7 | D11: =SUMPRODUCT(FleetByAge!D$6:D$51,Curves!$B$6:$B$51,Curves!$C$6:$C$51,Curves!$F$6:$F$51)/D7 | E11: =SUMPRODUCT(FleetByAge!E$6:E$51,Curves!$B$6:$B$51,Curves!$C$6:$C$51,Curves!$F$6:$F$51)/E7 | F11: =SUMPRODUCT(FleetByAge!F$6:F$51,Curves!$B$6:$B$51,Curves!$C$6:$C$51,Curves!$F$6:$F$51)/F7 | G11: =SUMPRODUCT(FleetByAge!G$6:G$51,Curves!$B$6:$B$51,Curves!$C$6:$C$51,Curves!$F$6:$F$51)/G7 | H11: =SUMPRODUCT(FleetByAge!H$6:H$51,Curves!$B$6:$B$51,Curves!$C$6:$C$51,Curves!$F$6:$F$51)/H7 | I11: =SUMPRODUCT(FleetByAge!I$6:I$51,Curves!$B$6:$B$51,Curves!$C$6:$C$51,Curves!$F$6:$F$51)/I7 | J11: =SUMPRODUCT(FleetByAge!J$6:J$51,Curves!$B$6:$B$51,Curves!$C$6:$C$51,Curves!$F$6:$F$51)/J7 | ... T11: =SUMPRODUCT(FleetByAge!T$6:T$51,Curves!$B$6:$B$51,Curves!$C$6:$C$51,Curves!$F$6:$F$51)/T7
A12: Repairable share, vehicles 7+ | C12: =(SUMPRODUCT(FleetByAge!C$6:C$51,Curves!$B$6:$B$51,Curves!$F$6:$F$51)-SUMPRODUCT(FleetByAge!C$6:C$51,Curves!$B$6:$B$51,Curves!$C$6:$C$51,Curves!$F$6:$F$51))/(C6-C7) | D12: =(SUMPRODUCT(FleetByAge!D$6:D$51,Curves!$B$6:$B$51,Curves!$F$6:$F$51)-SUMPRODUCT(FleetByAge!D$6:D$51,Curves!$B$6:$B$51,Curves!$C$6:$C$51,Curves!$F$6:$F$51))/(D6-D7) | E12: =(SUMPRODUCT(FleetByAge!E$6:E$51,Curves!$B$6:$B$51,Curves!$F$6:$F$51)-SUMPRODUCT(FleetByAge!E$6:E$51,Curves!$B$6:$B$51,Curves!$C$6:$C$51,Curves!$F$6:$F$51))/(E6-E7) | F12: =(SUMPRODUCT(FleetByAge!F$6:F$51,Curves!$B$6:$B$51,Curves!$F$6:$F$51)-SUMPRODUCT(FleetByAge!F$6:F$51,Curves!$B$6:$B$51,Curves!$C$6:$C$51,Curves!$F$6:$F$51))/(F6-F7) | G12: =(SUMPRODUCT(FleetByAge!G$6:G$51,Curves!$B$6:$B$51,Curves!$F$6:$F$51)-SUMPRODUCT(FleetByAge!G$6:G$51,Curves!$B$6:$B$51,Curves!$C$6:$C$51,Curves!$F$6:$F$51))/(G6-G7) | H12: =(SUMPRODUCT(FleetByAge!H$6:H$51,Curves!$B$6:$B$51,Curves!$F$6:$F$51)-SUMPRODUCT(FleetByAge!H$6:H$51,Curves!$B$6:$B$51,Curves!$C$6:$C$51,Curves!$F$6:$F$51))/(H6-H7) | I12: =(SUMPRODUCT(FleetByAge!I$6:I$51,Curves!$B$6:$B$51,Curves!$F$6:$F$51)-SUMPRODUCT(FleetByAge!I$6:I$51,Curves!$B$6:$B$51,Curves!$C$6:$C$51,Curves!$F$6:$F$51))/(I6-I7) | J12: =(SUMPRODUCT(FleetByAge!J$6:J$51,Curves!$B$6:$B$51,Curves!$F$6:$F$51)-SUMPRODUCT(FleetByAge!J$6:J$51,Curves!$B$6:$B$51,Curves!$C$6:$C$51,Curves!$F$6:$F$51))/(J6-J7) | ... T12: =(SUMPRODUCT(FleetByAge!T$6:T$51,Curves!$B$6:$B$51,Curves!$F$6:$F$51)-SUMPRODUCT(FleetByAge!T$6:T$51,Curves!$B$6:$B$51,Curves!$C$6:$C$51,Curves!$F$6:$F$51))/(T6-T7)
A13: Repairable share, vehicles ≤3 | C13: =(SUMPRODUCT(FleetByAge!C$6:C$51,Curves!$B$6:$B$51,Curves!$G$6:$G$51)-SUMPRODUCT(FleetByAge!C$6:C$51,Curves!$B$6:$B$51,Curves!$C$6:$C$51,Curves!$G$6:$G$51))/(C6-C7) | D13: =(SUMPRODUCT(FleetByAge!D$6:D$51,Curves!$B$6:$B$51,Curves!$G$6:$G$51)-SUMPRODUCT(FleetByAge!D$6:D$51,Curves!$B$6:$B$51,Curves!$C$6:$C$51,Curves!$G$6:$G$51))/(D6-D7) | E13: =(SUMPRODUCT(FleetByAge!E$6:E$51,Curves!$B$6:$B$51,Curves!$G$6:$G$51)-SUMPRODUCT(FleetByAge!E$6:E$51,Curves!$B$6:$B$51,Curves!$C$6:$C$51,Curves!$G$6:$G$51))/(E6-E7) | F13: =(SUMPRODUCT(FleetByAge!F$6:F$51,Curves!$B$6:$B$51,Curves!$G$6:$G$51)-SUMPRODUCT(FleetByAge!F$6:F$51,Curves!$B$6:$B$51,Curves!$C$6:$C$51,Curves!$G$6:$G$51))/(F6-F7) | G13: =(SUMPRODUCT(FleetByAge!G$6:G$51,Curves!$B$6:$B$51,Curves!$G$6:$G$51)-SUMPRODUCT(FleetByAge!G$6:G$51,Curves!$B$6:$B$51,Curves!$C$6:$C$51,Curves!$G$6:$G$51))/(G6-G7) | H13: =(SUMPRODUCT(FleetByAge!H$6:H$51,Curves!$B$6:$B$51,Curves!$G$6:$G$51)-SUMPRODUCT(FleetByAge!H$6:H$51,Curves!$B$6:$B$51,Curves!$C$6:$C$51,Curves!$G$6:$G$51))/(H6-H7) | I13: =(SUMPRODUCT(FleetByAge!I$6:I$51,Curves!$B$6:$B$51,Curves!$G$6:$G$51)-SUMPRODUCT(FleetByAge!I$6:I$51,Curves!$B$6:$B$51,Curves!$C$6:$C$51,Curves!$G$6:$G$51))/(I6-I7) | J13: =(SUMPRODUCT(FleetByAge!J$6:J$51,Curves!$B$6:$B$51,Curves!$G$6:$G$51)-SUMPRODUCT(FleetByAge!J$6:J$51,Curves!$B$6:$B$51,Curves!$C$6:$C$51,Curves!$G$6:$G$51))/(J6-J7) | ... T13: =(SUMPRODUCT(FleetByAge!T$6:T$51,Curves!$B$6:$B$51,Curves!$G$6:$G$51)-SUMPRODUCT(FleetByAge!T$6:T$51,Curves!$B$6:$B$51,Curves!$C$6:$C$51,Curves!$G$6:$G$51))/(T6-T7)
A14: Average age, claim vehicles | C14: =SUMPRODUCT(FleetByAge!C$6:C$51,Curves!$B$6:$B$51,Curves!$A$6:$A$51)/C6 | D14: =SUMPRODUCT(FleetByAge!D$6:D$51,Curves!$B$6:$B$51,Curves!$A$6:$A$51)/D6 | E14: =SUMPRODUCT(FleetByAge!E$6:E$51,Curves!$B$6:$B$51,Curves!$A$6:$A$51)/E6 | F14: =SUMPRODUCT(FleetByAge!F$6:F$51,Curves!$B$6:$B$51,Curves!$A$6:$A$51)/F6 | G14: =SUMPRODUCT(FleetByAge!G$6:G$51,Curves!$B$6:$B$51,Curves!$A$6:$A$51)/G6 | H14: =SUMPRODUCT(FleetByAge!H$6:H$51,Curves!$B$6:$B$51,Curves!$A$6:$A$51)/H6 | I14: =SUMPRODUCT(FleetByAge!I$6:I$51,Curves!$B$6:$B$51,Curves!$A$6:$A$51)/I6 | J14: =SUMPRODUCT(FleetByAge!J$6:J$51,Curves!$B$6:$B$51,Curves!$A$6:$A$51)/J6 | ... T14: =SUMPRODUCT(FleetByAge!T$6:T$51,Curves!$B$6:$B$51,Curves!$A$6:$A$51)/T6
A15: Average age, total losses | C15: =SUMPRODUCT(FleetByAge!C$6:C$51,Curves!$B$6:$B$51,Curves!$C$6:$C$51,Curves!$A$6:$A$51)/C7 | D15: =SUMPRODUCT(FleetByAge!D$6:D$51,Curves!$B$6:$B$51,Curves!$C$6:$C$51,Curves!$A$6:$A$51)/D7 | E15: =SUMPRODUCT(FleetByAge!E$6:E$51,Curves!$B$6:$B$51,Curves!$C$6:$C$51,Curves!$A$6:$A$51)/E7 | F15: =SUMPRODUCT(FleetByAge!F$6:F$51,Curves!$B$6:$B$51,Curves!$C$6:$C$51,Curves!$A$6:$A$51)/F7 | G15: =SUMPRODUCT(FleetByAge!G$6:G$51,Curves!$B$6:$B$51,Curves!$C$6:$C$51,Curves!$A$6:$A$51)/G7 | H15: =SUMPRODUCT(FleetByAge!H$6:H$51,Curves!$B$6:$B$51,Curves!$C$6:$C$51,Curves!$A$6:$A$51)/H7 | I15: =SUMPRODUCT(FleetByAge!I$6:I$51,Curves!$B$6:$B$51,Curves!$C$6:$C$51,Curves!$A$6:$A$51)/I7 | J15: =SUMPRODUCT(FleetByAge!J$6:J$51,Curves!$B$6:$B$51,Curves!$C$6:$C$51,Curves!$A$6:$A$51)/J7 | ... T15: =SUMPRODUCT(FleetByAge!T$6:T$51,Curves!$B$6:$B$51,Curves!$C$6:$C$51,Curves!$A$6:$A$51)/T7
A16: Average age, repairables | C16: =(SUMPRODUCT(FleetByAge!C$6:C$51,Curves!$B$6:$B$51,Curves!$A$6:$A$51)-SUMPRODUCT(FleetByAge!C$6:C$51,Curves!$B$6:$B$51,Curves!$C$6:$C$51,Curves!$A$6:$A$51))/(C6-C7) | D16: =(SUMPRODUCT(FleetByAge!D$6:D$51,Curves!$B$6:$B$51,Curves!$A$6:$A$51)-SUMPRODUCT(FleetByAge!D$6:D$51,Curves!$B$6:$B$51,Curves!$C$6:$C$51,Curves!$A$6:$A$51))/(D6-D7) | E16: =(SUMPRODUCT(FleetByAge!E$6:E$51,Curves!$B$6:$B$51,Curves!$A$6:$A$51)-SUMPRODUCT(FleetByAge!E$6:E$51,Curves!$B$6:$B$51,Curves!$C$6:$C$51,Curves!$A$6:$A$51))/(E6-E7) | F16: =(SUMPRODUCT(FleetByAge!F$6:F$51,Curves!$B$6:$B$51,Curves!$A$6:$A$51)-SUMPRODUCT(FleetByAge!F$6:F$51,Curves!$B$6:$B$51,Curves!$C$6:$C$51,Curves!$A$6:$A$51))/(F6-F7) | G16: =(SUMPRODUCT(FleetByAge!G$6:G$51,Curves!$B$6:$B$51,Curves!$A$6:$A$51)-SUMPRODUCT(FleetByAge!G$6:G$51,Curves!$B$6:$B$51,Curves!$C$6:$C$51,Curves!$A$6:$A$51))/(G6-G7) | H16: =(SUMPRODUCT(FleetByAge!H$6:H$51,Curves!$B$6:$B$51,Curves!$A$6:$A$51)-SUMPRODUCT(FleetByAge!H$6:H$51,Curves!$B$6:$B$51,Curves!$C$6:$C$51,Curves!$A$6:$A$51))/(H6-H7) | I16: =(SUMPRODUCT(FleetByAge!I$6:I$51,Curves!$B$6:$B$51,Curves!$A$6:$A$51)-SUMPRODUCT(FleetByAge!I$6:I$51,Curves!$B$6:$B$51,Curves!$C$6:$C$51,Curves!$A$6:$A$51))/(I6-I7) | J16: =(SUMPRODUCT(FleetByAge!J$6:J$51,Curves!$B$6:$B$51,Curves!$A$6:$A$51)-SUMPRODUCT(FleetByAge!J$6:J$51,Curves!$B$6:$B$51,Curves!$C$6:$C$51,Curves!$A$6:$A$51))/(J6-J7) | ... T16: =(SUMPRODUCT(FleetByAge!T$6:T$51,Curves!$B$6:$B$51,Curves!$A$6:$A$51)-SUMPRODUCT(FleetByAge!T$6:T$51,Curves!$B$6:$B$51,Curves!$C$6:$C$51,Curves!$A$6:$A$51))/(T6-T7)
A17: Total-loss rate, vehicles ≤3 | C17: =SUMPRODUCT(FleetByAge!C$6:C$51,Curves!$B$6:$B$51,Curves!$C$6:$C$51,Curves!$G$6:$G$51)/SUMPRODUCT(FleetByAge!C$6:C$51,Curves!$B$6:$B$51,Curves!$G$6:$G$51) | D17: =SUMPRODUCT(FleetByAge!D$6:D$51,Curves!$B$6:$B$51,Curves!$C$6:$C$51,Curves!$G$6:$G$51)/SUMPRODUCT(FleetByAge!D$6:D$51,Curves!$B$6:$B$51,Curves!$G$6:$G$51) | E17: =SUMPRODUCT(FleetByAge!E$6:E$51,Curves!$B$6:$B$51,Curves!$C$6:$C$51,Curves!$G$6:$G$51)/SUMPRODUCT(FleetByAge!E$6:E$51,Curves!$B$6:$B$51,Curves!$G$6:$G$51) | F17: =SUMPRODUCT(FleetByAge!F$6:F$51,Curves!$B$6:$B$51,Curves!$C$6:$C$51,Curves!$G$6:$G$51)/SUMPRODUCT(FleetByAge!F$6:F$51,Curves!$B$6:$B$51,Curves!$G$6:$G$51) | G17: =SUMPRODUCT(FleetByAge!G$6:G$51,Curves!$B$6:$B$51,Curves!$C$6:$C$51,Curves!$G$6:$G$51)/SUMPRODUCT(FleetByAge!G$6:G$51,Curves!$B$6:$B$51,Curves!$G$6:$G$51) | H17: =SUMPRODUCT(FleetByAge!H$6:H$51,Curves!$B$6:$B$51,Curves!$C$6:$C$51,Curves!$G$6:$G$51)/SUMPRODUCT(FleetByAge!H$6:H$51,Curves!$B$6:$B$51,Curves!$G$6:$G$51) | I17: =SUMPRODUCT(FleetByAge!I$6:I$51,Curves!$B$6:$B$51,Curves!$C$6:$C$51,Curves!$G$6:$G$51)/SUMPRODUCT(FleetByAge!I$6:I$51,Curves!$B$6:$B$51,Curves!$G$6:$G$51) | J17: =SUMPRODUCT(FleetByAge!J$6:J$51,Curves!$B$6:$B$51,Curves!$C$6:$C$51,Curves!$G$6:$G$51)/SUMPRODUCT(FleetByAge!J$6:J$51,Curves!$B$6:$B$51,Curves!$G$6:$G$51) | ... T17: =SUMPRODUCT(FleetByAge!T$6:T$51,Curves!$B$6:$B$51,Curves!$C$6:$C$51,Curves!$G$6:$G$51)/SUMPRODUCT(FleetByAge!T$6:T$51,Curves!$B$6:$B$51,Curves!$G$6:$G$51)
A18: VIO (M) — FleetByAge | C18: =FleetByAge!C53 | D18: =FleetByAge!D53 | E18: =FleetByAge!E53 | F18: =FleetByAge!F53 | G18: =FleetByAge!G53 | H18: =FleetByAge!H53 | I18: =FleetByAge!I53 | J18: =FleetByAge!J53 | ... T18: =FleetByAge!T53
A19: Fleet share aged 7+ — FleetByAge | C19: =FleetByAge!C54 | D19: =FleetByAge!D54 | E19: =FleetByAge!E54 | F19: =FleetByAge!F54 | G19: =FleetByAge!G54 | H19: =FleetByAge!H54 | I19: =FleetByAge!I54 | J19: =FleetByAge!J54 | ... T19: =FleetByAge!T54
A20: Average fleet age (t−MY+0.5) | C20: =FleetByAge!C57 | D20: =FleetByAge!D57 | E20: =FleetByAge!E57 | F20: =FleetByAge!F57 | G20: =FleetByAge!G57 | H20: =FleetByAge!H57 | I20: =FleetByAge!I57 | J20: =FleetByAge!J57 | ... T20: =FleetByAge!T57
A21: Total-loss index YoY % (demographic TL pool growth) | D21: =(D7/C7-1)*100 | E21: =(E7/D7-1)*100 | F21: =(F7/E7-1)*100 | G21: =(G7/F7-1)*100 | H21: =(H7/G7-1)*100 | I21: =(I7/H7-1)*100 | J21: =(J7/I7-1)*100 | K21: =(K7/J7-1)*100 | ... T21: =(T7/S7-1)*100
A24: Checks against CCC (R,P frozen at the 2024 fit — rows marked OOS were never used in the fit)
A25: use | B25: year | C25: statistic | D25: CCC actual | E25: model | F25: error | G25: quote
A26: FIT | B26: 2024 | C26: Total-loss frequency, all loss categories | D26: 0.223 | E26: =INDEX($C$8:$T$8,1,MATCH(B26,$C$4:$T$4,0)) | F26: =(E26-D26)*100 | G26: printed data label, chart "Total Loss Frequency Remains High as Vehicle Values Trend Up" (2024 = 22.3%)
A27: FIT | B27: 2024 | C27: Share of total-loss valuations on vehicles 7+ yrs | D27: 0.72 | E27: =INDEX($C$11:$T$11,1,MATCH(B27,$C$4:$T$4,0)) | F27: =(E27-D27)*100 | G27: almost 72% of valuations across all loss categories are for vehicles 7 years or older
A28: FIT | B28: 2024 | C28: Share of repairable claims on vehicles 7+ yrs | D28: 0.45 | E28: =INDEX($C$12:$T$12,1,MATCH(B28,$C$4:$T$4,0)) | F28: =(E28-D28)*100 | G28: vehicles seven years or older now make up nearly 45% of all repairable claims, up from 35% in 2019
A29: FIT | B29: 2024 | C29: Share of repairable claims on vehicles ≤3 yrs (all fuel) | D29: 0.3 | E29: =INDEX($C$13:$T$13,1,MATCH(B29,$C$4:$T$4,0)) | F29: =(E29-D29)*100 | G29: Only 26.3% of repairable ICE vehicles are three years or newer (EVs 79.4% / hybrids 60.3% ≤3 yrs → all-fuel ≈30%)
A30: FIT | B30: 2024 | C30: Average age of vehicles in claims (yrs) | D30: 7.6 | E30: =INDEX($C$14:$T$14,1,MATCH(B30,$C$4:$T$4,0)) | F30: =E30-D30 | G30: For claims, the average age of vehicles has increased to 7.6 years – up from 6.9 years in 2020
A31: FIT | B31: 2024 | C31: Average age of repairable vehicles (yrs) | D31: 6.8 | E31: =INDEX($C$16:$T$16,1,MATCH(B31,$C$4:$T$4,0)) | F31: =E31-D31 | G31: The average age of repairable vehicles was 6.8 years in 2024 (up from 6.1 years old in 2020)
A32: FIT | B32: 2024 | C32: Average age of total-loss vehicles (yrs) | D32: 10.6 | E32: =INDEX($C$15:$T$15,1,MATCH(B32,$C$4:$T$4,0)) | F32: =E32-D32 | G32: ... and 10.6 years for total loss vehicles (up from 10.0 years old in 2020)
A33: FIT | B33: 2024 | C33: Total-loss rate for claims on vehicles ≤3 yrs | D33: 0.1 | E33: =INDEX($C$17:$T$17,1,MATCH(B33,$C$4:$T$4,0)) | F33: =(E33-D33)*100 | G33: For claims that are three years old or newer, 1 in 10 are flagged as a total loss by the insurer
A34: OOS | B34: 2019 | C34: Share of repairable claims on vehicles 7+ yrs | D34: 0.35 | E34: =INDEX($C$12:$T$12,1,MATCH(B34,$C$4:$T$4,0)) | F34: =(E34-D34)*100 | G34: up from 35% in 2019
A35: OOS | B35: 2019 | C35: Share of repairable claims on vehicles ≤3 yrs | D35: 0.385 | E35: =INDEX($C$13:$T$13,1,MATCH(B35,$C$4:$T$4,0)) | F35: =(E35-D35)*100 | G35: vehicles 3 years or newer represented 38.5% of the repairable mix in 2019
A36: OOS | B36: 2020 | C36: Average age of vehicles in claims (yrs) | D36: 6.9 | E36: =INDEX($C$14:$T$14,1,MATCH(B36,$C$4:$T$4,0)) | F36: =E36-D36 | G36: up from 6.9 years in 2020
A37: OOS | B37: 2020 | C37: Average age of repairable vehicles (yrs) | D37: 6.1 | E37: =INDEX($C$16:$T$16,1,MATCH(B37,$C$4:$T$4,0)) | F37: =E37-D37 | G37: up from 6.1 years old in 2020
A38: OOS | B38: 2020 | C38: Average age of total-loss vehicles (yrs) | D38: 10 | E38: =INDEX($C$15:$T$15,1,MATCH(B38,$C$4:$T$4,0)) | F38: =E38-D38 | G38: up from 10.0 years old in 2020
A39: OOS | B39: 2025 | C39: Share of total-loss valuations on vehicles 7+ yrs | D39: 0.72 | E39: =INDEX($C$11:$T$11,1,MATCH(B39,$C$4:$T$4,0)) | F39: =(E39-D39)*100 | G39: over 72% of total loss valuations are on vehicles 7 years or older
A40: OOS | B40: 2025 | C40: Share of repairable claims on vehicles 7+ yrs | D40: 0.46 | E40: =INDEX($C$12:$T$12,1,MATCH(B40,$C$4:$T$4,0)) | F40: =(E40-D40)*100 | G40: almost 46% of repairable vehicles are 7 years or older
A41: OOS | B41: 2019 | C41: TLF all loss categories (demographics-only model vs actual) | D41: 0.192 | E41: =INDEX($C$8:$T$8,1,MATCH(B41,$C$4:$T$4,0)) | F41: =(E41-D41)*100 | G41: CCC annual 2019 = 19.2%; the gap is the non-demographic LEVEL (spread cycle, technology, filing)
A42: OOS | B42: 2020 | C42: TLF all loss categories | D42: 0.206 | E42: =INDEX($C$8:$T$8,1,MATCH(B42,$C$4:$T$4,0)) | F42: =(E42-D42)*100 | G42: CCC annual 2020 = 20.6%
A43: OOS | B43: 2025 | C43: TLF all loss categories | D43: 0.231 | E43: =INDEX($C$8:$T$8,1,MATCH(B43,$C$4:$T$4,0)) | F43: =(E43-D43)*100 | G43: CCC annual 2025 = 23.1%
A44: S | B44: 2024 | C44: Light vehicles in operation (M) | D44: 289 | E44: =INDEX($C$18:$T$18,1,MATCH(B44,$C$4:$T$4,0)) | F44: =E44-D44 | G44: S&P 2025 release — NOT on disk (from memory); Experian 292.1M at Q3-2024 is on disk (Crash Course 2025/Q1)
A45: S | B45: 2024 | C45: Share of fleet aged 7+ | D45: 0.66 | E45: =INDEX($C$19:$T$19,1,MATCH(B45,$C$4:$T$4,0)) | F45: =(E45-D45)*100 | G45: 66% of vehicles in operation are seven years or older (S&P Mobility)
A47: Demographic drift 2019→2025 (pp/yr) vs actual CCC rise | E47: =(O8-I8)*100/6 | F47: =(0.231-0.192)*100/6 | G47: model drift per year vs actual +0.65pp/yr (19.2% → 23.1%); the ratio is the share of the rise that is demographics (~24%)

Sheet Spread_Reg
A1: Totaling-spread regression — ΔTLF(pp, YoY) = a + b × spread(t−1), CCC quarterly
A2: spread = repair CPI YoY − used-car CPI YoY (BLS NSA, quarterly mean of monthly values; Data_Spread). ΔTLF = CCC quarterly TLF minus the same quarter a year earlier (Data_CCC_TLF_Quarterly). One-quarter lag. Reproduces scripts/analysis_20260911.py: all-loss a=0.599 b=0.0815 R²=0.81 n=27; non-comp a=0.609 b=0.0834 R²=0.79.
A4: quarter | B4: spread (pp) | C4: months | D4: note | F4: quarter | G4: TLF non-comp % | H4: TLF all-loss % | J4: quarter t | K4: year | L4: q | M4: prior-year quarter | N4: lag quarter t−1 | O4: ΔTLF all-loss (pp) | P4: ΔTLF non-comp (pp) | Q4: spread(t−1) | S4: regression | T4: all-loss | U4: non-comp
A5: 2016Q1 | B5: 1.401 | C5: 3 | F5: 2018Q1 | G5: 19.4 | H5: 18.7 | J5: 2019Q1 | K5: =VALUE(LEFT(J5,4)) | L5: =VALUE(RIGHT(J5,1)) | M5: =(K5-1)&"Q"&L5 | N5: =IF(L5=1,(K5-1)&"Q4",K5&"Q"&(L5-1)) | O5: =INDEX($H$5:$H$35,MATCH(J5,$F$5:$F$35,0))-INDEX($H$5:$H$35,MATCH(M5,$F$5:$F$35,0)) | P5: =INDEX($G$5:$G$35,MATCH(J5,$F$5:$F$35,0))-INDEX($G$5:$G$35,MATCH(M5,$F$5:$F$35,0)) | Q5: =INDEX($B$5:$B$47,MATCH(N5,$A$5:$A$47,0)) | S5: slope b (pp TLF per pp spread) | T5: =SLOPE($O$5:$O$31,$Q$5:$Q$31) | U5: =SLOPE($P$5:$P$31,$Q$5:$Q$31)
A6: 2016Q2 | B6: 4.047 | C6: 3 | F6: 2018Q2 | G6: 18.2 | H6: 17.6 | J6: 2019Q2 | K6: =VALUE(LEFT(J6,4)) | L6: =VALUE(RIGHT(J6,1)) | M6: =(K6-1)&"Q"&L6 | N6: =IF(L6=1,(K6-1)&"Q4",K6&"Q"&(L6-1)) | O6: =INDEX($H$5:$H$35,MATCH(J6,$F$5:$F$35,0))-INDEX($H$5:$H$35,MATCH(M6,$F$5:$F$35,0)) | P6: =INDEX($G$5:$G$35,MATCH(J6,$F$5:$F$35,0))-INDEX($G$5:$G$35,MATCH(M6,$F$5:$F$35,0)) | Q6: =INDEX($B$5:$B$47,MATCH(N6,$A$5:$A$47,0)) | S6: intercept a (pp/yr, unexplained drift) | T6: =INTERCEPT($O$5:$O$31,$Q$5:$Q$31) | U6: =INTERCEPT($P$5:$P$31,$Q$5:$Q$31)
A7: 2016Q3 | B7: 5.685 | C7: 3 | F7: 2018Q3 | G7: 18.3 | H7: 18.1 | J7: 2019Q3 | K7: =VALUE(LEFT(J7,4)) | L7: =VALUE(RIGHT(J7,1)) | M7: =(K7-1)&"Q"&L7 | N7: =IF(L7=1,(K7-1)&"Q4",K7&"Q"&(L7-1)) | O7: =INDEX($H$5:$H$35,MATCH(J7,$F$5:$F$35,0))-INDEX($H$5:$H$35,MATCH(M7,$F$5:$F$35,0)) | P7: =INDEX($G$5:$G$35,MATCH(J7,$F$5:$F$35,0))-INDEX($G$5:$G$35,MATCH(M7,$F$5:$F$35,0)) | Q7: =INDEX($B$5:$B$47,MATCH(N7,$A$5:$A$47,0)) | S7: R² | T7: =RSQ($O$5:$O$31,$Q$5:$Q$31) | U7: =RSQ($P$5:$P$31,$Q$5:$Q$31)
A8: 2016Q4 | B8: 5.52 | C8: 3 | F8: 2018Q4 | G8: 20.2 | H8: 19.5 | J8: 2019Q4 | K8: =VALUE(LEFT(J8,4)) | L8: =VALUE(RIGHT(J8,1)) | M8: =(K8-1)&"Q"&L8 | N8: =IF(L8=1,(K8-1)&"Q4",K8&"Q"&(L8-1)) | O8: =INDEX($H$5:$H$35,MATCH(J8,$F$5:$F$35,0))-INDEX($H$5:$H$35,MATCH(M8,$F$5:$F$35,0)) | P8: =INDEX($G$5:$G$35,MATCH(J8,$F$5:$F$35,0))-INDEX($G$5:$G$35,MATCH(M8,$F$5:$F$35,0)) | Q8: =INDEX($B$5:$B$47,MATCH(N8,$A$5:$A$47,0)) | S8: n | T8: =COUNT($O$5:$O$31) | U8: =COUNT($P$5:$P$31)
A9: 2017Q1 | B9: 6.488 | C9: 3 | F9: 2019Q1 | G9: 20 | H9: 19.2 | J9: 2020Q1 | K9: =VALUE(LEFT(J9,4)) | L9: =VALUE(RIGHT(J9,1)) | M9: =(K9-1)&"Q"&L9 | N9: =IF(L9=1,(K9-1)&"Q4",K9&"Q"&(L9-1)) | O9: =INDEX($H$5:$H$35,MATCH(J9,$F$5:$F$35,0))-INDEX($H$5:$H$35,MATCH(M9,$F$5:$F$35,0)) | P9: =INDEX($G$5:$G$35,MATCH(J9,$F$5:$F$35,0))-INDEX($G$5:$G$35,MATCH(M9,$F$5:$F$35,0)) | Q9: =INDEX($B$5:$B$47,MATCH(N9,$A$5:$A$47,0))
A10: 2017Q2 | B10: 6.122 | C10: 3 | F10: 2019Q2 | G10: 19.2 | H10: 18.5 | J10: 2020Q2 | K10: =VALUE(LEFT(J10,4)) | L10: =VALUE(RIGHT(J10,1)) | M10: =(K10-1)&"Q"&L10 | N10: =IF(L10=1,(K10-1)&"Q4",K10&"Q"&(L10-1)) | O10: =INDEX($H$5:$H$35,MATCH(J10,$F$5:$F$35,0))-INDEX($H$5:$H$35,MATCH(M10,$F$5:$F$35,0)) | P10: =INDEX($G$5:$G$35,MATCH(J10,$F$5:$F$35,0))-INDEX($G$5:$G$35,MATCH(M10,$F$5:$F$35,0)) | Q10: =INDEX($B$5:$B$47,MATCH(N10,$A$5:$A$47,0)) | S10: Prediction
A11: 2017Q3 | B11: 5.689 | C11: 3 | F11: 2019Q3 | G11: 19.2 | H11: 18.7 | J11: 2020Q3 | K11: =VALUE(LEFT(J11,4)) | L11: =VALUE(RIGHT(J11,1)) | M11: =(K11-1)&"Q"&L11 | N11: =IF(L11=1,(K11-1)&"Q4",K11&"Q"&(L11-1)) | O11: =INDEX($H$5:$H$35,MATCH(J11,$F$5:$F$35,0))-INDEX($H$5:$H$35,MATCH(M11,$F$5:$F$35,0)) | P11: =INDEX($G$5:$G$35,MATCH(J11,$F$5:$F$35,0))-INDEX($G$5:$G$35,MATCH(M11,$F$5:$F$35,0)) | Q11: =INDEX($B$5:$B$47,MATCH(N11,$A$5:$A$47,0)) | S11: Spread quarter to use (t−1) | T11: 2026Q1
A12: 2017Q4 | B12: 4.144 | C12: 3 | F12: 2019Q4 | G12: 21.2 | H12: 20.4 | J12: 2020Q4 | K12: =VALUE(LEFT(J12,4)) | L12: =VALUE(RIGHT(J12,1)) | M12: =(K12-1)&"Q"&L12 | N12: =IF(L12=1,(K12-1)&"Q4",K12&"Q"&(L12-1)) | O12: =INDEX($H$5:$H$35,MATCH(J12,$F$5:$F$35,0))-INDEX($H$5:$H$35,MATCH(M12,$F$5:$F$35,0)) | P12: =INDEX($G$5:$G$35,MATCH(J12,$F$5:$F$35,0))-INDEX($G$5:$G$35,MATCH(M12,$F$5:$F$35,0)) | Q12: =INDEX($B$5:$B$47,MATCH(N12,$A$5:$A$47,0)) | S12: spread(t−1) | T12: =INDEX($B$5:$B$47,MATCH(T11,$A$5:$A$47,0))
A13: 2018Q1 | B13: 1.553 | C13: 3 | F13: 2020Q1 | G13: 20.9 | H13: 20 | J13: 2021Q1 | K13: =VALUE(LEFT(J13,4)) | L13: =VALUE(RIGHT(J13,1)) | M13: =(K13-1)&"Q"&L13 | N13: =IF(L13=1,(K13-1)&"Q4",K13&"Q"&(L13-1)) | O13: =INDEX($H$5:$H$35,MATCH(J13,$F$5:$F$35,0))-INDEX($H$5:$H$35,MATCH(M13,$F$5:$F$35,0)) | P13: =INDEX($G$5:$G$35,MATCH(J13,$F$5:$F$35,0))-INDEX($G$5:$G$35,MATCH(M13,$F$5:$F$35,0)) | Q13: =INDEX($B$5:$B$47,MATCH(N13,$A$5:$A$47,0)) | S13: Predicted ΔTLF all-loss, quarter t (pp YoY) | T13: =T6+T5*T12
A14: 2018Q2 | B14: 2.887 | C14: 3 | F14: 2020Q2 | G14: 20.9 | H14: 19.6 | J14: 2021Q2 | K14: =VALUE(LEFT(J14,4)) | L14: =VALUE(RIGHT(J14,1)) | M14: =(K14-1)&"Q"&L14 | N14: =IF(L14=1,(K14-1)&"Q4",K14&"Q"&(L14-1)) | O14: =INDEX($H$5:$H$35,MATCH(J14,$F$5:$F$35,0))-INDEX($H$5:$H$35,MATCH(M14,$F$5:$F$35,0)) | P14: =INDEX($G$5:$G$35,MATCH(J14,$F$5:$F$35,0))-INDEX($G$5:$G$35,MATCH(M14,$F$5:$F$35,0)) | Q14: =INDEX($B$5:$B$47,MATCH(N14,$A$5:$A$47,0)) | S14: Live OOS: mgmt-cited CCC 2Q26 23.3 vs 22.4 (2026-09-10 call) | T14: 0.9
A15: 2018Q3 | B15: 2.067 | C15: 3 | F15: 2020Q3 | G15: 21.8 | H15: 20.9 | J15: 2021Q3 | K15: =VALUE(LEFT(J15,4)) | L15: =VALUE(RIGHT(J15,1)) | M15: =(K15-1)&"Q"&L15 | N15: =IF(L15=1,(K15-1)&"Q4",K15&"Q"&(L15-1)) | O15: =INDEX($H$5:$H$35,MATCH(J15,$F$5:$F$35,0))-INDEX($H$5:$H$35,MATCH(M15,$F$5:$F$35,0)) | P15: =INDEX($G$5:$G$35,MATCH(J15,$F$5:$F$35,0))-INDEX($G$5:$G$35,MATCH(M15,$F$5:$F$35,0)) | Q15: =INDEX($B$5:$B$47,MATCH(N15,$A$5:$A$47,0)) | S15: error (pp) | T15: =T13-T14
A16: 2018Q4 | B16: 0.969 | C16: 3 | F16: 2020Q4 | G16: 23.1 | H16: 21.7 | J16: 2021Q4 | K16: =VALUE(LEFT(J16,4)) | L16: =VALUE(RIGHT(J16,1)) | M16: =(K16-1)&"Q"&L16 | N16: =IF(L16=1,(K16-1)&"Q4",K16&"Q"&(L16-1)) | O16: =INDEX($H$5:$H$35,MATCH(J16,$F$5:$F$35,0))-INDEX($H$5:$H$35,MATCH(M16,$F$5:$F$35,0)) | P16: =INDEX($G$5:$G$35,MATCH(J16,$F$5:$F$35,0))-INDEX($G$5:$G$35,MATCH(M16,$F$5:$F$35,0)) | Q16: =INDEX($B$5:$B$47,MATCH(N16,$A$5:$A$47,0))
A17: 2019Q1 | B17: 1.986 | C17: 3 | F17: 2021Q1 | G17: 22.1 | H17: 20.7 | J17: 2022Q1 | K17: =VALUE(LEFT(J17,4)) | L17: =VALUE(RIGHT(J17,1)) | M17: =(K17-1)&"Q"&L17 | N17: =IF(L17=1,(K17-1)&"Q4",K17&"Q"&(L17-1)) | O17: =INDEX($H$5:$H$35,MATCH(J17,$F$5:$F$35,0))-INDEX($H$5:$H$35,MATCH(M17,$F$5:$F$35,0)) | P17: =INDEX($G$5:$G$35,MATCH(J17,$F$5:$F$35,0))-INDEX($G$5:$G$35,MATCH(M17,$F$5:$F$35,0)) | Q17: =INDEX($B$5:$B$47,MATCH(N17,$A$5:$A$47,0)) | S17: Why the intercept matters: with spread = 0 the model still adds ~0.6pp/yr of TLF; the cohort roll (TLF_Roll) explains ~0.15pp of that. Use the spread term for 12 months, not for the decade. MODEL_BLUEPRINT §3.
A18: 2019Q2 | B18: 2.806 | C18: 3 | F18: 2021Q2 | G18: 20.9 | H18: 19.7 | J18: 2022Q2 | K18: =VALUE(LEFT(J18,4)) | L18: =VALUE(RIGHT(J18,1)) | M18: =(K18-1)&"Q"&L18 | N18: =IF(L18=1,(K18-1)&"Q4",K18&"Q"&(L18-1)) | O18: =INDEX($H$5:$H$35,MATCH(J18,$F$5:$F$35,0))-INDEX($H$5:$H$35,MATCH(M18,$F$5:$F$35,0)) | P18: =INDEX($G$5:$G$35,MATCH(J18,$F$5:$F$35,0))-INDEX($G$5:$G$35,MATCH(M18,$F$5:$F$35,0)) | Q18: =INDEX($B$5:$B$47,MATCH(N18,$A$5:$A$47,0))
A19: 2019Q3 | B19: 1.459 | C19: 3 | F19: 2021Q3 | G19: 19.5 | H19: 19.3 | J19: 2022Q3 | K19: =VALUE(LEFT(J19,4)) | L19: =VALUE(RIGHT(J19,1)) | M19: =(K19-1)&"Q"&L19 | N19: =IF(L19=1,(K19-1)&"Q4",K19&"Q"&(L19-1)) | O19: =INDEX($H$5:$H$35,MATCH(J19,$F$5:$F$35,0))-INDEX($H$5:$H$35,MATCH(M19,$F$5:$F$35,0)) | P19: =INDEX($G$5:$G$35,MATCH(J19,$F$5:$F$35,0))-INDEX($G$5:$G$35,MATCH(M19,$F$5:$F$35,0)) | Q19: =INDEX($B$5:$B$47,MATCH(N19,$A$5:$A$47,0))
A20: 2019Q4 | B20: 3.225 | C20: 3 | F20: 2021Q4 | G20: 20.3 | H20: 19.2 | J20: 2022Q4 | K20: =VALUE(LEFT(J20,4)) | L20: =VALUE(RIGHT(J20,1)) | M20: =(K20-1)&"Q"&L20 | N20: =IF(L20=1,(K20-1)&"Q4",K20&"Q"&(L20-1)) | O20: =INDEX($H$5:$H$35,MATCH(J20,$F$5:$F$35,0))-INDEX($H$5:$H$35,MATCH(M20,$F$5:$F$35,0)) | P20: =INDEX($G$5:$G$35,MATCH(J20,$F$5:$F$35,0))-INDEX($G$5:$G$35,MATCH(M20,$F$5:$F$35,0)) | Q20: =INDEX($B$5:$B$47,MATCH(N20,$A$5:$A$47,0))
A21: 2020Q1 | B21: 4.419 | C21: 3 | F21: 2022Q1 | G21: 19.9 | H21: 18.8 | J21: 2023Q1 | K21: =VALUE(LEFT(J21,4)) | L21: =VALUE(RIGHT(J21,1)) | M21: =(K21-1)&"Q"&L21 | N21: =IF(L21=1,(K21-1)&"Q4",K21&"Q"&(L21-1)) | O21: =INDEX($H$5:$H$35,MATCH(J21,$F$5:$F$35,0))-INDEX($H$5:$H$35,MATCH(M21,$F$5:$F$35,0)) | P21: =INDEX($G$5:$G$35,MATCH(J21,$F$5:$F$35,0))-INDEX($G$5:$G$35,MATCH(M21,$F$5:$F$35,0)) | Q21: =INDEX($B$5:$B$47,MATCH(N21,$A$5:$A$47,0))
A22: 2020Q2 | B22: 4.701 | C22: 3 | F22: 2022Q2 | G22: 18.9 | H22: 17.6 | J22: 2023Q2 | K22: =VALUE(LEFT(J22,4)) | L22: =VALUE(RIGHT(J22,1)) | M22: =(K22-1)&"Q"&L22 | N22: =IF(L22=1,(K22-1)&"Q4",K22&"Q"&(L22-1)) | O22: =INDEX($H$5:$H$35,MATCH(J22,$F$5:$F$35,0))-INDEX($H$5:$H$35,MATCH(M22,$F$5:$F$35,0)) | P22: =INDEX($G$5:$G$35,MATCH(J22,$F$5:$F$35,0))-INDEX($G$5:$G$35,MATCH(M22,$F$5:$F$35,0)) | Q22: =INDEX($B$5:$B$47,MATCH(N22,$A$5:$A$47,0))
A23: 2020Q3 | B23: -1.133 | C23: 3 | F23: 2022Q3 | G23: 18.9 | H23: 18 | J23: 2023Q3 | K23: =VALUE(LEFT(J23,4)) | L23: =VALUE(RIGHT(J23,1)) | M23: =(K23-1)&"Q"&L23 | N23: =IF(L23=1,(K23-1)&"Q4",K23&"Q"&(L23-1)) | O23: =INDEX($H$5:$H$35,MATCH(J23,$F$5:$F$35,0))-INDEX($H$5:$H$35,MATCH(M23,$F$5:$F$35,0)) | P23: =INDEX($G$5:$G$35,MATCH(J23,$F$5:$F$35,0))-INDEX($G$5:$G$35,MATCH(M23,$F$5:$F$35,0)) | Q23: =INDEX($B$5:$B$47,MATCH(N23,$A$5:$A$47,0))
A24: 2020Q4 | B24: -7.403 | C24: 3 | F24: 2022Q4 | G24: 21 | H24: 20.6 | J24: 2023Q4 | K24: =VALUE(LEFT(J24,4)) | L24: =VALUE(RIGHT(J24,1)) | M24: =(K24-1)&"Q"&L24 | N24: =IF(L24=1,(K24-1)&"Q4",K24&"Q"&(L24-1)) | O24: =INDEX($H$5:$H$35,MATCH(J24,$F$5:$F$35,0))-INDEX($H$5:$H$35,MATCH(M24,$F$5:$F$35,0)) | P24: =INDEX($G$5:$G$35,MATCH(J24,$F$5:$F$35,0))-INDEX($G$5:$G$35,MATCH(M24,$F$5:$F$35,0)) | Q24: =INDEX($B$5:$B$47,MATCH(N24,$A$5:$A$47,0))
A25: 2021Q1 | B25: -6.188 | C25: 3 | F25: 2023Q1 | G25: 21.1 | H25: 20.1 | J25: 2024Q1 | K25: =VALUE(LEFT(J25,4)) | L25: =VALUE(RIGHT(J25,1)) | M25: =(K25-1)&"Q"&L25 | N25: =IF(L25=1,(K25-1)&"Q4",K25&"Q"&(L25-1)) | O25: =INDEX($H$5:$H$35,MATCH(J25,$F$5:$F$35,0))-INDEX($H$5:$H$35,MATCH(M25,$F$5:$F$35,0)) | P25: =INDEX($G$5:$G$35,MATCH(J25,$F$5:$F$35,0))-INDEX($G$5:$G$35,MATCH(M25,$F$5:$F$35,0)) | Q25: =INDEX($B$5:$B$47,MATCH(N25,$A$5:$A$47,0))
A26: 2021Q2 | B26: -28.83 | C26: 3 | F26: 2023Q2 | G26: 20.5 | H26: 19.4 | J26: 2024Q2 | K26: =VALUE(LEFT(J26,4)) | L26: =VALUE(RIGHT(J26,1)) | M26: =(K26-1)&"Q"&L26 | N26: =IF(L26=1,(K26-1)&"Q4",K26&"Q"&(L26-1)) | O26: =INDEX($H$5:$H$35,MATCH(J26,$F$5:$F$35,0))-INDEX($H$5:$H$35,MATCH(M26,$F$5:$F$35,0)) | P26: =INDEX($G$5:$G$35,MATCH(J26,$F$5:$F$35,0))-INDEX($G$5:$G$35,MATCH(M26,$F$5:$F$35,0)) | Q26: =INDEX($B$5:$B$47,MATCH(N26,$A$5:$A$47,0))
A27: 2021Q3 | B27: -28.565 | C27: 3 | F27: 2023Q3 | G27: 20.7 | H27: 19.9 | J27: 2024Q3 | K27: =VALUE(LEFT(J27,4)) | L27: =VALUE(RIGHT(J27,1)) | M27: =(K27-1)&"Q"&L27 | N27: =IF(L27=1,(K27-1)&"Q4",K27&"Q"&(L27-1)) | O27: =INDEX($H$5:$H$35,MATCH(J27,$F$5:$F$35,0))-INDEX($H$5:$H$35,MATCH(M27,$F$5:$F$35,0)) | P27: =INDEX($G$5:$G$35,MATCH(J27,$F$5:$F$35,0))-INDEX($G$5:$G$35,MATCH(M27,$F$5:$F$35,0)) | Q27: =INDEX($B$5:$B$47,MATCH(N27,$A$5:$A$47,0))
A28: 2021Q4 | B28: -26.722 | C28: 3 | F28: 2023Q4 | G28: 22.4 | H28: 21.5 | J28: 2024Q4 | K28: =VALUE(LEFT(J28,4)) | L28: =VALUE(RIGHT(J28,1)) | M28: =(K28-1)&"Q"&L28 | N28: =IF(L28=1,(K28-1)&"Q4",K28&"Q"&(L28-1)) | O28: =INDEX($H$5:$H$35,MATCH(J28,$F$5:$F$35,0))-INDEX($H$5:$H$35,MATCH(M28,$F$5:$F$35,0)) | P28: =INDEX($G$5:$G$35,MATCH(J28,$F$5:$F$35,0))-INDEX($G$5:$G$35,MATCH(M28,$F$5:$F$35,0)) | Q28: =INDEX($B$5:$B$47,MATCH(N28,$A$5:$A$47,0))
A29: 2022Q1 | B29: -33.698 | C29: 3 | F29: 2024Q1 | G29: 22.7 | H29: 21.8 | J29: 2025Q1 | K29: =VALUE(LEFT(J29,4)) | L29: =VALUE(RIGHT(J29,1)) | M29: =(K29-1)&"Q"&L29 | N29: =IF(L29=1,(K29-1)&"Q4",K29&"Q"&(L29-1)) | O29: =INDEX($H$5:$H$35,MATCH(J29,$F$5:$F$35,0))-INDEX($H$5:$H$35,MATCH(M29,$F$5:$F$35,0)) | P29: =INDEX($G$5:$G$35,MATCH(J29,$F$5:$F$35,0))-INDEX($G$5:$G$35,MATCH(M29,$F$5:$F$35,0)) | Q29: =INDEX($B$5:$B$47,MATCH(N29,$A$5:$A$47,0))
... A31: 2022Q3 | B31: 2.223 | C31: 3 | F31: 2024Q3 | G31: 22.5 | H31: 21.9 | J31: 2025Q3 | K31: =VALUE(LEFT(J31,4)) | L31: =VALUE(RIGHT(J31,1)) | M31: =(K31-1)&"Q"&L31 | N31: =IF(L31=1,(K31-1)&"Q4",K31&"Q"&(L31-1)) | O31: =INDEX($H$5:$H$35,MATCH(J31,$F$5:$F$35,0))-INDEX($H$5:$H$35,MATCH(M31,$F$5:$F$35,0)) | P31: =INDEX($G$5:$G$35,MATCH(J31,$F$5:$F$35,0))-INDEX($G$5:$G$35,MATCH(M31,$F$5:$F$35,0)) | Q31: =INDEX($B$5:$B$47,MATCH(N31,$A$5:$A$47,0))
A32: 2022Q4 | B32: 15.063 | C32: 3 | F32: 2024Q4 | G32: 24.3 | H32: 24.1
A33: 2023Q1 | B33: 25.466 | C33: 3 | F33: 2025Q1 | G33: 23.8 | H33: 22.9
A34: 2023Q2 | B34: 18.471 | C34: 3 | F34: 2025Q2 | G34: 23.2 | H34: 22.4
A35: 2023Q3 | B35: 18.348 | C35: 3 | F35: 2025Q3 | G35: 23.4 | H35: 22.8
A36: 2023Q4 | B36: 12.429 | C36: 3
A37: 2024Q1 | B37: 9.619 | C37: 3
A38: 2024Q2 | B38: 15.705 | C38: 3
A39: 2024Q3 | B39: 13.312 | C39: 3
A40: 2024Q4 | B40: 9.239 | C40: 3
A41: 2025Q1 | B41: 4.717 | C41: 3
A42: 2025Q2 | B42: 3.243 | C42: 3
A43: 2025Q3 | B43: 2.265 | C43: 3
A44: 2025Q4 | B44: 3.562 | C44: 2 | D44: partial quarter (BLS gap or not yet published)
A45: 2026Q1 | B45: 8.318 | C45: 3
A46: 2026Q2 | B46: 8.256 | C46: 3
A47: 2026Q3 | B47: 8.494 | C47: 1 | D47: partial quarter (BLS gap or not yet published)

Sheet RPU_Reg
A1: RPU chain — ASP ~ used-car CPI (nowcast) and service RPU ~ ASP (elasticity)
A2: Step 1: Copart US insurance ASP YoY (transcripts, Data_ReportedUnits) on used-car CPI YoY (BLS CUSR0000SETA02, SA, fiscal-quarter average of the three months vs the same months a year earlier; Data_CPI col B). Step 2: implied service RPU YoY on global ASP YoY, n=17 (Data_Elasticity). Reference values: step 1 a=3.23 b=0.599 r=0.77 (n=15); step 2 b=0.514 a=4.13 R²=0.61; total-RPU b=0.752 a=2.84.
A4: fiscal quarter | B4: month 1 | C4: month 2 | D4: month 3 | E4: CPI used cars, qtr avg | F4: same qtr prior year | G4: CPI YoY % | H4: US ins ASP YoY % (reported) | J4: Step 1: ASP = a + b × CPI | K4: value
A5: FY2023 Q1 | B5: 2022-08 | C5: 2022-09 | D5: 2022-10 | E5: =IFERROR(AVERAGE(INDEX(Data_CPI!$B$5:$B$912,MATCH(B5,Data_CPI!$A$5:$A$912,0)),INDEX(Data_CPI!$B$5:$B$912,MATCH(C5,Data_CPI!$A$5:$A$912,0)),INDEX(Data_CPI!$B$5:$B$912,MATCH(D5,Data_CPI!$A$5:$A$912,0))),"") | F5: =IFERROR(AVERAGE(INDEX(Data_CPI!$B$5:$B$912,MATCH((VALUE(LEFT(B5,4))-1)&RIGHT(B5,3),Data_CPI!$A$5:$A$912,0)),INDEX(Data_CPI!$B$5:$B$912,MATCH((VALUE(LEFT(C5,4))-1)&RIGHT(C5,3),Data_CPI!$A$5:$A$912,0)),INDEX(Data_CPI!$B$5:$B$912,MATCH((VALUE(LEFT(D5,4))-1)&RIGHT(D5,3),Data_CPI!$A$5:$A$912,0))),"") | G5: =IF(OR(E5="",F5=""),"",(E5/F5-1)*100) | H5: =IFERROR(INDEX(Data_ReportedUnits!$F$5:$F$20,MATCH(A5,Data_ReportedUnits!$A$5:$A$20,0)),"") | J5: slope b | K5: =SLOPE(H5:H19,G5:G19)
A6: FY2023 Q2 | B6: 2022-11 | C6: 2022-12 | D6: 2023-01 | E6: =IFERROR(AVERAGE(INDEX(Data_CPI!$B$5:$B$912,MATCH(B6,Data_CPI!$A$5:$A$912,0)),INDEX(Data_CPI!$B$5:$B$912,MATCH(C6,Data_CPI!$A$5:$A$912,0)),INDEX(Data_CPI!$B$5:$B$912,MATCH(D6,Data_CPI!$A$5:$A$912,0))),"") | F6: =IFERROR(AVERAGE(INDEX(Data_CPI!$B$5:$B$912,MATCH((VALUE(LEFT(B6,4))-1)&RIGHT(B6,3),Data_CPI!$A$5:$A$912,0)),INDEX(Data_CPI!$B$5:$B$912,MATCH((VALUE(LEFT(C6,4))-1)&RIGHT(C6,3),Data_CPI!$A$5:$A$912,0)),INDEX(Data_CPI!$B$5:$B$912,MATCH((VALUE(LEFT(D6,4))-1)&RIGHT(D6,3),Data_CPI!$A$5:$A$912,0))),"") | G6: =IF(OR(E6="",F6=""),"",(E6/F6-1)*100) | H6: =IFERROR(INDEX(Data_ReportedUnits!$F$5:$F$20,MATCH(A6,Data_ReportedUnits!$A$5:$A$20,0)),"") | J6: intercept a (pp) | K6: =INTERCEPT(H5:H19,G5:G19)
A7: FY2023 Q3 | B7: 2023-02 | C7: 2023-03 | D7: 2023-04 | E7: =IFERROR(AVERAGE(INDEX(Data_CPI!$B$5:$B$912,MATCH(B7,Data_CPI!$A$5:$A$912,0)),INDEX(Data_CPI!$B$5:$B$912,MATCH(C7,Data_CPI!$A$5:$A$912,0)),INDEX(Data_CPI!$B$5:$B$912,MATCH(D7,Data_CPI!$A$5:$A$912,0))),"") | F7: =IFERROR(AVERAGE(INDEX(Data_CPI!$B$5:$B$912,MATCH((VALUE(LEFT(B7,4))-1)&RIGHT(B7,3),Data_CPI!$A$5:$A$912,0)),INDEX(Data_CPI!$B$5:$B$912,MATCH((VALUE(LEFT(C7,4))-1)&RIGHT(C7,3),Data_CPI!$A$5:$A$912,0)),INDEX(Data_CPI!$B$5:$B$912,MATCH((VALUE(LEFT(D7,4))-1)&RIGHT(D7,3),Data_CPI!$A$5:$A$912,0))),"") | G7: =IF(OR(E7="",F7=""),"",(E7/F7-1)*100) | H7: =IFERROR(INDEX(Data_ReportedUnits!$F$5:$F$20,MATCH(A7,Data_ReportedUnits!$A$5:$A$20,0)),"") | J7: correlation r | K7: =CORREL(H5:H19,G5:G19)
A8: FY2023 Q4 | B8: 2023-05 | C8: 2023-06 | D8: 2023-07 | E8: =IFERROR(AVERAGE(INDEX(Data_CPI!$B$5:$B$912,MATCH(B8,Data_CPI!$A$5:$A$912,0)),INDEX(Data_CPI!$B$5:$B$912,MATCH(C8,Data_CPI!$A$5:$A$912,0)),INDEX(Data_CPI!$B$5:$B$912,MATCH(D8,Data_CPI!$A$5:$A$912,0))),"") | F8: =IFERROR(AVERAGE(INDEX(Data_CPI!$B$5:$B$912,MATCH((VALUE(LEFT(B8,4))-1)&RIGHT(B8,3),Data_CPI!$A$5:$A$912,0)),INDEX(Data_CPI!$B$5:$B$912,MATCH((VALUE(LEFT(C8,4))-1)&RIGHT(C8,3),Data_CPI!$A$5:$A$912,0)),INDEX(Data_CPI!$B$5:$B$912,MATCH((VALUE(LEFT(D8,4))-1)&RIGHT(D8,3),Data_CPI!$A$5:$A$912,0))),"") | G8: =IF(OR(E8="",F8=""),"",(E8/F8-1)*100) | H8: =IFERROR(INDEX(Data_ReportedUnits!$F$5:$F$20,MATCH(A8,Data_ReportedUnits!$A$5:$A$20,0)),"") | J8: n | K8: =COUNT(H5:H19)
A9: FY2024 Q1 | B9: 2023-08 | C9: 2023-09 | D9: 2023-10 | E9: =IFERROR(AVERAGE(INDEX(Data_CPI!$B$5:$B$912,MATCH(B9,Data_CPI!$A$5:$A$912,0)),INDEX(Data_CPI!$B$5:$B$912,MATCH(C9,Data_CPI!$A$5:$A$912,0)),INDEX(Data_CPI!$B$5:$B$912,MATCH(D9,Data_CPI!$A$5:$A$912,0))),"") | F9: =IFERROR(AVERAGE(INDEX(Data_CPI!$B$5:$B$912,MATCH((VALUE(LEFT(B9,4))-1)&RIGHT(B9,3),Data_CPI!$A$5:$A$912,0)),INDEX(Data_CPI!$B$5:$B$912,MATCH((VALUE(LEFT(C9,4))-1)&RIGHT(C9,3),Data_CPI!$A$5:$A$912,0)),INDEX(Data_CPI!$B$5:$B$912,MATCH((VALUE(LEFT(D9,4))-1)&RIGHT(D9,3),Data_CPI!$A$5:$A$912,0))),"") | G9: =IF(OR(E9="",F9=""),"",(E9/F9-1)*100) | H9: =IFERROR(INDEX(Data_ReportedUnits!$F$5:$F$20,MATCH(A9,Data_ReportedUnits!$A$5:$A$20,0)),"") | J9: Nowcast row: FY2026 Q4 (A20) has CPI but ASP is not in the CSV yet (call: US ins ASP +3.7%). Extend Q0:Q1 when the CSV is updated.
A10: FY2024 Q2 | B10: 2023-11 | C10: 2023-12 | D10: 2024-01 | E10: =IFERROR(AVERAGE(INDEX(Data_CPI!$B$5:$B$912,MATCH(B10,Data_CPI!$A$5:$A$912,0)),INDEX(Data_CPI!$B$5:$B$912,MATCH(C10,Data_CPI!$A$5:$A$912,0)),INDEX(Data_CPI!$B$5:$B$912,MATCH(D10,Data_CPI!$A$5:$A$912,0))),"") | F10: =IFERROR(AVERAGE(INDEX(Data_CPI!$B$5:$B$912,MATCH((VALUE(LEFT(B10,4))-1)&RIGHT(B10,3),Data_CPI!$A$5:$A$912,0)),INDEX(Data_CPI!$B$5:$B$912,MATCH((VALUE(LEFT(C10,4))-1)&RIGHT(C10,3),Data_CPI!$A$5:$A$912,0)),INDEX(Data_CPI!$B$5:$B$912,MATCH((VALUE(LEFT(D10,4))-1)&RIGHT(D10,3),Data_CPI!$A$5:$A$912,0))),"") | G10: =IF(OR(E10="",F10=""),"",(E10/F10-1)*100) | H10: =IFERROR(INDEX(Data_ReportedUnits!$F$5:$F$20,MATCH(A10,Data_ReportedUnits!$A$5:$A$20,0)),"")
A11: FY2024 Q3 | B11: 2024-02 | C11: 2024-03 | D11: 2024-04 | E11: =IFERROR(AVERAGE(INDEX(Data_CPI!$B$5:$B$912,MATCH(B11,Data_CPI!$A$5:$A$912,0)),INDEX(Data_CPI!$B$5:$B$912,MATCH(C11,Data_CPI!$A$5:$A$912,0)),INDEX(Data_CPI!$B$5:$B$912,MATCH(D11,Data_CPI!$A$5:$A$912,0))),"") | F11: =IFERROR(AVERAGE(INDEX(Data_CPI!$B$5:$B$912,MATCH((VALUE(LEFT(B11,4))-1)&RIGHT(B11,3),Data_CPI!$A$5:$A$912,0)),INDEX(Data_CPI!$B$5:$B$912,MATCH((VALUE(LEFT(C11,4))-1)&RIGHT(C11,3),Data_CPI!$A$5:$A$912,0)),INDEX(Data_CPI!$B$5:$B$912,MATCH((VALUE(LEFT(D11,4))-1)&RIGHT(D11,3),Data_CPI!$A$5:$A$912,0))),"") | G11: =IF(OR(E11="",F11=""),"",(E11/F11-1)*100) | H11: =IFERROR(INDEX(Data_ReportedUnits!$F$5:$F$20,MATCH(A11,Data_ReportedUnits!$A$5:$A$20,0)),"") | J11: Step 2: RPU = a + b × ASP (global, n=17) | K11: service RPU | L11: total RPU (mgmt def.)
A12: FY2024 Q4 | B12: 2024-05 | C12: 2024-06 | D12: 2024-07 | E12: =IFERROR(AVERAGE(INDEX(Data_CPI!$B$5:$B$912,MATCH(B12,Data_CPI!$A$5:$A$912,0)),INDEX(Data_CPI!$B$5:$B$912,MATCH(C12,Data_CPI!$A$5:$A$912,0)),INDEX(Data_CPI!$B$5:$B$912,MATCH(D12,Data_CPI!$A$5:$A$912,0))),"") | F12: =IFERROR(AVERAGE(INDEX(Data_CPI!$B$5:$B$912,MATCH((VALUE(LEFT(B12,4))-1)&RIGHT(B12,3),Data_CPI!$A$5:$A$912,0)),INDEX(Data_CPI!$B$5:$B$912,MATCH((VALUE(LEFT(C12,4))-1)&RIGHT(C12,3),Data_CPI!$A$5:$A$912,0)),INDEX(Data_CPI!$B$5:$B$912,MATCH((VALUE(LEFT(D12,4))-1)&RIGHT(D12,3),Data_CPI!$A$5:$A$912,0))),"") | G12: =IF(OR(E12="",F12=""),"",(E12/F12-1)*100) | H12: =IFERROR(INDEX(Data_ReportedUnits!$F$5:$F$20,MATCH(A12,Data_ReportedUnits!$A$5:$A$20,0)),"") | J12: slope b (elasticity) | K12: =SLOPE(Data_Elasticity!$F$5:$F$21,Data_Elasticity!$E$5:$E$21) | L12: =SLOPE(Data_Elasticity!$G$5:$G$21,Data_Elasticity!$E$5:$E$21)
A13: FY2025 Q1 | B13: 2024-08 | C13: 2024-09 | D13: 2024-10 | E13: =IFERROR(AVERAGE(INDEX(Data_CPI!$B$5:$B$912,MATCH(B13,Data_CPI!$A$5:$A$912,0)),INDEX(Data_CPI!$B$5:$B$912,MATCH(C13,Data_CPI!$A$5:$A$912,0)),INDEX(Data_CPI!$B$5:$B$912,MATCH(D13,Data_CPI!$A$5:$A$912,0))),"") | F13: =IFERROR(AVERAGE(INDEX(Data_CPI!$B$5:$B$912,MATCH((VALUE(LEFT(B13,4))-1)&RIGHT(B13,3),Data_CPI!$A$5:$A$912,0)),INDEX(Data_CPI!$B$5:$B$912,MATCH((VALUE(LEFT(C13,4))-1)&RIGHT(C13,3),Data_CPI!$A$5:$A$912,0)),INDEX(Data_CPI!$B$5:$B$912,MATCH((VALUE(LEFT(D13,4))-1)&RIGHT(D13,3),Data_CPI!$A$5:$A$912,0))),"") | G13: =IF(OR(E13="",F13=""),"",(E13/F13-1)*100) | H13: =IFERROR(INDEX(Data_ReportedUnits!$F$5:$F$20,MATCH(A13,Data_ReportedUnits!$A$5:$A$20,0)),"") | J13: intercept a (pp = fee/mix growth at flat ASP) | K13: =INTERCEPT(Data_Elasticity!$F$5:$F$21,Data_Elasticity!$E$5:$E$21) | L13: =INTERCEPT(Data_Elasticity!$G$5:$G$21,Data_Elasticity!$E$5:$E$21)
A14: FY2025 Q2 | B14: 2024-11 | C14: 2024-12 | D14: 2025-01 | E14: =IFERROR(AVERAGE(INDEX(Data_CPI!$B$5:$B$912,MATCH(B14,Data_CPI!$A$5:$A$912,0)),INDEX(Data_CPI!$B$5:$B$912,MATCH(C14,Data_CPI!$A$5:$A$912,0)),INDEX(Data_CPI!$B$5:$B$912,MATCH(D14,Data_CPI!$A$5:$A$912,0))),"") | F14: =IFERROR(AVERAGE(INDEX(Data_CPI!$B$5:$B$912,MATCH((VALUE(LEFT(B14,4))-1)&RIGHT(B14,3),Data_CPI!$A$5:$A$912,0)),INDEX(Data_CPI!$B$5:$B$912,MATCH((VALUE(LEFT(C14,4))-1)&RIGHT(C14,3),Data_CPI!$A$5:$A$912,0)),INDEX(Data_CPI!$B$5:$B$912,MATCH((VALUE(LEFT(D14,4))-1)&RIGHT(D14,3),Data_CPI!$A$5:$A$912,0))),"") | G14: =IF(OR(E14="",F14=""),"",(E14/F14-1)*100) | H14: =IFERROR(INDEX(Data_ReportedUnits!$F$5:$F$20,MATCH(A14,Data_ReportedUnits!$A$5:$A$20,0)),"") | J14: R² | K14: =RSQ(Data_Elasticity!$F$5:$F$21,Data_Elasticity!$E$5:$E$21) | L14: =RSQ(Data_Elasticity!$G$5:$G$21,Data_Elasticity!$E$5:$E$21)
A15: FY2025 Q3 | B15: 2025-02 | C15: 2025-03 | D15: 2025-04 | E15: =IFERROR(AVERAGE(INDEX(Data_CPI!$B$5:$B$912,MATCH(B15,Data_CPI!$A$5:$A$912,0)),INDEX(Data_CPI!$B$5:$B$912,MATCH(C15,Data_CPI!$A$5:$A$912,0)),INDEX(Data_CPI!$B$5:$B$912,MATCH(D15,Data_CPI!$A$5:$A$912,0))),"") | F15: =IFERROR(AVERAGE(INDEX(Data_CPI!$B$5:$B$912,MATCH((VALUE(LEFT(B15,4))-1)&RIGHT(B15,3),Data_CPI!$A$5:$A$912,0)),INDEX(Data_CPI!$B$5:$B$912,MATCH((VALUE(LEFT(C15,4))-1)&RIGHT(C15,3),Data_CPI!$A$5:$A$912,0)),INDEX(Data_CPI!$B$5:$B$912,MATCH((VALUE(LEFT(D15,4))-1)&RIGHT(D15,3),Data_CPI!$A$5:$A$912,0))),"") | G15: =IF(OR(E15="",F15=""),"",(E15/F15-1)*100) | H15: =IFERROR(INDEX(Data_ReportedUnits!$F$5:$F$20,MATCH(A15,Data_ReportedUnits!$A$5:$A$20,0)),"") | J15: n | K15: =COUNT(Data_Elasticity!$F$5:$F$21) | L15: =COUNT(Data_Elasticity!$G$5:$G$21)
A16: FY2025 Q4 | B16: 2025-05 | C16: 2025-06 | D16: 2025-07 | E16: =IFERROR(AVERAGE(INDEX(Data_CPI!$B$5:$B$912,MATCH(B16,Data_CPI!$A$5:$A$912,0)),INDEX(Data_CPI!$B$5:$B$912,MATCH(C16,Data_CPI!$A$5:$A$912,0)),INDEX(Data_CPI!$B$5:$B$912,MATCH(D16,Data_CPI!$A$5:$A$912,0))),"") | F16: =IFERROR(AVERAGE(INDEX(Data_CPI!$B$5:$B$912,MATCH((VALUE(LEFT(B16,4))-1)&RIGHT(B16,3),Data_CPI!$A$5:$A$912,0)),INDEX(Data_CPI!$B$5:$B$912,MATCH((VALUE(LEFT(C16,4))-1)&RIGHT(C16,3),Data_CPI!$A$5:$A$912,0)),INDEX(Data_CPI!$B$5:$B$912,MATCH((VALUE(LEFT(D16,4))-1)&RIGHT(D16,3),Data_CPI!$A$5:$A$912,0))),"") | G16: =IF(OR(E16="",F16=""),"",(E16/F16-1)*100) | H16: =IFERROR(INDEX(Data_ReportedUnits!$F$5:$F$20,MATCH(A16,Data_ReportedUnits!$A$5:$A$20,0)),"") | J16: Caveat: residual autocorrelation → effective n ≈ 6; 95% CI on service-RPU slope [0.29, 0.73]. The INTERCEPT is the robust finding (fee/mix adds ~4pp/yr at flat ASP), and it decelerated in FY26 (+1.3 to +3.5pp).
A17: FY2026 Q1 | B17: 2025-08 | C17: 2025-09 | D17: 2025-10 | E17: =IFERROR(AVERAGE(INDEX(Data_CPI!$B$5:$B$912,MATCH(B17,Data_CPI!$A$5:$A$912,0)),INDEX(Data_CPI!$B$5:$B$912,MATCH(C17,Data_CPI!$A$5:$A$912,0)),INDEX(Data_CPI!$B$5:$B$912,MATCH(D17,Data_CPI!$A$5:$A$912,0))),"") | F17: =IFERROR(AVERAGE(INDEX(Data_CPI!$B$5:$B$912,MATCH((VALUE(LEFT(B17,4))-1)&RIGHT(B17,3),Data_CPI!$A$5:$A$912,0)),INDEX(Data_CPI!$B$5:$B$912,MATCH((VALUE(LEFT(C17,4))-1)&RIGHT(C17,3),Data_CPI!$A$5:$A$912,0)),INDEX(Data_CPI!$B$5:$B$912,MATCH((VALUE(LEFT(D17,4))-1)&RIGHT(D17,3),Data_CPI!$A$5:$A$912,0))),"") | G17: =IF(OR(E17="",F17=""),"",(E17/F17-1)*100) | H17: =IFERROR(INDEX(Data_ReportedUnits!$F$5:$F$20,MATCH(A17,Data_ReportedUnits!$A$5:$A$20,0)),"")
A18: FY2026 Q2 | B18: 2025-11 | C18: 2025-12 | D18: 2026-01 | E18: =IFERROR(AVERAGE(INDEX(Data_CPI!$B$5:$B$912,MATCH(B18,Data_CPI!$A$5:$A$912,0)),INDEX(Data_CPI!$B$5:$B$912,MATCH(C18,Data_CPI!$A$5:$A$912,0)),INDEX(Data_CPI!$B$5:$B$912,MATCH(D18,Data_CPI!$A$5:$A$912,0))),"") | F18: =IFERROR(AVERAGE(INDEX(Data_CPI!$B$5:$B$912,MATCH((VALUE(LEFT(B18,4))-1)&RIGHT(B18,3),Data_CPI!$A$5:$A$912,0)),INDEX(Data_CPI!$B$5:$B$912,MATCH((VALUE(LEFT(C18,4))-1)&RIGHT(C18,3),Data_CPI!$A$5:$A$912,0)),INDEX(Data_CPI!$B$5:$B$912,MATCH((VALUE(LEFT(D18,4))-1)&RIGHT(D18,3),Data_CPI!$A$5:$A$912,0))),"") | G18: =IF(OR(E18="",F18=""),"",(E18/F18-1)*100) | H18: =IFERROR(INDEX(Data_ReportedUnits!$F$5:$F$20,MATCH(A18,Data_ReportedUnits!$A$5:$A$20,0)),"")
A19: FY2026 Q3 | B19: 2026-02 | C19: 2026-03 | D19: 2026-04 | E19: =IFERROR(AVERAGE(INDEX(Data_CPI!$B$5:$B$912,MATCH(B19,Data_CPI!$A$5:$A$912,0)),INDEX(Data_CPI!$B$5:$B$912,MATCH(C19,Data_CPI!$A$5:$A$912,0)),INDEX(Data_CPI!$B$5:$B$912,MATCH(D19,Data_CPI!$A$5:$A$912,0))),"") | F19: =IFERROR(AVERAGE(INDEX(Data_CPI!$B$5:$B$912,MATCH((VALUE(LEFT(B19,4))-1)&RIGHT(B19,3),Data_CPI!$A$5:$A$912,0)),INDEX(Data_CPI!$B$5:$B$912,MATCH((VALUE(LEFT(C19,4))-1)&RIGHT(C19,3),Data_CPI!$A$5:$A$912,0)),INDEX(Data_CPI!$B$5:$B$912,MATCH((VALUE(LEFT(D19,4))-1)&RIGHT(D19,3),Data_CPI!$A$5:$A$912,0))),"") | G19: =IF(OR(E19="",F19=""),"",(E19/F19-1)*100) | H19: =IFERROR(INDEX(Data_ReportedUnits!$F$5:$F$20,MATCH(A19,Data_ReportedUnits!$A$5:$A$20,0)),"") | J19: Chain (type a used-car CPI YoY assumption)
A20: FY2026 Q4 | B20: 2026-05 | C20: 2026-06 | D20: 2026-07 | E20: =IFERROR(AVERAGE(INDEX(Data_CPI!$B$5:$B$912,MATCH(B20,Data_CPI!$A$5:$A$912,0)),INDEX(Data_CPI!$B$5:$B$912,MATCH(C20,Data_CPI!$A$5:$A$912,0)),INDEX(Data_CPI!$B$5:$B$912,MATCH(D20,Data_CPI!$A$5:$A$912,0))),"") | F20: =IFERROR(AVERAGE(INDEX(Data_CPI!$B$5:$B$912,MATCH((VALUE(LEFT(B20,4))-1)&RIGHT(B20,3),Data_CPI!$A$5:$A$912,0)),INDEX(Data_CPI!$B$5:$B$912,MATCH((VALUE(LEFT(C20,4))-1)&RIGHT(C20,3),Data_CPI!$A$5:$A$912,0)),INDEX(Data_CPI!$B$5:$B$912,MATCH((VALUE(LEFT(D20,4))-1)&RIGHT(D20,3),Data_CPI!$A$5:$A$912,0))),"") | G20: =IF(OR(E20="",F20=""),"",(E20/F20-1)*100) | H20: =IFERROR(INDEX(Data_ReportedUnits!$F$5:$F$20,MATCH(A20,Data_ReportedUnits!$A$5:$A$20,0)),"") | J20: Used-car CPI YoY % (assumption) | K20: -2
J21: → US insurance ASP YoY % | K21: =K6+K5*K20
J22: → Service RPU YoY % | K22: =K13+K12*K21
J23: → Total RPU YoY % (mgmt definition) | K23: =L13+L12*K21
J24: Back-test FY26Q4: used-car CPI ≈ −1.9% → service RPU ≈ +4.4%; reported +4.4%. RPU is low-variance: +3.3% to +8.9% across used-car CPI −8% to +10%.

Sheet Checks
A1: Checks — every one should read OK
A3: check | B3: value | C3: target | D3: tolerance | E3: status
A4: Calibration loss (Solver objective) small | B4: =Calibration!N22 | C4: 0 | D4: 3 | E4: =IF(ABS(B4-C4)<=D4,"OK","FAIL")
A5: Baseline TLF 2024 ≈ CCC 22.3% | B5: =TLF_Roll!N8 | C5: 0.223 | D5: 0.005 | E5: =IF(ABS(B5-C5)<=D5,"OK","FAIL")
A6: VIO 2024 ≈ 292M (Experian) / 289M (S&P) | B6: =TLF_Roll!N18 | C6: 292 | D6: 9 | E6: =IF(ABS(B6-C6)<=D6,"OK","FAIL")
A7: Fleet share 7+ 2024 ≈ 66% | B7: =TLF_Roll!N19 | C7: 0.66 | D7: 0.025 | E7: =IF(ABS(B7-C7)<=D7,"OK","FAIL")
A8: Survival at age 0 = 1 in every year | B8: =MIN(Survival!C6:T6,Survival!C55:T55) | C8: 1 | D8: 0.0001 | E8: =IF(ABS(B8-C8)<=D8,"OK","FAIL")
A9: Fleet matrix: 2013 total ≈ 2013 census light vehicles (~243M) | B9: =Fleet!C68/1000 | C9: 243 | D9: 12 | E9: =IF(ABS(B9-C9)<=D9,"OK","FAIL")
A10: Spread regression slope ≈ 0.0815 (all-loss) | B10: =Spread_Reg!T5 | C10: 0.0815 | D10: 0.003 | E10: =IF(ABS(B10-C10)<=D10,"OK","FAIL")
A11: Spread regression intercept ≈ 0.599 (all-loss) | B11: =Spread_Reg!T6 | C11: 0.599 | D11: 0.03 | E11: =IF(ABS(B11-C11)<=D11,"OK","FAIL")
A12: Service-RPU elasticity ≈ 0.514 | B12: =RPU_Reg!K12 | C12: 0.514 | D12: 0.01 | E12: =IF(ABS(B12-C12)<=D12,"OK","FAIL")
A13: Service-RPU intercept ≈ 4.13 | B13: =RPU_Reg!K13 | C13: 4.13 | D13: 0.1 | E13: =IF(ABS(B13-C13)<=D13,"OK","FAIL")
A14: ASP ~ CPI slope ≈ 0.60 (n=15) | B14: =RPU_Reg!K5 | C14: 0.599 | D14: 0.05 | E14: =IF(ABS(B14-C14)<=D14,"OK","FAIL")
A15: P(≤3) 2024 ≈ 10% | B15: =TLF_Roll!N17 | C15: 0.1 | D15: 0.01 | E15: =IF(ABS(B15-C15)<=D15,"OK","FAIL")
A17: ALL CHECKS | E17: =IF(COUNTIF(E4:E15,"OK")=12,"OK","FAIL")

Sheet Data_ReportedUnits
A1: reported_units.csv
A2: Copart quarterly YoY series, HAND-TRANSCRIBED from earnings-call transcripts (no filing discloses them). Tier 2. scripts/reported_series.py
A3: data/csv/reported_units.csv · 16 rows · BLUE = raw data as committed; do not type over it — edit the CSV and rebuild.
A4: fiscal_q | B4: call_date | C4: us_inventory_yoy | D4: us_ins_units_yoy | E4: us_ins_units_exCAT_yoy | F4: us_ins_asp_yoy | G4: global_asp_yoy | H4: global_ins_units_yoy
A5: FY2022 Q4 | B5: 2022-09-08 | C5: -9.6 | F5: 9.2 | G5: 8.3
A6: FY2023 Q1 | B6: 2022-11-17 | C6: -6.3 | F6: 6.4 | G6: 5
A7: FY2023 Q2 | B7: 2023-02-21 | C7: -3 | D7: 9 | F7: 1 | G7: 0
A8: FY2023 Q3 | B8: 2023-05-17 | C8: 2 | D8: 6 | F8: -1 | G8: -1
A9: FY2023 Q4 | B9: 2023-09-14 | C9: 8 | D9: 9 | F9: 2 | G9: 2
A10: FY2024 Q1 | B10: 2023-11-16 | C10: 1 | D10: 9.7 | F10: -1.7 | G10: -1
A11: FY2024 Q2 | B11: 2024-02-22 | C11: 4 | D11: 0.3 | E11: 9.2 | F11: -5 | G11: -5
A12: FY2024 Q3 | B12: 2024-05-16 | C12: 3 | D12: 6.8 | F12: -2 | G12: -3
A13: FY2024 Q4 | B13: 2024-09-04 | C13: 6 | D13: 6 | F13: -4 | G13: -5
A14: FY2025 Q1 | B14: 2024-11-21 | C14: 5 | D14: 12 | E14: 9 | F14: -1 | G14: -1
A15: FY2025 Q2 | B15: 2025-02-20 | C15: -4 | D15: 9 | E15: 2 | F15: 2 | G15: 2
A16: FY2025 Q3 | B16: 2025-05-22 | C16: -11 | D16: -1 | E16: -2 | F16: 2 | G16: 3
A17: FY2025 Q4 | B17: 2025-09-04 | C17: -14.8 | D17: -2.1 | F17: 5.7 | G17: 5.6 | H17: -1.9
A18: FY2026 Q1 | B18: 2025-11-20 | C18: -17 | D18: -9.5 | E18: -7.3 | F18: 8.4 | G18: 8.5
A19: FY2026 Q2 | B19: 2026-02-19 | C19: -8.1 | D19: -10.7 | E19: -4.8 | F19: 6 | G19: 6 | H19: -8
A20: FY2026 Q3 | B20: 2026-05-21 | C20: -4.7 | D20: -4.2 | E20: -3.1 | F20: 4.1 | G20: 4.6 | H20: -2.7

Sheet Data_QuarterlyPL
A1: quarterly_pl.csv
A2: Copart quarterly P&L lines from 8-K Ex-99.1 press releases (SEC EDGAR). Tier 1.
A3: data/csv/quarterly_pl.csv · 19 rows · BLUE = raw data as committed; do not type over it — edit the CSV and rebuild.
A4: filed | B4: quarter_end | C4: service_rev_m | D4: prior_service_rev_m | E4: service_yoy_pct | F4: vehicle_sales_m | G4: vehicle_yoy_pct | H4: total_rev_m | I4: total_yoy_pct
A5: 2021-09-08 | B5: July 31, 2021 | C5: 620.048 | D5: 457.668 | E5: 35.5 | F5: 128.582 | G5: 89.1 | H5: 748.63 | I5: 42.4
A6: 2021-11-17 | C6: 667.818 | D6: 515.372 | E6: 29.6 | F6: 142.314 | G6: 83.5 | H6: 810.132 | I6: 36.6
A7: 2022-02-16 | B7: January 31, 2022 | C7: 711.09 | D7: 532.601 | E7: 33.5 | F7: 156.37 | G7: 85.2 | H7: 867.46 | I7: 40.6
A8: 2022-05-19 | B8: April 30, 2022 | C8: 766.316 | D8: 623.846 | E8: 22.8 | F8: 173.625 | G8: 57.7 | H8: 939.941 | I8: 28.1
A9: 2022-09-07 | B9: July 31, 2022 | C9: 707.816 | D9: 620.048 | E9: 14.2 | F9: 175.572 | G9: 36.5 | H9: 883.388 | I9: 18
A10: 2022-11-17 | C10: 726.84 | D10: 667.818 | E10: 8.8 | F10: 166.532 | G10: 17 | H10: 893.372 | I10: 10.3
A11: 2023-02-21 | B11: January 31, 2023 | C11: 789.797 | D11: 711.09 | E11: 11.1 | F11: 166.927 | G11: 6.8 | H11: 956.724 | I11: 10.3
A12: 2023-05-17 | B12: April 30, 2023 | C12: 847.249 | D12: 766.316 | E12: 10.6 | F12: 174.582 | G12: 0.6 | H12: 1021.831 | I12: 8.7
A13: 2023-09-14 | B13: July 31, 2023 | C13: 834.242 | D13: 707.816 | E13: 17.9 | F13: 163.349 | G13: -7 | H13: 997.591 | I13: 12.9
A14: 2023-11-16 | C14: 859.536 | D14: 726.84 | E14: 18.3 | F14: 160.88 | G14: -3.4 | H14: 1020.416 | I14: 14.2
A15: 2024-02-22 | B15: January 31, 2024 | C15: 861.745 | D15: 789.797 | E15: 9.1 | F15: 158.404 | G15: -5.1 | H15: 1020.149 | I15: 6.6
A16: 2024-05-16 | B16: April 30, 2024 | C16: 946.63 | D16: 847.249 | E16: 11.7 | F16: 180.629 | G16: 3.5 | H16: 1127.259 | I16: 10.3
A17: 2024-09-04 | B17: July 31, 2024 | C17: 893.091 | D17: 834.242 | E17: 7.1 | F17: 175.908 | G17: 7.7 | H17: 1068.999 | I17: 7.2
A18: 2024-11-21 | C18: 986.336 | D18: 859.536 | E18: 14.8 | F18: 160.493 | G18: -0.2 | H18: 1146.829 | I18: 12.4
A19: 2025-02-20 | B19: January 31, 2025 | C19: 991.281 | D19: 861.745 | E19: 15 | F19: 172.035 | G19: 8.6 | H19: 1163.316 | I19: 14
A20: 2025-05-22 | B20: April 30, 2025 | C20: 1034.836 | D20: 946.63 | E20: 9.3 | F20: 176.88 | G20: -2.1 | H20: 1211.716 | I20: 7.5
A21: 2025-09-04 | B21: July 31, 2025 | C21: 956.209 | D21: 893.091 | E21: 7.1 | F21: 168.888 | G21: -4 | H21: 1125.097 | I21: 5.2
A22: 2025-11-20 | C22: 991.845 | D22: 986.336 | E22: 0.6 | F22: 163.185 | G22: 1.7 | H22: 1155.03 | I22: 0.7
A23: 2026-05-21 | B23: April 30, 2026 | C23: 1056.08 | D23: 1034.836 | E23: 2.1 | F23: 180.986 | G23: 2.3 | H23: 1237.066 | I23: 2.1

Sheet Data_QuarterlyMargin
A1: quarterly_margin.csv
A2: Copart quarterly gross margin and facility-operations % of revenue, from 8-K Ex-99.1. Tier 1.
A3: data/csv/quarterly_margin.csv · 20 rows · BLUE = raw data as committed; do not type over it — edit the CSV and rebuild.
